Workbook
Name IQ_CH: 110000
Name IQ_CQ: 5000
Name IQ_CY: 10000
Name IQ_DAILY: 500000
Name IQ_FH: 100000
Name IQ_FQ: 500
Name IQ_FY: 1000
Name IQ_LTM: 2000
Name IQ_MONTH: 15000
Name IQ_NTM: 6000
Name IQ_WEEK: 50000
Name IQ_YTD: 3000

Sheet _CIQHiddenCacheSheet
A1: 157 | B1: AwABTAVMT0NBTAFI/////wFQ9QIAAClDSVEuVFNFOjc5NzQuSVFfQ0xPU0VQUklDRS4yMDE4LTAxLTMwLlVTRAEAAACkXQ0AAgAAAAo0MzEuNzIwMDk2AOcQwSddQNcIcWgDKF1A1wgpQ0lRLlRTRTo3OTc0LklRX0NMT1NFUFJJQ0UuMjAxOS0wMi0xMi5VU0QBAAAApF0NAAIAAAAKMjY0LjU1ODE1NwDnEMEnXUDXCAMGAShdQNcIKUNJUS5UU0U6Nzk3NC5JUV9DTE9TRVBSSUNFLjIwMTctMDQtMTguVVNEAQAAAKRdDQACAAAACjI0NS42ODkwNjYA5xDBJ11A1whrQfwnXUDXCClDSVEuVFNFOjc5NzQuSVFfQ0xPU0VQUklDRS4yMDE5LTA5LTEwLlVTRAEAAACkXQ0AAgAAAAozODguMzgwMzA4AKeZyiddQNcIcWgDKF1A1wgpQ0lRLlRTRTo3OTc0LklRX0NMT1NFUFJJQ0UuMjAxOC0wNy0zMS5VU0QBAAAApF0NAAIAAAAKMzI4LjQ5MjkxMQDnEMEnXUDXCAMGAShdQNcIPUNJUS5LT1NFOkEyNTEyNzAuSVFfU0hPUlRfQlVTSU5FU1NfREVTQ1JJUFRJT04uMjAxOS0wOS0yMy5VU0QBAAAAWe4vCQMAAACMAU5ldG1hcmJsZSBDb3Jwb3JhdGlvbiBkZXZlbG9wcyBhbmQgcHVibGlzaGVzIG9ubGluZSBnYW1lcyBmb3IgdGhlIFBDIGFuZCBtb2JpbGUgZ2FtZSBwdWJsaXNoaW5nIGluZHVzdHJ5IGluIFNvdXRoIEtvcmVhIGFuZCBpbnRlcm5hdGlvbmFsbHkuAOcQwSddQNcIYsoFKF1A1wgsQ0lRLlRTRTo3OTc0LklR | C1: X1RFVl9FQklUREEuSVFfTFRNLjIwMTktMDYtMjUBAAAApF0NAAIAAAAIMTMuMDIyMzkBBwAAAAUAAAABMQEAAAAKMTk1Njc0ODA4NgMAAAABMAIAAAAGMTAwMDMwBAAAAAEwBwAAAAk2LzI1LzIwMTkIAAAACTYvMjUvMjAxOaeZyiddQNcIt6P+J11A1wg3Q0lRLlRTRTozNjU5LklRX0VGRkVDVF9UQVhfUkFURS5JUV9MVE0uMjAxOS0wOS0yMy4uLlVTRAEAAACeH4IIAgAAAAcxNi4yNjYxAQgAAAAFAAAAATEBAAAACjE5NzU3OTI0MzcDAAAAAjc5AgAAAAQ0Mzc2BAAAAAEwBwAAAAk5LzIzLzIwMTkIAAAACTYvMzAvMjAxOQkAAAABMKeZyiddQNcIa0H8J11A1wg0Q0lRLk5BU0RBUUdTOkVBLklRX1RPVEFMX1JFVi5DWTIwMTcuMjAxOS0wOS0yMy4uLlVTRAEAAAA7bQAAAgAAAAQ1MDk1AQgAAAAFAAAAATEBAAAACjE5NDM5MTUwMjEDAAAAAzE2MAIAAAACMjgEAAAAATAHAAAACTkvMjMvMjAxOQgAAAAKMTIvMzEvMjAxNwkAAAABMOcQwSddQNcIAwYBKF1A1wg3Q0lRLk5BU0RBUUdTOlRUV08uSVFfRUJJVERBX0VTVC5DWTIwMjAuMjAxOS0wOS0yMy4uLlVTRAEAAABRqgUAAgAAAAg3MjguNjM0NwEOAAAABQAAAAIxMQEAAAABMAIAAAAHMTExNzE5OAMAAAAGMTAwMTg3BAAAAAEyBgAAAAEwBwAAAAMxNjAIAAAAATAJAAAAATEKAAAAATALAAAACzExNjExMzc3MTMxDAAAAAE3DQAAAAk5LzI0LzIwMTkQAAAA | D1: CTkvMjMvMjAxOecQwSddQNcIcWgDKF1A1wgoQ0lRLlRTRTo5Njg0LklRX01BUktFVENBUC4yMDE5LTA5LTIzLlVTRAEAAACpfQ0AAgAAAAk1MTc5LjY4MTcBBgAAAAUAAAABMQEAAAAKMTk3NTc4NjYwOQMAAAADMTYwAgAAAAYxMDAwNTQEAAAAATAHAAAACTkvMjAvMjAxOecQwSddQNcIt6P+J11A1wgpQ0lRLlRTRTo3OTc0LklRX0NMT1NFUFJJQ0UuMjAxOS0wOC0xMy5VU0QBAAAApF0NAAIAAAAKMzYwLjk0ODc1NwCnmconXUDXCHFoAyhdQNcILENJUS5UU0U6Nzk3NC5JUV9URVZfRUJJVERBLklRX0xUTS4yMDE3LTEyLTEyAQAAAKRdDQACAAAACTQzLjc0MzQ5MQEHAAAABQAAAAExAQAAAAoxODY1NzkyMzYzAwAAAAEwAgAAAAYxMDAwMzAEAAAAATAHAAAACjEyLzEyLzIwMTcIAAAACjEyLzEyLzIwMTfnEMEnXUDXCLej/iddQNcIMUNJUS5UU0U6Nzk3NC5JUV9UT1RBTF9SRVYuSVFfTFRNLjIwMTktMDktMjMuLi5VU0QBAAAApF0NAAIAAAAMMTExNzUuMTU0NDY5AQgAAAAFAAAAATEBAAAACjE5NzU3OTI0NzADAAAAAzE2MAIAAAACMjgEAAAAATAHAAAACTkvMjMvMjAxOQgAAAAJNi8zMC8yMDE5CQAAAAEwp5nKJ11A1wgDBgEoXUDXCClDSVEuVFNFOjc5NzQuSVFfQ0xPU0VQUklDRS4yMDE3LTA4LTA4LlVTRAEAAACkXQ0AAgAAAAozNDQuNzY4NDM2AOcQwSddQNcIa0H8J11A1wgpQ0lRLlRTRTo3OTc0 | E1: LklRX0NMT1NFUFJJQ0UuMjAxOC0wMi0wNi5VU0QBAAAApF0NAAIAAAAKNDA3LjQ1ODMzMgDnEMEnXUDXCLej/iddQNcILENJUS5FTlhUUEE6VUJJLklRX1RFVi40NDkyNi4yMDE5LTA5LTIzLi4uVVNEAQAAABl2DQACAAAACzg3NjkuNjU5MTA4AQYAAAAFAAAAATEBAAAACjE5Njg0NjI4NjkDAAAAAzE2MAIAAAAGMTAwMDYwBAAAAAEwBwAAAAk5LzIzLzIwMTnnEMEnXUDXCHFoAyhdQNcIKkNJUS5OQVNEQVFHUzpBVFZJLklRX1RFVi4uMjAxOS0wOS0yMy4uLlVTRAEAAAAXbUAAAgAAAAwzOTg0OS40NjU0MjkBBgAAAAUAAAABMQEAAAAKMTk3NTAzODc5OQMAAAADMTYwAgAAAAYxMDAwNjAEAAAAATAHAAAACTkvMjMvMjAxOecQwSddQNcIcWgDKF1A1wgqQ0lRLlRTRTo5Njg0LklRX0dQLkNZMjAxOC4yMDE5LTA5LTIzLi4uVVNEAQAAAKl9DQACAAAACjk4NC4zNjg1OTIBCAAAAAUAAAABMQEAAAAKMTk0NDM4ODIyNAMAAAADMTYwAgAAAAIxMAQAAAABMAcAAAAJOS8yMy8yMDE5CAAAAAoxMi8zMS8yMDE4CQAAAAEw5xDBJ11A1wgDBgEoXUDXCCVDSVEuVFNFOjk2ODQuSVFfVEVWLi4yMDE5LTA5LTIzLi4uVVNEAQAAAKl9DQACAAAACzQxMzAuNjA2NzM2AQYAAAAFAAAAATEBAAAACjE5NzU3ODY2MDkDAAAAAzE2MAIAAAAGMTAwMDYwBAAAAAEwBwAAAAk5LzIwLzIwMTnnEMEnXUDXCAMGAShdQNcILkNJUS5U | F1: U0U6MzY1OS5JUV9FQklUREEuQ1kyMDE4LjIwMTktMDktMjMuLi5VU0QBAAAAnh+CCAIAAAALMTAzNC4yMTU5MjQBCAAAAAUAAAABMQEAAAAKMTk1MTg2NzkyOQMAAAADMTYwAgAAAAQ0MDUxBAAAAAEwBwAAAAk5LzIzLzIwMTkIAAAACjEyLzMxLzIwMTgJAAAAATDnEMEnXUDXCHFoAyhdQNcILENJUS5UU0U6Nzk3NC5JUV9URVZfRUJJVERBLklRX0xUTS4yMDE5LTA4LTA2AQAAAKRdDQACAAAACTE0LjE3ODU0MgEHAAAABQAAAAExAQAAAAoxOTcyODcwMjA4AwAAAAEwAgAAAAYxMDAwMzAEAAAAATAHAAAACDgvNi8yMDE5CAAAAAg4LzYvMjAxOaeZyiddQNcIa0H8J11A1wg1Q0lRLk5BU0RBUUdTOkVBLklRX0VCSVREQV9FU1QuQ1kyMDE5LjIwMTktMDktMjMuLi5VU0QBAAAAO20AAAIAAAAJMTgxNS42NzYzAQ4AAAAFAAAAAjExAQAAAAEwAgAAAAc3ODc1MzYxAwAAAAYxMDAxODcEAAAAATIGAAAAATAHAAAAAzE2MAgAAAABMAkAAAABMQoAAAABMAsAAAALMTE1NDQ1MTEyNTQMAAAAATcNAAAACTkvMjQvMjAxORAAAAAJOS8yMy8yMDE55xDBJ11A1wgDBgEoXUDXCDJDSVEuVFNFOjM2NTkuSVFfRUJJVERBX0VTVC5DWTIwMjAuMjAxOS0wOS0yMy4uLlVTRAEAAACeH4IIAgAAABAxMTE0LjQ3NjAxNzIxMTc0AQ4AAAAFAAAAAjExAQAAAAEwAgAAAAoxMDAxNDIyODI0AwAAAAYxMDAxODcEAAAAATMGAAAAATAH | G1: AAAAAzE2MAgAAAABMAkAAAABMQoAAAABMAsAAAALMTE2MDM0NDcwNTEMAAAAATcNAAAACTkvMjQvMjAxORAAAAAJOS8yMy8yMDE55xDBJ11A1whrQfwnXUDXCCxDSVEuVFNFOjc5NzQuSVFfVEVWX0VCSVREQS5JUV9MVE0uMjAxOC0wNS0yOQEAAACkXQ0AAgAAAAkyMC44Njg3MjQBBwAAAAUAAAABMQEAAAAKMTg4NDg2NDk2NAMAAAABMAIAAAAGMTAwMDMwBAAAAAEwBwAAAAk1LzI5LzIwMTgIAAAACTUvMjkvMjAxOOcQwSddQNcIt6P+J11A1wgsQ0lRLlRTRTo3OTc0LklRX1RFVl9FQklUREEuSVFfTFRNLjIwMTctMDItMjgBAAAApF0NAAIAAAAJNDEuOTM3MTMxAQcAAAAFAAAAATEBAAAACjE4Mjc3Njc3OTcDAAAAATACAAAABjEwMDAzMAQAAAABMAcAAAAJMi8yOC8yMDE3CAAAAAkyLzI4LzIwMTfnEMEnXUDXCGLKBShdQNcILENJUS5UU0U6Nzk3NC5JUV9URVZfRUJJVERBLklRX0xUTS4yMDE5LTA5LTE3AQAAAKRdDQACAAAACTE1LjUxMzU0NgEHAAAABQAAAAExAQAAAAoxOTc1NzkyNDcwAwAAAAEwAgAAAAYxMDAwMzAEAAAAATAHAAAACTkvMTcvMjAxOQgAAAAJOS8xNy8yMDE5p5nKJ11A1wi3o/4nXUDXCCxDSVEuVFNFOjc5NzQuSVFfVEVWX0VCSVREQS5JUV9MVE0uMjAxNi0wOS0yMAEAAACkXQ0AAgAAAAk2NS42NjE0NzYBBwAAAAUAAAABMQEAAAAKMTgwMjc3Njc3NQMAAAABMAIAAAAGMTAwMDMw | H1: BAAAAAEwBwAAAAk5LzIwLzIwMTYIAAAACTkvMjAvMjAxNucQwSddQNcIAwYBKF1A1wg2Q0lRLlRTRTo3OTc0LklRX0RJTFVUX0VQU19FWENMLklRX0xUTS4yMDE5LTA5LTIzLi4uVVNEAQAAAKRdDQACAAAACTEzLjkzNjA5MwEIAAAABQAAAAExAQAAAAoxOTc1NzkyNDcwAwAAAAMxNjACAAAAAzE0MgQAAAABMAcAAAAJOS8yMy8yMDE5CAAAAAk2LzMwLzIwMTkJAAAAATDnEMEnXUDXCLej/iddQNcILUNJUS5OQVNEQVFHUzpFQS5JUV9URVYuNDI3MzUuMjAxOS0wOS0yMy4uLlVTRAEAAAA7bQAAAgAAAAoyMTQ5MC42MTc2AQYAAAAFAAAAATEBAAAACjE4MTcxMjY1NjADAAAAAzE2MAIAAAAGMTAwMDYwBAAAAAEwBwAAAAoxMi8zMS8yMDE25xDBJ11A1wi3o/4nXUDXCCxDSVEuVFNFOjc5NzQuSVFfVEVWX0VCSVREQS5JUV9MVE0uMjAxNy0wNC0yNQEAAACkXQ0AAgAAAAk1My45NDU4ODUBBwAAAAUAAAABMQEAAAAKMTgyNzc2Nzc5NwMAAAABMAIAAAAGMTAwMDMwBAAAAAEwBwAAAAk0LzI1LzIwMTcIAAAACTQvMjUvMjAxN+cQwSddQNcIcWgDKF1A1wgzQ0lRLk5BU0RBUUdTOkFUVkkuSVFfRUJJVERBLkNZMjAxNS4yMDE5LTA5LTIzLi4uVVNEAQAAABdtQAACAAAABDE0MTkBCAAAAAUAAAABMQEAAAAKMTg3Njc1NDg3NwMAAAADMTYwAgAAAAQ0MDUxBAAAAAEwBwAAAAk5LzIzLzIwMTkIAAAACjEyLzMxLzIw | I1: MTUJAAAAATDnEMEnXUDXCLej/iddQNcIKUNJUS5UU0U6Nzk3NC5JUV9DTE9TRVBSSUNFLjIwMTYtMDEtMDUuVVNEAQAAAKRdDQACAAAACjEzNy43ODkxNTgA5xDBJ11A1whxaAMoXUDXCClDSVEuVFNFOjc5NzQuSVFfQ0xPU0VQUklDRS4yMDE5LTA0LTAyLlVTRAEAAACkXQ0AAgAAAAoyODcuNTQ5NDE1AOcQwSddQNcIt6P+J11A1wgsQ0lRLlRTRTo3OTc0LklRX1RFVl9FQklUREEuSVFfTFRNLjIwMTgtMDYtMjYBAAAApF0NAAIAAAAJMTcuMDA3NjY5AQcAAAAFAAAAATEBAAAACjE4ODQ4NjQ5NjQDAAAAATACAAAABjEwMDAzMAQAAAABMAcAAAAJNi8yNi8yMDE4CAAAAAk2LzI2LzIwMTjnEMEnXUDXCLej/iddQNcIKUNJUS5UU0U6Nzk3NC5JUV9DTE9TRVBSSUNFLjIwMTktMDgtMjAuVVNEAQAAAKRdDQACAAAACjM3Ni4xMDgwODQAp5nKJ11A1wi3o/4nXUDXCDhDSVEuTkFTREFRR1M6QVRWSS5JUV9SRVZFTlVFX0VTVC5DWTIwMjEuMjAxOS0wOS0yMy4uLlVTRAEAAAAXbUAAAgAAAAo3NjA2LjE4MDU0AQ4AAAAFAAAAAjExAQAAAAEwAgAAAAoxMDAxMzQ2MjczAwAAAAYxMDAxODAEAAAAATIGAAAAATAHAAAAAzE2MAgAAAABMAkAAAABMQoAAAABMAsAAAALMTE2MTAwMTIzODIMAAAAATcNAAAACTkvMjQvMjAxORAAAAAJOS8yMy8yMDE55xDBJ11A1wi3o/4nXUDXCClDSVEuVFNFOjc5NzQuSVFfQ0xPU0VQ | J1: UklDRS4yMDE3LTExLTE0LlVTRAEAAACkXQ0AAgAAAAozOTQuOTIwMTk0AOcQwSddQNcIt6P+J11A1wgvQ0lRLlRTRTo3OTc0LklRX1BFX0VYQ0wuSVFfTFRNLjIwMTktMDktMjMuLi5VU0QBAAAApF0NAAIAAAAJMjguNTEzMzgxAQcAAAAFAAAAATEBAAAACjE5NzU3OTI0NzADAAAAATACAAAABjEwMDAyNwQAAAABMAcAAAAJOS8yMC8yMDE5CAAAAAk5LzIwLzIwMTnnEMEnXUDXCLej/iddQNcILENJUS5UU0U6Nzk3NC5JUV9URVZfRUJJVERBLklRX0xUTS4yMDE5LTA4LTIwAQAAAKRdDQACAAAACTE0LjY2Mjc2NAEHAAAABQAAAAExAQAAAAoxOTc1NzkyNDcwAwAAAAEwAgAAAAYxMDAwMzAEAAAAATAHAAAACTgvMjAvMjAxOQgAAAAJOC8yMC8yMDE5p5nKJ11A1wi3o/4nXUDXCC5DSVEuVFNFOjk2ODQuSVFfRUJJVERBLkNZMjAxNS4yMDE5LTA5LTIzLi4uVVNEAQAAAKl9DQACAAAACjI3MC45MjM0NzUBCAAAAAUAAAABMQEAAAAKMTc3NTgxMjAxNgMAAAADMTYwAgAAAAQ0MDUxBAAAAAEwBwAAAAk5LzIzLzIwMTkIAAAACjEyLzMxLzIwMTUJAAAAATDnEMEnXUDXCHFoAyhdQNcILENJUS5UU0U6Nzk3NC5JUV9URVZfRUJJVERBLklRX0xUTS4yMDE4LTExLTEzAQAAAKRdDQACAAAACTE2LjExNDM4OAEHAAAABQAAAAExAQAAAAoxOTIxNTE4NDIzAwAAAAEwAgAAAAYxMDAwMzAEAAAAATAHAAAACjExLzEzLzIw | K1: MTgIAAAACjExLzEzLzIwMTjnEMEnXUDXCLej/iddQNcIKUNJUS5UU0U6Nzk3NC5JUV9DTE9TRVBSSUNFLjIwMTctMTAtMDMuVVNEAQAAAKRdDQACAAAACjM3MC4yNjE5OTIA5xDBJ11A1whrQfwnXUDXCD5DSVEuTkFTREFRR1M6QVRWSS5JUV9TSE9SVF9CVVNJTkVTU19ERVNDUklQVElPTi4yMDE5LTA5LTIzLlVTRAEAAAAXbUAAAwAAAIwBQWN0aXZpc2lvbiBCbGl6emFyZCwgSW5jLiBkZXZlbG9wcyBhbmQgZGlzdHJpYnV0ZXMgY29udGVudCBhbmQgc2VydmljZXMgb24gdmlkZW8gZ2FtZSBjb25zb2xlcywgcGVyc29uYWwgY29tcHV0ZXJzIChQQyksIGFuZCBtb2JpbGUgZGV2aWNlcy4A5xDBJ11A1wi3o/4nXUDXCClDSVEuVFNFOjc5NzQuSVFfQ0xPU0VQUklDRS4yMDE2LTA3LTI2LlVTRAEAAACkXQ0AAgAAAAoyMjUuMzg1NzQ4AOcQwSddQNcIt6P+J11A1wgpQ0lRLlRTRTo3OTc0LklRX0NMT1NFUFJJQ0UuMjAxOC0wMy0xMy5VU0QBAAAApF0NAAIAAAAKNDU3LjcyNzMyNQDnEMEnXUDXCAMGAShdQNcIJkNJUS5LT1NFOkEyNTEyNzAuSVFfVEVWLjIwMTktMDktMjMuVVNEAQAAAFnuLwkCAAAACzUyMjguNjIyOTY5AQYAAAAFAAAAATEBAAAACjE5ODExNTY1NDADAAAAAzE2MAIAAAAGMTAwMDYwBAAAAAEwBwAAAAk5LzIzLzIwMTnnEMEnXUDXCAMGAShdQNcIMUNJUS5UU0U6Nzk3NC5JUV9SRF9FWFBf | L1: Rk4uQ1kyMDE3LjIwMTktMDktMjMuLi5VU0QBAAAApF0NAAIAAAAKNTI1LjU2NDg3NwEIAAAABQAAAAExAQAAAAoxODc0MTkzMzQwAwAAAAMxNjACAAAABDMxNjgEAAAAATAHAAAACTkvMjMvMjAxOQgAAAAKMTIvMzEvMjAxNwkAAAABMKeZyiddQNcIYsoFKF1A1wgxQ0lRLlRTRTo3OTc0LklRX1RPVEFMX1JFVi5DWTIwMTcuMjAxOS0wOS0yMy4uLlVTRAEAAACkXQ0AAgAAAAo5MTg4Ljg0ODkzAQgAAAAFAAAAATEBAAAACjE4NzQxOTMzNDADAAAAAzE2MAIAAAACMjgEAAAAATAHAAAACTkvMjMvMjAxOQgAAAAKMTIvMzEvMjAxNwkAAAABMKeZyiddQNcIYsoFKF1A1wgpQ0lRLlRTRTo3OTc0LklRX0NMT1NFUFJJQ0UuMjAxOC0wMy0yNy5VU0QBAAAApF0NAAIAAAAKNDUzLjA1MzI4OADnEMEnXUDXCHFoAyhdQNcIKUNJUS5UU0U6Nzk3NC5JUV9DTE9TRVBSSUNFLjIwMTUtMDktMDEuVVNEAQAAAKRdDQACAAAACjE5OC45MTY0NDYA5xDBJ11A1wgDBgEoXUDXCDRDSVEuTkFTREFRR1M6RUEuSVFfVE9UQUxfUkVWLklRX0xUTS4yMDE5LTA5LTIzLi4uVVNEAQAAADttAAACAAAABDUwMjIBCAAAAAUAAAABMQEAAAAKMTk3NDIzNTgxMgMAAAADMTYwAgAAAAIyOAQAAAABMAcAAAAJOS8yMy8yMDE5CAAAAAk2LzMwLzIwMTkJAAAAATDnEMEnXUDXCHFoAyhdQNcIKUNJUS5UU0U6Nzk3NC5JUV9DTE9TRVBSSUNFLjIw | M1: MTctMDMtMDcuVVNEAQAAAKRdDQACAAAACjIxNi40ODM5OTQA5xDBJ11A1wi3o/4nXUDXCCxDSVEuVFNFOjc5NzQuSVFfVEVWX0VCSVREQS5JUV9MVE0uMjAxNi0wMy0yMgEAAACkXQ0AAgAAAAkyNC41NTM0MTcBBwAAAAUAAAABMQEAAAAKMTc3NjU4NDA0MwMAAAABMAIAAAAGMTAwMDMwBAAAAAEwBwAAAAkzLzIyLzIwMTYIAAAACTMvMjIvMjAxNucQwSddQNcIa0H8J11A1wgpQ0lRLlRTRTo3OTc0LklRX0NMT1NFUFJJQ0UuMjAxNy0xMi0wNS5VU0QBAAAApF0NAAIAAAAKMzgxLjQ4NDQ1MwDnEMEnXUDXCHFoAyhdQNcIKkNJUS5FTlhUUEE6VUJJLklRX01BUktFVENBUC4yMDE5LTA5LTIzLlVTRAEAAAAZdg0AAgAAAAs4NDQ2LjUyMDc3NQEGAAAABQAAAAExAQAAAAoxOTY4NDYyODY5AwAAAAMxNjACAAAABjEwMDA1NAQAAAABMAcAAAAJOS8yMy8yMDE55xDBJ11A1whrQfwnXUDXCDdDSVEuTkFTREFRR1M6VFRXTy5JUV9FQklUREFfRVNULkNZMjAyMi4yMDE5LTA5LTIzLi4uVVNEAQAAAFGqBQACAAAACDg2Mi4xNzE1AQ4AAAAFAAAAAjExAQAAAAEwAgAAAAcxMzE0NzUwAwAAAAYxMDAxODcEAAAAATIGAAAAATAHAAAAAzE2MAgAAAABMAkAAAABMQoAAAABMAsAAAALMTE2MTEzNzcxNDMMAAAAATcNAAAACTkvMjQvMjAxORAAAAAJOS8yMy8yMDE55xDBJ11A1whrQfwnXUDXCClDSVEuVFNFOjc5NzQuSVFf | N1: Q0xPU0VQUklDRS4yMDE3LTA5LTEyLlVTRAEAAACkXQ0AAgAAAAozNDQuMjg1MzczAOcQwSddQNcIcWgDKF1A1wgsQ0lRLlRTRTo3OTc0LklRX1RFVl9FQklUREEuSVFfTFRNLjIwMTctMDMtMjgBAAAApF0NAAIAAAAJNTAuMzc4MjYyAQcAAAAFAAAAATEBAAAACjE4Mjc3Njc3OTcDAAAAATACAAAABjEwMDAzMAQAAAABMAcAAAAJMy8yOC8yMDE3CAAAAAkzLzI4LzIwMTfnEMEnXUDXCHFoAyhdQNcINENJUS5OQVNEQVFHUzpFQS5JUV9UT1RBTF9SRVYuQ1kyMDE1LjIwMTktMDktMjMuLi5VU0QBAAAAO20AAAIAAAAENDI3MwEIAAAABQAAAAExAQAAAAoxODI2NjY1MjgwAwAAAAMxNjACAAAAAjI4BAAAAAEwBwAAAAk5LzIzLzIwMTkIAAAACjEyLzMxLzIwMTUJAAAAATDnEMEnXUDXCLej/iddQNcIKUNJUS5JUVRSMzI3NjQ0ODkyLklRX1RSX0lNUExJRURfRVZfRUJJVERBAQAAANx2hxMCAAAACTExLjgyNTQyMgEGAAAABQAAAAI1NAEAAAAGMTAyMDk0AgAAAAkzMjc2NDQ4OTIDAAAACTMyNzY0NTQ0MAQAAAACODUGAAAABUZhbHNl5xDBJ11A1wgDBgEoXUDXCC9DSVEuS09TRTpBMjUxMjcwLklRX0NPTVBBTllfTkFNRS4yMDE5LTA5LTIzLlVTRAEAAABZ7i8JAwAAABVOZXRtYXJibGUgQ29ycG9yYXRpb24A5xDBJ11A1whrQfwnXUDXCCxDSVEuVFNFOjc5NzQuSVFfVEVWX0VCSVREQS5JUV9MVE0uMjAxOC0x | O1: Mi0xMQEAAACkXQ0AAgAAAAkxNC40NDk1NzYBBwAAAAUAAAABMQEAAAAKMTkyMTUxODQyMwMAAAABMAIAAAAGMTAwMDMwBAAAAAEwBwAAAAoxMi8xMS8yMDE4CAAAAAoxMi8xMS8yMDE45xDBJ11A1wi3o/4nXUDXCDNDSVEuTkFTREFRR1M6QVRWSS5JUV9FQklUREEuSVFfTFRNLjIwMTktMDktMjMuLi5VU0QBAAAAF21AAAIAAAAEMjM2MgEIAAAABQAAAAExAQAAAAoxOTc1MDM5MDUyAwAAAAMxNjACAAAABDQwNTEEAAAAATAHAAAACTkvMjMvMjAxOQgAAAAJNi8zMC8yMDE5CQAAAAEw5xDBJ11A1whxaAMoXUDXCDhDSVEuTkFTREFRR1M6QVRWSS5JUV9SRVZFTlVFX0VTVC5DWTIwMjIuMjAxOS0wOS0yMy4uLlVTRAEAAAAXbUAAAgAAAAg4NDE5LjI3NQEOAAAABQAAAAIxMQEAAAABMAIAAAAKMTAwMTM5OTIxNQMAAAAGMTAwMTgwBAAAAAEyBgAAAAEwBwAAAAMxNjAIAAAAATAJAAAAATEKAAAAATALAAAACzExNTYzMzUwMjY2DAAAAAE3DQAAAAk5LzI0LzIwMTkQAAAACTkvMjMvMjAxOecQwSddQNcIAwYBKF1A1wgpQ0lRLklRVFI2MDU0MDAzNjQuSVFfVFJfSU1QTElFRF9FVl9FQklUREEBAAAALK0VJAIAAAAJMTQuOTI2MjY4AQYAAAAFAAAAAjU0AQAAAAYxMDIwOTQCAAAACTYwNTQwMDM2NAMAAAAJNjA1NDAwNjgxBAAAAAI1MAYAAAAFRmFsc2XnEMEnXUDXCGtB/CddQNcIKUNJUS5UU0U6Nzk3NC5JUV9D | P1: TE9TRVBSSUNFLjIwMTgtMTAtMDIuVVNEAQAAAKRdDQACAAAACTM3MS40MDA4OQDnEMEnXUDXCGtB/CddQNcILUNJUS5UU0U6Nzk3NC5JUV9DQVBFWC5DWTIwMTcuMjAxOS0wOS0yMy4uLlVTRAEAAACkXQ0AAwAAAAAAp5nKJ11A1whiygUoXUDXCClDSVEuVFNFOjc5NzQuSVFfQ0xPU0VQUklDRS4yMDE3LTA4LTIyLlVTRAEAAACkXQ0AAgAAAAozMjkuOTM0NjA2AOcQwSddQNcIt6P+J11A1wgpQ0lRLlRTRTo3OTc0LklRX0NMT1NFUFJJQ0UuMjAxNi0wMi0xNi5VU0QBAAAApF0NAAIAAAAKMTM5Ljk0Mzc0MQDnEMEnXUDXCAMGAShdQNcILkNJUS5LT1NFOkEyNTEyNzAuSVFfVEVWLjQzNDY1LjIwMTktMDktMjMuLi5VU0QBAAAAWe4vCQIAAAALNjU3Mi42Nzk0MDEBBgAAAAUAAAABMQEAAAAKMTkyNjIzNjAyOAMAAAADMTYwAgAAAAYxMDAwNjAEAAAAATAHAAAACjEyLzMxLzIwMTjnEMEnXUDXCGtB/CddQNcIMkNJUS5LT1NFOkEyNTEyNzAuSVFfRUJJVERBLklRX0xUTS4yMDE5LTA5LTIzLi4uVVNEAQAAAFnuLwkCAAAACjIzNi45NTIyNTYBCAAAAAUAAAABMQEAAAAKMTk4MTE3MDA1MgMAAAADMTYwAgAAAAQ0MDUxBAAAAAEwBwAAAAk5LzIzLzIwMTkIAAAACTYvMzAvMjAxOQkAAAABMOcQwSddQNcIa0H8J11A1wgyQ0lRLlRTRTo3OTc0LklRX0VCSVREQV9FU1QuQ1kyMDIxLjIwMTktMDktMjMuLi5VU0QB | Q1: AAAApF0NAAIAAAAQMzM5Ni41Mzg1NTg2NjI4OAEOAAAABQAAAAIxMQEAAAABMAIAAAAJNjUyOTE0MTgwAwAAAAYxMDAxODcEAAAAAjU2BgAAAAEwBwAAAAMxNjAIAAAAATAJAAAAATEKAAAAATALAAAACzExNjAzNTc0MDA0DAAAAAE3DQAAAAk5LzI0LzIwMTkQAAAACTkvMjMvMjAxOecQwSddQNcIt6P+J11A1wgvQ0lRLk5BU0RBUUdTOlRUV08uSVFfVEVWLjQzMTAwLjIwMTktMDktMjMuLi5VU0QBAAAAUaoFAAIAAAAJMTEzMDkuNjM2AQYAAAAFAAAAATEBAAAACjE4NjQ2NzkzMTcDAAAAAzE2MAIAAAAGMTAwMDYwBAAAAAEwBwAAAAoxMi8zMS8yMDE35xDBJ11A1wgDBgEoXUDXCCJDSVEuSVFUUjYwNTQwMDM2NC5JUV9UUl9TRUxMRVJOQU1FAQAAACytFSQDAAAAClZpdmVuZGkgU0EA5xDBJ11A1whxaAMoXUDXCCxDSVEuVFNFOjc5NzQuSVFfVEVWX0VCSVREQS5JUV9MVE0uMjAxNi0xMS0yOQEAAACkXQ0AAgAAAAk2Mi4wMzcwMzYBBwAAAAUAAAABMQEAAAAKMTgxODA2ODIyMQMAAAABMAIAAAAGMTAwMDMwBAAAAAEwBwAAAAoxMS8yOS8yMDE2CAAAAAoxMS8yOS8yMDE25xDBJ11A1whrQfwnXUDXCClDSVEuVFNFOjc5NzQuSVFfQ0xPU0VQUklDRS4yMDE2LTA5LTIwLlVTRAEAAACkXQ0AAgAAAAoyNjguNTQ0NDcyAOcQwSddQNcIt6P+J11A1wgqQ0lRLlRTRTo3OTc0LklRX1RFVi40MzQ2NS4yMDE5LTA5 | R1: LTIzLi4uVVNEAQAAAKRdDQACAAAADDI0Mjg3LjIxNjYzNAEGAAAABQAAAAExAQAAAAoxOTIxNTExNDE2AwAAAAMxNjACAAAABjEwMDA2MAQAAAABMAcAAAAKMTIvMzEvMjAxOOcQwSddQNcIYsoFKF1A1wgsQ0lRLlRTRTo3OTc0LklRX1RFVl9FQklUREEuSVFfTFRNLjIwMTYtMDItMDkBAAAApF0NAAIAAAAJMjIuNjk2MDk3AQcAAAAFAAAAATEBAAAACjE3NzQyODE2MjgDAAAAATACAAAABjEwMDAzMAQAAAABMAcAAAAIMi85LzIwMTYIAAAACDIvOS8yMDE25xDBJ11A1wgDBgEoXUDXCDNDSVEuVFNFOjk2ODQuSVFfUkVWRU5VRV9FU1QuQ1kyMDIyLjIwMTktMDktMjMuLi5VU0QBAAAAqX0NAAIAAAAQMjczOC42NjMxNTEyMDU0OAEOAAAABQAAAAIxMQEAAAABMAIAAAAJNzI2ODYzOTU3AwAAAAYxMDAxODAEAAAAAjU2BgAAAAEwBwAAAAMxNjAIAAAAATAJAAAAATEKAAAAATALAAAACzExNjA4ODA4MTkwDAAAAAE3DQAAAAk5LzI0LzIwMTkQAAAACTkvMjMvMjAxOecQwSddQNcIa0H8J11A1wg2Q0lRLk5BU0RBUUdTOkFUVkkuSVFfVE9UQUxfUkVWLkNZMjAxNS4yMDE5LTA5LTIzLi4uVVNEAQAAABdtQAACAAAABDQ2NjQBCAAAAAUAAAABMQEAAAAKMTg3Njc1NDg3NwMAAAADMTYwAgAAAAIyOAQAAAABMAcAAAAJOS8yMy8yMDE5CAAAAAoxMi8zMS8yMDE1CQAAAAEw5xDBJ11A1wgDBgEoXUDXCC5DSVEuVFNF | S1: Ojk2ODQuSVFfRUJJVERBLkNZMjAxOC4yMDE5LTA5LTIzLi4uVVNEAQAAAKl9DQACAAAACjE5OS4wNDA2OTYBCAAAAAUAAAABMQEAAAAKMTk0NDM4ODIyNAMAAAADMTYwAgAAAAQ0MDUxBAAAAAEwBwAAAAk5LzIzLzIwMTkIAAAACjEyLzMxLzIwMTgJAAAAATDnEMEnXUDXCGtB/CddQNcIKUNJUS5UU0U6Nzk3NC5JUV9DTE9TRVBSSUNFLjIwMTUtMDUtMjYuVVNEAQAAAKRdDQACAAAACjE3Mi41NTgwOTQA5xDBJ11A1whxaAMoXUDXCClDSVEuVFNFOjc5NzQuSVFfQ0xPU0VQUklDRS4yMDE2LTEyLTA2LlVTRAEAAACkXQ0AAgAAAAoyNDQuNTU4NTM4AOcQwSddQNcIcWgDKF1A1wguQ0lRLktPU0U6QTI1MTI3MC5JUV9URVYuNDM4MzAuMjAxOS0wOS0yMy4uLlVTRAEAAABZ7i8JAgAAAAs1MjI4LjYyMjk2OQEGAAAABQAAAAExAQAAAAoxOTgxMTU2NTQwAwAAAAMxNjACAAAABjEwMDA2MAQAAAABMAcAAAAJOS8yMy8yMDE55xDBJ11A1wgDBgEoXUDXCClDSVEuVFNFOjc5NzQuSVFfQ0xPU0VQUklDRS4yMDE5LTA3LTE2LlVTRAEAAACkXQ0AAgAAAAozODQuMjQ2MDA1AKeZyiddQNcIcWgDKF1A1wgsQ0lRLlRTRTo3OTc0LklRX1RFVl9FQklUREEuSVFfTFRNLjIwMTYtMTAtMTEBAAAApF0NAAIAAAAJNjIuMzc1NTk4AQcAAAAFAAAAATEBAAAACjE4MDI3NzY3NzUDAAAAATACAAAABjEwMDAzMAQAAAABMAcAAAAK | T1: MTAvMTEvMjAxNggAAAAKMTAvMTEvMjAxNucQwSddQNcIYsoFKF1A1wgpQ0lRLlRTRTo3OTc0LklRX0NMT1NFUFJJQ0UuMjAxOS0wNS0yOC5VU0QBAAAApF0NAAIAAAAKMzU3LjIxNzg3MwDnEMEnXUDXCLej/iddQNcILENJUS5UU0U6Nzk3NC5JUV9URVZfRUJJVERBLklRX0xUTS4yMDE2LTEyLTI3AQAAAKRdDQACAAAACTUxLjc2NDQwMwEHAAAABQAAAAExAQAAAAoxODE4MDY4MjIxAwAAAAEwAgAAAAYxMDAwMzAEAAAAATAHAAAACjEyLzI3LzIwMTYIAAAACjEyLzI3LzIwMTbnEMEnXUDXCGtB/CddQNcINkNJUS5OQVNEQVFHUzpBVFZJLklRX1RPVEFMX1JFVi5DWTIwMTguMjAxOS0wOS0yMy4uLlVTRAEAAAAXbUAAAgAAAAQ3NTAwAQgAAAAFAAAAATEBAAAACjE5NDc4Mjg3NjkDAAAAAzE2MAIAAAACMjgEAAAAATAHAAAACTkvMjMvMjAxOQgAAAAKMTIvMzEvMjAxOAkAAAABMOcQwSddQNcIcWgDKF1A1wgpQ0lRLklRVFIyMzMzNzg0MzkuSVFfVFJfSU1QTElFRF9FVl9FQklUREEBAAAAhxLpDQIAAAAJMzQuNDUwMDg2AQYAAAAFAAAAAjU0AQAAAAYxMDIwOTQCAAAACTIzMzM3ODQzOQMAAAAJMjMzMzc4NzgxBAAAAAI3OQYAAAAFRmFsc2XnEMEnXUDXCGtB/CddQNcIKUNJUS5UU0U6Nzk3NC5JUV9DTE9TRVBSSUNFLjIwMTUtMDktMTUuVVNEAQAAAKRdDQACAAAACjE4OC4xNjI4NjQA5xDBJ11A1whxaAMo | U1: XUDXCClDSVEuVFNFOjc5NzQuSVFfQ0xPU0VQUklDRS4yMDE3LTA1LTE2LlVTRAEAAACkXQ0AAgAAAAoyNjUuMTI4Mzk0AOcQwSddQNcIa0H8J11A1wg2Q0lRLk5BU0RBUUdTOkFUVkkuSVFfVE9UQUxfUkVWLkNZMjAxNi4yMDE5LTA5LTIzLi4uVVNEAQAAABdtQAACAAAABDY2MDgBCAAAAAUAAAABMQEAAAAKMTk0NzgyODc1NAMAAAADMTYwAgAAAAIyOAQAAAABMAcAAAAJOS8yMy8yMDE5CAAAAAoxMi8zMS8yMDE2CQAAAAEw5xDBJ11A1whxaAMoXUDXCDdDSVEuVFNFOjc5NzQuSVFfQ0FTSF9BQ1FVSVJFX0NGLklRX0xUTS4yMDE5LTA5LTIzLi4uVVNEAQAAAKRdDQADAAAAAACnmconXUDXCGLKBShdQNcIKUNJUS5UU0U6Nzk3NC5JUV9DTE9TRVBSSUNFLjIwMTgtMDgtMjguVVNEAQAAAKRdDQACAAAACjM0Ny45NzA4MzUA5xDBJ11A1wgDBgEoXUDXCCxDSVEuVFNFOjc5NzQuSVFfVEVWX0VCSVREQS5JUV9MVE0uMjAxNi0wNy0yNgEAAACkXQ0AAgAAAAk0My44MzMyNTMBBwAAAAUAAAABMQEAAAAKMTc5OTI0OTA1NwMAAAABMAIAAAAGMTAwMDMwBAAAAAEwBwAAAAk3LzI2LzIwMTYIAAAACTcvMjYvMjAxNucQwSddQNcIAwYBKF1A1wgqQ0lRLlRTRTo3OTc0LklRX1RFVi40NDU2MS4yMDE5LTA5LTIzLi4uVVNEAQAAAKRdDQACAAAADDM4ODcxLjMyOTE0MQEGAAAABQAAAAExAQAAAAoxOTc1Nzg3MDg2AwAA | V1: AAMxNjACAAAABjEwMDA2MAQAAAABMAcAAAAJOS8yMC8yMDE55xDBJ11A1wi3o/4nXUDXCCxDSVEuRU5YVFBBOlVCSS5JUV9URVYuNDI3MzUuMjAxOS0wOS0yMy4uLlVTRAEAAAAZdg0AAgAAAAszOTUwLjIyNjA5NgEGAAAABQAAAAExAQAAAAoxODE5NzQyMzQ5AwAAAAMxNjACAAAABjEwMDA2MAQAAAABMAcAAAAKMTIvMzEvMjAxNucQwSddQNcIcWgDKF1A1wgqQ0lRLlRTRTo3OTc0LklRX1RFVi40NDE5Ni4yMDE5LTA5LTIzLi4uVVNEAQAAAKRdDQACAAAADDM4ODcxLjMyOTE0MQEGAAAABQAAAAExAQAAAAoxOTc1Nzg3MDg2AwAAAAMxNjACAAAABjEwMDA2MAQAAAABMAcAAAAJOS8yMC8yMDE55xDBJ11A1wi3o/4nXUDXCCxDSVEuVFNFOjc5NzQuSVFfVEVWX0VCSVREQS5JUV9MVE0uMjAxNy0wOC0wOAEAAACkXQ0AAgAAAAk0NC4xMTEzOTcBBwAAAAUAAAABMQEAAAAKMTg1MDM3ODU5OQMAAAABMAIAAAAGMTAwMDMwBAAAAAEwBwAAAAg4LzgvMjAxNwgAAAAIOC84LzIwMTfnEMEnXUDXCGtB/CddQNcIKUNJUS5UU0U6Nzk3NC5JUV9DTE9TRVBSSUNFLjIwMTktMDktMjMuVVNEAQAAAKRdDQACAAAACjM5Ni44MDU1NTkA5xDBJ11A1whiygUoXUDXCCxDSVEuVFNFOjc5NzQuSVFfVEVWX0VCSVREQS5JUV9MVE0uMjAxOS0wMy0xOQEAAACkXQ0AAgAAAAkxMC44NDYwMDgBBwAAAAUAAAABMQEAAAAKMTk0NDU5 | W1: NzY1OAMAAAABMAIAAAAGMTAwMDMwBAAAAAEwBwAAAAkzLzE5LzIwMTkIAAAACTMvMTkvMjAxOecQwSddQNcIa0H8J11A1wgpQ0lRLlRTRTo3OTc0LklRX0NMT1NFUFJJQ0UuMjAxOC0wNy0yNC5VU0QBAAAApF0NAAIAAAAKMzMzLjAwMzYwNgDnEMEnXUDXCLej/iddQNcIM0NJUS5UU0U6Nzk3NC5JUV9SRVZFTlVFX0VTVC5DWTIwMjIuMjAxOS0wOS0yMy4uLlVTRAEAAACkXQ0AAgAAABAxMDkwMy45NTYxOTc3OTY4AQ4AAAAFAAAAAjExAQAAAAEwAgAAAAk2NTI5MTQxODEDAAAABjEwMDE4MAQAAAACNTYGAAAAATAHAAAAAzE2MAgAAAABMAkAAAABMQoAAAABMAsAAAALMTE2MTA4MjYyMjAMAAAAATcNAAAACTkvMjQvMjAxORAAAAAJOS8yMy8yMDE55xDBJ11A1whxaAMoXUDXCCxDSVEuVFNFOjc5NzQuSVFfVEVWX0VCSVREQS5JUV9MVE0uMjAxOS0wNy0xNgEAAACkXQ0AAgAAAAkxNC41NzA1MzMBBwAAAAUAAAABMQEAAAAKMTk3MDIyMDUxNQMAAAABMAIAAAAGMTAwMDMwBAAAAAEwBwAAAAk3LzE2LzIwMTkIAAAACTcvMTYvMjAxOaeZyiddQNcIYsoFKF1A1wgpQ0lRLlRTRTo3OTc0LklRX0NMT1NFUFJJQ0UuMjAxNy0xMC0yNC5VU0QBAAAApF0NAAIAAAAKMzg3LjEzMDc0OADnEMEnXUDXCAMGAShdQNcILENJUS5UU0U6Nzk3NC5JUV9URVZfRUJJVERBLklRX0xUTS4yMDE1LTA4LTExAQAAAKRdDQACAAAA | X1: CTQ3LjE0ODE2NwEHAAAABQAAAAExAQAAAAoxNzQ5ODU3MDk3AwAAAAEwAgAAAAYxMDAwMzAEAAAAATAHAAAACTgvMTEvMjAxNQgAAAAJOC8xMS8yMDE15xDBJ11A1whrQfwnXUDXCDNDSVEuTkFTREFRR1M6QVRWSS5JUV9FQklUREEuQ1kyMDE3LjIwMTktMDktMjMuLi5VU0QBAAAAF21AAAIAAAAEMjIyNwEIAAAABQAAAAExAQAAAAoxOTQ3ODI4NzYwAwAAAAMxNjACAAAABDQwNTEEAAAAATAHAAAACTkvMjMvMjAxOQgAAAAKMTIvMzEvMjAxNwkAAAABMOcQwSddQNcIAwYBKF1A1wgtQ0lRLktPU0U6QTI1MTI3MC5JUV9DTE9TRVBSSUNFLjIwMTktMDktMjMuVVNEAQAAAFnuLwkCAAAACTgxLjg1NjgzMwDnEMEnXUDXCLej/iddQNcIKUNJUS5UU0U6Nzk3NC5JUV9DTE9TRVBSSUNFLjIwMTctMDctMTEuVVNEAQAAAKRdDQACAAAACjMxNi4wMjQ3MTkA5xDBJ11A1whrQfwnXUDXCC9DSVEuTkFTREFRR1M6VFRXTy5JUV9HUC5DWTIwMTcuMjAxOS0wOS0yMy4uLlVTRAEAAABRqgUAAgAAAAc4OTEuOTc1AQgAAAAFAAAAATEBAAAACjE5NDM5MjUyMzQDAAAAAzE2MAIAAAACMTAEAAAAATAHAAAACTkvMjMvMjAxOQgAAAAKMTIvMzEvMjAxNwkAAAABMOcQwSddQNcIcWgDKF1A1wgqQ0lRLlRTRTo3OTc0LklRX1RFVi40MzgzMC4yMDE5LTA5LTIzLi4uVVNEAQAAAKRdDQACAAAADDM4ODcxLjMyOTE0MQEGAAAABQAA | Y1: AAExAQAAAAoxOTc1Nzg3MDg2AwAAAAMxNjACAAAABjEwMDA2MAQAAAABMAcAAAAJOS8yMC8yMDE55xDBJ11A1whiygUoXUDXCCxDSVEuS09TRTpBMjUxMjcwLklRX01BUktFVENBUC4yMDE5LTA5LTIzLlVTRAEAAABZ7i8JAgAAAAs2ODY0LjM1NDMzOAEGAAAABQAAAAExAQAAAAoxOTgxMTU2NTQwAwAAAAMxNjACAAAABjEwMDA1NAQAAAABMAcAAAAJOS8yMy8yMDE55xDBJ11A1whrQfwnXUDXCCxDSVEuVFNFOjc5NzQuSVFfVEVWX0VCSVREQS5JUV9MVE0uMjAxNi0xMi0wNgEAAACkXQ0AAgAAAAk2MS42NjMyMTQBBwAAAAUAAAABMQEAAAAKMTgxODA2ODIyMQMAAAABMAIAAAAGMTAwMDMwBAAAAAEwBwAAAAkxMi82LzIwMTYIAAAACTEyLzYvMjAxNucQwSddQNcIYsoFKF1A1wgsQ0lRLlRTRTo3OTc0LklRX1RFVl9FQklUREEuSVFfTFRNLjIwMTUtMTAtMDYBAAAApF0NAAIAAAAJMzguMzM3MDQ4AQcAAAAFAAAAATEBAAAACjE3NDk4NTcwOTcDAAAAATACAAAABjEwMDAzMAQAAAABMAcAAAAJMTAvNi8yMDE1CAAAAAkxMC82LzIwMTXnEMEnXUDXCGtB/CddQNcIKUNJUS5UU0U6Nzk3NC5JUV9DTE9TRVBSSUNFLjIwMTctMDMtMjEuVVNEAQAAAKRdDQACAAAACjIzNC41Mjk4NzcA5xDBJ11A1whrQfwnXUDXCCxDSVEuVFNFOjc5NzQuSVFfVEVWX0VCSVREQS5JUV9MVE0uMjAxNy0wNy0xOAEAAACkXQ0AAgAA | Z1: AAg1OS4yODgyMgEHAAAABQAAAAExAQAAAAoxODQ5MDMzMTM4AwAAAAEwAgAAAAYxMDAwMzAEAAAAATAHAAAACTcvMTgvMjAxNwgAAAAJNy8xOC8yMDE35xDBJ11A1whiygUoXUDXCCxDSVEuVFNFOjc5NzQuSVFfVEVWX0VCSVREQS5JUV9MVE0uMjAxNy0xMS0wNwEAAACkXQ0AAgAAAAk0Mi44MzMyMDIBBwAAAAUAAAABMQEAAAAKMTg2MzA3Njc5NAMAAAABMAIAAAAGMTAwMDMwBAAAAAEwBwAAAAkxMS83LzIwMTcIAAAACTExLzcvMjAxN+cQwSddQNcIcWgDKF1A1wgUQ0lRLi5JUV9DT01QQU5ZX05BTUUFAAAAAAAAAAgAAAAUKEludmFsaWQgSWRlbnRpZmllcinnEMEnXUDXCGLKBShdQNcIL0NJUS5OQVNEQVFHUzpUVFdPLklRX1RFVi40NDkyNi4yMDE5LTA5LTIzLi4uVVNEAQAAAFGqBQACAAAACzEyMDcxLjQ3MTUyAQYAAAAFAAAAATEBAAAACjE5NzQzMDI0ODgDAAAAAzE2MAIAAAAGMTAwMDYwBAAAAAEwBwAAAAk5LzIzLzIwMTnnEMEnXUDXCLej/iddQNcINUNJUS5FTlhUUEE6VUJJLklRX1JFVkVOVUVfRVNULkNZMjAyMC4yMDE5LTA5LTIzLi4uVVNEAQAAABl2DQACAAAADzMwMzUuMTg4MDM1NzQ1NAEOAAAABQAAAAIxMQEAAAABMAIAAAAINDc1MTQ3MTcDAAAABjEwMDE4MAQAAAABMwYAAAABMAcAAAADMTYwCAAAAAEwCQAAAAExCgAAAAEwCwAAAAsxMTU0NjM4MzEyMQwAAAABNw0AAAAJOS8yNC8y | AA1: MDE5EAAAAAk5LzIzLzIwMTnnEMEnXUDXCAMGAShdQNcIM0NJUS5UU0U6Nzk3NC5JUV9SRVZFTlVFX0VTVC5DWTIwMTkuMjAxOS0wOS0yMy4uLlVTRAEAAACkXQ0AAgAAABAxMTMwMC4wMzA1OTgwNDQzAQ4AAAAFAAAAAjExAQAAAAEwAgAAAAgxMDc2ODY0OQMAAAAGMTAwMTgwBAAAAAI1NgYAAAABMAcAAAADMTYwCAAAAAEwCQAAAAExCgAAAAEwCwAAAAsxMTYwMzQ0NTIxNAwAAAABNw0AAAAJOS8yNC8yMDE5EAAAAAk5LzIzLzIwMTnnEMEnXUDXCLej/iddQNcIL0NJUS5UU0U6MzY1OS5JUV9QRV9FWENMLklRX0xUTS4yMDE5LTA5LTIzLi4uVVNEAQAAAJ4fgggCAAAACTEyLjU4MDU0NQEHAAAABQAAAAExAQAAAAoxOTc1NzkyNDM3AwAAAAEwAgAAAAYxMDAwMjcEAAAAATAHAAAACTkvMjAvMjAxOQgAAAAJOS8yMC8yMDE55xDBJ11A1wgDBgEoXUDXCClDSVEuVFNFOjc5NzQuSVFfQ0xPU0VQUklDRS4yMDE4LTEwLTE2LlVTRAEAAACkXQ0AAgAAAAozNTIuNDExNTMxAOcQwSddQNcIt6P+J11A1wgpQ0lRLlRTRTo3OTc0LklRX0NMT1NFUFJJQ0UuMjAxOC0wMS0wOS5VU0QBAAAApF0NAAIAAAAJMzgzLjM5ODUxAOcQwSddQNcIt6P+J11A1wgqQ0lRLlRTRTo3OTc0LklRX0dQLkNZMjAxNS4yMDE5LTA5LTIzLi4uVVNEAQAAAKRdDQACAAAACzE4NzEuMzgxMTMyAQgAAAAFAAAAATEBAAAACjE3NzY1ODQwNDMD | AB1: AAAAAzE2MAIAAAACMTAEAAAAATAHAAAACTkvMjMvMjAxOQgAAAAKMTIvMzEvMjAxNQkAAAABMOcQwSddQNcIcWgDKF1A1wgpQ0lRLlRTRTo3OTc0LklRX0NMT1NFUFJJQ0UuMjAxNy0xMC0xNy5VU0QBAAAApF0NAAIAAAAKMzg5LjA2Njk1NgDnEMEnXUDXCLej/iddQNcIL0NJUS5OQVNEQVFHUzpUVFdPLklRX1RFVi40MzgzMC4yMDE5LTA5LTIzLi4uVVNEAQAAAFGqBQACAAAACzEyMDcxLjQ3MTUyAQYAAAAFAAAAATEBAAAACjE5NzQzMDI0ODgDAAAAAzE2MAIAAAAGMTAwMDYwBAAAAAEwBwAAAAk5LzIzLzIwMTnnEMEnXUDXCGLKBShdQNcILENJUS5UU0U6Nzk3NC5JUV9URVZfRUJJVERBLklRX0xUTS4yMDE3LTAxLTI0AQAAAKRdDQACAAAACTQ3LjkwNjU1OAEHAAAABQAAAAExAQAAAAoxODE4MDY4MjIxAwAAAAEwAgAAAAYxMDAwMzAEAAAAATAHAAAACTEvMjQvMjAxNwgAAAAJMS8yNC8yMDE35xDBJ11A1whrQfwnXUDXCCxDSVEuVFNFOjc5NzQuSVFfVEVWX0VCSVREQS5JUV9MVE0uMjAxNy0wNS0xNgEAAACkXQ0AAgAAAAk0NS44MDUwMDgBBwAAAAUAAAABMQEAAAAKMTgzODIwNDA3NAMAAAABMAIAAAAGMTAwMDMwBAAAAAEwBwAAAAk1LzE2LzIwMTcIAAAACTUvMTYvMjAxN+cQwSddQNcIa0H8J11A1wgpQ0lRLlRTRTo3OTc0LklRX0NMT1NFUFJJQ0UuMjAxNS0wNy0yOC5VU0QBAAAApF0NAAIAAAAK | AC1: MTY3Ljc2NjIyMgDnEMEnXUDXCLej/iddQNcIN0NJUS5UU0U6Nzk3NC5JUV9FRkZFQ1RfVEFYX1JBVEUuQ1kyMDE3LjIwMTktMDktMjMuLi5VU0QBAAAApF0NAAIAAAAHMzEuMDk3MwEIAAAABQAAAAExAQAAAAoxODc0MTkzMzQwAwAAAAI3OQIAAAAENDM3NgQAAAABMAcAAAAJOS8yMy8yMDE5CAAAAAoxMi8zMS8yMDE3CQAAAAEwp5nKJ11A1whiygUoXUDXCDJDSVEuVFNFOjc5NzQuSVFfRUJJVERBX0VTVC5DWTIwMjIuMjAxOS0wOS0yMy4uLlVTRAEAAACkXQ0AAgAAABAzNTAxLjE5NDU1NTYyNDM2AQ4AAAAFAAAAAjExAQAAAAEwAgAAAAk2NTI5MTQxODEDAAAABjEwMDE4NwQAAAACNTYGAAAAATAHAAAAAzE2MAgAAAABMAkAAAABMQoAAAABMAsAAAALMTE1OTkwNTIyMzUMAAAAATcNAAAACTkvMjQvMjAxORAAAAAJOS8yMy8yMDE55xDBJ11A1wi3o/4nXUDXCCpDSVEuVFNFOjM2NTkuSVFfVEVWLjQzODMwLjIwMTktMDktMjMuLi5VU0QBAAAAnh+CCAIAAAALNzAxMS4zMDQwMDYBBgAAAAUAAAABMQEAAAAKMTk3NTc4NjYyMgMAAAADMTYwAgAAAAYxMDAwNjAEAAAAATAHAAAACTkvMjAvMjAxOecQwSddQNcIa0H8J11A1wgsQ0lRLlRTRTo3OTc0LklRX1RFVl9FQklUREEuSVFfTFRNLjIwMTktMDQtMjMBAAAApF0NAAIAAAAJMTMuNDczNTM2AQcAAAAFAAAAATEBAAAACjE5NDQ1OTc2NTgDAAAAATACAAAA | AD1: BjEwMDAzMAQAAAABMAcAAAAJNC8yMy8yMDE5CAAAAAk0LzIzLzIwMTnnEMEnXUDXCGLKBShdQNcILENJUS5UU0U6Nzk3NC5JUV9URVZfRUJJVERBLklRX0xUTS4yMDE2LTAzLTI5AQAAAKRdDQACAAAACTI1LjMzMTg1MgEHAAAABQAAAAExAQAAAAoxNzc2NTg0MDQzAwAAAAEwAgAAAAYxMDAwMzAEAAAAATAHAAAACTMvMjkvMjAxNggAAAAJMy8yOS8yMDE25xDBJ11A1whiygUoXUDXCClDSVEuVFNFOjc5NzQuSVFfQ0xPU0VQUklDRS4yMDE1LTA2LTIzLlVTRAEAAACkXQ0AAgAAAAoxNjkuMzA2NjA4AOcQwSddQNcIcWgDKF1A1wgqQ0lRLlRTRTozNjU5LklRX0dQLkNZMjAxNy4yMDE5LTA5LTIzLi4uVVNEAQAAAJ4fgggCAAAACzE1ODIuNzQ5NTg4AQgAAAAFAAAAATEBAAAACjE4ODE0Mzg3MTQDAAAAAzE2MAIAAAACMTAEAAAAATAHAAAACTkvMjMvMjAxOQgAAAAKMTIvMzEvMjAxNwkAAAABMOcQwSddQNcIa0H8J11A1wgsQ0lRLlRTRTo3OTc0LklRX1RFVl9FQklUREEuSVFfTFRNLjIwMTgtMDMtMjABAAAApF0NAAIAAAAJMjYuNzA1MDEyAQcAAAAFAAAAATEBAAAACjE4NzQxOTMzNDADAAAAATACAAAABjEwMDAzMAQAAAABMAcAAAAJMy8yMC8yMDE4CAAAAAkzLzIwLzIwMTjnEMEnXUDXCGtB/CddQNcILENJUS5UU0U6Nzk3NC5JUV9URVZfRUJJVERBLklRX0xUTS4yMDE3LTEwLTE3AQAAAKRdDQACAAAA | AE1: CTUyLjExNjYxOQEHAAAABQAAAAExAQAAAAoxODU0MDQzODg4AwAAAAEwAgAAAAYxMDAwMzAEAAAAATAHAAAACjEwLzE3LzIwMTcIAAAACjEwLzE3LzIwMTfnEMEnXUDXCLej/iddQNcILENJUS5UU0U6Nzk3NC5JUV9URVZfRUJJVERBLklRX0xUTS4yMDE1LTExLTEwAQAAAKRdDQACAAAACTM2Ljk0ODMwNgEHAAAABQAAAAExAQAAAAoxNzYxNTE0MzM2AwAAAAEwAgAAAAYxMDAwMzAEAAAAATAHAAAACjExLzEwLzIwMTUIAAAACjExLzEwLzIwMTXnEMEnXUDXCGLKBShdQNcILENJUS5FTlhUUEE6VUJJLklRX1RFVi40MjM2OS4yMDE5LTA5LTIzLi4uVVNEAQAAABl2DQACAAAACjMzMjkuODk0MDQBBgAAAAUAAAABMQEAAAAKMTc2NDA4NTUwMQMAAAADMTYwAgAAAAYxMDAwNjAEAAAAATAHAAAACjEyLzMxLzIwMTXnEMEnXUDXCHFoAyhdQNcILENJUS5UU0U6Nzk3NC5JUV9URVZfRUJJVERBLklRX0xUTS4yMDE4LTAxLTAyAQAAAKRdDQACAAAACTQwLjQ1MTI0NAEHAAAABQAAAAExAQAAAAoxODY1NzkyMzYzAwAAAAEwAgAAAAYxMDAwMzAEAAAAATAHAAAACjEyLzI5LzIwMTcIAAAACjEyLzI5LzIwMTfnEMEnXUDXCGLKBShdQNcIL0NJUS5OQVNEQVFHUzpBVFZJLklRX0dQLklRX0xUTS4yMDE5LTA5LTIzLi4uVVNEAQAAABdtQAACAAAABDQ3NzMBCAAAAAUAAAABMQEAAAAKMTk3NTAzOTA1MgMAAAADMTYwAgAA | AF1: AAIxMAQAAAABMAcAAAAJOS8yMy8yMDE5CAAAAAk2LzMwLzIwMTkJAAAAATDnEMEnXUDXCGtB/CddQNcINENJUS5OQVNEQVFHUzpBVFZJLklRX1BFX0VYQ0wuSVFfTFRNLjIwMTktMDktMjMuLi5VU0QBAAAAF21AAAIAAAAJMjQuNzM3Mzg3AQcAAAAFAAAAATEBAAAACjE5NzUwMzkwNTIDAAAAATACAAAABjEwMDAyNwQAAAABMAcAAAAJOS8yMy8yMDE5CAAAAAk5LzIzLzIwMTnnEMEnXUDXCLej/iddQNcILENJUS5UU0U6Nzk3NC5JUV9URVZfRUJJVERBLklRX0xUTS4yMDE2LTAxLTEyAQAAAKRdDQACAAAACTE5LjU3NTE1OAEHAAAABQAAAAExAQAAAAoxNzY1MTUzNjcxAwAAAAEwAgAAAAYxMDAwMzAEAAAAATAHAAAACTEvMTIvMjAxNggAAAAJMS8xMi8yMDE25xDBJ11A1wgDBgEoXUDXCClDSVEuVFNFOjc5NzQuSVFfQ0xPU0VQUklDRS4yMDE1LTA2LTAyLlVTRAEAAACkXQ0AAgAAAAkxNjkuODEyODMA5xDBJ11A1wi3o/4nXUDXCCJDSVEuSVFUUjYwNTQwMDM2NC5JUV9UUl9UT1RBTFZBTFVFAQAAACytFSQCAAAAAzQyOQEGAAAABQAAAAI1NAEAAAAGMTAwNTA0AgAAAAk2MDU0MDAzNjQDAAAACTYwNTQwMDM2NAQAAAACNTAGAAAABUZhbHNl5xDBJ11A1whrQfwnXUDXCCRDSVEuRU5YVFBBOlVCSS5JUV9URVYuMjAxOS0wOS0yMy5VU0QBAAAAGXYNAAIAAAALODc2OS42NTkxMDgBBgAAAAUAAAABMQEAAAAK | AG1: MTk2ODQ2Mjg2OQMAAAADMTYwAgAAAAYxMDAwNjAEAAAAATAHAAAACTkvMjMvMjAxOecQwSddQNcIt6P+J11A1wg3Q0lRLlRTRTo3OTc0LklRX0NBU0hfQUNRVUlSRV9DRi5DWTIwMTguMjAxOS0wOS0yMy4uLlVTRAEAAACkXQ0AAwAAAAAAp5nKJ11A1whiygUoXUDXCCxDSVEuVFNFOjc5NzQuSVFfVEVWX0VCSVREQS5JUV9MVE0uMjAxOS0wOC0xMwEAAACkXQ0AAgAAAAkxMy45Mzg2OTQBBwAAAAUAAAABMQEAAAAKMTk3NTc5MjQ3MAMAAAABMAIAAAAGMTAwMDMwBAAAAAEwBwAAAAk4LzEzLzIwMTkIAAAACTgvMTMvMjAxOaeZyiddQNcIcWgDKF1A1wgpQ0lRLlRTRTo3OTc0LklRX0NMT1NFUFJJQ0UuMjAxOS0wMy0yNi5VU0QBAAAApF0NAAIAAAAKMjg4LjYwOTQxMgDnEMEnXUDXCHFoAyhdQNcILENJUS5UU0U6Nzk3NC5JUV9URVZfRUJJVERBLklRX0xUTS4yMDE4LTA4LTE0AQAAAKRdDQACAAAACTE2Ljc5NTMyOQEHAAAABQAAAAExAQAAAAoxOTAwMjcyNzk2AwAAAAEwAgAAAAYxMDAwMzAEAAAAATAHAAAACTgvMTQvMjAxOAgAAAAJOC8xNC8yMDE45xDBJ11A1whiygUoXUDXCCxDSVEuVFNFOjc5NzQuSVFfVEVWX0VCSVREQS5JUV9MVE0uMjAxNy0wMi0wNwEAAACkXQ0AAgAAAAk0Mi44MjA2NTgBBwAAAAUAAAABMQEAAAAKMTgyNTkyMjA3MgMAAAABMAIAAAAGMTAwMDMwBAAAAAEwBwAAAAgyLzcvMjAx | AH1: NwgAAAAIMi83LzIwMTfnEMEnXUDXCLej/iddQNcILENJUS5UU0U6Nzk3NC5JUV9URVZfRUJJVERBLklRX0xUTS4yMDE2LTA0LTE5AQAAAKRdDQACAAAACTI1Ljg3ODEyMgEHAAAABQAAAAExAQAAAAoxNzc2NTg0MDQzAwAAAAEwAgAAAAYxMDAwMzAEAAAAATAHAAAACTQvMTkvMjAxNggAAAAJNC8xOS8yMDE25xDBJ11A1whrQfwnXUDXCDdDSVEuTkFTREFRR1M6VFRXTy5JUV9FQklUREFfRVNULkNZMjAxOS4yMDE5LTA5LTIzLi4uVVNEAQAAAFGqBQACAAAACDY3MC40OTM3AQ4AAAAFAAAAAjExAQAAAAEwAgAAAAcxMDg1NzU3AwAAAAYxMDAxODcEAAAAATIGAAAAATAHAAAAAzE2MAgAAAABMAkAAAABMQoAAAABMAsAAAALMTE2MTEzNzcxMjMMAAAAATcNAAAACTkvMjQvMjAxORAAAAAJOS8yMy8yMDE55xDBJ11A1whxaAMoXUDXCClDSVEuVFNFOjc5NzQuSVFfQ0xPU0VQUklDRS4yMDE1LTExLTAzLlVTRAEAAACkXQ0AAwAAAAAA5xDBJ11A1wgDBgEoXUDXCDNDSVEuRU5YVFBBOlVCSS5JUV9UT1RBTF9SRVYuQ1kyMDE4LjIwMTktMDktMjMuLi5VU0QBAAAAGXYNAAIAAAALMjIyMC4xODc3NzIBCAAAAAUAAAABMQEAAAAKMTk2ODQ2MjkwMAMAAAADMTYwAgAAAAIyOAQAAAABMAcAAAAJOS8yMy8yMDE5CAAAAAoxMi8zMS8yMDE4CQAAAAEw5xDBJ11A1whrQfwnXUDXCDdDSVEuTkFTREFRR1M6QVRWSS5JUV9F | AI1: QklUREFfRVNULkNZMjAyMS4yMDE5LTA5LTIzLi4uVVNEAQAAABdtQAACAAAACDI5MzcuNTYxAQ4AAAAFAAAAAjExAQAAAAEwAgAAAAoxMDAxMzQ2MjczAwAAAAYxMDAxODcEAAAAATIGAAAAATAHAAAAAzE2MAgAAAABMAkAAAABMQoAAAABMAsAAAALMTE2MTAwMTIzOTQMAAAAATcNAAAACTkvMjQvMjAxORAAAAAJOS8yMy8yMDE55xDBJ11A1whrQfwnXUDXCDlDSVEuS09TRTpBMjUxMjcwLklRX0NBU0hfSU5URVJFU1QuSVFfTFRNLjIwMTktMDktMjMuLi5VU0QBAAAAWe4vCQIAAAAIMy44NTI4NzYBCAAAAAUAAAABMQEAAAAKMTk4MTE3MDA1MgMAAAADMTYwAgAAAAQzMDI4BAAAAAEwBwAAAAk5LzIzLzIwMTkIAAAACTYvMzAvMjAxOQkAAAABMKeZyiddQNcIAwYBKF1A1wgsQ0lRLlRTRTo3OTc0LklRX1RFVl9FQklUREEuSVFfTFRNLjIwMTctMDMtMDcBAAAApF0NAAIAAAAJNDUuMTQxMjYxAQcAAAAFAAAAATEBAAAACjE4Mjc3Njc3OTcDAAAAATACAAAABjEwMDAzMAQAAAABMAcAAAAIMy83LzIwMTcIAAAACDMvNy8yMDE35xDBJ11A1wi3o/4nXUDXCClDSVEuVFNFOjc5NzQuSVFfQ0xPU0VQUklDRS4yMDE3LTA2LTA2LlVTRAEAAACkXQ0AAgAAAAozMTYuOTIxMzk3AOcQwSddQNcIAwYBKF1A1wgzQ0lRLlRTRTo3OTc0LklRX1JFVkVOVUVfRVNULkNZMjAyMC4yMDE5LTA5LTIzLi4uVVNEAQAAAKRdDQAC | AJ1: AAAAEDEyMzg1LjE1OTIwNzQ1ODkBDgAAAAUAAAACMTEBAAAAATACAAAACTY1MjkxNDE3OQMAAAAGMTAwMTgwBAAAAAI1NgYAAAABMAcAAAADMTYwCAAAAAEwCQAAAAExCgAAAAEwCwAAAAsxMTYwMzQ0NDk5NAwAAAABNw0AAAAJOS8yNC8yMDE5EAAAAAk5LzIzLzIwMTnnEMEnXUDXCLej/iddQNcIM0NJUS5UU0U6MzY1OS5JUV9SRVZFTlVFX0VTVC5DWTIwMjIuMjAxOS0wOS0yMy4uLlVTRAEAAACeH4IIAgAAAA4yNjYxLjg5MzIyOTYzOQEOAAAABQAAAAIxMQEAAAABMAIAAAAKMTAwMTY0OTQ2MwMAAAAGMTAwMTgwBAAAAAEzBgAAAAEwBwAAAAMxNjAIAAAAATAJAAAAATEKAAAAATALAAAACzExNTk2OTczMTA5DAAAAAE3DQAAAAk5LzI0LzIwMTkQAAAACTkvMjMvMjAxOecQwSddQNcIcWgDKF1A1wgyQ0lRLktPU0U6QTI1MTI3MC5JUV9FQklUREEuQ1kyMDE4LjIwMTktMDktMjMuLi5VU0QBAAAAWe4vCQIAAAAKMjg4LjU3OTc2MwEIAAAABQAAAAExAQAAAAoxOTUwOTM2NTM4AwAAAAMxNjACAAAABDQwNTEEAAAAATAHAAAACTkvMjMvMjAxOQgAAAAKMTIvMzEvMjAxOAkAAAABMOcQwSddQNcIa0H8J11A1wgpQ0lRLlRTRTo3OTc0LklRX0NMT1NFUFJJQ0UuMjAxNy0wMy0xNC5VU0QBAAAApF0NAAIAAAAKMjE3LjI0NzA4OADnEMEnXUDXCAMGAShdQNcIMkNJUS5UU0U6OTY4NC5JUV9FQklUREFfRVNULkNZ | AK1: MjAyMi4yMDE5LTA5LTIzLi4uVVNEAQAAAKl9DQACAAAAEDQ1MC4zNDc0NjM4NDA1MTkBDgAAAAUAAAACMTEBAAAAATACAAAACTcyNjg2Mzk1NwMAAAAGMTAwMTg3BAAAAAI1NgYAAAABMAcAAAADMTYwCAAAAAEwCQAAAAExCgAAAAEwCwAAAAsxMTYwODg5MjkzMAwAAAABNw0AAAAJOS8yNC8yMDE5EAAAAAk5LzIzLzIwMTnnEMEnXUDXCGLKBShdQNcIM0NJUS5UU0U6OTY4NC5JUV9SRVZFTlVFX0VTVC5DWTIwMjAuMjAxOS0wOS0yMy4uLlVTRAEAAACpfQ0AAgAAABAyOTM1LjgzODU0MDkzNjE1AQ4AAAAFAAAAAjExAQAAAAEwAgAAAAk3MjY4NjM5NTUDAAAABjEwMDE4MAQAAAACNTYGAAAAATAHAAAAAzE2MAgAAAABMAkAAAABMQoAAAABMAsAAAALMTE2MDg4MDgxMzEMAAAAATcNAAAACTkvMjQvMjAxORAAAAAJOS8yMy8yMDE55xDBJ11A1whxaAMoXUDXCCFDSVEuSVFUUjIzMzM3ODQzOS5JUV9UUl9CVVlFUk5BTUUBAAAAhxLpDQMAAAAqU29mdEJhbmsgTW9iaWxlIENvcnAuIChua2E6U29mdEJhbmsgQ29ycC4pAOcQwSddQNcIt6P+J11A1wgWQ0lRLi5JUV9UUl9DTE9TRURfREFURQUAAAAAAAAACAAAABQoSW52YWxpZCBJZGVudGlmaWVyKecQwSddQNcIcWgDKF1A1wgyQ0lRLktPU0U6QTI1MTI3MC5JUV9FQklUREEuQ1kyMDE1LjIwMTktMDktMjMuLi5VU0QBAAAAWe4vCQIAAAAKMjA4LjQ1MDc1MwEI | AL1: AAAABQAAAAExAQAAAAoxODMzMDU5MDUyAwAAAAMxNjACAAAABDQwNTEEAAAAATAHAAAACTkvMjMvMjAxOQgAAAAKMTIvMzEvMjAxNQkAAAABMOcQwSddQNcIcWgDKF1A1wguQ0lRLk5BU0RBUUdTOlRUV08uSVFfQ0xPU0VQUklDRS4yMDE5LTA5LTIzLlVTRAEAAABRqgUAAgAAAAYxMjUuNzMA5xDBJ11A1whxaAMoXUDXCC1DSVEuTkFTREFRR1M6RUEuSVFfR1AuQ1kyMDE2LjIwMTktMDktMjMuLi5VU0QBAAAAO20AAAIAAAAEMzMwNAEIAAAABQAAAAExAQAAAAoxODczMjY3NDAwAwAAAAMxNjACAAAAAjEwBAAAAAEwBwAAAAk5LzIzLzIwMTkIAAAACjEyLzMxLzIwMTYJAAAAATDnEMEnXUDXCAMGAShdQNcILkNJUS5UU0U6OTY4NC5JUV9FQklUREEuSVFfTFRNLjIwMTktMDktMjMuLi5VU0QBAAAAqX0NAAIAAAAKMzIwLjYzMzY3NQEIAAAABQAAAAExAQAAAAoxOTc1NzkyNjQzAwAAAAMxNjACAAAABDQwNTEEAAAAATAHAAAACTkvMjMvMjAxOQgAAAAJNi8zMC8yMDE5CQAAAAEw5xDBJ11A1wi3o/4nXUDXCClDSVEuVFNFOjc5NzQuSVFfQ0xPU0VQUklDRS4yMDE3LTA4LTI5LlVTRAEAAACkXQ0AAgAAAAozMzUuNDAwODczAOcQwSddQNcIAwYBKF1A1wgsQ0lRLlRTRTo3OTc0LklRX1RFVl9FQklUREEuSVFfTFRNLjIwMTctMTItMjYBAAAApF0NAAIAAAAJNDEuMDQ2NTIxAQcAAAAFAAAAATEBAAAACjE4NjU3 | AM1: OTIzNjMDAAAAATACAAAABjEwMDAzMAQAAAABMAcAAAAKMTIvMjYvMjAxNwgAAAAKMTIvMjYvMjAxN+cQwSddQNcIa0H8J11A1wgsQ0lRLlRTRTo3OTc0LklRX1RFVl9FQklUREEuSVFfTFRNLjIwMTktMDEtMjkBAAAApF0NAAIAAAAJMTQuOTI1MjM3AQcAAAAFAAAAATEBAAAACjE5MjE1MTg0MjMDAAAAATACAAAABjEwMDAzMAQAAAABMAcAAAAJMS8yOS8yMDE5CAAAAAkxLzI5LzIwMTnnEMEnXUDXCHFoAyhdQNcILENJUS5UU0U6Nzk3NC5JUV9URVZfRUJJVERBLklRX0xUTS4yMDE4LTAxLTIzAQAAAKRdDQACAAAACTUwLjY1NTk5NQEHAAAABQAAAAExAQAAAAoxODY1NzkyMzYzAwAAAAEwAgAAAAYxMDAwMzAEAAAAATAHAAAACTEvMjMvMjAxOAgAAAAJMS8yMy8yMDE45xDBJ11A1whrQfwnXUDXCCxDSVEuVFNFOjc5NzQuSVFfVEVWX0VCSVREQS5JUV9MVE0uMjAxNi0xMS0wMQEAAACkXQ0AAgAAAAc1NS4yNDg1AQcAAAAFAAAAATEBAAAACjE4MTQ1NjcxMDgDAAAAATACAAAABjEwMDAzMAQAAAABMAcAAAAJMTEvMS8yMDE2CAAAAAkxMS8xLzIwMTbnEMEnXUDXCGtB/CddQNcIKUNJUS5UU0U6Nzk3NC5JUV9DTE9TRVBSSUNFLjIwMTctMDItMDcuVVNEAQAAAKRdDQACAAAACjIwNy4xMTQ4NDcA5xDBJ11A1wi3o/4nXUDXCClDSVEuVFNFOjc5NzQuSVFfQ0xPU0VQUklDRS4yMDE4LTA4LTE0LlVTRAEAAACk | AN1: XQ0AAgAAAAozMjMuOTY1OTA3AOcQwSddQNcIcWgDKF1A1wgpQ0lRLlRTRTo3OTc0LklRX0NMT1NFUFJJQ0UuMjAxNi0wMy0yMi5VU0QBAAAApF0NAAIAAAAKMTQ3LjU2MDc2NQDnEMEnXUDXCGtB/CddQNcIKUNJUS5UU0U6Nzk3NC5JUV9DTE9TRVBSSUNFLjIwMTktMDEtMDguVVNEAQAAAKRdDQACAAAACjI3Ni40NzgxNjYA5xDBJ11A1wi3o/4nXUDXCC1DSVEuTkFTREFRR1M6RUEuSVFfVEVWLjQyMzY5LjIwMTktMDktMjMuLi5VU0QBAAAAO20AAAIAAAAMMTkxOTIuNzE0OTAyAQYAAAAFAAAAATEBAAAACjE3NjQwODU0MzIDAAAAAzE2MAIAAAAGMTAwMDYwBAAAAAEwBwAAAAoxMi8zMS8yMDE15xDBJ11A1whrQfwnXUDXCDZDSVEuVFNFOjM2NTkuSVFfRElMVVRfRVBTX0VYQ0wuSVFfTFRNLjIwMTktMDktMjMuLi5VU0QBAAAAnh+CCAIAAAAHMS4wMzkwOQEIAAAABQAAAAExAQAAAAoxOTc1NzkyNDM3AwAAAAMxNjACAAAAAzE0MgQAAAABMAcAAAAJOS8yMy8yMDE5CAAAAAk2LzMwLzIwMTkJAAAAATDnEMEnXUDXCLej/iddQNcILENJUS5FTlhUUEE6VUJJLklRX0dQLkNZMjAxNy4yMDE5LTA5LTIzLi4uVVNEAQAAABl2DQACAAAACzE2NzMuNjk5NTY4AQgAAAAFAAAAATEBAAAACjE5Njg0NjI4OTEDAAAAAzE2MAIAAAACMTAEAAAAATAHAAAACTkvMjMvMjAxOQgAAAAKMTIvMzEvMjAxNwkAAAABMOcQwSdd | AO1: QNcIa0H8J11A1wgtQ0lRLk5BU0RBUUdTOkVBLklRX1RFVi40NDE5Ni4yMDE5LTA5LTIzLi4uVVNEAQAAADttAAACAAAADDI0OTgyLjM4MTQ2NgEGAAAABQAAAAExAQAAAAoxOTc0MjM1MzQ5AwAAAAMxNjACAAAABjEwMDA2MAQAAAABMAcAAAAJOS8yMy8yMDE55xDBJ11A1whiygUoXUDXCC5DSVEuVFNFOjM2NTkuSVFfRUJJVERBLkNZMjAxNi4yMDE5LTA5LTIzLi4uVVNEAQAAAJ4fgggCAAAACjY0OS41MTYwMjMBCAAAAAUAAAABMQEAAAAKMTgzNTA0MjkwNwMAAAADMTYwAgAAAAQ0MDUxBAAAAAEwBwAAAAk5LzIzLzIwMTkIAAAACjEyLzMxLzIwMTYJAAAAATDnEMEnXUDXCAMGAShdQNcIN0NJUS5UU0U6Nzk3NC5JUV9FRkZFQ1RfVEFYX1JBVEUuQ1kyMDE2LjIwMTktMDktMjMuLi5VU0QBAAAApF0NAAIAAAAGNy44MTc0AQgAAAAFAAAAATEBAAAACjE4Mjc3Njc3OTcDAAAAAjc5AgAAAAQ0Mzc2BAAAAAEwBwAAAAk5LzIzLzIwMTkIAAAACjEyLzMxLzIwMTYJAAAAATCnmconXUDXCGLKBShdQNcIMUNJUS5UU0U6Nzk3NC5JUV9SRF9FWFBfRk4uQ1kyMDE2LjIwMTktMDktMjMuLi5VU0QBAAAApF0NAAIAAAAINTkxLjU3MTcBCAAAAAUAAAABMQEAAAAKMTgyNzc2Nzc5NwMAAAADMTYwAgAAAAQzMTY4BAAAAAEwBwAAAAk5LzIzLzIwMTkIAAAACjEyLzMxLzIwMTYJAAAAATCnmconXUDXCGLKBShdQNcIKUNJ | AP1: US5UU0U6Nzk3NC5JUV9DTE9TRVBSSUNFLjIwMTctMDktMDUuVVNEAQAAAKRdDQACAAAACjMyOS44MjY4MzQA5xDBJ11A1whrQfwnXUDXCCdDSVEuRU5YVFBBOlVCSS5JUV9URVYuLjIwMTktMDktMjMuLi5VU0QBAAAAGXYNAAIAAAALODc2OS42NTkxMDgBBgAAAAUAAAABMQEAAAAKMTk2ODQ2Mjg2OQMAAAADMTYwAgAAAAYxMDAwNjAEAAAAATAHAAAACTkvMjMvMjAxOecQwSddQNcIa0H8J11A1wgwQ0lRLkVOWFRQQTpVQkkuSVFfRUJJVERBLkNZMjAxNi4yMDE5LTA5LTIzLi4uVVNEAQAAABl2DQACAAAACjcxNS44ODM1NjQBCAAAAAUAAAABMQEAAAAKMTg5MzUxNDU3NgMAAAADMTYwAgAAAAQ0MDUxBAAAAAEwBwAAAAk5LzIzLzIwMTkIAAAACjEyLzMxLzIwMTYJAAAAATDnEMEnXUDXCHFoAyhdQNcIL0NJUS5OQVNEQVFHUzpUVFdPLklRX1RFVi40NDU2MS4yMDE5LTA5LTIzLi4uVVNEAQAAAFGqBQACAAAACzEyMDcxLjQ3MTUyAQYAAAAFAAAAATEBAAAACjE5NzQzMDI0ODgDAAAAAzE2MAIAAAAGMTAwMDYwBAAAAAEwBwAAAAk5LzIzLzIwMTnnEMEnXUDXCGtB/CddQNcIKUNJUS5UU0U6Nzk3NC5JUV9DTE9TRVBSSUNFLjIwMTktMDgtMjcuVVNEAQAAAKRdDQACAAAACjM4MC4yODM4MTEAp5nKJ11A1wgDBgEoXUDXCC9DSVEuVFNFOjk2ODQuSVFfUEVfRVhDTC5JUV9MVE0uMjAxOS0wOS0yMy4uLlVTRAEA | AQ1: AACpfQ0AAgAAAAkzMy40ODgyNjQBBwAAAAUAAAABMQEAAAAKMTk3NTc5MjY0MwMAAAABMAIAAAAGMTAwMDI3BAAAAAEwBwAAAAk5LzIwLzIwMTkIAAAACTkvMjAvMjAxOecQwSddQNcIYsoFKF1A1wgsQ0lRLlRTRTo3OTc0LklRX1RFVl9FQklUREEuSVFfTFRNLjIwMTYtMDgtMjMBAAAApF0NAAIAAAAINTAuNjAzODYBBwAAAAUAAAABMQEAAAAKMTgwMjc3Njc3NQMAAAABMAIAAAAGMTAwMDMwBAAAAAEwBwAAAAk4LzIzLzIwMTYIAAAACTgvMjMvMjAxNucQwSddQNcIAwYBKF1A1wgzQ0lRLktPU0U6QTI1MTI3MC5JUV9QRV9FWENMLklRX0xUTS4yMDE5LTA5LTIzLi4uVVNEAQAAAFnuLwkCAAAACTYxLjMwMjk3NwEHAAAABQAAAAExAQAAAAoxOTgxMTcwMDUyAwAAAAEwAgAAAAYxMDAwMjcEAAAAATAHAAAACTkvMjMvMjAxOQgAAAAJOS8yMy8yMDE55xDBJ11A1whxaAMoXUDXCClDSVEuVFNFOjc5NzQuSVFfQ0xPU0VQUklDRS4yMDE5LTA0LTIzLlVTRAEAAACkXQ0AAgAAAAozMzIuMDk3MzcyAOcQwSddQNcIcWgDKF1A1wgsQ0lRLlRTRTo3OTc0LklRX1RFVl9FQklUREEuSVFfTFRNLjIwMTUtMDktMDgBAAAApF0NAAIAAAAJNDAuODExNzc2AQcAAAAFAAAAATEBAAAACjE3NDk4NTcwOTcDAAAAATACAAAABjEwMDAzMAQAAAABMAcAAAAIOS84LzIwMTUIAAAACDkvOC8yMDE15xDBJ11A1whrQfwnXUDXCCFD | AR1: SVEuSVFUUjYwNTQwMDM2NC5JUV9DT01QQU5ZX05BTUUBAAAAGXYNAAMAAAAYVWJpc29mdCBFbnRlcnRhaW5tZW50IFNBAOcQwSddQNcIcWgDKF1A1wgiQ0lRLklRVFIyMzMzNzg0MzkuSVFfVFJfVE9UQUxWQUxVRQEAAACHEukNAgAAAAoyNDk3Ni4yNTg0AQYAAAAFAAAAAjU0AQAAAAYxMDA1MDQCAAAACTIzMzM3ODQzOQMAAAAJMjMzMzc4NDM5BAAAAAI3OQYAAAAFRmFsc2XnEMEnXUDXCAMGAShdQNcIKkNJUS5UU0U6Nzk3NC5JUV9URVYuNDI3MzUuMjAxOS0wOS0yMy4uLlVTRAEAAACkXQ0AAgAAAAwxNzc5NC42MjMzMDIBBgAAAAUAAAABMQEAAAAKMTgxODA2MjYyMQMAAAADMTYwAgAAAAYxMDAwNjAEAAAAATAHAAAACjEyLzMxLzIwMTbnEMEnXUDXCHFoAyhdQNcINENJUS5OQVNEQVFHUzpFQS5JUV9UT1RBTF9SRVYuQ1kyMDE4LjIwMTktMDktMjMuLi5VU0QBAAAAO20AAAIAAAAENTI5NAEIAAAABQAAAAExAQAAAAoxOTQzOTE1MDIyAwAAAAMxNjACAAAAAjI4BAAAAAEwBwAAAAk5LzIzLzIwMTkIAAAACjEyLzMxLzIwMTgJAAAAATDnEMEnXUDXCAMGAShdQNcIKUNJUS5UU0U6Nzk3NC5JUV9DTE9TRVBSSUNFLjIwMTgtMDItMjAuVVNEAQAAAKRdDQACAAAACjQzNy42NzE4NDkA5xDBJ11A1whrQfwnXUDXCDVDSVEuS09TRTpBMjUxMjcwLklRX1RPVEFMX1JFVi5DWTIwMTYuMjAxOS0wOS0yMy4uLlVT | AS1: RAEAAABZ7i8JAgAAAAsxMjQ1Ljk3NDU5MgEIAAAABQAAAAExAQAAAAoxODgwMjYyMTMyAwAAAAMxNjACAAAAAjI4BAAAAAEwBwAAAAk5LzIzLzIwMTkIAAAACjEyLzMxLzIwMTYJAAAAATDnEMEnXUDXCGtB/CddQNcIKUNJUS5UU0U6Nzk3NC5JUV9DTE9TRVBSSUNFLjIwMTgtMDUtMDEuVVNEAQAAAKRdDQACAAAACjQyMC44NDE1MDUA5xDBJ11A1wi3o/4nXUDXCCxDSVEuRU5YVFBBOlVCSS5JUV9HUC5DWTIwMTYuMjAxOS0wOS0yMy4uLlVTRAEAAAAZdg0AAgAAAAsxMjQwLjQwMDYxMwEIAAAABQAAAAExAQAAAAoxODkzNTE0NTc2AwAAAAMxNjACAAAAAjEwBAAAAAEwBwAAAAk5LzIzLzIwMTkIAAAACjEyLzMxLzIwMTYJAAAAATDnEMEnXUDXCGtB/CddQNcILkNJUS5UU0U6Nzk3NC5JUV9FQklUREEuQ1kyMDE4LjIwMTktMDktMjMuLi5VU0QBAAAApF0NAAIAAAALMjI4NS4xMjUwOTgBCAAAAAUAAAABMQEAAAAKMTk0NDU5NzY1OAMAAAADMTYwAgAAAAQ0MDUxBAAAAAEwBwAAAAk5LzIzLzIwMTkIAAAACjEyLzMxLzIwMTgJAAAAATCnmconXUDXCGLKBShdQNcIJUNJUS5UU0U6MzY1OS5JUV9URVYuLjIwMTktMDktMjMuLi5VU0QBAAAAnh+CCAIAAAALNzAxMS4zMDQwMDYBBgAAAAUAAAABMQEAAAAKMTk3NTc4NjYyMgMAAAADMTYwAgAAAAYxMDAwNjAEAAAAATAHAAAACTkvMjAvMjAxOecQwSddQNcIa0H8 | AT1: J11A1wgsQ0lRLlRTRTo3OTc0LklRX1RFVl9FQklUREEuSVFfTFRNLjIwMTgtMDMtMDYBAAAApF0NAAIAAAAJMjYuMjI5NjgyAQcAAAAFAAAAATEBAAAACjE4NzQxOTMzNDADAAAAATACAAAABjEwMDAzMAQAAAABMAcAAAAIMy82LzIwMTgIAAAACDMvNi8yMDE45xDBJ11A1wi3o/4nXUDXCClDSVEuVFNFOjc5NzQuSVFfQ0xPU0VQUklDRS4yMDE2LTAxLTI2LlVTRAEAAACkXQ0AAgAAAAoxMzMuMzk1MjQ1AOcQwSddQNcIa0H8J11A1wgpQ0lRLlRTRTo3OTc0LklRX0NMT1NFUFJJQ0UuMjAxOC0wMy0yMC5VU0QBAAAApF0NAAIAAAAKNDUzLjA1NTMwNQDnEMEnXUDXCGtB/CddQNcIKUNJUS5UU0U6Nzk3NC5JUV9DTE9TRVBSSUNFLjIwMTYtMDktMjcuVVNEAQAAAKRdDQACAAAACjI2OS4wMzE3NDYA5xDBJ11A1wgDBgEoXUDXCClDSVEuVFNFOjc5NzQuSVFfQ0xPU0VQUklDRS4yMDE4LTExLTA2LlVTRAEAAACkXQ0AAgAAAAkzMTEuNzIyNjkA5xDBJ11A1whxaAMoXUDXCClDSVEuVFNFOjc5NzQuSVFfQ0xPU0VQUklDRS4yMDE4LTA4LTIxLlVTRAEAAACkXQ0AAgAAAAkzMzUuMDg0MjEA5xDBJ11A1wi3o/4nXUDXCC9DSVEuTkFTREFRR1M6QVRWSS5JUV9URVYuNDQxOTYuMjAxOS0wOS0yMy4uLlVTRAEAAAAXbUAAAgAAAAwzOTg0OS40NjU0MjkBBgAAAAUAAAABMQEAAAAKMTk3NTAzODc5OQMAAAADMTYwAgAA | AU1: AAYxMDAwNjAEAAAAATAHAAAACTkvMjMvMjAxOecQwSddQNcIa0H8J11A1wgpQ0lRLlRTRTo3OTc0LklRX0NMT1NFUFJJQ0UuMjAxNS0wNi0xNi5VU0QBAAAApF0NAAIAAAAKMTY0LjkxMDg2NQDnEMEnXUDXCGtB/CddQNcIKUNJUS5UU0U6Nzk3NC5JUV9DTE9TRVBSSUNFLjIwMTYtMDYtMTQuVVNEAQAAAKRdDQACAAAACjE0My42MTE3NDYA5xDBJ11A1whrQfwnXUDXCDVDSVEuS09TRTpBMjUxMjcwLklRX1RPVEFMX1JFVi5DWTIwMTcuMjAxOS0wOS0yMy4uLlVTRAEAAABZ7i8JAgAAAAsyMjY5LjgxODA0MwEIAAAABQAAAAExAQAAAAoxOTUwOTM2NzAwAwAAAAMxNjACAAAAAjI4BAAAAAEwBwAAAAk5LzIzLzIwMTkIAAAACjEyLzMxLzIwMTcJAAAAATDnEMEnXUDXCGtB/CddQNcILUNJUS5OQVNEQVFHUzpFQS5JUV9HUC5DWTIwMTguMjAxOS0wOS0yMy4uLlVTRAEAAAA7bQAAAgAAAAQ0MDE1AQgAAAAFAAAAATEBAAAACjE5NDM5MTUwMjIDAAAAAzE2MAIAAAACMTAEAAAAATAHAAAACTkvMjMvMjAxOQgAAAAKMTIvMzEvMjAxOAkAAAABMOcQwSddQNcIcWgDKF1A1wgsQ0lRLlRTRTo3OTc0LklRX1RFVl9FQklUREEuSVFfTFRNLjIwMTUtMTItMjkBAAAApF0NAAIAAAAJMjYuMzg5OTc0AQcAAAAFAAAAATEBAAAACjE3NjUxNTM2NzEDAAAAATACAAAABjEwMDAzMAQAAAABMAcAAAAKMTIvMjkvMjAxNQgAAAAK | AV1: MTIvMjkvMjAxNecQwSddQNcIa0H8J11A1wgpQ0lRLlRTRTo3OTc0LklRX0NMT1NFUFJJQ0UuMjAxOC0xMi0wNC5VU0QBAAAApF0NAAIAAAAKMjkyLjEzODgwMwDnEMEnXUDXCHFoAyhdQNcIM0NJUS5FTlhUUEE6VUJJLklRX1RPVEFMX1JFVi5DWTIwMTUuMjAxOS0wOS0yMy4uLlVTRAEAAAAZdg0AAgAAAAkxNDAxLjUyMDUBCAAAAAUAAAABMQEAAAAKMTg1NTUyMjUxNgMAAAADMTYwAgAAAAIyOAQAAAABMAcAAAAJOS8yMy8yMDE5CAAAAAoxMi8zMS8yMDE1CQAAAAEw5xDBJ11A1whxaAMoXUDXCDtDSVEuS09TRTpBMjUxMjcwLklRX0VGRkVDVF9UQVhfUkFURS5JUV9MVE0uMjAxOS0wOS0yMy4uLlVTRAEAAABZ7i8JAgAAAAcyMy4zMzc1AQgAAAAFAAAAATEBAAAACjE5ODExNzAwNTIDAAAAAjg1AgAAAAQ0Mzc2BAAAAAEwBwAAAAk5LzIzLzIwMTkIAAAACTYvMzAvMjAxOQkAAAABMKeZyiddQNcIt6P+J11A1wgsQ0lRLlRTRTo3OTc0LklRX1RFVl9FQklUREEuSVFfTFRNLjIwMTctMDUtMzABAAAApF0NAAIAAAAJNTQuMTMxMDk3AQcAAAAFAAAAATEBAAAACjE4MzgyMDQwNzQDAAAAATACAAAABjEwMDAzMAQAAAABMAcAAAAJNS8zMC8yMDE3CAAAAAk1LzMwLzIwMTfnEMEnXUDXCLej/iddQNcINUNJUS5FTlhUUEE6VUJJLklRX1JFVkVOVUVfRVNULkNZMjAyMS4yMDE5LTA5LTIzLi4uVVNEAQAAABl2DQAC | AW1: AAAAEDI3OTUuMDcyNDY1MDY0OTQBDgAAAAUAAAACMTEBAAAAATACAAAACDQ3NTE0NzE4AwAAAAYxMDAxODAEAAAAATMGAAAAATAHAAAAAzE2MAgAAAABMAkAAAABMQoAAAABMAsAAAALMTE2MTE3MTAyMDAMAAAAATcNAAAACTkvMjQvMjAxORAAAAAJOS8yMy8yMDE55xDBJ11A1whxaAMoXUDXCC9DSVEuTkFTREFRR1M6VFRXTy5JUV9HUC5DWTIwMTUuMjAxOS0wOS0yMy4uLlVTRAEAAABRqgUAAgAAAAczMDkuMzE5AQgAAAAFAAAAATEBAAAACjE4MjcwMDAxMDcDAAAAAzE2MAIAAAACMTAEAAAAATAHAAAACTkvMjMvMjAxOQgAAAAKMTIvMzEvMjAxNQkAAAABMOcQwSddQNcIAwYBKF1A1wgtQ0lRLlRTRTo5Njg0LklRX0NVU1RPTV9CRVRBLi4yMDE5LTA5LTIzLi4uVVNEAQAAAKl9DQACAAAAETAuODc4MzE2Mzk1NTcyNzUyAKeZyiddQNcIcWgDKF1A1wgsQ0lRLlRTRTo3OTc0LklRX1RFVl9FQklUREEuSVFfTFRNLjIwMTYtMDYtMjgBAAAApF0NAAIAAAAJMTcuMTQ0MzI4AQcAAAAFAAAAATEBAAAACjE3ODc5MjU4NzYDAAAAATACAAAABjEwMDAzMAQAAAABMAcAAAAJNi8yOC8yMDE2CAAAAAk2LzI4LzIwMTbnEMEnXUDXCAMGAShdQNcINkNJUS5OQVNEQVFHUzpUVFdPLklRX1RPVEFMX1JFVi5DWTIwMTUuMjAxOS0wOS0yMy4uLlVTRAEAAABRqgUAAgAAAAgxMzM2LjU4MQEIAAAABQAAAAExAQAAAAoxODI3 | AX1: MDAwMTA3AwAAAAMxNjACAAAAAjI4BAAAAAEwBwAAAAk5LzIzLzIwMTkIAAAACjEyLzMxLzIwMTUJAAAAATDnEMEnXUDXCLej/iddQNcIKkNJUS5UU0U6MzY1OS5JUV9HUC5DWTIwMTUuMjAxOS0wOS0yMy4uLlVTRAEAAACeH4IIAgAAAAsxMTY5LjQwMTA2MQEIAAAABQAAAAExAQAAAAoxNzg0NDk5MTg0AwAAAAMxNjACAAAAAjEwBAAAAAEwBwAAAAk5LzIzLzIwMTkIAAAACjEyLzMxLzIwMTUJAAAAATDnEMEnXUDXCGLKBShdQNcIKUNJUS5UU0U6Nzk3NC5JUV9DTE9TRVBSSUNFLjIwMTYtMDctMTkuVVNEAQAAAKRdDQACAAAACjI5OS4wMzk5MjIA5xDBJ11A1whxaAMoXUDXCCdDSVEuTkFTREFRR1M6VFRXTy5JUV9URVYuMjAxOS0wOS0yMy5VU0QBAAAAUaoFAAIAAAALMTIwNzEuNDcxNTIBBgAAAAUAAAABMQEAAAAKMTk3NDMwMjQ4OAMAAAADMTYwAgAAAAYxMDAwNjAEAAAAATAHAAAACTkvMjMvMjAxOecQwSddQNcIYsoFKF1A1wgyQ0lRLlRTRTo5Njg0LklRX0VCSVREQV9FU1QuQ1kyMDIwLjIwMTktMDktMjMuLi5VU0QBAAAAqX0NAAIAAAAQNDA4LjExMjUyMzk0NjQ5OQEOAAAABQAAAAIxMQEAAAABMAIAAAAJNzI2ODYzOTU1AwAAAAYxMDAxODcEAAAAAjU2BgAAAAEwBwAAAAMxNjAIAAAAATAJAAAAATEKAAAAATALAAAACzExNjA4ODkyOTU0DAAAAAE3DQAAAAk5LzI0LzIwMTkQAAAACTkvMjMvMjAx | AY1: OecQwSddQNcIAwYBKF1A1wgpQ0lRLlRTRTo3OTc0LklRX0NMT1NFUFJJQ0UuMjAxOS0wMi0yNi5VU0QBAAAApF0NAAIAAAAKMjc1LjEzNjU3NADnEMEnXUDXCHFoAyhdQNcIKUNJUS5UU0U6Nzk3NC5JUV9DTE9TRVBSSUNFLjIwMTYtMTAtMDQuVVNEAQAAAKRdDQACAAAACjI1NC41MzQ4MzcA5xDBJ11A1whrQfwnXUDXCCFDSVEuSVFUUjMxNDIyMDA1OS5JUV9UUl9CVVlFUk5BTUUBAAAAG566EgMAAAAKVml2ZW5kaSBTQQDnEMEnXUDXCHFoAyhdQNcIKUNJUS5UU0U6Nzk3NC5JUV9DTE9TRVBSSUNFLjIwMTctMDUtMjMuVVNEAQAAAKRdDQACAAAACjI3Ny41NjA1NTcA5xDBJ11A1whxaAMoXUDXCClDSVEuVFNFOjc5NzQuSVFfQ0xPU0VQUklDRS4yMDE3LTA2LTEzLlVTRAEAAACkXQ0AAgAAAAozMTAuNTMxMzQzAOcQwSddQNcIa0H8J11A1wg1Q0lRLkVOWFRQQTpVQkkuSVFfUkVWRU5VRV9FU1QuQ1kyMDE5LjIwMTktMDktMjMuLi5VU0QBAAAAGXYNAAIAAAAQMTk5Mi42ODc0ODYwNDMwNQEOAAAABQAAAAIxMQEAAAABMAIAAAAIMTAyNTIzNDYDAAAABjEwMDE4MAQAAAABMwYAAAABMAcAAAADMTYwCAAAAAEwCQAAAAExCgAAAAEwCwAAAAsxMTU0NjM4MzA3MAwAAAABNw0AAAAJOS8yNC8yMDE5EAAAAAk5LzIzLzIwMTnnEMEnXUDXCAMGAShdQNcILENJUS5UU0U6Nzk3NC5JUV9URVZfRUJJVERBLklRX0xU | AZ1: TS4yMDE3LTExLTE0AQAAAKRdDQACAAAACDQ0LjgxMjU2AQcAAAAFAAAAATEBAAAACjE4NjU3OTIzNjMDAAAAATACAAAABjEwMDAzMAQAAAABMAcAAAAKMTEvMTQvMjAxNwgAAAAKMTEvMTQvMjAxN+cQwSddQNcIt6P+J11A1wgxQ0lRLk5BU0RBUUdTOkVBLklRX0VCSVREQS5DWTIwMTguMjAxOS0wOS0yMy4uLlVTRAEAAAA7bQAAAgAAAAQxNzAxAQgAAAAFAAAAATEBAAAACjE5NDM5MTUwMjIDAAAAAzE2MAIAAAAENDA1MQQAAAABMAcAAAAJOS8yMy8yMDE5CAAAAAoxMi8zMS8yMDE4CQAAAAEw5xDBJ11A1wi3o/4nXUDXCDhDSVEuTkFTREFRR1M6VFRXTy5JUV9SRVZFTlVFX0VTVC5DWTIwMjAuMjAxOS0wOS0yMy4uLlVTRAEAAABRqgUAAgAAAAkyNzkxLjA2NjUBDgAAAAUAAAACMTEBAAAAATACAAAABzExMTcxOTgDAAAABjEwMDE4MAQAAAABMgYAAAABMAcAAAADMTYwCAAAAAEwCQAAAAExCgAAAAEwCwAAAAsxMTYxMTI5NjU0MQwAAAABNw0AAAAJOS8yNC8yMDE5EAAAAAk5LzIzLzIwMTnnEMEnXUDXCGtB/CddQNcIKkNJUS5UU0U6OTY4NC5JUV9URVYuNDM0NjUuMjAxOS0wOS0yMy4uLlVTRAEAAACpfQ0AAgAAAAsyMzEzLjIzMDIyNAEGAAAABQAAAAExAQAAAAoxOTIyMTE1MjE0AwAAAAMxNjACAAAABjEwMDA2MAQAAAABMAcAAAAKMTIvMzEvMjAxOOcQwSddQNcIt6P+J11A1wgtQ0lRLk5BU0RBUUdT | BA1: OkVBLklRX1RFVi40MzEwMC4yMDE5LTA5LTIzLi4uVVNEAQAAADttAAACAAAADDI4OTg2LjY0ODA5MgEGAAAABQAAAAExAQAAAAoxODY0NDM5NzUyAwAAAAMxNjACAAAABjEwMDA2MAQAAAABMAcAAAAKMTIvMzEvMjAxN+cQwSddQNcIt6P+J11A1wg0Q0lRLlRTRTo3OTc0LklRX0dST1NTX1BST0ZJVC5JUV9MVE0uMjAxOS0wOS0yMy4uLlVTRAEAAACkXQ0AAgAAAAs0NjU0LjYzNjYzOQEIAAAABQAAAAExAQAAAAoxOTc1NzkyNDcwAwAAAAMxNjACAAAAAjEwBAAAAAEwBwAAAAk5LzIzLzIwMTkIAAAACTYvMzAvMjAxOQkAAAABMKeZyiddQNcIcWgDKF1A1wgpQ0lRLlRTRTo3OTc0LklRX0NMT1NFUFJJQ0UuMjAxOC0wMi0xMy5VU0QBAAAApF0NAAIAAAAKNDEyLjk4NDgyNADnEMEnXUDXCAMGAShdQNcIKkNJUS5UU0U6OTY4NC5JUV9HUC5JUV9MVE0uMjAxOS0wOS0yMy4uLlVTRAEAAACpfQ0AAgAAAAsxMTUwLjU0OTcyOQEIAAAABQAAAAExAQAAAAoxOTc1NzkyNjQzAwAAAAMxNjACAAAAAjEwBAAAAAEwBwAAAAk5LzIzLzIwMTkIAAAACTYvMzAvMjAxOQkAAAABMOcQwSddQNcIcWgDKF1A1wgvQ0lRLk5BU0RBUUdTOkFUVkkuSVFfR1AuQ1kyMDE2LjIwMTktMDktMjMuLi5VU0QBAAAAF21AAAIAAAAENDIxNAEIAAAABQAAAAExAQAAAAoxOTQ3ODI4NzU0AwAAAAMxNjACAAAAAjEwBAAAAAEwBwAAAAk5LzIz | BB1: LzIwMTkIAAAACjEyLzMxLzIwMTYJAAAAATDnEMEnXUDXCHFoAyhdQNcIL0NJUS5OQVNEQVFHUzpBVFZJLklRX1RFVi40MjczNS4yMDE5LTA5LTIzLi4uVVNEAQAAABdtQAACAAAADDI5MTcwLjQzNDgyNgEGAAAABQAAAAExAQAAAAoxODE2MzMzNzM3AwAAAAMxNjACAAAABjEwMDA2MAQAAAABMAcAAAAKMTIvMzEvMjAxNucQwSddQNcIYsoFKF1A1wgpQ0lRLlRTRTo3OTc0LklRX0NMT1NFUFJJQ0UuMjAxNS0wNy0yMS5VU0QBAAAApF0NAAIAAAAKMTc1LjUzNTU2OQDnEMEnXUDXCHFoAyhdQNcILUNJUS5OQVNEQVFHUzpFQS5JUV9URVYuNDM0NjUuMjAxOS0wOS0yMy4uLlVTRAEAAAA7bQAAAgAAAAwyMDI4OC45NzU0MDEBBgAAAAUAAAABMQEAAAAKMTkxOTg3MDE5MgMAAAADMTYwAgAAAAYxMDAwNjAEAAAAATAHAAAACjEyLzMxLzIwMTjnEMEnXUDXCAMGAShdQNcIKkNJUS5UU0U6MzY1OS5JUV9HUC5JUV9MVE0uMjAxOS0wOS0yMy4uLlVTRAEAAACeH4IIAgAAAAsxODY3Ljc4MzEyNQEIAAAABQAAAAExAQAAAAoxOTc1NzkyNDM3AwAAAAMxNjACAAAAAjEwBAAAAAEwBwAAAAk5LzIzLzIwMTkIAAAACTYvMzAvMjAxOQkAAAABMOcQwSddQNcIt6P+J11A1wgxQ0lRLk5BU0RBUUdTOkVBLklRX0VCSVREQS5JUV9MVE0uMjAxOS0wOS0yMy4uLlVTRAEAAAA7bQAAAgAAAAQxMjY4AQgAAAAFAAAAATEBAAAACjE5 | BC1: NzQyMzU4MTIDAAAAAzE2MAIAAAAENDA1MQQAAAABMAcAAAAJOS8yMy8yMDE5CAAAAAk2LzMwLzIwMTkJAAAAATDnEMEnXUDXCAMGAShdQNcII0NJUS5JUVRSMjMzMzc4NDM5LklRX1RSX0NMT1NFRF9EQVRFAQAAAIcS6Q0FAAAACjIwMTMtMDQtMjYA5xDBJ11A1wgDBgEoXUDXCDFDSVEuVFNFOjM2NTkuSVFfVE9UQUxfUkVWLkNZMjAxNS4yMDE5LTA5LTIzLi4uVVNEAQAAAJ4fgggCAAAACjE1ODIuODg2OTQBCAAAAAUAAAABMQEAAAAKMTc4NDQ5OTE4NAMAAAADMTYwAgAAAAIyOAQAAAABMAcAAAAJOS8yMy8yMDE5CAAAAAoxMi8zMS8yMDE1CQAAAAEw5xDBJ11A1whxaAMoXUDXCClDSVEuVFNFOjk2ODQuSVFfQ0xPU0VQUklDRS4yMDE5LTA5LTIzLlVTRAEAAACpfQ0AAgAAAAk0My40NTEyNzQA5xDBJ11A1wgDBgEoXUDXCClDSVEuVFNFOjc5NzQuSVFfQ0xPU0VQUklDRS4yMDE3LTAxLTI0LlVTRAEAAACkXQ0AAgAAAAoyMDUuMjAzOTc3AOcQwSddQNcIa0H8J11A1wg3Q0lRLlRTRTo3OTc0LklRX0NBU0hfQUNRVUlSRV9DRi5DWTIwMTUuMjAxOS0wOS0yMy4uLlVTRAEAAACkXQ0AAwAAAAAAp5nKJ11A1whiygUoXUDXCClDSVEuVFNFOjc5NzQuSVFfQ0xPU0VQUklDRS4yMDE4LTEyLTE4LlVTRAEAAACkXQ0AAgAAAAoyNzUuNTI3OTA2AOcQwSddQNcIAwYBKF1A1wgxQ0lRLlRTRTo3OTc0LklRX1RPVEFM | BD1: X1JFVi5DWTIwMTUuMjAxOS0wOS0yMy4uLlVTRAEAAACkXQ0AAgAAAAs0NDMwLjMxNjM3NwEIAAAABQAAAAExAQAAAAoxNzc2NTg0MDQzAwAAAAMxNjACAAAAAjI4BAAAAAEwBwAAAAk5LzIzLzIwMTkIAAAACjEyLzMxLzIwMTUJAAAAATCnmconXUDXCHFoAyhdQNcILENJUS5UU0U6Nzk3NC5JUV9URVZfRUJJVERBLklRX0xUTS4yMDE1LTA1LTI2AQAAAKRdDQACAAAACTQ3LjMxNzkwOQEHAAAABQAAAAExAQAAAAoxNzMyNjYwNjYyAwAAAAEwAgAAAAYxMDAwMzAEAAAAATAHAAAACTUvMjYvMjAxNQgAAAAJNS8yNi8yMDE15xDBJ11A1whxaAMoXUDXCCxDSVEuVFNFOjc5NzQuSVFfVEVWX0VCSVREQS5JUV9MVE0uMjAxNy0wNC0xOAEAAACkXQ0AAgAAAAk1MC41OTM2NjYBBwAAAAUAAAABMQEAAAAKMTgyNzc2Nzc5NwMAAAABMAIAAAAGMTAwMDMwBAAAAAEwBwAAAAk0LzE4LzIwMTcIAAAACTQvMTgvMjAxN+cQwSddQNcIa0H8J11A1wghQ0lRLklRVFIzMjc2NDQ4OTIuSVFfVFJfQlVZRVJOQU1FAQAAANx2hxMDAAAAEU91cnBhbG0gQ28uLCBMdGQuAOcQwSddQNcIa0H8J11A1whCQ0lRLlRTRTo3OTc0LklRX0NIQU5HRV9ORVRfV09SS0lOR19DQVBJVEFMLkNZMjAxNi4yMDE5LTA5LTIzLi4uVVNEAQAAAKRdDQACAAAACi02OC41OTEwMDIBCAAAAAUAAAABMQEAAAAKMTgyNzc2Nzc5NwMAAAADMTYwAgAAAAQ0 | BE1: NDIxBAAAAAEwBwAAAAk5LzIzLzIwMTkIAAAACjEyLzMxLzIwMTYJAAAAATCnmconXUDXCGLKBShdQNcILENJUS5UU0U6Nzk3NC5JUV9URVZfRUJJVERBLklRX0xUTS4yMDE5LTA1LTIxAQAAAKRdDQACAAAACTEyLjk0NjMxOQEHAAAABQAAAAExAQAAAAoxOTU2NzQ4MDg2AwAAAAEwAgAAAAYxMDAwMzAEAAAAATAHAAAACTUvMjEvMjAxOQgAAAAJNS8yMS8yMDE55xDBJ11A1whiygUoXUDXCCxDSVEuVFNFOjc5NzQuSVFfVEVWX0VCSVREQS5JUV9MVE0uMjAxNS0xMS0xNwEAAACkXQ0AAgAAAAkzMi43MTExNjMBBwAAAAUAAAABMQEAAAAKMTc2NTE1MzY3MQMAAAABMAIAAAAGMTAwMDMwBAAAAAEwBwAAAAoxMS8xNy8yMDE1CAAAAAoxMS8xNy8yMDE15xDBJ11A1wgDBgEoXUDXCClDSVEuVFNFOjc5NzQuSVFfQ0xPU0VQUklDRS4yMDE3LTA2LTIwLlVTRAEAAACkXQ0AAgAAAAozMzUuNTg4NTE0AOcQwSddQNcIcWgDKF1A1wgrQ0lRLlRTRTo3OTc0LklRX0NPTVBBTllfTkFNRS4yMDE5LTA5LTIzLlVTRAEAAACkXQ0AAwAAABJOaW50ZW5kbyBDby4sIEx0ZC4A5xDBJ11A1whxaAMoXUDXCC5DSVEuS09TRTpBMjUxMjcwLklRX1RFVi40NDE5Ni4yMDE5LTA5LTIzLi4uVVNEAQAAAFnuLwkCAAAACzUyMjguNjIyOTY5AQYAAAAFAAAAATEBAAAACjE5ODExNTY1NDADAAAAAzE2MAIAAAAGMTAwMDYwBAAAAAEwBwAA | BF1: AAk5LzIzLzIwMTnnEMEnXUDXCAMGAShdQNcIKUNJUS5UU0U6Nzk3NC5JUV9DTE9TRVBSSUNFLjIwMTUtMDctMDcuVVNEAQAAAKRdDQACAAAACjE2Ni42NTMwMTYA5xDBJ11A1wgDBgEoXUDXCCxDSVEuVFNFOjc5NzQuSVFfVEVWX0VCSVREQS5JUV9MVE0uMjAxOC0wOS0xMQEAAACkXQ0AAgAAAAkxOC42NjUxMjgBBwAAAAUAAAABMQEAAAAKMTkwMDI3Mjc5NgMAAAABMAIAAAAGMTAwMDMwBAAAAAEwBwAAAAk5LzExLzIwMTgIAAAACTkvMTEvMjAxOOcQwSddQNcIYsoFKF1A1wgsQ0lRLlRTRTo3OTc0LklRX1RFVl9FQklUREEuSVFfTFRNLjIwMTctMDktMTIBAAAApF0NAAIAAAAJNDMuNjQwNjY1AQcAAAAFAAAAATEBAAAACjE4NTQwNDM4ODgDAAAAATACAAAABjEwMDAzMAQAAAABMAcAAAAJOS8xMi8yMDE3CAAAAAk5LzEyLzIwMTfnEMEnXUDXCGLKBShdQNcIKUNJUS5UU0U6Nzk3NC5JUV9DTE9TRVBSSUNFLjIwMTYtMDktMDYuVVNEAQAAAKRdDQACAAAACjIzMC4xMzc3ODMA5xDBJ11A1whrQfwnXUDXCCpDSVEuVFNFOjM2NTkuSVFfVEVWLjQ0NTYxLjIwMTktMDktMjMuLi5VU0QBAAAAnh+CCAIAAAALNzAxMS4zMDQwMDYBBgAAAAUAAAABMQEAAAAKMTk3NTc4NjYyMgMAAAADMTYwAgAAAAYxMDAwNjAEAAAAATAHAAAACTkvMjAvMjAxOecQwSddQNcIAwYBKF1A1wgpQ0lRLlRTRTo3OTc0LklRX0NMT1NF | BG1: UFJJQ0UuMjAxOC0wNC0wMy5VU0QBAAAApF0NAAIAAAAKNDM0LjMzNzczOQDnEMEnXUDXCLej/iddQNcIMENJUS5OQVNEQVFHUzpBVFZJLklRX0NPTVBBTllfTkFNRS4yMDE5LTA5LTIzLlVTRAEAAAAXbUAAAwAAABlBY3RpdmlzaW9uIEJsaXp6YXJkLCBJbmMuAOcQwSddQNcIcWgDKF1A1wgzQ0lRLlRTRTo3OTc0LklRX1JFVkVOVUVfRVNULkNZMjAyMS4yMDE5LTA5LTIzLi4uVVNEAQAAAKRdDQACAAAAEDEyMzI1LjEwMzIwMzU5ODUBDgAAAAUAAAACMTEBAAAAATACAAAACTY1MjkxNDE4MAMAAAAGMTAwMTgwBAAAAAI1NgYAAAABMAcAAAADMTYwCAAAAAEwCQAAAAExCgAAAAEwCwAAAAsxMTU0MTUwOTk0NQwAAAABNw0AAAAJOS8yNC8yMDE5EAAAAAk5LzIzLzIwMTnnEMEnXUDXCHFoAyhdQNcILENJUS5UU0U6Nzk3NC5JUV9URVZfRUJJVERBLklRX0xUTS4yMDE4LTEwLTAyAQAAAKRdDQACAAAACTIwLjQxMzczNwEHAAAABQAAAAExAQAAAAoxOTAwMjcyNzk2AwAAAAEwAgAAAAYxMDAwMzAEAAAAATAHAAAACTEwLzIvMjAxOAgAAAAJMTAvMi8yMDE45xDBJ11A1whrQfwnXUDXCCxDSVEuVFNFOjc5NzQuSVFfVEVWX0VCSVREQS5JUV9MVE0uMjAxNy0wOC0xNQEAAACkXQ0AAgAAAAk0MS44MzQ3OTIBBwAAAAUAAAABMQEAAAAKMTg1NDA0Mzg4OAMAAAABMAIAAAAGMTAwMDMwBAAAAAEwBwAAAAk4LzE1LzIw | BH1: MTcIAAAACTgvMTUvMjAxN+cQwSddQNcIYsoFKF1A1wgsQ0lRLkVOWFRQQTpVQkkuSVFfVEVWLjQzODMwLjIwMTktMDktMjMuLi5VU0QBAAAAGXYNAAIAAAALODc2OS42NTkxMDgBBgAAAAUAAAABMQEAAAAKMTk2ODQ2Mjg2OQMAAAADMTYwAgAAAAYxMDAwNjAEAAAAATAHAAAACTkvMjMvMjAxOecQwSddQNcIt6P+J11A1wgxQ0lRLlRTRTo3OTc0LklRX1RPVEFMX1JFVi5DWTIwMTYuMjAxOS0wOS0yMy4uLlVTRAEAAACkXQ0AAgAAAAszMzM5Ljc1MTQxNAEIAAAABQAAAAExAQAAAAoxODI3NzY3Nzk3AwAAAAMxNjACAAAAAjI4BAAAAAEwBwAAAAk5LzIzLzIwMTkIAAAACjEyLzMxLzIwMTYJAAAAATCnmconXUDXCGLKBShdQNcIKUNJUS5UU0U6Nzk3NC5JUV9DTE9TRVBSSUNFLjIwMTctMDItMTQuVVNEAQAAAKRdDQACAAAACjIwMy40OTk1NTQA5xDBJ11A1wgDBgEoXUDXCCxDSVEuVFNFOjc5NzQuSVFfVEVWX0VCSVREQS5JUV9MVE0uMjAxOS0wNS0xNAEAAACkXQ0AAgAAAAgxMi41MTY3NAEHAAAABQAAAAExAQAAAAoxOTU2NzQ4MDg2AwAAAAEwAgAAAAYxMDAwMzAEAAAAATAHAAAACTUvMTQvMjAxOQgAAAAJNS8xNC8yMDE55xDBJ11A1whrQfwnXUDXCC1DSVEuTkFTREFRR1M6RUEuSVFfVEVWLjQzODMwLjIwMTktMDktMjMuLi5VU0QBAAAAO20AAAIAAAAMMjQ5ODIuMzgxNDY2AQYAAAAFAAAAATEBAAAA | BI1: CjE5NzQyMzUzNDkDAAAAAzE2MAIAAAAGMTAwMDYwBAAAAAEwBwAAAAk5LzIzLzIwMTnnEMEnXUDXCHFoAyhdQNcILkNJUS5LT1NFOkEyNTEyNzAuSVFfR1AuSVFfTFRNLjIwMTktMDktMjMuLi5VU0QBAAAAWe4vCQIAAAALMTc0Mi42Njc1ODMBCAAAAAUAAAABMQEAAAAKMTk4MTE3MDA1MgMAAAADMTYwAgAAAAIxMAQAAAABMAcAAAAJOS8yMy8yMDE5CAAAAAk2LzMwLzIwMTkJAAAAATDnEMEnXUDXCAMGAShdQNcIKUNJUS5UU0U6Nzk3NC5JUV9DTE9TRVBSSUNFLjIwMTgtMDYtMTIuVVNEAQAAAKRdDQACAAAACjM3OC40NTkzMTQA5xDBJ11A1whrQfwnXUDXCClDSVEuVFNFOjc5NzQuSVFfQ0xPU0VQUklDRS4yMDE4LTA5LTExLlVTRAEAAACkXQ0AAgAAAAozNTEuMDg5NjA1AOcQwSddQNcIcWgDKF1A1wguQ0lRLktPU0U6QTI1MTI3MC5JUV9URVYuNDIzNjkuMjAxOS0wOS0yMy4uLlVTRAEAAABZ7i8JAwAAAAAA5xDBJ11A1whiygUoXUDXCCtDSVEuVFNFOjk2ODQuSVFfQ09NUEFOWV9OQU1FLjIwMTktMDktMjMuVVNEAQAAAKl9DQADAAAAHlNxdWFyZSBFbml4IEhvbGRpbmdzIENvLiwgTHRkLgDnEMEnXUDXCLej/iddQNcILENJUS5UU0U6Nzk3NC5JUV9URVZfRUJJVERBLklRX0xUTS4yMDE5LTAyLTA1AQAAAKRdDQACAAAACTEwLjg1MTY3MwEHAAAABQAAAAExAQAAAAoxOTQzMzU4MDQ3AwAAAAEwAgAA | BJ1: AAYxMDAwMzAEAAAAATAHAAAACDIvNS8yMDE5CAAAAAgyLzUvMjAxOecQwSddQNcIt6P+J11A1wgpQ0lRLlRTRTo3OTc0LklRX0NMT1NFUFJJQ0UuMjAxNS0wNi0wOS5VU0QBAAAApF0NAAIAAAAJMTYyLjUyMzE0AOcQwSddQNcIAwYBKF1A1wgqQ0lRLlRTRTozNjU5LklRX1RFVi40MjM2OS4yMDE5LTA5LTIzLi4uVVNEAQAAAJ4fgggCAAAACjU1MTYuMDUwMTUBBgAAAAUAAAABMQEAAAAKMTc2NTQxMDM3NwMAAAADMTYwAgAAAAYxMDAwNjAEAAAAATAHAAAACjEyLzMxLzIwMTXnEMEnXUDXCAMGAShdQNcILENJUS5UU0U6Nzk3NC5JUV9URVZfRUJJVERBLklRX0xUTS4yMDE3LTA4LTIyAQAAAKRdDQACAAAACTQxLjAxOTIzNgEHAAAABQAAAAExAQAAAAoxODU0MDQzODg4AwAAAAEwAgAAAAYxMDAwMzAEAAAAATAHAAAACTgvMjIvMjAxNwgAAAAJOC8yMi8yMDE35xDBJ11A1wi3o/4nXUDXCCxDSVEuVFNFOjc5NzQuSVFfVEVWX0VCSVREQS5JUV9MVE0uMjAxNy0wOS0wNQEAAACkXQ0AAgAAAAk0MC43NTcwOTMBBwAAAAUAAAABMQEAAAAKMTg1NDA0Mzg4OAMAAAABMAIAAAAGMTAwMDMwBAAAAAEwBwAAAAg5LzUvMjAxNwgAAAAIOS81LzIwMTfnEMEnXUDXCGtB/CddQNcIL0NJUS5OQVNEQVFHUzpUVFdPLklRX1RFVi40MzQ2NS4yMDE5LTA5LTIzLi4uVVNEAQAAAFGqBQACAAAADDEwNjkyLjE3NzY1NwEGAAAA | BK1: BQAAAAExAQAAAAoxOTIwNTA0ODY0AwAAAAMxNjACAAAABjEwMDA2MAQAAAABMAcAAAAKMTIvMzEvMjAxOOcQwSddQNcIcWgDKF1A1wgxQ0lRLlRTRTo3OTc0LklRX1RPVEFMX1JFVi5DWTIwMTguMjAxOS0wOS0yMy4uLlVTRAEAAACkXQ0AAgAAAAwxMDkwMC42NTE2OTYBCAAAAAUAAAABMQEAAAAKMTk0NDU5NzY1OAMAAAADMTYwAgAAAAIyOAQAAAABMAcAAAAJOS8yMy8yMDE5CAAAAAoxMi8zMS8yMDE4CQAAAAEwp5nKJ11A1whiygUoXUDXCClDSVEuVFNFOjc5NzQuSVFfQ0xPU0VQUklDRS4yMDE2LTA1LTI0LlVTRAEAAACkXQ0AAgAAAAoxNDMuNTY1MjU0AOcQwSddQNcIcWgDKF1A1wgpQ0lRLlRTRTo3OTc0LklRX0NMT1NFUFJJQ0UuMjAxOS0wMy0xMi5VU0QBAAAApF0NAAIAAAAKMjc0Ljk2NDA3OQDnEMEnXUDXCAMGAShdQNcILENJUS5OQVNEQVFHUzpFQS5JUV9DTE9TRVBSSUNFLjIwMTktMDktMjMuVVNEAQAAADttAAACAAAABTk4LjE4AOcQwSddQNcIAwYBKF1A1wgoQ0lRLlRTRTo3OTc0LklRX01BUktFVENBUC4yMDE5LTA5LTIzLlVTRAEAAACkXQ0AAgAAAAw0NzI2OS4yNDY3NjUBBgAAAAUAAAABMQEAAAAKMTk3NTc4NzA4NgMAAAADMTYwAgAAAAYxMDAwNTQEAAAAATAHAAAACTkvMjAvMjAxOecQwSddQNcIYsoFKF1A1wgiQ0lRLklRVFIzMjc2NDQ4OTIuSVFfVFJfVE9UQUxWQUxVRQEAAADc | BL1: docTAgAAAAkyMDM4NTQuMjkBBgAAAAUAAAACNTQBAAAABjEwMDUwNAIAAAAJMzI3NjQ0ODkyAwAAAAkzMjc2NDQ4OTIEAAAAAjg1BgAAAAVGYWxzZecQwSddQNcIt6P+J11A1wgpQ0lRLlRTRTo3OTc0LklRX0NMT1NFUFJJQ0UuMjAxNS0wNi0zMC5VU0QBAAAApF0NAAIAAAAKMTY3LjM3NTMwOQDnEMEnXUDXCLej/iddQNcII0NJUS5JUVRSMzE0MjIwMDU5LklRX1RSX0NMT1NFRF9EQVRFAQAAABueuhIFAAAACjIwMTUtMTAtMTQA5xDBJ11A1whiygUoXUDXCDNDSVEuRU5YVFBBOlVCSS5JUV9UT1RBTF9SRVYuQ1kyMDE3LjIwMTktMDktMjMuLi5VU0QBAAAAGXYNAAIAAAALMjAyNy4yNzE4NTQBCAAAAAUAAAABMQEAAAAKMTk2ODQ2Mjg5MQMAAAADMTYwAgAAAAIyOAQAAAABMAcAAAAJOS8yMy8yMDE5CAAAAAoxMi8zMS8yMDE3CQAAAAEw5xDBJ11A1whrQfwnXUDXCDBDSVEuRU5YVFBBOlVCSS5JUV9FQklUREEuQ1kyMDE3LjIwMTktMDktMjMuLi5VU0QBAAAAGXYNAAIAAAAKOTA3LjIwNTIxMQEIAAAABQAAAAExAQAAAAoxOTY4NDYyODkxAwAAAAMxNjACAAAABDQwNTEEAAAAATAHAAAACTkvMjMvMjAxOQgAAAAKMTIvMzEvMjAxNwkAAAABMOcQwSddQNcIYsoFKF1A1wgpQ0lRLlRTRTo3OTc0LklRX0NMT1NFUFJJQ0UuMjAxNy0wOC0wMS5VU0QBAAAApF0NAAIAAAAKMzM2LjU5OTU0NADnEMEnXUDXCAMG | BM1: AShdQNcILENJUS5UU0U6Nzk3NC5JUV9URVZfRUJJVERBLklRX0xUTS4yMDE1LTA3LTE0AQAAAKRdDQACAAAACDQzLjA4OTQ4AQcAAAAFAAAAATEBAAAACjE3NDU5MjI3NzIDAAAAATACAAAABjEwMDAzMAQAAAABMAcAAAAJNy8xNC8yMDE1CAAAAAk3LzE0LzIwMTXnEMEnXUDXCGtB/CddQNcIMENJUS5FTlhUUEE6VUJJLklRX0VCSVREQS5DWTIwMTUuMjAxOS0wOS0yMy4uLlVTRAEAAAAZdg0AAgAAAAo2MDcuMDY4MTUxAQgAAAAFAAAAATEBAAAACjE4NTU1MjI1MTYDAAAAAzE2MAIAAAAENDA1MQQAAAABMAcAAAAJOS8yMy8yMDE5CAAAAAoxMi8zMS8yMDE1CQAAAAEw5xDBJ11A1wgDBgEoXUDXCCxDSVEuVFNFOjc5NzQuSVFfVEVWX0VCSVREQS5JUV9MVE0uMjAxOC0wNi0xMgEAAACkXQ0AAgAAAAkyMC40NDc4NTEBBwAAAAUAAAABMQEAAAAKMTg4NDg2NDk2NAMAAAABMAIAAAAGMTAwMDMwBAAAAAEwBwAAAAk2LzEyLzIwMTgIAAAACTYvMTIvMjAxOOcQwSddQNcIa0H8J11A1wgsQ0lRLlRTRTo3OTc0LklRX1RFVl9FQklUREEuSVFfTFRNLjIwMTUtMTAtMjABAAAApF0NAAIAAAAJNDMuMzgxNjg1AQcAAAAFAAAAATEBAAAACjE3NDk4NTcwOTcDAAAAATACAAAABjEwMDAzMAQAAAABMAcAAAAKMTAvMjAvMjAxNQgAAAAKMTAvMjAvMjAxNecQwSddQNcIAwYBKF1A1wgvQ0lRLk5BU0RBUUdTOkFUVkkuSVFf | BN1: R1AuQ1kyMDE3LjIwMTktMDktMjMuLi5VU0QBAAAAF21AAAIAAAAENDUxNgEIAAAABQAAAAExAQAAAAoxOTQ3ODI4NzYwAwAAAAMxNjACAAAAAjEwBAAAAAEwBwAAAAk5LzIzLzIwMTkIAAAACjEyLzMxLzIwMTcJAAAAATDnEMEnXUDXCGLKBShdQNcIN0NJUS5LT1NFOkEyNTEyNzAuSVFfUkVWRU5VRV9FU1QuQ1kyMDIwLjIwMTktMDktMjMuLi5VU0QBAAAAWe4vCQIAAAAQMjE5My41NTc0MjAxMTQxOQEOAAAABQAAAAIxMQEAAAABMAIAAAAKMTAwMzczODI4OQMAAAAGMTAwMTgwBAAAAAEzBgAAAAEwBwAAAAMxNjAIAAAAATAJAAAAATEKAAAAATALAAAACzExNjEwODM3NTA1DAAAAAE3DQAAAAk5LzI0LzIwMTkQAAAACTkvMjMvMjAxOecQwSddQNcIcWgDKF1A1wgpQ0lRLlRTRTo3OTc0LklRX0NMT1NFUFJJQ0UuMjAxNi0wNy0wNS5VU0QBAAAApF0NAAIAAAAKMTQyLjU1NDk2NwDnEMEnXUDXCAMGAShdQNcIMUNJUS5OQVNEQVFHUzpFQS5JUV9FQklUREEuQ1kyMDE3LjIwMTktMDktMjMuLi5VU0QBAAAAO20AAAIAAAAEMTU0MQEIAAAABQAAAAExAQAAAAoxOTQzOTE1MDIxAwAAAAMxNjACAAAABDQwNTEEAAAAATAHAAAACTkvMjMvMjAxOQgAAAAKMTIvMzEvMjAxNwkAAAABMOcQwSddQNcIt6P+J11A1wgpQ0lRLlRTRTo3OTc0LklRX0NMT1NFUFJJQ0UuMjAxOC0xMS0xMy5VU0QBAAAApF0NAAIAAAAJMzEx | BO1: LjkwMjQ1AOcQwSddQNcIt6P+J11A1wgwQ0lRLlRTRTo3OTc0LklRX0RBX1NVUFBMLklRX0xUTS4yMDE5LTA5LTIzLi4uVVNEAQAAAKRdDQACAAAACTU5LjU0NDQ2NQEIAAAABQAAAAExAQAAAAoxOTc1NzkyNDcwAwAAAAMxNjACAAAAAjQxBAAAAAEwBwAAAAk5LzIzLzIwMTkIAAAACTYvMzAvMjAxOQkAAAABMKeZyiddQNcIYsoFKF1A1wgyQ0lRLlRTRTozNjU5LklRX0VCSVREQV9FU1QuQ1kyMDE5LjIwMTktMDktMjMuLi5VU0QBAAAAnh+CCAIAAAAQOTczLjg5OTQ3NzMyOTI2NQEOAAAABQAAAAIxMQEAAAABMAIAAAAKMTAwMTQyMjgyMQMAAAAGMTAwMTg3BAAAAAEzBgAAAAEwBwAAAAMxNjAIAAAAATAJAAAAATEKAAAAATALAAAACzExNjAzNDQ3MTMwDAAAAAE3DQAAAAk5LzI0LzIwMTkQAAAACTkvMjMvMjAxOecQwSddQNcIa0H8J11A1wgsQ0lRLlRTRTo3OTc0LklRX1RFVl9FQklUREEuSVFfTFRNLjIwMTgtMTAtMDkBAAAApF0NAAIAAAAJMTkuMjM2NDU2AQcAAAAFAAAAATEBAAAACjE5MDAyNzI3OTYDAAAAATACAAAABjEwMDAzMAQAAAABMAcAAAAJMTAvOS8yMDE4CAAAAAkxMC85LzIwMTjnEMEnXUDXCGLKBShdQNcIKUNJUS5UU0U6Nzk3NC5JUV9DTE9TRVBSSUNFLjIwMTYtMDItMDIuVVNEAQAAAKRdDQACAAAACjE0Mi43MDg3NTgA5xDBJ11A1whxaAMoXUDXCClDSVEuVFNFOjc5NzQuSVFfQ0xP | BP1: U0VQUklDRS4yMDE4LTA0LTE3LlVTRAEAAACkXQ0AAgAAAAk0MTQuNjE3MDgA5xDBJ11A1whrQfwnXUDXCCpDSVEuVFNFOjk2ODQuSVFfVEVWLjQ0NTYxLjIwMTktMDktMjMuLi5VU0QBAAAAqX0NAAIAAAALNDEzMC42MDY3MzYBBgAAAAUAAAABMQEAAAAKMTk3NTc4NjYwOQMAAAADMTYwAgAAAAYxMDAwNjAEAAAAATAHAAAACTkvMjAvMjAxOecQwSddQNcIYsoFKF1A1wgsQ0lRLlRTRTo3OTc0LklRX1RFVl9FQklUREEuSVFfTFRNLjIwMTgtMDYtMTkBAAAApF0NAAIAAAAIMTcuMDAxNTcBBwAAAAUAAAABMQEAAAAKMTg4NDg2NDk2NAMAAAABMAIAAAAGMTAwMDMwBAAAAAEwBwAAAAk2LzE5LzIwMTgIAAAACTYvMTkvMjAxOOcQwSddQNcIcWgDKF1A1wgpQ0lRLlRTRTo3OTc0LklRX0NMT1NFUFJJQ0UuMjAxNi0wNi0yOC5VU0QBAAAApF0NAAIAAAAKMTM0LjY3MzQxOADnEMEnXUDXCLej/iddQNcILkNJUS5UU0U6Nzk3NC5JUV9FQklUREEuQ1kyMDE2LjIwMTktMDktMjMuLi5VU0QBAAAApF0NAAIAAAAKMjIyLjI0NDA5OQEIAAAABQAAAAExAQAAAAoxODI3NzY3Nzk3AwAAAAMxNjACAAAABDQwNTEEAAAAATAHAAAACTkvMjMvMjAxOQgAAAAKMTIvMzEvMjAxNgkAAAABMKeZyiddQNcIYsoFKF1A1wgpQ0lRLlRTRTo3OTc0LklRX0NMT1NFUFJJQ0UuMjAxNy0xMS0yMS5VU0QBAAAApF0NAAIAAAAKMzk1Ljk0 | BQ1: MjcxMQDnEMEnXUDXCAMGAShdQNcILENJUS5UU0U6Nzk3NC5JUV9URVZfRUJJVERBLklRX0xUTS4yMDE5LTAxLTA4AQAAAKRdDQACAAAACTEyLjk3NzI5MwEHAAAABQAAAAExAQAAAAoxOTIxNTE4NDIzAwAAAAEwAgAAAAYxMDAwMzAEAAAAATAHAAAACDEvOC8yMDE5CAAAAAgxLzgvMjAxOecQwSddQNcIt6P+J11A1wgsQ0lRLkVOWFRQQTpVQkkuSVFfR1AuSVFfTFRNLjIwMTktMDktMjMuLi5VU0QBAAAAGXYNAAIAAAALMTcwMi4wNzYzMTkBCAAAAAUAAAABMQEAAAAKMTk2ODQ2Mjg3MQMAAAADMTYwAgAAAAIxMAQAAAABMAcAAAAJOS8yMy8yMDE5CAAAAAkzLzMxLzIwMTkJAAAAATDnEMEnXUDXCAMGAShdQNcILENJUS5UU0U6Nzk3NC5JUV9URVZfRUJJVERBLklRX0xUTS4yMDE2LTA1LTMxAQAAAKRdDQACAAAACTI0LjI5ODc5MgEHAAAABQAAAAExAQAAAAoxNzg3OTI1ODc2AwAAAAEwAgAAAAYxMDAwMzAEAAAAATAHAAAACTUvMzEvMjAxNggAAAAJNS8zMS8yMDE25xDBJ11A1wgDBgEoXUDXCClDSVEuVFNFOjc5NzQuSVFfQ0xPU0VQUklDRS4yMDE1LTA4LTE4LlVTRAEAAACkXQ0AAgAAAAoxOTguOTc4OTg2AOcQwSddQNcIcWgDKF1A1wg+Q0lRLk5BU0RBUUdTOkFUVkkuSVFfVE9UQUxfREVCVF9FUVVJVFkuSVFfTFRNLjIwMTktMDktMjMuLi5VU0QBAAAAF21AAAIAAAAHMjQuNzMwNwEIAAAABQAAAAEx | BR1: AQAAAAoxOTc1MDM5MDUyAwAAAAMxNjACAAAABDQwMzQEAAAAATAHAAAACTkvMjMvMjAxOQgAAAAJNi8zMC8yMDE5CQAAAAEwp5nKJ11A1whrQfwnXUDXCDVDSVEuS09TRTpBMjUxMjcwLklRX1RPVEFMX1JFVi5JUV9MVE0uMjAxOS0wOS0yMy4uLlVTRAEAAABZ7i8JAgAAAAsxNzQyLjk3MzA5NAEIAAAABQAAAAExAQAAAAoxOTgxMTcwMDUyAwAAAAMxNjACAAAAAjI4BAAAAAEwBwAAAAk5LzIzLzIwMTkIAAAACTYvMzAvMjAxOQkAAAABMOcQwSddQNcIAwYBKF1A1wgsQ0lRLlRTRTo3OTc0LklRX1RFVl9FQklUREEuSVFfTFRNLjIwMTgtMDQtMDMBAAAApF0NAAIAAAAJMjUuMzkyODMzAQcAAAAFAAAAATEBAAAACjE4NzQxOTMzNDADAAAAATACAAAABjEwMDAzMAQAAAABMAcAAAAINC8zLzIwMTgIAAAACDQvMy8yMDE45xDBJ11A1wi3o/4nXUDXCDBDSVEuVFNFOjc5NzQuSVFfREFfU1VQUEwuQ1kyMDE3LjIwMTktMDktMjMuLi5VU0QBAAAApF0NAAIAAAAJNDcuMjc2NjAxAQgAAAAFAAAAATEBAAAACjE4NzQxOTMzNDADAAAAAzE2MAIAAAACNDEEAAAAATAHAAAACTkvMjMvMjAxOQgAAAAKMTIvMzEvMjAxNwkAAAABMKeZyiddQNcIYsoFKF1A1wgsQ0lRLlRTRTo3OTc0LklRX1RFVl9FQklUREEuSVFfTFRNLjIwMTUtMTItMDEBAAAApF0NAAIAAAAJMzIuNjcwMDI3AQcAAAAFAAAAATEBAAAACjE3NjUxNTM2 | BS1: NzEDAAAAATACAAAABjEwMDAzMAQAAAABMAcAAAAJMTIvMS8yMDE1CAAAAAkxMi8xLzIwMTXnEMEnXUDXCGtB/CddQNcILUNJUS5OQVNEQVFHUzpFQS5JUV9HUC5DWTIwMTcuMjAxOS0wOS0yMy4uLlVTRAEAAAA7bQAAAgAAAAQzODY0AQgAAAAFAAAAATEBAAAACjE5NDM5MTUwMjEDAAAAAzE2MAIAAAACMTAEAAAAATAHAAAACTkvMjMvMjAxOQgAAAAKMTIvMzEvMjAxNwkAAAABMOcQwSddQNcIAwYBKF1A1wg6Q0lRLktPU0U6QTI1MTI3MC5JUV9ESUxVVF9FUFNfRVhDTC5JUV9MVE0uMjAxOS0wOS0yMy4uLlVTRAEAAABZ7i8JAgAAAAgxLjM4MDA5MQEIAAAABQAAAAExAQAAAAoxOTgxMTcwMDUyAwAAAAMxNjACAAAAAzE0MgQAAAABMAcAAAAJOS8yMy8yMDE5CAAAAAk2LzMwLzIwMTkJAAAAATDnEMEnXUDXCAMGAShdQNcILENJUS5UU0U6Nzk3NC5JUV9URVZfRUJJVERBLklRX0xUTS4yMDE3LTA1LTAyAQAAAKRdDQACAAAACTQyLjQxODY1MQEHAAAABQAAAAExAQAAAAoxODM4MjA0MDc0AwAAAAEwAgAAAAYxMDAwMzAEAAAAATAHAAAACDUvMi8yMDE3CAAAAAg1LzIvMjAxN+cQwSddQNcIt6P+J11A1wgpQ0lRLlRTRTo3OTc0LklRX0NMT1NFUFJJQ0UuMjAxOC0wNC0yNC5VU0QBAAAApF0NAAIAAAAKNDI0LjI2NDYzMwDnEMEnXUDXCHFoAyhdQNcILENJUS5UU0U6Nzk3NC5JUV9URVZfRUJJVERBLklRX0xU | BT1: TS4yMDE1LTA2LTE2AQAAAKRdDQACAAAACTQ0LjIxNjc4MQEHAAAABQAAAAExAQAAAAoxNzMyNjYwNjYyAwAAAAEwAgAAAAYxMDAwMzAEAAAAATAHAAAACTYvMTYvMjAxNQgAAAAJNi8xNi8yMDE15xDBJ11A1whrQfwnXUDXCCpDSVEuVFNFOjc5NzQuSVFfR1AuQ1kyMDE4LjIwMTktMDktMjMuLi5VU0QBAAAApF0NAAIAAAALNDQzMi40NzUwNTIBCAAAAAUAAAABMQEAAAAKMTk0NDU5NzY1OAMAAAADMTYwAgAAAAIxMAQAAAABMAcAAAAJOS8yMy8yMDE5CAAAAAoxMi8zMS8yMDE4CQAAAAEw5xDBJ11A1whrQfwnXUDXCC1DSVEuTkFTREFRR1M6RUEuSVFfR1AuSVFfTFRNLjIwMTktMDktMjMuLi5VU0QBAAAAO20AAAIAAAAEMzcyOAEIAAAABQAAAAExAQAAAAoxOTc0MjM1ODEyAwAAAAMxNjACAAAAAjEwBAAAAAEwBwAAAAk5LzIzLzIwMTkIAAAACTYvMzAvMjAxOQkAAAABMOcQwSddQNcIYsoFKF1A1wgsQ0lRLlRTRTo3OTc0LklRX1RFVl9FQklUREEuSVFfTFRNLjIwMTYtMTAtMDQBAAAApF0NAAIAAAAJNjIuMDA4NzI4AQcAAAAFAAAAATEBAAAACjE4MDI3NzY3NzUDAAAAATACAAAABjEwMDAzMAQAAAABMAcAAAAJMTAvNC8yMDE2CAAAAAkxMC80LzIwMTbnEMEnXUDXCGtB/CddQNcILENJUS5UU0U6Nzk3NC5JUV9URVZfRUJJVERBLklRX0xUTS4yMDE2LTA0LTA1AQAAAKRdDQACAAAACTIwLjQ3MDA0NQEH | BU1: AAAABQAAAAExAQAAAAoxNzc2NTg0MDQzAwAAAAEwAgAAAAYxMDAwMzAEAAAAATAHAAAACDQvNS8yMDE2CAAAAAg0LzUvMjAxNucQwSddQNcIAwYBKF1A1wgqQ0lRLlRTRTozNjU5LklRX0dQLkNZMjAxOC4yMDE5LTA5LTIzLi4uVVNEAQAAAJ4fgggCAAAACzE3ODcuOTc3OTQ0AQgAAAAFAAAAATEBAAAACjE5NTE4Njc5MjkDAAAAAzE2MAIAAAACMTAEAAAAATAHAAAACTkvMjMvMjAxOQgAAAAKMTIvMzEvMjAxOAkAAAABMOcQwSddQNcIa0H8J11A1wgsQ0lRLlRTRTo3OTc0LklRX1RFVl9FQklUREEuSVFfTFRNLjIwMTgtMDEtMzABAAAApF0NAAIAAAAJNDcuNTIxNjc4AQcAAAAFAAAAATEBAAAACjE4NjU3OTIzNjMDAAAAATACAAAABjEwMDAzMAQAAAABMAcAAAAJMS8zMC8yMDE4CAAAAAkxLzMwLzIwMTjnEMEnXUDXCGLKBShdQNcII0NJUS5JUVRSMzI3NjQ0ODkyLklRX1RSX0NMT1NFRF9EQVRFAQAAANx2hxMFAAAACjIwMTYtMDctMDQA5xDBJ11A1whrQfwnXUDXCClDSVEuVFNFOjc5NzQuSVFfQ0xPU0VQUklDRS4yMDE4LTA3LTAzLlVTRAEAAACkXQ0AAgAAAAkzMjkuNDI5ODYA5xDBJ11A1wgDBgEoXUDXCClDSVEuVFNFOjc5NzQuSVFfQ0xPU0VQUklDRS4yMDE5LTAyLTA1LlVTRAEAAACkXQ0AAgAAAAoyODQuMzg3ODExAOcQwSddQNcIt6P+J11A1wgpQ0lRLlRTRTo3OTc0LklRX0NMT1NFUFJJQ0Uu | BV1: MjAxOC0wMS0yMy5VU0QBAAAApF0NAAIAAAAKNDQ5LjM2Nzk2NwDnEMEnXUDXCGtB/CddQNcIKkNJUS5UU0U6MzY1OS5JUV9URVYuNDI3MzUuMjAxOS0wOS0yMy4uLlVTRAEAAACeH4IIAgAAAAs0MDQwLjI1NTUwNQEGAAAABQAAAAExAQAAAAoxODE4NTM0MjUwAwAAAAMxNjACAAAABjEwMDA2MAQAAAABMAcAAAAKMTIvMzEvMjAxNucQwSddQNcIcWgDKF1A1wgpQ0lRLktPU0U6QTI1MTI3MC5JUV9URVYuLjIwMTktMDktMjMuLi5VU0QBAAAAWe4vCQIAAAALNTIyOC42MjI5NjkBBgAAAAUAAAABMQEAAAAKMTk4MTE1NjU0MAMAAAADMTYwAgAAAAYxMDAwNjAEAAAAATAHAAAACTkvMjMvMjAxOecQwSddQNcIt6P+J11A1wgsQ0lRLlRTRTo3OTc0LklRX1RFVl9FQklUREEuSVFfTFRNLjIwMTYtMTAtMTgBAAAApF0NAAIAAAAJNjIuMTUyMjg2AQcAAAAFAAAAATEBAAAACjE4MDI3NzY3NzUDAAAAATACAAAABjEwMDAzMAQAAAABMAcAAAAKMTAvMTgvMjAxNggAAAAKMTAvMTgvMjAxNucQwSddQNcIAwYBKF1A1wgpQ0lRLlRTRTo3OTc0LklRX0NMT1NFUFJJQ0UuMjAxNy0wOS0yNi5VU0QBAAAApF0NAAIAAAAKMzYwLjQ3NDQ1MgDnEMEnXUDXCAMGAShdQNcIM0NJUS5OQVNEQVFHUzpUVFdPLklRX0VCSVREQS5DWTIwMTguMjAxOS0wOS0yMy4uLlVTRAEAAABRqgUAAgAAAAcyOTYuOTM3AQgAAAAFAAAAATEBAAAA | BW1: CjE5NDM5MjUyMzYDAAAAAzE2MAIAAAAENDA1MQQAAAABMAcAAAAJOS8yMy8yMDE5CAAAAAoxMi8zMS8yMDE4CQAAAAEw5xDBJ11A1wgDBgEoXUDXCClDSVEuVFNFOjc5NzQuSVFfQ0xPU0VQUklDRS4yMDE4LTA4LTA3LlVTRAEAAACkXQ0AAgAAAAozMzQuOTM3MjY4AOcQwSddQNcIa0H8J11A1wgpQ0lRLlRTRTo3OTc0LklRX0NMT1NFUFJJQ0UuMjAxNy0wMi0yMS5VU0QBAAAApF0NAAIAAAAKMjAzLjc2MDc5NQDnEMEnXUDXCGtB/CddQNcILENJUS5UU0U6Nzk3NC5JUV9URVZfRUJJVERBLklRX0xUTS4yMDE4LTA5LTA0AQAAAKRdDQACAAAACTE5LjAxMTM4OAEHAAAABQAAAAExAQAAAAoxOTAwMjcyNzk2AwAAAAEwAgAAAAYxMDAwMzAEAAAAATAHAAAACDkvNC8yMDE4CAAAAAg5LzQvMjAxOOcQwSddQNcIa0H8J11A1wgsQ0lRLlRTRTo3OTc0LklRX1RFVl9FQklUREEuSVFfTFRNLjIwMTgtMDctMTcBAAAApF0NAAIAAAAJMTcuODEyNzk3AQcAAAAFAAAAATEBAAAACjE4OTUxOTAzMTIDAAAAATACAAAABjEwMDAzMAQAAAABMAcAAAAJNy8xNy8yMDE4CAAAAAk3LzE3LzIwMTjnEMEnXUDXCHFoAyhdQNcINENJUS5UU0U6Nzk3NC5JUV9HUk9TU19QUk9GSVQuQ1kyMDE4LjIwMTktMDktMjMuLi5VU0QBAAAApF0NAAIAAAALNDQzMi40NzUwNTIBCAAAAAUAAAABMQEAAAAKMTk0NDU5NzY1OAMAAAADMTYwAgAA | BX1: AAIxMAQAAAABMAcAAAAJOS8yMy8yMDE5CAAAAAoxMi8zMS8yMDE4CQAAAAEwp5nKJ11A1whiygUoXUDXCDlDSVEuRU5YVFBBOlVCSS5JUV9FRkZFQ1RfVEFYX1JBVEUuSVFfTFRNLjIwMTktMDktMjMuLi5VU0QBAAAAGXYNAAIAAAAGMzIuNjI2AQgAAAAFAAAAATEBAAAACjE5Njg0NjI4NzEDAAAAAjUwAgAAAAQ0Mzc2BAAAAAEwBwAAAAk5LzIzLzIwMTkIAAAACTMvMzEvMjAxOQkAAAABMKeZyiddQNcIcWgDKF1A1wg4Q0lRLk5BU0RBUUdTOkFUVkkuSVFfUkVWRU5VRV9FU1QuQ1kyMDIwLjIwMTktMDktMjMuLi5VU0QBAAAAF21AAAIAAAAKNzAxNC43MTQxMgEOAAAABQAAAAIxMQEAAAABMAIAAAAKMTAwMDc4MzExOAMAAAAGMTAwMTgwBAAAAAEyBgAAAAEwBwAAAAMxNjAIAAAAATAJAAAAATEKAAAAATALAAAACzExNjEwMDg1NjQ2DAAAAAE3DQAAAAk5LzI0LzIwMTkQAAAACTkvMjMvMjAxOecQwSddQNcIt6P+J11A1wgpQ0lRLlRTRTo3OTc0LklRX0NMT1NFUFJJQ0UuMjAxNy0wOC0xNS5VU0QBAAAApF0NAAIAAAAKMzMxLjYyODcxMwDnEMEnXUDXCHFoAyhdQNcIM0NJUS5UU0U6MzY1OS5JUV9SRVZFTlVFX0VTVC5DWTIwMjEuMjAxOS0wOS0yMy4uLlVTRAEAAACeH4IIAgAAAA8yNzYzLjU5Mjg0NDM1MTgBDgAAAAUAAAACMTEBAAAAATACAAAACjEwMDE2NDg4MjIDAAAABjEwMDE4MAQAAAABMwYAAAAB | BY1: MAcAAAADMTYwCAAAAAEwCQAAAAExCgAAAAEwCwAAAAsxMTYwMzQ0NzIzMwwAAAABNw0AAAAJOS8yNC8yMDE5EAAAAAk5LzIzLzIwMTnnEMEnXUDXCAMGAShdQNcIKUNJUS5UU0U6Nzk3NC5JUV9DTE9TRVBSSUNFLjIwMTUtMTEtMTAuVVNEAQAAAKRdDQACAAAACjE2NS41NTA4MTQA5xDBJ11A1whxaAMoXUDXCEJDSVEuVFNFOjc5NzQuSVFfQ0hBTkdFX05FVF9XT1JLSU5HX0NBUElUQUwuSVFfTFRNLjIwMTktMDktMjMuLi5VU0QBAAAApF0NAAIAAAALLTYxMy4yMjA3NzYBCAAAAAUAAAABMQEAAAAKMTk3NTc5MjQ3MAMAAAADMTYwAgAAAAQ0NDIxBAAAAAEwBwAAAAk5LzIzLzIwMTkIAAAACTYvMzAvMjAxOQkAAAABMKeZyiddQNcIcWgDKF1A1wgpQ0lRLlRTRTo3OTc0LklRX0NMT1NFUFJJQ0UuMjAxOC0xMC0yMy5VU0QBAAAApF0NAAIAAAAKMzM0LjQwMjg1MwDnEMEnXUDXCAMGAShdQNcIKUNJUS5UU0U6Nzk3NC5JUV9DTE9TRVBSSUNFLjIwMTUtMDgtMTEuVVNEAQAAAKRdDQACAAAACjE5Ny42OTM1MDEA5xDBJ11A1whrQfwnXUDXCDJDSVEuVFNFOjM2NTkuSVFfVE9UQUxfREVCVC5JUV9MVE0uMjAxOS0wOS0yMy4uLlVTRAEAAACeH4IIAgAAAAk5Ny44MjQzNzUBCAAAAAUAAAABMQEAAAAKMTk3NTc5MjQzNwMAAAADMTYwAgAAAAQ0MTczBAAAAAEwBwAAAAk5LzIzLzIwMTkIAAAACTYvMzAvMjAxOQkA | BZ1: AAABMKeZyiddQNcIt6P+J11A1wgsQ0lRLkVOWFRQQTpVQkkuSVFfVEVWLjQ0MTk2LjIwMTktMDktMjMuLi5VU0QBAAAAGXYNAAIAAAALODc2OS42NTkxMDgBBgAAAAUAAAABMQEAAAAKMTk2ODQ2Mjg2OQMAAAADMTYwAgAAAAYxMDAwNjAEAAAAATAHAAAACTkvMjMvMjAxOecQwSddQNcIAwYBKF1A1wgpQ0lRLklRVFI1NTE3OTk2NjkuSVFfVFJfSU1QTElFRF9FVl9FQklUREEBAAAAdcvjIAIAAAAIMTguMzMxNDIBBgAAAAUAAAACNTQBAAAABjEwMjA5NAIAAAAJNTUxNzk5NjY5AwAAAAk1NTE4MDAzMDkEAAAAAjMyBgAAAAVGYWxzZecQwSddQNcIYsoFKF1A1wguQ0lRLktPU0U6QTI1MTI3MC5JUV9URVYuNDQ5MjYuMjAxOS0wOS0yMy4uLlVTRAEAAABZ7i8JAgAAAAs1MjI4LjYyMjk2OQEGAAAABQAAAAExAQAAAAoxOTgxMTU2NTQwAwAAAAMxNjACAAAABjEwMDA2MAQAAAABMAcAAAAJOS8yMy8yMDE55xDBJ11A1whiygUoXUDXCClDSVEuVFNFOjc5NzQuSVFfQ0xPU0VQUklDRS4yMDE3LTExLTA3LlVTRAEAAACkXQ0AAgAAAAozNzUuMTY0MzIyAOcQwSddQNcIcWgDKF1A1wg0Q0lRLkVOWFRQQTpVQkkuSVFfRUJJVERBX0VTVC5DWTIwMjIuMjAxOS0wOS0yMy4uLlVTRAEAAAAZdg0AAgAAAA8xNTkyLjU0NjA3NDE2NTYBDgAAAAUAAAACMTEBAAAAATACAAAACDQ3NTE0NzE5AwAAAAYxMDAxODcEAAAAATMG | CA1: AAAAATAHAAAAAzE2MAgAAAABMAkAAAABMQoAAAABMAsAAAALMTE1OTkyNTkzOTkMAAAAATcNAAAACTkvMjQvMjAxORAAAAAJOS8yMy8yMDE55xDBJ11A1wgDBgEoXUDXCCxDSVEuVFNFOjc5NzQuSVFfVEVWX0VCSVREQS5JUV9MVE0uMjAxNy0xMC0xMAEAAACkXQ0AAgAAAAk1MS42NjUxNTEBBwAAAAUAAAABMQEAAAAKMTg1NDA0Mzg4OAMAAAABMAIAAAAGMTAwMDMwBAAAAAEwBwAAAAoxMC8xMC8yMDE3CAAAAAoxMC8xMC8yMDE35xDBJ11A1whxaAMoXUDXCC5DSVEuS09TRTpBMjUxMjcwLklRX0dQLkNZMjAxNy4yMDE5LTA5LTIzLi4uVVNEAQAAAFnuLwkCAAAACzIyNjkuNDgyNjM2AQgAAAAFAAAAATEBAAAACjE5NTA5MzY3MDADAAAAAzE2MAIAAAACMTAEAAAAATAHAAAACTkvMjMvMjAxOQgAAAAKMTIvMzEvMjAxNwkAAAABMOcQwSddQNcIt6P+J11A1wgpQ0lRLlRTRTo3OTc0LklRX0NMT1NFUFJJQ0UuMjAxNy0wNy0wNC5VU0QBAAAApF0NAAIAAAAKMzEwLjAyMzQxMwDnEMEnXUDXCAMGAShdQNcIKUNJUS5UU0U6Nzk3NC5JUV9DTE9TRVBSSUNFLjIwMTktMDktMTcuVVNEAQAAAKRdDQACAAAACjM4Ny4zMjUyNDUAp5nKJ11A1wi3o/4nXUDXCDdDSVEuVFNFOjc5NzQuSVFfQ0FTSF9BQ1FVSVJFX0NGLkNZMjAxNy4yMDE5LTA5LTIzLi4uVVNEAQAAAKRdDQADAAAAAACnmconXUDXCGLKBShdQNcILENJ | CB1: US5UU0U6Nzk3NC5JUV9URVZfRUJJVERBLklRX0xUTS4yMDE2LTA1LTE3AQAAAKRdDQACAAAACTIzLjA4MTMwMgEHAAAABQAAAAExAQAAAAoxNzg3OTI1ODc2AwAAAAEwAgAAAAYxMDAwMzAEAAAAATAHAAAACTUvMTcvMjAxNggAAAAJNS8xNy8yMDE25xDBJ11A1whrQfwnXUDXCDNDSVEuTkFTREFRR1M6QVRWSS5JUV9FQklUREEuQ1kyMDE4LjIwMTktMDktMjMuLi5VU0QBAAAAF21AAAIAAAAEMjUwNwEIAAAABQAAAAExAQAAAAoxOTQ3ODI4NzY5AwAAAAMxNjACAAAABDQwNTEEAAAAATAHAAAACTkvMjMvMjAxOQgAAAAKMTIvMzEvMjAxOAkAAAABMOcQwSddQNcIcWgDKF1A1wg4Q0lRLk5BU0RBUUdTOkFUVkkuSVFfUkVWRU5VRV9FU1QuQ1kyMDE5LjIwMTktMDktMjMuLi5VU0QBAAAAF21AAAIAAAAKNjM0NS40NTQ1NwEOAAAABQAAAAIxMQEAAAABMAIAAAAKMTAwMDc3ODQ1MAMAAAAGMTAwMTgwBAAAAAEyBgAAAAEwBwAAAAMxNjAIAAAAATAJAAAAATEKAAAAATALAAAACzExNjEwMDg1Njc2DAAAAAE3DQAAAAk5LzI0LzIwMTkQAAAACTkvMjMvMjAxOecQwSddQNcIa0H8J11A1wgpQ0lRLlRTRTo3OTc0LklRX0NMT1NFUFJJQ0UuMjAxNy0wNC0xMS5VU0QBAAAApF0NAAIAAAAKMjM0LjM3OTk4NQDnEMEnXUDXCAMGAShdQNcIKkNJUS5UU0U6Nzk3NC5JUV9HUC5JUV9MVE0uMjAxOS0wOS0yMy4uLlVTRAEA | CC1: AACkXQ0AAgAAAAs0NjU0LjYzNjYzOQEIAAAABQAAAAExAQAAAAoxOTc1NzkyNDcwAwAAAAMxNjACAAAAAjEwBAAAAAEwBwAAAAk5LzIzLzIwMTkIAAAACTYvMzAvMjAxOQkAAAABMOcQwSddQNcIt6P+J11A1wgsQ0lRLlRTRTo3OTc0LklRX1RFVl9FQklUREEuSVFfTFRNLjIwMTktMDktMTABAAAApF0NAAIAAAAJMTUuNDA5NDYxAQcAAAAFAAAAATEBAAAACjE5NzU3OTI0NzADAAAAATACAAAABjEwMDAzMAQAAAABMAcAAAAJOS8xMC8yMDE5CAAAAAk5LzEwLzIwMTmnmconXUDXCHFoAyhdQNcIKkNJUS5UU0U6Nzk3NC5JUV9URVYuNDQ5MjYuMjAxOS0wOS0yMy4uLlVTRAEAAACkXQ0AAgAAAAwzODg3MS4zMjkxNDEBBgAAAAUAAAABMQEAAAAKMTk3NTc4NzA4NgMAAAADMTYwAgAAAAYxMDAwNjAEAAAAATAHAAAACTkvMjAvMjAxOecQwSddQNcIYsoFKF1A1wguQ0lRLlRTRTo3OTc0LklRX0VCSVREQS5DWTIwMTUuMjAxOS0wOS0yMy4uLlVTRAEAAACkXQ0AAgAAAAozNjUuOTA0NzYyAQgAAAAFAAAAATEBAAAACjE3NzY1ODQwNDMDAAAAAzE2MAIAAAAENDA1MQQAAAABMAcAAAAJOS8yMy8yMDE5CAAAAAoxMi8zMS8yMDE1CQAAAAEwp5nKJ11A1whiygUoXUDXCClDSVEuVFNFOjc5NzQuSVFfQ0xPU0VQUklDRS4yMDE2LTAyLTIzLlVTRAEAAACkXQ0AAgAAAAkxNDUuNDYyNjYA5xDBJ11A1whrQfwnXUDXCDRD | CD1: SVEuTkFTREFRR1M6VFRXTy5JUV9QRV9FWENMLklRX0xUTS4yMDE5LTA5LTIzLi4uVVNEAQAAAFGqBQACAAAACTQ2LjY1NjU5MgEHAAAABQAAAAExAQAAAAoxOTc0MzA0MDY2AwAAAAEwAgAAAAYxMDAwMjcEAAAAATAHAAAACTkvMjMvMjAxOQgAAAAJOS8yMy8yMDE55xDBJ11A1whrQfwnXUDXCCpDSVEuVFNFOjc5NzQuSVFfVEVWLjQzMTAwLjIwMTktMDktMjMuLi5VU0QBAAAApF0NAAIAAAAMMzU1MTIuMDUxODA3AQYAAAAFAAAAATEBAAAACjE4NjU3ODIxMzEDAAAAAzE2MAIAAAAGMTAwMDYwBAAAAAEwBwAAAAoxMi8zMS8yMDE35xDBJ11A1whxaAMoXUDXCClDSVEuVFNFOjc5NzQuSVFfQ0xPU0VQUklDRS4yMDE3LTAxLTE3LlVTRAEAAACkXQ0AAgAAAAoyMDkuMDU5MDY3AOcQwSddQNcIAwYBKF1A1wgpQ0lRLlRTRTo3OTc0LklRX0NMT1NFUFJJQ0UuMjAxNi0xMi0xMy5VU0QBAAAApF0NAAIAAAAKMjQ1LjYxMzI3NgDnEMEnXUDXCLej/iddQNcIKUNJUS5UU0U6Nzk3NC5JUV9DTE9TRVBSSUNFLjIwMTktMDUtMDcuVVNEAQAAAKRdDQACAAAACjMzNy4xNTI5NDEA5xDBJ11A1wgDBgEoXUDXCDhDSVEuRU5YVFBBOlVCSS5JUV9ESUxVVF9FUFNfRVhDTC5JUV9MVE0uMjAxOS0wOS0yMy4uLlVTRAEAAAAZdg0AAgAAAAgwLjk5MzI3MgEIAAAABQAAAAExAQAAAAoxOTY4NDYyODcxAwAAAAMxNjACAAAAAzE0 | CE1: MgQAAAABMAcAAAAJOS8yMy8yMDE5CAAAAAkzLzMxLzIwMTkJAAAAATDnEMEnXUDXCAMGAShdQNcIIkNJUS5UU0U6MzY1OS5JUV9URVYuMjAxOS0wOS0yMy5VU0QBAAAAnh+CCAIAAAALNzAxMS4zMDQwMDYBBgAAAAUAAAABMQEAAAAKMTk3NTc4NjYyMgMAAAADMTYwAgAAAAYxMDAwNjAEAAAAATAHAAAACTkvMjAvMjAxOecQwSddQNcIa0H8J11A1wgsQ0lRLlRTRTo3OTc0LklRX1RFVl9FQklUREEuSVFfTFRNLjIwMTUtMDYtMDIBAAAApF0NAAIAAAAJNDYuODI3MzM1AQcAAAAFAAAAATEBAAAACjE3MzI2NjA2NjIDAAAAATACAAAABjEwMDAzMAQAAAABMAcAAAAINi8yLzIwMTUIAAAACDYvMi8yMDE15xDBJ11A1wgDBgEoXUDXCCxDSVEuVFNFOjc5NzQuSVFfVEVWX0VCSVREQS5JUV9MVE0uMjAxNy0wNi0yNwEAAACkXQ0AAgAAAAk2NS4xMjg5OTIBBwAAAAUAAAABMQEAAAAKMTgzODIwNDA3NAMAAAABMAIAAAAGMTAwMDMwBAAAAAEwBwAAAAk2LzI3LzIwMTcIAAAACTYvMjcvMjAxN+cQwSddQNcIt6P+J11A1wgqQ0lRLlRTRTo5Njg0LklRX0dQLkNZMjAxNS4yMDE5LTA5LTIzLi4uVVNEAQAAAKl9DQACAAAACjc4Ny4zMDQ1MzUBCAAAAAUAAAABMQEAAAAKMTc3NTgxMjAxNgMAAAADMTYwAgAAAAIxMAQAAAABMAcAAAAJOS8yMy8yMDE5CAAAAAoxMi8zMS8yMDE1CQAAAAEw5xDBJ11A1whrQfwnXUDXCCxD | CF1: SVEuVFNFOjc5NzQuSVFfVEVWX0VCSVREQS5JUV9MVE0uMjAxNy0wMS0wMwEAAACkXQ0AAgAAAAk1MS43MTk1NDQBBwAAAAUAAAABMQEAAAAKMTgxODA2ODIyMQMAAAABMAIAAAAGMTAwMDMwBAAAAAEwBwAAAAoxMi8zMC8yMDE2CAAAAAoxMi8zMC8yMDE25xDBJ11A1whiygUoXUDXCCxDSVEuVFNFOjc5NzQuSVFfVEVWX0VCSVREQS5JUV9MVE0uMjAxOC0wNC0yNAEAAACkXQ0AAgAAAAkyNS40MTI5MTgBBwAAAAUAAAABMQEAAAAKMTg3NDE5MzM0MAMAAAABMAIAAAAGMTAwMDMwBAAAAAEwBwAAAAk0LzI0LzIwMTgIAAAACTQvMjQvMjAxOOcQwSddQNcIYsoFKF1A1wgpQ0lRLlRTRTo3OTc0LklRX0NMT1NFUFJJQ0UuMjAxOS0wNS0yMS5VU0QBAAAApF0NAAIAAAAKMzQzLjI1OTk3NADnEMEnXUDXCHFoAyhdQNcIKUNJUS5UU0U6Nzk3NC5JUV9DTE9TRVBSSUNFLjIwMTgtMTEtMjAuVVNEAQAAAKRdDQACAAAACjI3Ny4zMTM4OTgA5xDBJ11A1wgDBgEoXUDXCClDSVEuVFNFOjc5NzQuSVFfQ0xPU0VQUklDRS4yMDE5LTAzLTA1LlVTRAEAAACkXQ0AAgAAAAoyNzEuMTI3Mzg1AOcQwSddQNcIt6P+J11A1wgpQ0lRLlRTRTozNjU5LklRX0NMT1NFUFJJQ0UuMjAxOS0wOS0yMy5VU0QBAAAAnh+CCAIAAAAJMTMuMDUzOTEyAOcQwSddQNcIa0H8J11A1wgyQ0lRLktPU0U6QTI1MTI3MC5JUV9FQklUREEuQ1kyMDE2 | CG1: LjIwMTktMDktMjMuLi5VU0QBAAAAWe4vCQIAAAAKMjY5LjM3MDM5OQEIAAAABQAAAAExAQAAAAoxODgwMjYyMTMyAwAAAAMxNjACAAAABDQwNTEEAAAAATAHAAAACTkvMjMvMjAxOQgAAAAKMTIvMzEvMjAxNgkAAAABMOcQwSddQNcIYsoFKF1A1wgpQ0lRLlRTRTo3OTc0LklRX0NMT1NFUFJJQ0UuMjAxNi0wMS0xMi5VU0QBAAAApF0NAAIAAAAKMTIyLjc2MDg0NQDnEMEnXUDXCLej/iddQNcIKUNJUS5UU0U6Nzk3NC5JUV9DTE9TRVBSSUNFLjIwMTUtMDUtMTkuVVNEAQAAAKRdDQACAAAACjE4Mi43NTI0NzMA5xDBJ11A1whrQfwnXUDXCCxDSVEuVFNFOjc5NzQuSVFfVEVWX0VCSVREQS5JUV9MVE0uMjAxOC0wMi0wNgEAAACkXQ0AAgAAAAkyNC4xODc3NzEBBwAAAAUAAAABMQEAAAAKMTg3MjYwODY4MgMAAAABMAIAAAAGMTAwMDMwBAAAAAEwBwAAAAgyLzYvMjAxOAgAAAAIMi82LzIwMTjnEMEnXUDXCLej/iddQNcIKUNJUS5UU0U6Nzk3NC5JUV9DTE9TRVBSSUNFLjIwMTktMDEtMjkuVVNEAQAAAKRdDQACAAAACjMwNi4xMTU5MDQA5xDBJ11A1whxaAMoXUDXCCxDSVEuVFNFOjc5NzQuSVFfVEVWX0VCSVREQS5JUV9MVE0uMjAxNi0wOC0xNgEAAACkXQ0AAgAAAAk0Ny44MTI0NTkBBwAAAAUAAAABMQEAAAAKMTgwMjc3Njc3NQMAAAABMAIAAAAGMTAwMDMwBAAAAAEwBwAAAAk4LzE2LzIwMTYIAAAACTgv | CH1: MTYvMjAxNucQwSddQNcIcWgDKF1A1wgpQ0lRLlRTRTo3OTc0LklRX0NMT1NFUFJJQ0UuMjAxNi0wOC0yMy5VU0QBAAAApF0NAAIAAAAKMjI1LjUyMTUwOADnEMEnXUDXCLej/iddQNcIL0NJUS5OQVNEQVFHUzpBVFZJLklRX1RFVi40MjM2OS4yMDE5LTA5LTIzLi4uVVNEAQAAABdtQAACAAAACzI3ODYzLjEyNzIyAQYAAAAFAAAAATEBAAAACjE3NjMzNjE4NjEDAAAAAzE2MAIAAAAGMTAwMDYwBAAAAAEwBwAAAAoxMi8zMS8yMDE15xDBJ11A1wi3o/4nXUDXCCxDSVEuVFNFOjc5NzQuSVFfVEVWX0VCSVREQS5JUV9MVE0uMjAxNi0wMi0yMwEAAACkXQ0AAgAAAAkyMy45OTM0ODkBBwAAAAUAAAABMQEAAAAKMTc3NjU4NDA0MwMAAAABMAIAAAAGMTAwMDMwBAAAAAEwBwAAAAkyLzIzLzIwMTYIAAAACTIvMjMvMjAxNucQwSddQNcIa0H8J11A1wgyQ0lRLlRTRTo5Njg0LklRX0VCSVREQV9FU1QuQ1kyMDIxLjIwMTktMDktMjMuLi5VU0QBAAAAqX0NAAIAAAAQNDQ3LjE1ODI3ODA4Mjg3MgEOAAAABQAAAAIxMQEAAAABMAIAAAAJNzI2ODYzOTU2AwAAAAYxMDAxODcEAAAAAjU2BgAAAAEwBwAAAAMxNjAIAAAAATAJAAAAATEKAAAAATALAAAACzExNjA4ODkyOTQyDAAAAAE3DQAAAAk5LzI0LzIwMTkQAAAACTkvMjMvMjAxOecQwSddQNcIcWgDKF1A1wgxQ0lRLk5BU0RBUUdTOkVBLklRX0VCSVREQS5DWTIwMTYu | CI1: MjAxOS0wOS0yMy4uLlVTRAEAAAA7bQAAAgAAAAQxMjIzAQgAAAAFAAAAATEBAAAACjE4NzMyNjc0MDADAAAAAzE2MAIAAAAENDA1MQQAAAABMAcAAAAJOS8yMy8yMDE5CAAAAAoxMi8zMS8yMDE2CQAAAAEw5xDBJ11A1whrQfwnXUDXCCxDSVEuVFNFOjc5NzQuSVFfVEVWX0VCSVREQS5JUV9MVE0uMjAxNy0wNy0xMQEAAACkXQ0AAgAAAAk1OC4zNzY5MDcBBwAAAAUAAAABMQEAAAAKMTg0OTAzMzEzOAMAAAABMAIAAAAGMTAwMDMwBAAAAAEwBwAAAAk3LzExLzIwMTcIAAAACTcvMTEvMjAxN+cQwSddQNcIa0H8J11A1wgqQ0lRLlRTRTo5Njg0LklRX1RFVi40MjczNS4yMDE5LTA5LTIzLi4uVVNEAQAAAKl9DQACAAAACzIzMTUuNzc4NjgxAQYAAAAFAAAAATEBAAAACjE4MTg3NzA3OTcDAAAAAzE2MAIAAAAGMTAwMDYwBAAAAAEwBwAAAAoxMi8zMS8yMDE25xDBJ11A1whrQfwnXUDXCClDSVEuVFNFOjc5NzQuSVFfQ0xPU0VQUklDRS4yMDE2LTA4LTMwLlVTRAEAAACkXQ0AAgAAAAoyMTUuNjQyNDQ3AOcQwSddQNcIAwYBKF1A1wgsQ0lRLlRTRTo3OTc0LklRX1RFVl9FQklUREEuSVFfTFRNLjIwMTYtMDEtMDUBAAAApF0NAAIAAAAJMjQuOTIyODAxAQcAAAAFAAAAATEBAAAACjE3NjUxNTM2NzEDAAAAATACAAAABjEwMDAzMAQAAAABMAcAAAAIMS81LzIwMTYIAAAACDEvNS8yMDE25xDBJ11A1whxaAMoXUDX | CJ1: CClDSVEuVFNFOjc5NzQuSVFfQ0xPU0VQUklDRS4yMDE5LTA2LTE4LlVTRAEAAACkXQ0AAgAAAAozNDcuODUwMTcyAKeZyiddQNcIcWgDKF1A1wgxQ0lRLlRTRTo3OTc0LklRX1JEX0VYUF9GTi5DWTIwMTguMjAxOS0wOS0yMy4uLlVTRAEAAACkXQ0AAgAAAAo1ODMuNjIxMjAxAQgAAAAFAAAAATEBAAAACjE5NDQ1OTc2NTgDAAAAAzE2MAIAAAAEMzE2OAQAAAABMAcAAAAJOS8yMy8yMDE5CAAAAAoxMi8zMS8yMDE4CQAAAAEwp5nKJ11A1whiygUoXUDXCCxDSVEuVFNFOjc5NzQuSVFfVEVWX0VCSVREQS5JUV9MVE0uMjAxOC0xMi0yNQEAAACkXQ0AAgAAAAkxMS43MDMyMDIBBwAAAAUAAAABMQEAAAAKMTkyMTUxODQyMwMAAAABMAIAAAAGMTAwMDMwBAAAAAEwBwAAAAoxMi8yNS8yMDE4CAAAAAoxMi8yNS8yMDE45xDBJ11A1whrQfwnXUDXCCFDSVEuSVFUUjU1MTc5OTY2OS5JUV9DT01QQU5ZX05BTUUBAAAAoCUuEAMAAAAXUGVyZmVjdCBXb3JsZCBDby4sIEx0ZC4A5xDBJ11A1wi3o/4nXUDXCCpDSVEuVFNFOjk2ODQuSVFfVEVWLjQ0MTk2LjIwMTktMDktMjMuLi5VU0QBAAAAqX0NAAIAAAALNDEzMC42MDY3MzYBBgAAAAUAAAABMQEAAAAKMTk3NTc4NjYwOQMAAAADMTYwAgAAAAYxMDAwNjAEAAAAATAHAAAACTkvMjAvMjAxOecQwSddQNcIcWgDKF1A1wgzQ0lRLk5BU0RBUUdTOlRUV08uSVFfRUJJVERB | CK1: LkNZMjAxNS4yMDE5LTA5LTIzLi4uVVNEAQAAAFGqBQACAAAACC0yMTEuMTY4AQgAAAAFAAAAATEBAAAACjE4MjcwMDAxMDcDAAAAAzE2MAIAAAAENDA1MQQAAAABMAcAAAAJOS8yMy8yMDE5CAAAAAoxMi8zMS8yMDE1CQAAAAEw5xDBJ11A1whrQfwnXUDXCClDSVEuVFNFOjc5NzQuSVFfQ0xPU0VQUklDRS4yMDE3LTA2LTI3LlVTRAEAAACkXQ0AAgAAAAozNTAuMjExNTIzAOcQwSddQNcIt6P+J11A1wgsQ0lRLlRTRTo3OTc0LklRX1RFVl9FQklUREEuSVFfTFRNLjIwMTktMDktMDMBAAAApF0NAAIAAAAJMTQuODk4MDg3AQcAAAAFAAAAATEBAAAACjE5NzU3OTI0NzADAAAAATACAAAABjEwMDAzMAQAAAABMAcAAAAIOS8zLzIwMTkIAAAACDkvMy8yMDE5p5nKJ11A1whrQfwnXUDXCDRDSVEuVFNFOjc5NzQuSVFfR1JPU1NfUFJPRklULkNZMjAxNy4yMDE5LTA5LTIzLi4uVVNEAQAAAKRdDQACAAAACzM0MTkuMzM2NzkzAQgAAAAFAAAAATEBAAAACjE4NzQxOTMzNDADAAAAAzE2MAIAAAACMTAEAAAAATAHAAAACTkvMjMvMjAxOQgAAAAKMTIvMzEvMjAxNwkAAAABMKeZyiddQNcIYsoFKF1A1wg2Q0lRLktPU0U6QTI1MTI3MC5JUV9FQklUREFfRVNULkNZMjAyMi4yMDE5LTA5LTIzLi4uVVNEAQAAAFnuLwkDAAAAAADnEMEnXUDXCHFoAyhdQNcIKUNJUS5UU0U6Nzk3NC5JUV9DTE9TRVBSSUNFLjIwMTgtMDYt | CL1: MDUuVVNEAQAAAKRdDQACAAAACjM3Mi40NTM0MDUA5xDBJ11A1wgDBgEoXUDXCClDSVEuVFNFOjc5NzQuSVFfQ0xPU0VQUklDRS4yMDE3LTA5LTE5LlVTRAEAAACkXQ0AAgAAAAozNjcuMDE3NjkyAOcQwSddQNcIt6P+J11A1wgsQ0lRLlRTRTo3OTc0LklRX1RFVl9FQklUREEuSVFfTFRNLjIwMTktMDYtMTgBAAAApF0NAAIAAAAJMTIuODIxMDI1AQcAAAAFAAAAATEBAAAACjE5NTY3NDgwODYDAAAAATACAAAABjEwMDAzMAQAAAABMAcAAAAJNi8xOC8yMDE5CAAAAAk2LzE4LzIwMTmnmconXUDXCGLKBShdQNcILENJUS5UU0U6Nzk3NC5JUV9URVZfRUJJVERBLklRX0xUTS4yMDE2LTA5LTA2AQAAAKRdDQACAAAACTUzLjY1MDQ3NQEHAAAABQAAAAExAQAAAAoxODAyNzc2Nzc1AwAAAAEwAgAAAAYxMDAwMzAEAAAAATAHAAAACDkvNi8yMDE2CAAAAAg5LzYvMjAxNucQwSddQNcIa0H8J11A1wgvQ0lRLk5BU0RBUUdTOkFUVkkuSVFfR1AuQ1kyMDE1LjIwMTktMDktMjMuLi5VU0QBAAAAF21AAAIAAAAEMzA3OQEIAAAABQAAAAExAQAAAAoxODc2NzU0ODc3AwAAAAMxNjACAAAAAjEwBAAAAAEwBwAAAAk5LzIzLzIwMTkIAAAACjEyLzMxLzIwMTUJAAAAATDnEMEnXUDXCHFoAyhdQNcIL0NJUS5OQVNEQVFHUzpUVFdPLklRX0dQLkNZMjAxNi4yMDE5LTA5LTIzLi4uVVNEAQAAAFGqBQACAAAABzcwNy43NDUBCAAA | CM1: AAUAAAABMQEAAAAKMTg3MzUzNDI4MgMAAAADMTYwAgAAAAIxMAQAAAABMAcAAAAJOS8yMy8yMDE5CAAAAAoxMi8zMS8yMDE2CQAAAAEw5xDBJ11A1whxaAMoXUDXCClDSVEuVFNFOjc5NzQuSVFfQ0xPU0VQUklDRS4yMDE4LTA5LTE4LlVTRAEAAACkXQ0AAgAAAAozNDcuNTc0NTYxAOcQwSddQNcIt6P+J11A1wgpQ0lRLlRTRTo3OTc0LklRX0NMT1NFUFJJQ0UuMjAxNi0wNC0xOS5VU0QBAAAApF0NAAIAAAAKMTU1LjU4NTA1NADnEMEnXUDXCGtB/CddQNcIKUNJUS5JUVRSMzE0MjIwMDU5LklRX1RSX0lNUExJRURfRVZfRUJJVERBAQAAABueuhICAAAACTQ1LjQ4NTU3MQEGAAAABQAAAAI1NAEAAAAGMTAyMDk0AgAAAAkzMTQyMjAwNTkDAAAACTMxNDIyMDI2NAQAAAACNTAGAAAABUZhbHNl5xDBJ11A1whrQfwnXUDXCCxDSVEuVFNFOjc5NzQuSVFfVEVWX0VCSVREQS5JUV9MVE0uMjAxOC0xMS0wNgEAAACkXQ0AAgAAAAgxNS41MDc2MwEHAAAABQAAAAExAQAAAAoxOTE2NzQ2NTc4AwAAAAEwAgAAAAYxMDAwMzAEAAAAATAHAAAACTExLzYvMjAxOAgAAAAJMTEvNi8yMDE45xDBJ11A1whiygUoXUDXCCxDSVEuVFNFOjc5NzQuSVFfVEVWX0VCSVREQS5JUV9MVE0uMjAxOS0wNy0wOQEAAACkXQ0AAgAAAAkxNC4wOTE3MzUBBwAAAAUAAAABMQEAAAAKMTk3MDIyMDUxNQMAAAABMAIAAAAGMTAwMDMwBAAAAAEw | CN1: BwAAAAg3LzkvMjAxOQgAAAAINy85LzIwMTmnmconXUDXCGtB/CddQNcIKUNJUS5UU0U6Nzk3NC5JUV9DTE9TRVBSSUNFLjIwMTgtMDUtMTUuVVNEAQAAAKRdDQACAAAACjQxNy4xOTU3MTIA5xDBJ11A1whrQfwnXUDXCDRDSVEuVFNFOjc5NzQuSVFfR1JPU1NfUFJPRklULkNZMjAxNS4yMDE5LTA5LTIzLi4uVVNEAQAAAKRdDQACAAAACzE4NzEuMzgxMTMyAQgAAAAFAAAAATEBAAAACjE3NzY1ODQwNDMDAAAAAzE2MAIAAAACMTAEAAAAATAHAAAACTkvMjMvMjAxOQgAAAAKMTIvMzEvMjAxNQkAAAABMKeZyiddQNcIcWgDKF1A1wgsQ0lRLlRTRTo3OTc0LklRX1RFVl9FQklUREEuSVFfTFRNLjIwMTktMDQtMDIBAAAApF0NAAIAAAAJMTEuMDg2NTU3AQcAAAAFAAAAATEBAAAACjE5NDQ1OTc2NTgDAAAAATACAAAABjEwMDAzMAQAAAABMAcAAAAINC8yLzIwMTkIAAAACDQvMi8yMDE55xDBJ11A1wi3o/4nXUDXCClDSVEuVFNFOjc5NzQuSVFfQ0xPU0VQUklDRS4yMDE4LTA1LTIyLlVTRAEAAACkXQ0AAgAAAAozOTkuMDA5NDY3AOcQwSddQNcIcWgDKF1A1wgpQ0lRLlRTRTo3OTc0LklRX0NMT1NFUFJJQ0UuMjAxOC0wNS0wOC5VU0QBAAAApF0NAAIAAAAKNDMyLjIwNDk0OADnEMEnXUDXCAMGAShdQNcIKUNJUS5UU0U6Nzk3NC5JUV9DTE9TRVBSSUNFLjIwMTYtMDEtMTkuVVNEAQAAAKRdDQACAAAACjEzNS44 | CO1: MzA3ODEA5xDBJ11A1wgDBgEoXUDXCCxDSVEuVFNFOjc5NzQuSVFfVEVWX0VCSVREQS5JUV9MVE0uMjAxNy0xMC0zMQEAAACkXQ0AAgAAAAg0NC4wNDc2NAEHAAAABQAAAAExAQAAAAoxODYzMDc2Nzk0AwAAAAEwAgAAAAYxMDAwMzAEAAAAATAHAAAACjEwLzMxLzIwMTcIAAAACjEwLzMxLzIwMTfnEMEnXUDXCGtB/CddQNcINENJUS5UU0U6Nzk3NC5JUV9HUk9TU19QUk9GSVQuQ1kyMDE2LjIwMTktMDktMjMuLi5VU0QBAAAApF0NAAIAAAALMTUyMi4zMjExMTIBCAAAAAUAAAABMQEAAAAKMTgyNzc2Nzc5NwMAAAADMTYwAgAAAAIxMAQAAAABMAcAAAAJOS8yMy8yMDE5CAAAAAoxMi8zMS8yMDE2CQAAAAEwp5nKJ11A1whiygUoXUDXCCxDSVEuVFNFOjc5NzQuSVFfVEVWX0VCSVREQS5JUV9MVE0uMjAxNy0xMi0wNQEAAACkXQ0AAgAAAAk0Mi42NzQ0MjIBBwAAAAUAAAABMQEAAAAKMTg2NTc5MjM2MwMAAAABMAIAAAAGMTAwMDMwBAAAAAEwBwAAAAkxMi81LzIwMTcIAAAACTEyLzUvMjAxN+cQwSddQNcIcWgDKF1A1wgpQ0lRLlRTRTo3OTc0LklRX0NMT1NFUFJJQ0UuMjAxNi0wOC0wOS5VU0QBAAAApF0NAAIAAAAKMjI0LjEyOTQ4MQDnEMEnXUDXCGtB/CddQNcIKUNJUS5UU0U6Nzk3NC5JUV9DTE9TRVBSSUNFLjIwMTYtMDYtMjEuVVNEAQAAAKRdDQACAAAACjE0NC4yNTY5NTkA5xDBJ11A1whxaAMoXUDX | CP1: CCxDSVEuVFNFOjc5NzQuSVFfVEVWX0VCSVREQS5JUV9MVE0uMjAxNi0wNy0xMgEAAACkXQ0AAgAAAAk0MS43ODEzMDYBBwAAAAUAAAABMQEAAAAKMTc5OTI0OTA1NwMAAAABMAIAAAAGMTAwMDMwBAAAAAEwBwAAAAk3LzEyLzIwMTYIAAAACTcvMTIvMjAxNucQwSddQNcIa0H8J11A1wg1Q0lRLlRTRTo5Njg0LklRX0NBU0hfSU5URVJFU1QuSVFfTFRNLjIwMTktMDktMjMuLi5VU0QBAAAAqX0NAAMAAAAAAKeZyiddQNcIa0H8J11A1wgsQ0lRLlRTRTo3OTc0LklRX1RFVl9FQklUREEuSVFfTFRNLjIwMTgtMDItMjcBAAAApF0NAAIAAAAJMjcuNTA4Mzg3AQcAAAAFAAAAATEBAAAACjE4NzQxOTMzNDADAAAAATACAAAABjEwMDAzMAQAAAABMAcAAAAJMi8yNy8yMDE4CAAAAAkyLzI3LzIwMTjnEMEnXUDXCGLKBShdQNcIPkNJUS5OQVNEQVFHUzpUVFdPLklRX1NIT1JUX0JVU0lORVNTX0RFU0NSSVBUSU9OLjIwMTktMDktMjMuVVNEAQAAAFGqBQADAAAAgQFUYWtlLVR3byBJbnRlcmFjdGl2ZSBTb2Z0d2FyZSwgSW5jLiBkZXZlbG9wcywgcHVibGlzaGVzLCBhbmQgbWFya2V0cyBpbnRlcmFjdGl2ZSBlbnRlcnRhaW5tZW50IHNvbHV0aW9ucyBmb3IgY29uc3VtZXJzIHdvcmxkd2lkZS4A5xDBJ11A1wi3o/4nXUDXCClDSVEuVFNFOjc5NzQuSVFfQ0xPU0VQUklDRS4yMDE4LTA5LTI1LlVTRAEAAACkXQ0AAgAA | CQ1: AAozNjguNTMyOTQ0AOcQwSddQNcIAwYBKF1A1wgsQ0lRLlRTRTo3OTc0LklRX1RFVl9FQklUREEuSVFfTFRNLjIwMTctMDQtMDQBAAAApF0NAAIAAAAJNDguODE2NTg1AQcAAAAFAAAAATEBAAAACjE4Mjc3Njc3OTcDAAAAATACAAAABjEwMDAzMAQAAAABMAcAAAAINC80LzIwMTcIAAAACDQvNC8yMDE35xDBJ11A1wi3o/4nXUDXCCxDSVEuRU5YVFBBOlVCSS5JUV9HUC5DWTIwMTguMjAxOS0wOS0yMy4uLlVTRAEAAAAZdg0AAgAAAAsxODQxLjk1NDQzMQEIAAAABQAAAAExAQAAAAoxOTY4NDYyOTAwAwAAAAMxNjACAAAAAjEwBAAAAAEwBwAAAAk5LzIzLzIwMTkIAAAACjEyLzMxLzIwMTgJAAAAATDnEMEnXUDXCLej/iddQNcILENJUS5UU0U6Nzk3NC5JUV9URVZfRUJJVERBLklRX0xUTS4yMDE4LTEyLTA0AQAAAKRdDQACAAAACTE0LjY2NDc1NgEHAAAABQAAAAExAQAAAAoxOTIxNTE4NDIzAwAAAAEwAgAAAAYxMDAwMzAEAAAAATAHAAAACTEyLzQvMjAxOAgAAAAJMTIvNC8yMDE45xDBJ11A1whiygUoXUDXCDFDSVEuVFNFOjk2ODQuSVFfVE9UQUxfUkVWLkNZMjAxNy4yMDE5LTA5LTIzLi4uVVNEAQAAAKl9DQACAAAACzIyNjIuNDQwNjI1AQgAAAAFAAAAATEBAAAACjE4NzQwMDc5MTUDAAAAAzE2MAIAAAACMjgEAAAAATAHAAAACTkvMjMvMjAxOQgAAAAKMTIvMzEvMjAxNwkAAAABMOcQwSddQNcIt6P+ | CR1: J11A1wgxQ0lRLkVOWFRQQTpVQkkuSVFfUEVfRVhDTC5JUV9MVE0uMjAxOS0wOS0yMy4uLlVTRAEAAAAZdg0AAgAAAAk3OC4xMDEyNTMBBwAAAAUAAAABMQEAAAAKMTk2ODQ2Mjg3MQMAAAABMAIAAAAGMTAwMDI3BAAAAAEwBwAAAAk5LzIzLzIwMTkIAAAACTkvMjMvMjAxOecQwSddQNcIAwYBKF1A1wgwQ0lRLkVOWFRQQTpVQkkuSVFfRUJJVERBLklRX0xUTS4yMDE5LTA5LTIzLi4uVVNEAQAAABl2DQACAAAACTI3NS45MTgwNwEIAAAABQAAAAExAQAAAAoxOTY4NDYyODcxAwAAAAMxNjACAAAABDQwNTEEAAAAATAHAAAACTkvMjMvMjAxOQgAAAAJMy8zMS8yMDE5CQAAAAEw5xDBJ11A1whrQfwnXUDXCDFDSVEuVFNFOjk2ODQuSVFfVE9UQUxfUkVWLkNZMjAxNS4yMDE5LTA5LTIzLi4uVVNEAQAAAKl9DQACAAAACzE2NzguNjc3Mjk1AQgAAAAFAAAAATEBAAAACjE3NzU4MTIwMTYDAAAAAzE2MAIAAAACMjgEAAAAATAHAAAACTkvMjMvMjAxOQgAAAAKMTIvMzEvMjAxNQkAAAABMOcQwSddQNcIa0H8J11A1wgpQ0lRLlRTRTo3OTc0LklRX0NMT1NFUFJJQ0UuMjAxNi0wMy0yOS5VU0QBAAAApF0NAAIAAAAKMTQ4LjE3NDI4NgDnEMEnXUDXCHFoAyhdQNcILENJUS5UU0U6Nzk3NC5JUV9URVZfRUJJVERBLklRX0xUTS4yMDE1LTA3LTI4AQAAAKRdDQACAAAACTQ2LjYxMDA5NAEHAAAABQAAAAExAQAAAAoxNzQ1 | CS1: OTIyNzcyAwAAAAEwAgAAAAYxMDAwMzAEAAAAATAHAAAACTcvMjgvMjAxNQgAAAAJNy8yOC8yMDE15xDBJ11A1wgDBgEoXUDXCCxDSVEuVFNFOjc5NzQuSVFfVEVWX0VCSVREQS5JUV9MVE0uMjAxOC0wNy0yNAEAAACkXQ0AAgAAAAkxNy41OTMyMTIBBwAAAAUAAAABMQEAAAAKMTg5NTE5MDMxMgMAAAABMAIAAAAGMTAwMDMwBAAAAAEwBwAAAAk3LzI0LzIwMTgIAAAACTcvMjQvMjAxOOcQwSddQNcIt6P+J11A1wgpQ0lRLlRTRTo3OTc0LklRX0NMT1NFUFJJQ0UuMjAxNy0wMi0yOC5VU0QBAAAApF0NAAIAAAAKMjA5LjgzMDc5NQDnEMEnXUDXCHFoAyhdQNcIKUNJUS5UU0U6Nzk3NC5JUV9DTE9TRVBSSUNFLjIwMTctMTItMTkuVVNEAQAAAKRdDQACAAAACjM3Ny44NzEyMTgA5xDBJ11A1wgDBgEoXUDXCDJDSVEuVFNFOjc5NzQuSVFfRUJJVERBX0VTVC5DWTIwMjAuMjAxOS0wOS0yMy4uLlVTRAEAAACkXQ0AAgAAAA8zMzYwLjA2NDc5OTI3MjcBDgAAAAUAAAACMTEBAAAAATACAAAACTY1MjkxNDE3OQMAAAAGMTAwMTg3BAAAAAI1NgYAAAABMAcAAAADMTYwCAAAAAEwCQAAAAExCgAAAAEwCwAAAAsxMTYwMzU3NDExNQwAAAABNw0AAAAJOS8yNC8yMDE5EAAAAAk5LzIzLzIwMTnnEMEnXUDXCGtB/CddQNcIM0NJUS5UU0U6MzY1OS5JUV9SRVZFTlVFX0VTVC5DWTIwMjAuMjAxOS0wOS0yMy4uLlVTRAEAAACe | CT1: H4IIAgAAABAyNjYyLjc2MDA0NzUyMjY1AQ4AAAAFAAAAAjExAQAAAAEwAgAAAAoxMDAxNDIyODI0AwAAAAYxMDAxODAEAAAAATMGAAAAATAHAAAAAzE2MAgAAAABMAkAAAABMQoAAAABMAsAAAALMTE2MDM0NDc1OTkMAAAAATcNAAAACTkvMjQvMjAxORAAAAAJOS8yMy8yMDE55xDBJ11A1wgDBgEoXUDXCCxDSVEuVFNFOjc5NzQuSVFfVEVWX0VCSVREQS5JUV9MVE0uMjAxNy0wMS0zMQEAAACkXQ0AAgAAAAk0Mi41MTI5MDMBBwAAAAUAAAABMQEAAAAKMTgyNTkyMjA3MgMAAAABMAIAAAAGMTAwMDMwBAAAAAEwBwAAAAkxLzMxLzIwMTcIAAAACTEvMzEvMjAxN+cQwSddQNcIYsoFKF1A1wgpQ0lRLlRTRTo3OTc0LklRX0NMT1NFUFJJQ0UuMjAxOS0wNy0yMy5VU0QBAAAApF0NAAIAAAAKMzY5LjYzNzAxNQCnmconXUDXCLej/iddQNcII0NJUS5JUVRSNTUxNzk5NjY5LklRX1RSX0NMT1NFRF9EQVRFAQAAAHXL4yAFAAAACjIwMTgtMDQtMTcA5xDBJ11A1wgDBgEoXUDXCC5DSVEuVFNFOjM2NTkuSVFfRUJJVERBLkNZMjAxNS4yMDE5LTA5LTIzLi4uVVNEAQAAAJ4fgggCAAAACjY2NS45NDAxMzYBCAAAAAUAAAABMQEAAAAKMTc4NDQ5OTE4NAMAAAADMTYwAgAAAAQ0MDUxBAAAAAEwBwAAAAk5LzIzLzIwMTkIAAAACjEyLzMxLzIwMTUJAAAAATDnEMEnXUDXCAMGAShdQNcIL0NJUS5OQVNEQVFHUzpBVFZJLklR | CU1: X1RFVi40MzQ2NS4yMDE5LTA5LTIzLi4uVVNEAQAAABdtQAACAAAADDM0NzgxLjI3MTkzNwEGAAAABQAAAAExAQAAAAoxOTIwNjMyMDk2AwAAAAMxNjACAAAABjEwMDA2MAQAAAABMAcAAAAKMTIvMzEvMjAxOOcQwSddQNcIcWgDKF1A1wgqQ0lRLlRTRTo5Njg0LklRX0dQLkNZMjAxNy4yMDE5LTA5LTIzLi4uVVNEAQAAAKl9DQACAAAACzExMjQuMjE1Mzg1AQgAAAAFAAAAATEBAAAACjE4NzQwMDc5MTUDAAAAAzE2MAIAAAACMTAEAAAAATAHAAAACTkvMjMvMjAxOQgAAAAKMTIvMzEvMjAxNwkAAAABMOcQwSddQNcIAwYBKF1A1wgpQ0lRLlRTRTo3OTc0LklRX0NMT1NFUFJJQ0UuMjAxNy0wNS0wOS5VU0QBAAAApF0NAAIAAAAKMjUxLjg2MjU2MgDnEMEnXUDXCAMGAShdQNcIKkNJUS5UU0U6OTY4NC5JUV9HUC5DWTIwMTYuMjAxOS0wOS0yMy4uLlVTRAEAAACpfQ0AAgAAAAo4OTcuNTMzMTM5AQgAAAAFAAAAATEBAAAACjE4Mjc1MDgyMDcDAAAAAzE2MAIAAAACMTAEAAAAATAHAAAACTkvMjMvMjAxOQgAAAAKMTIvMzEvMjAxNgkAAAABMOcQwSddQNcIt6P+J11A1wgpQ0lRLlRTRTo3OTc0LklRX0NMT1NFUFJJQ0UuMjAxOC0wMS0xNi5VU0QBAAAApF0NAAIAAAAKNDA3LjE0ODMzNQDnEMEnXUDXCAMGAShdQNcILENJUS5UU0U6Nzk3NC5JUV9URVZfRUJJVERBLklRX0xUTS4yMDE3LTA5LTE5AQAAAKRdDQAC | CV1: AAAACTQ4LjExMTY1OAEHAAAABQAAAAExAQAAAAoxODU0MDQzODg4AwAAAAEwAgAAAAYxMDAwMzAEAAAAATAHAAAACTkvMTkvMjAxNwgAAAAJOS8xOS8yMDE35xDBJ11A1wi3o/4nXUDXCCJDSVEuVFNFOjk2ODQuSVFfVEVWLjIwMTktMDktMjMuVVNEAQAAAKl9DQACAAAACzQxMzAuNjA2NzM2AQYAAAAFAAAAATEBAAAACjE5NzU3ODY2MDkDAAAAAzE2MAIAAAAGMTAwMDYwBAAAAAEwBwAAAAk5LzIwLzIwMTnnEMEnXUDXCAMGAShdQNcILENJUS5UU0U6Nzk3NC5JUV9URVZfRUJJVERBLklRX0xUTS4yMDE2LTA1LTI0AQAAAKRdDQACAAAACTIyLjQ3OTM5NwEHAAAABQAAAAExAQAAAAoxNzg3OTI1ODc2AwAAAAEwAgAAAAYxMDAwMzAEAAAAATAHAAAACTUvMjQvMjAxNggAAAAJNS8yNC8yMDE25xDBJ11A1whiygUoXUDXCClDSVEuVFNFOjc5NzQuSVFfQ0xPU0VQUklDRS4yMDE4LTAzLTA2LlVTRAEAAACkXQ0AAgAAAAo0NDguNTc2OTY4AOcQwSddQNcIt6P+J11A1wgyQ0lRLlRTRTo5Njg0LklRX1RPVEFMX0RFQlQuSVFfTFRNLjIwMTktMDktMjMuLi5VU0QBAAAAqX0NAAIAAAAJNzYuMTg4NzExAQgAAAAFAAAAATEBAAAACjE5NzU3OTI2NDMDAAAAAzE2MAIAAAAENDE3MwQAAAABMAcAAAAJOS8yMy8yMDE5CAAAAAk2LzMwLzIwMTkJAAAAATCnmconXUDXCLej/iddQNcILENJUS5UU0U6Nzk3NC5JUV9URVZf | CW1: RUJJVERBLklRX0xUTS4yMDE3LTA1LTIzAQAAAKRdDQACAAAACTQ3LjY0ODM0NgEHAAAABQAAAAExAQAAAAoxODM4MjA0MDc0AwAAAAEwAgAAAAYxMDAwMzAEAAAAATAHAAAACTUvMjMvMjAxNwgAAAAJNS8yMy8yMDE35xDBJ11A1whiygUoXUDXCClDSVEuVFNFOjc5NzQuSVFfQ0xPU0VQUklDRS4yMDE5LTA3LTMwLlVTRAEAAACkXQ0AAgAAAAozNzMuNDc0OTIyAKeZyiddQNcIAwYBKF1A1wg2Q0lRLktPU0U6QTI1MTI3MC5JUV9UT1RBTF9ERUJULklRX0xUTS4yMDE5LTA5LTIzLi4uVVNEAQAAAFnuLwkCAAAACTE5Ni42Nzg2NAEIAAAABQAAAAExAQAAAAoxOTgxMTcwMDUyAwAAAAMxNjACAAAABDQxNzMEAAAAATAHAAAACTkvMjMvMjAxOQgAAAAJNi8zMC8yMDE5CQAAAAEwp5nKJ11A1whxaAMoXUDXCCxDSVEuVFNFOjc5NzQuSVFfVEVWX0VCSVREQS5JUV9MVE0uMjAxOS0wMy0wNQEAAACkXQ0AAgAAAAkxMC40MzY1MDkBBwAAAAUAAAABMQEAAAAKMTk0NDU5NzY1OAMAAAABMAIAAAAGMTAwMDMwBAAAAAEwBwAAAAgzLzUvMjAxOQgAAAAIMy81LzIwMTnnEMEnXUDXCLej/iddQNcIO0NJUS5FTlhUUEE6VUJJLklRX1NIT1JUX0JVU0lORVNTX0RFU0NSSVBUSU9OLjIwMTktMDktMjMuVVNEAQAAABl2DQADAAAAowFVYmlzb2Z0IEVudGVydGFpbm1lbnQgU0EgcHJvZHVjZSwgcHVibGlzaGVzLCBhbmQgZGlz | CX1: dHJpYnV0ZXMgdmlkZW8gZ2FtZXMgZm9yIGNvbnNvbGVzLCBQQywgc21hcnRwaG9uZXMsIGFuZCB0YWJsZXRzIGluIGJvdGggcGh5c2ljYWwgYW5kIGRpZ2l0YWwgZm9ybWF0cyB3b3JsZHdpZGUuAOcQwSddQNcIcWgDKF1A1wgpQ0lRLlRTRTo3OTc0LklRX0NMT1NFUFJJQ0UuMjAxNy0wNC0wNC5VU0QBAAAApF0NAAIAAAAKMjM1LjM3NjQ5MwDnEMEnXUDXCLej/iddQNcIKUNJUS5UU0U6Nzk3NC5JUV9DTE9TRVBSSUNFLjIwMTctMDUtMzAuVVNEAQAAAKRdDQACAAAACjMwNy4wMDQ4NjkA5xDBJ11A1wi3o/4nXUDXCDRDSVEuRU5YVFBBOlVCSS5JUV9FQklUREFfRVNULkNZMjAxOS4yMDE5LTA5LTIzLi4uVVNEAQAAABl2DQACAAAAEDgzNS4yNzI3MDcxOTA4MTkBDgAAAAUAAAACMTEBAAAAATACAAAACDEwMjUyMzQ2AwAAAAYxMDAxODcEAAAAATMGAAAAATAHAAAAAzE2MAgAAAABMAkAAAABMQoAAAABMAsAAAALMTE1OTkyNTkzMzEMAAAAATcNAAAACTkvMjQvMjAxORAAAAAJOS8yMy8yMDE55xDBJ11A1whrQfwnXUDXCCxDSVEuVFNFOjc5NzQuSVFfVEVWX0VCSVREQS5JUV9MVE0uMjAxNy0wMy0yMQEAAACkXQ0AAgAAAAg0OS4zODIwMgEHAAAABQAAAAExAQAAAAoxODI3NzY3Nzk3AwAAAAEwAgAAAAYxMDAwMzAEAAAAATAHAAAACTMvMjEvMjAxNwgAAAAJMy8yMS8yMDE35xDBJ11A1whrQfwnXUDXCClD | CY1: SVEuVFNFOjc5NzQuSVFfQ0xPU0VQUklDRS4yMDE3LTA3LTE4LlVTRAEAAACkXQ0AAgAAAAozMjYuMTI1ODIxAOcQwSddQNcIcWgDKF1A1wgsQ0lRLlRTRTo3OTc0LklRX1RFVl9FQklUREEuSVFfTFRNLjIwMTktMDEtMjIBAAAApF0NAAIAAAAIMTUuMDYxMTQBBwAAAAUAAAABMQEAAAAKMTkyMTUxODQyMwMAAAABMAIAAAAGMTAwMDMwBAAAAAEwBwAAAAkxLzIyLzIwMTkIAAAACTEvMjIvMjAxOecQwSddQNcIa0H8J11A1wgpQ0lRLlRTRTo3OTc0LklRX0NMT1NFUFJJQ0UuMjAxNS0xMi0xNS5VU0QBAAAApF0NAAIAAAAKMTM5LjAwNTM0MQDnEMEnXUDXCLej/iddQNcIL0NJUS5FTlhUUEE6VUJJLklRX0NVU1RPTV9CRVRBLi4yMDE5LTA5LTIzLi4uVVNEAQAAABl2DQACAAAAEDEuMDczNjU4MzI1MzE1NDIAp5nKJ11A1wgDBgEoXUDXCClDSVEuVFNFOjc5NzQuSVFfQ0xPU0VQUklDRS4yMDE4LTEyLTExLlVTRAEAAACkXQ0AAgAAAAgyODcuNTUyOQDnEMEnXUDXCLej/iddQNcIKkNJUS5UU0U6MzY1OS5JUV9URVYuNDQ5MjYuMjAxOS0wOS0yMy4uLlVTRAEAAACeH4IIAgAAAAs3MDExLjMwNDAwNgEGAAAABQAAAAExAQAAAAoxOTc1Nzg2NjIyAwAAAAMxNjACAAAABjEwMDA2MAQAAAABMAcAAAAJOS8yMC8yMDE55xDBJ11A1wgDBgEoXUDXCCxDSVEuVFNFOjc5NzQuSVFfVEVWX0VCSVREQS5JUV9MVE0uMjAx | CZ1: OC0wNC0xNwEAAACkXQ0AAgAAAAkyNC4xNTQyOTcBBwAAAAUAAAABMQEAAAAKMTg3NDE5MzM0MAMAAAABMAIAAAAGMTAwMDMwBAAAAAEwBwAAAAk0LzE3LzIwMTgIAAAACTQvMTcvMjAxOOcQwSddQNcIa0H8J11A1wgzQ0lRLk5BU0RBUUdTOlRUV08uSVFfRUJJVERBLkNZMjAxNy4yMDE5LTA5LTIzLi4uVVNEAQAAAFGqBQACAAAABzI0Ny4wMDMBCAAAAAUAAAABMQEAAAAKMTk0MzkyNTIzNAMAAAADMTYwAgAAAAQ0MDUxBAAAAAEwBwAAAAk5LzIzLzIwMTkIAAAACjEyLzMxLzIwMTcJAAAAATDnEMEnXUDXCLej/iddQNcIK0NJUS5UU0U6MzY1OS5JUV9DT01QQU5ZX05BTUUuMjAxOS0wOS0yMy5VU0QBAAAAnh+CCAMAAAAPTkVYT04gQ28uLCBMdGQuAOcQwSddQNcIYsoFKF1A1wgpQ0lRLlRTRTo3OTc0LklRX0NMT1NFUFJJQ0UuMjAxNi0wNS0wMy5VU0QBAAAApF0NAAMAAAAAAOcQwSddQNcIcWgDKF1A1wg5Q0lRLlRTRTo3OTc0LklRX1NIT1JUX0JVU0lORVNTX0RFU0NSSVBUSU9OLjIwMTktMDktMjMuVVNEAQAAAKRdDQADAAAAyAFOaW50ZW5kbyBDby4sIEx0ZC4sIHRvZ2V0aGVyIHdpdGggaXRzIHN1YnNpZGlhcmllcywgZGV2ZWxvcHMsIG1hbnVmYWN0dXJlcywgYW5kIGRpc3RyaWJ1dGVzIGVsZWN0cm9uaWMgZW50ZXJ0YWlubWVudCBwcm9kdWN0cyBpbiBKYXBhbiwgdGhlIFVuaXRlZCBTdGF0ZXMs | DA1: IEV1cm9wZSwgQXVzdHJhbGlhLCBBc2lhLCBhbmQgaW50ZXJuYXRpb25hbGx5LgDnEMEnXUDXCGLKBShdQNcIKENJUS5OQVNEQVFHUzpFQS5JUV9URVYuLjIwMTktMDktMjMuLi5VU0QBAAAAO20AAAIAAAAMMjQ5ODIuMzgxNDY2AQYAAAAFAAAAATEBAAAACjE5NzQyMzUzNDkDAAAAAzE2MAIAAAAGMTAwMDYwBAAAAAEwBwAAAAk5LzIzLzIwMTnnEMEnXUDXCAMGAShdQNcIN0NJUS5OQVNEQVFHUzpBVFZJLklRX0VCSVREQV9FU1QuQ1kyMDE5LjIwMTktMDktMjMuLi5VU0QBAAAAF21AAAIAAAAKMjIyNS4xNTgwMQEOAAAABQAAAAIxMQEAAAABMAIAAAAKMTAwMDc3ODQ1MAMAAAAGMTAwMTg3BAAAAAEyBgAAAAEwBwAAAAMxNjAIAAAAATAJAAAAATEKAAAAATALAAAACzExNjEwMDEyNTg2DAAAAAE3DQAAAAk5LzI0LzIwMTkQAAAACTkvMjMvMjAxOecQwSddQNcIYsoFKF1A1wgsQ0lRLlRTRTo3OTc0LklRX1RFVl9FQklUREEuSVFfTFRNLjIwMTktMDQtMzABAAAApF0NAAIAAAAJMTIuOTU1MjY4AQcAAAAFAAAAATEBAAAACjE5NTY3NDgwODYDAAAAATACAAAABjEwMDAzMAQAAAABMAcAAAAJNC8yNi8yMDE5CAAAAAk0LzI2LzIwMTnnEMEnXUDXCLej/iddQNcIIkNJUS5JUVRSNTUxNzk5NjY5LklRX1RSX1RPVEFMVkFMVUUBAAAAdcvjIAIAAAAJMjU4My45NDY4AQYAAAAFAAAAAjU0AQAAAAYxMDA1MDQCAAAA | DB1: CTU1MTc5OTY2OQMAAAAJNTUxNzk5NjY5BAAAAAIzMgYAAAAFRmFsc2XnEMEnXUDXCHFoAyhdQNcIM0NJUS5OQVNEQVFHUzpUVFdPLklRX0VCSVREQS5DWTIwMTYuMjAxOS0wOS0yMy4uLlVTRAEAAABRqgUAAgAAAAY5NS40MTgBCAAAAAUAAAABMQEAAAAKMTg3MzUzNDI4MgMAAAADMTYwAgAAAAQ0MDUxBAAAAAEwBwAAAAk5LzIzLzIwMTkIAAAACjEyLzMxLzIwMTYJAAAAATDnEMEnXUDXCLej/iddQNcINUNJUS5FTlhUUEE6VUJJLklRX1JFVkVOVUVfRVNULkNZMjAyMi4yMDE5LTA5LTIzLi4uVVNEAQAAABl2DQACAAAAEDI5MDQuMDczODk0NTY3MzMBDgAAAAUAAAACMTEBAAAAATACAAAACDQ3NTE0NzE5AwAAAAYxMDAxODAEAAAAATMGAAAAATAHAAAAAzE2MAgAAAABMAkAAAABMQoAAAABMAsAAAALMTE2MDUxNjU5NTAMAAAAATcNAAAACTkvMjQvMjAxORAAAAAJOS8yMy8yMDE55xDBJ11A1whiygUoXUDXCCxDSVEuVFNFOjc5NzQuSVFfVEVWX0VCSVREQS5JUV9MVE0uMjAxOC0wOS0xOAEAAACkXQ0AAgAAAAkxOC42MDc0MTkBBwAAAAUAAAABMQEAAAAKMTkwMDI3Mjc5NgMAAAABMAIAAAAGMTAwMDMwBAAAAAEwBwAAAAk5LzE4LzIwMTgIAAAACTkvMTgvMjAxOOcQwSddQNcIt6P+J11A1wgtQ0lRLlRTRTo3OTc0LklRX0NBUEVYLklRX0xUTS4yMDE5LTA5LTIzLi4uVVNEAQAAAKRdDQADAAAAAACnmcon | DC1: XUDXCHFoAyhdQNcINUNJUS5UU0U6MzY1OS5JUV9DQVNIX0lOVEVSRVNULklRX0xUTS4yMDE5LTA5LTIzLi4uVVNEAQAAAJ4fgggCAAAACDEuMzgyMzgyAQgAAAAFAAAAATEBAAAACjE5NzU3OTI0MzcDAAAAAzE2MAIAAAAEMzAyOAQAAAABMAcAAAAJOS8yMy8yMDE5CAAAAAk2LzMwLzIwMTkJAAAAATCnmconXUDXCLej/iddQNcIN0NJUS5OQVNEQVFHUzpBVFZJLklRX1RPVEFMX0RFQlQuSVFfTFRNLjIwMTktMDktMjMuLi5VU0QBAAAAF21AAAIAAAAEMjk2MgEIAAAABQAAAAExAQAAAAoxOTc1MDM5MDUyAwAAAAMxNjACAAAABDQxNzMEAAAAATAHAAAACTkvMjMvMjAxOQgAAAAJNi8zMC8yMDE5CQAAAAEwp5nKJ11A1wgDBgEoXUDXCCxDSVEuVFNFOjc5NzQuSVFfVEVWX0VCSVREQS5JUV9MVE0uMjAxOS0wMS0wMQEAAACkXQ0AAgAAAAgxMi41NjEwOQEHAAAABQAAAAExAQAAAAoxOTIxNTE4NDIzAwAAAAEwAgAAAAYxMDAwMzAEAAAAATAHAAAACjEyLzI4LzIwMTgIAAAACjEyLzI4LzIwMTjnEMEnXUDXCHFoAyhdQNcIMUNJUS5UU0U6MzY1OS5JUV9UT1RBTF9SRVYuSVFfTFRNLjIwMTktMDktMjMuLi5VU0QBAAAAnh+CCAIAAAALMjQzNC4wNTg1OTIBCAAAAAUAAAABMQEAAAAKMTk3NTc5MjQzNwMAAAADMTYwAgAAAAIyOAQAAAABMAcAAAAJOS8yMy8yMDE5CAAAAAk2LzMwLzIwMTkJAAAAATDnEMEnXUDX | DD1: CGtB/CddQNcIIUNJUS5JUVRSMzE0MjIwMDU5LklRX0NPTVBBTllfTkFNRQEAAAAZdg0AAwAAABhVYmlzb2Z0IEVudGVydGFpbm1lbnQgU0EA5xDBJ11A1wgDBgEoXUDXCDtDSVEuTkFTREFRR1M6QVRWSS5JUV9ESUxVVF9FUFNfRVhDTC5JUV9MVE0uMjAxOS0wOS0yMy4uLlVTRAEAAAAXbUAAAgAAAAgyLjE5MDIwNwEIAAAABQAAAAExAQAAAAoxOTc1MDM5MDUyAwAAAAMxNjACAAAAAzE0MgQAAAABMAcAAAAJOS8yMy8yMDE5CAAAAAk2LzMwLzIwMTkJAAAAATDnEMEnXUDXCGtB/CddQNcILkNJUS5LT1NFOkEyNTEyNzAuSVFfVEVWLjQ0NTYxLjIwMTktMDktMjMuLi5VU0QBAAAAWe4vCQIAAAALNTIyOC42MjI5NjkBBgAAAAUAAAABMQEAAAAKMTk4MTE1NjU0MAMAAAADMTYwAgAAAAYxMDAwNjAEAAAAATAHAAAACTkvMjMvMjAxOecQwSddQNcIcWgDKF1A1wg8Q0lRLk5BU0RBUUdTOkVBLklRX1RPVEFMX0RFQlRfRVFVSVRZLklRX0xUTS4yMDE5LTA5LTIzLi4uVVNEAQAAADttAAACAAAABzE5LjA0MzkBCAAAAAUAAAABMQEAAAAKMTk3NDIzNTgxMgMAAAADMTYwAgAAAAQ0MDM0BAAAAAEwBwAAAAk5LzIzLzIwMTkIAAAACTYvMzAvMjAxOQkAAAABMKeZyiddQNcIAwYBKF1A1wgsQ0lRLlRTRTo3OTc0LklRX1RFVl9FQklUREEuSVFfTFRNLjIwMTUtMDYtMjMBAAAApF0NAAIAAAAJNDYuMzE5MjQxAQcAAAAF | DE1: AAAAATEBAAAACjE3MzI2NjA2NjIDAAAAATACAAAABjEwMDAzMAQAAAABMAcAAAAJNi8yMy8yMDE1CAAAAAk2LzIzLzIwMTXnEMEnXUDXCHFoAyhdQNcIM0NJUS5OQVNEQVFHUzpUVFdPLklRX0VCSVREQS5JUV9MVE0uMjAxOS0wOS0yMy4uLlVTRAEAAABRqgUAAgAAAAYyNTQuOTYBCAAAAAUAAAABMQEAAAAKMTk3NDMwNDA2NgMAAAADMTYwAgAAAAQ0MDUxBAAAAAEwBwAAAAk5LzIzLzIwMTkIAAAACTYvMzAvMjAxOQkAAAABMOcQwSddQNcIcWgDKF1A1wg3Q0lRLktPU0U6QTI1MTI3MC5JUV9SRVZFTlVFX0VTVC5DWTIwMTkuMjAxOS0wOS0yMy4uLlVTRAEAAABZ7i8JAgAAABAxOTAwLjQ0NjQ4NjQ5OTYyAQ4AAAAFAAAAAjExAQAAAAEwAgAAAAoxMDAzNjYzMTA5AwAAAAYxMDAxODAEAAAAATMGAAAAATAHAAAAAzE2MAgAAAABMAkAAAABMQoAAAABMAsAAAALMTE2MTA4MzUzOTcMAAAAATcNAAAACTkvMjQvMjAxORAAAAAJOS8yMy8yMDE55xDBJ11A1wgDBgEoXUDXCClDSVEuVFNFOjc5NzQuSVFfQ0xPU0VQUklDRS4yMDE1LTA5LTA4LlVTRAEAAACkXQ0AAgAAAAoxODYuNzg5NzczAOcQwSddQNcIa0H8J11A1wgpQ0lRLlRTRTo3OTc0LklRX0NMT1NFUFJJQ0UuMjAxNi0wMy0wMS5VU0QBAAAApF0NAAIAAAAKMTM1LjM5MTkyNADnEMEnXUDXCHFoAyhdQNcIKUNJUS5UU0U6Nzk3NC5JUV9DTE9TRVBSSUNF | DF1: LjIwMTUtMTItMjIuVVNEAQAAAKRdDQACAAAACjEzNC40OTEzMjIA5xDBJ11A1wgDBgEoXUDXCDhDSVEuTkFTREFRR1M6VFRXTy5JUV9SRVZFTlVFX0VTVC5DWTIwMjEuMjAxOS0wOS0yMy4uLlVTRAEAAABRqgUAAgAAAAkzMzE3LjE2MjcBDgAAAAUAAAACMTEBAAAAATACAAAABzEyNDM0MjIDAAAABjEwMDE4MAQAAAABMgYAAAABMAcAAAADMTYwCAAAAAEwCQAAAAExCgAAAAEwCwAAAAsxMTYwNzA3MjI5MwwAAAABNw0AAAAJOS8yNC8yMDE5EAAAAAk5LzIzLzIwMTnnEMEnXUDXCLej/iddQNcILENJUS5FTlhUUEE6VUJJLklRX1RFVi40NDU2MS4yMDE5LTA5LTIzLi4uVVNEAQAAABl2DQACAAAACzg3NjkuNjU5MTA4AQYAAAAFAAAAATEBAAAACjE5Njg0NjI4NjkDAAAAAzE2MAIAAAAGMTAwMDYwBAAAAAEwBwAAAAk5LzIzLzIwMTnnEMEnXUDXCAMGAShdQNcILkNJUS5LT1NFOkEyNTEyNzAuSVFfR1AuQ1kyMDE1LjIwMTktMDktMjMuLi5VU0QBAAAAWe4vCQIAAAAKNDExLjYxOTc4MgEIAAAABQAAAAExAQAAAAoxODMzMDU5MDUyAwAAAAMxNjACAAAAAjEwBAAAAAEwBwAAAAk5LzIzLzIwMTkIAAAACjEyLzMxLzIwMTUJAAAAATDnEMEnXUDXCGtB/CddQNcIKUNJUS5UU0U6Nzk3NC5JUV9DTE9TRVBSSUNFLjIwMTUtMDctMTQuVVNEAQAAAKRdDQACAAAACTE1OS45NjU5NQDnEMEnXUDXCGtB/CddQNcILENJ | DG1: US5UU0U6Nzk3NC5JUV9URVZfRUJJVERBLklRX0xUTS4yMDE3LTA3LTI1AQAAAKRdDQACAAAACTU2LjgwMjgyMwEHAAAABQAAAAExAQAAAAoxODQ5MDMzMTM4AwAAAAEwAgAAAAYxMDAwMzAEAAAAATAHAAAACTcvMjUvMjAxNwgAAAAJNy8yNS8yMDE35xDBJ11A1wi3o/4nXUDXCDNDSVEuTkFTREFRR1M6QVRWSS5JUV9FQklUREEuQ1kyMDE2LjIwMTktMDktMjMuLi5VU0QBAAAAF21AAAIAAAAEMjI4OAEIAAAABQAAAAExAQAAAAoxOTQ3ODI4NzU0AwAAAAMxNjACAAAABDQwNTEEAAAAATAHAAAACTkvMjMvMjAxOQgAAAAKMTIvMzEvMjAxNgkAAAABMOcQwSddQNcIt6P+J11A1wg1Q0lRLktPU0U6QTI1MTI3MC5JUV9UT1RBTF9SRVYuQ1kyMDE4LjIwMTktMDktMjMuLi5VU0QBAAAAWe4vCQIAAAALMTgxNS42NTA3MzgBCAAAAAUAAAABMQEAAAAKMTk1MDkzNjUzOAMAAAADMTYwAgAAAAIyOAQAAAABMAcAAAAJOS8yMy8yMDE5CAAAAAoxMi8zMS8yMDE4CQAAAAEw5xDBJ11A1wi3o/4nXUDXCClDSVEuVFNFOjc5NzQuSVFfQ0xPU0VQUklDRS4yMDE2LTExLTE1LlVTRAEAAACkXQ0AAgAAAAoyMjguMzY2NzE5AOcQwSddQNcIt6P+J11A1wgpQ0lRLlRTRTo3OTc0LklRX0NMT1NFUFJJQ0UuMjAxNy0wNy0yNS5VU0QBAAAApF0NAAIAAAAKMzE2LjI3OTkxNgDnEMEnXUDXCLej/iddQNcIOkNJUS5OQVNEQVFHUzpF | DH1: QS5JUV9FRkZFQ1RfVEFYX1JBVEUuSVFfTFRNLjIwMTktMDktMjMuLi5VU0QBAAAAO20AAAMAAAACTk0BCAAAAAUAAAABMQEAAAAKMTk3NDIzNTgxMgMAAAADMTYwAgAAAAQ0Mzc2BAAAAAEwBwAAAAk5LzIzLzIwMTkIAAAACTYvMzAvMjAxOQkAAAABMKeZyiddQNcIcWgDKF1A1wgpQ0lRLlRTRTo3OTc0LklRX0NMT1NFUFJJQ0UuMjAxNi0wNS0zMS5VU0QBAAAApF0NAAIAAAAKMTQ4LjI3MTY2NADnEMEnXUDXCLej/iddQNcILENJUS5UU0U6Nzk3NC5JUV9URVZfRUJJVERBLklRX0xUTS4yMDE1LTA4LTE4AQAAAKRdDQACAAAACTQ3LjMyNDkzMwEHAAAABQAAAAExAQAAAAoxNzQ5ODU3MDk3AwAAAAEwAgAAAAYxMDAwMzAEAAAAATAHAAAACTgvMTgvMjAxNQgAAAAJOC8xOC8yMDE15xDBJ11A1whiygUoXUDXCC5DSVEuVFNFOjc5NzQuSVFfRUJJVERBLkNZMjAxNy4yMDE5LTA5LTIzLi4uVVNEAQAAAKRdDQACAAAACzE0ODUuMjk1NDIyAQgAAAAFAAAAATEBAAAACjE4NzQxOTMzNDADAAAAAzE2MAIAAAAENDA1MQQAAAABMAcAAAAJOS8yMy8yMDE5CAAAAAoxMi8zMS8yMDE3CQAAAAEwp5nKJ11A1whiygUoXUDXCD1DSVEuS09TRTpBMjUxMjcwLklRX1RPVEFMX0RFQlRfRVFVSVRZLklRX0xUTS4yMDE5LTA5LTIzLi4uVVNEAQAAAFnuLwkCAAAABjQuODM1OQEIAAAABQAAAAExAQAAAAoxOTgxMTcwMDUyAwAA | DI1: AAI4NQIAAAAENDAzNAQAAAABMAcAAAAJOS8yMy8yMDE5CAAAAAk2LzMwLzIwMTkJAAAAATCnmconXUDXCLej/iddQNcIKUNJUS5UU0U6Nzk3NC5JUV9DTE9TRVBSSUNFLjIwMTUtMTAtMTMuVVNEAQAAAKRdDQACAAAACjE4NC4wMTUwMTYA5xDBJ11A1whxaAMoXUDXCClDSVEuVFNFOjc5NzQuSVFfQ0xPU0VQUklDRS4yMDE1LTEyLTI5LlVTRAEAAACkXQ0AAgAAAAoxNDAuNjc0OTMzAOcQwSddQNcIa0H8J11A1wgsQ0lRLlRTRTo3OTc0LklRX1RFVl9FQklUREEuSVFfTFRNLjIwMTgtMDUtMTUBAAAApF0NAAIAAAAJMjMuMDY0NTg1AQcAAAAFAAAAATEBAAAACjE4ODQ4NjQ5NjQDAAAAATACAAAABjEwMDAzMAQAAAABMAcAAAAJNS8xNS8yMDE4CAAAAAk1LzE1LzIwMTjnEMEnXUDXCGtB/CddQNcINkNJUS5OQVNEQVFHUzpUVFdPLklRX1RPVEFMX1JFVi5DWTIwMTguMjAxOS0wOS0yMy4uLlVTRAEAAABRqgUAAgAAAAgyNTc5LjY2MQEIAAAABQAAAAExAQAAAAoxOTQzOTI1MjM2AwAAAAMxNjACAAAAAjI4BAAAAAEwBwAAAAk5LzIzLzIwMTkIAAAACjEyLzMxLzIwMTgJAAAAATDnEMEnXUDXCHFoAyhdQNcIMkNJUS5UU0U6MzY1OS5JUV9FQklUREFfRVNULkNZMjAyMi4yMDE5LTA5LTIzLi4uVVNEAQAAAJ4fgggCAAAADjExOTUuNTkxMzAxNDAxAQ4AAAAFAAAAAjExAQAAAAEwAgAAAAoxMDAxNjQ5NDYzAwAA | DJ1: AAYxMDAxODcEAAAAATMGAAAAATAHAAAAAzE2MAgAAAABMAkAAAABMQoAAAABMAsAAAALMTE1OTY5NzI3MjcMAAAAATcNAAAACTkvMjQvMjAxORAAAAAJOS8yMy8yMDE55xDBJ11A1wgDBgEoXUDXCCxDSVEuVFNFOjc5NzQuSVFfVEVWX0VCSVREQS5JUV9MVE0uMjAxNS0wOS0xNQEAAACkXQ0AAgAAAAk0MS41MzI0MzgBBwAAAAUAAAABMQEAAAAKMTc0OTg1NzA5NwMAAAABMAIAAAAGMTAwMDMwBAAAAAEwBwAAAAk5LzE1LzIwMTUIAAAACTkvMTUvMjAxNecQwSddQNcIYsoFKF1A1wgzQ0lRLlRTRTozNjU5LklRX1JFVkVOVUVfRVNULkNZMjAxOS4yMDE5LTA5LTIzLi4uVVNEAQAAAJ4fgggCAAAAEDIzODQuNjQzNjg1NjM5MDIBDgAAAAUAAAACMTEBAAAAATACAAAACjEwMDE0MjI4MjEDAAAABjEwMDE4MAQAAAABMwYAAAABMAcAAAADMTYwCAAAAAEwCQAAAAExCgAAAAEwCwAAAAsxMTYwMzQ0NzI4NwwAAAABNw0AAAAJOS8yNC8yMDE5EAAAAAk5LzIzLzIwMTnnEMEnXUDXCLej/iddQNcIKUNJUS5UU0U6Nzk3NC5JUV9DTE9TRVBSSUNFLjIwMTYtMDgtMDIuVVNEAQAAAKRdDQACAAAACjIwOC4wNDIzODQA5xDBJ11A1wgDBgEoXUDXCCxDSVEuVFNFOjc5NzQuSVFfVEVWX0VCSVREQS5JUV9MVE0uMjAxOS0wMi0yNgEAAACkXQ0AAgAAAAkxMC40OTI0ODYBBwAAAAUAAAABMQEAAAAKMTk0NDU5NzY1OAMAAAAB | DK1: MAIAAAAGMTAwMDMwBAAAAAEwBwAAAAkyLzI2LzIwMTkIAAAACTIvMjYvMjAxOecQwSddQNcIcWgDKF1A1wgsQ0lRLlRTRTo3OTc0LklRX1RFVl9FQklUREEuSVFfTFRNLjIwMTYtMDYtMjEBAAAApF0NAAIAAAAJMjAuNTc3OTIzAQcAAAAFAAAAATEBAAAACjE3ODc5MjU4NzYDAAAAATACAAAABjEwMDAzMAQAAAABMAcAAAAJNi8yMS8yMDE2CAAAAAk2LzIxLzIwMTbnEMEnXUDXCGLKBShdQNcIKUNJUS5UU0U6Nzk3NC5JUV9DTE9TRVBSSUNFLjIwMTYtMDktMTMuVVNEAQAAAKRdDQACAAAACjI1MC44MTk3NTUA5xDBJ11A1whxaAMoXUDXCClDSVEuVFNFOjc5NzQuSVFfQ0xPU0VQUklDRS4yMDE5LTAxLTE1LlVTRAEAAACkXQ0AAgAAAAoyOTIuMTE5MzI2AOcQwSddQNcIAwYBKF1A1wgzQ0lRLkVOWFRQQTpVQkkuSVFfVE9UQUxfUkVWLklRX0xUTS4yMDE5LTA5LTIzLi4uVVNEAQAAABl2DQACAAAACjIwNzEuMjkyOTMBCAAAAAUAAAABMQEAAAAKMTk2ODQ2Mjg3MQMAAAADMTYwAgAAAAIyOAQAAAABMAcAAAAJOS8yMy8yMDE5CAAAAAkzLzMxLzIwMTkJAAAAATDnEMEnXUDXCLej/iddQNcIOUNJUS5OQVNEQVFHUzpFQS5JUV9ESUxVVF9FUFNfRVhDTC5JUV9MVE0uMjAxOS0wOS0yMy4uLlVTRAEAAAA7bQAAAgAAAAg3LjA3MjQ4MQEIAAAABQAAAAExAQAAAAoxOTc0MjM1ODEyAwAAAAMxNjACAAAAAzE0MgQA | DL1: AAABMAcAAAAJOS8yMy8yMDE5CAAAAAk2LzMwLzIwMTkJAAAAATDnEMEnXUDXCHFoAyhdQNcILUNJUS5UU0U6Nzk3NC5JUV9DQVBFWC5DWTIwMTguMjAxOS0wOS0yMy4uLlVTRAEAAACkXQ0AAwAAAAAAp5nKJ11A1whiygUoXUDXCDBDSVEuTkFTREFRR1M6RUEuSVFfQ1VTVE9NX0JFVEEuLjIwMTktMDktMjMuLi5VU0QBAAAAO20AAAIAAAAQMS4yNTU1ODQ2MTMyODAzNwCnmconXUDXCLej/iddQNcILENJUS5UU0U6Nzk3NC5JUV9URVZfRUJJVERBLklRX0xUTS4yMDE1LTA3LTIxAQAAAKRdDQACAAAACTUwLjI3Mjk1NQEHAAAABQAAAAExAQAAAAoxNzQ1OTIyNzcyAwAAAAEwAgAAAAYxMDAwMzAEAAAAATAHAAAACTcvMjEvMjAxNQgAAAAJNy8yMS8yMDE15xDBJ11A1whiygUoXUDXCCxDSVEuVFNFOjc5NzQuSVFfVEVWX0VCSVREQS5JUV9MVE0uMjAxNi0wNy0xOQEAAACkXQ0AAgAAAAk2Ni4yMTMxNDcBBwAAAAUAAAABMQEAAAAKMTc5OTI0OTA1NwMAAAABMAIAAAAGMTAwMDMwBAAAAAEwBwAAAAk3LzE5LzIwMTYIAAAACTcvMTkvMjAxNucQwSddQNcIYsoFKF1A1wgsQ0lRLkVOWFRQQTpVQkkuSVFfVEVWLjQzNDY1LjIwMTktMDktMjMuLi5VU0QBAAAAGXYNAAIAAAALOTI1OS4xOTcyOTYBBgAAAAUAAAABMQEAAAAKMTkyMTExNDUzNgMAAAADMTYwAgAAAAYxMDAwNjAEAAAAATAHAAAACjEyLzMxLzIwMTjn | DM1: EMEnXUDXCGtB/CddQNcIKkNJUS5UU0U6OTY4NC5JUV9URVYuNDMxMDAuMjAxOS0wOS0yMy4uLlVTRAEAAACpfQ0AAgAAAAs0NTQ1Ljk5MzIwMQEGAAAABQAAAAExAQAAAAoxODY2MjM1ODkzAwAAAAMxNjACAAAABjEwMDA2MAQAAAABMAcAAAAKMTIvMzEvMjAxN+cQwSddQNcIt6P+J11A1wgpQ0lRLlRTRTo3OTc0LklRX0NMT1NFUFJJQ0UuMjAxNy0wMy0yOC5VU0QBAAAApF0NAAIAAAAKMjQxLjI5MTg0NQDnEMEnXUDXCHFoAyhdQNcILUNJUS5OQVNEQVFHUzpFQS5JUV9HUC5DWTIwMTUuMjAxOS0wOS0yMy4uLlVTRAEAAAA7bQAAAgAAAAQyOTExAQgAAAAFAAAAATEBAAAACjE4MjY2NjUyODADAAAAAzE2MAIAAAACMTAEAAAAATAHAAAACTkvMjMvMjAxOQgAAAAKMTIvMzEvMjAxNQkAAAABMOcQwSddQNcIt6P+J11A1wgsQ0lRLlRTRTo3OTc0LklRX1RFVl9FQklUREEuSVFfTFRNLjIwMTgtMDUtMDEBAAAApF0NAAIAAAAJMjMuMTYyMTc4AQcAAAAFAAAAATEBAAAACjE4ODQ4NjQ5NjQDAAAAATACAAAABjEwMDAzMAQAAAABMAcAAAAINS8xLzIwMTgIAAAACDUvMS8yMDE45xDBJ11A1wi3o/4nXUDXCCpDSVEuVFNFOjM2NTkuSVFfVEVWLjQ0MTk2LjIwMTktMDktMjMuLi5VU0QBAAAAnh+CCAIAAAALNzAxMS4zMDQwMDYBBgAAAAUAAAABMQEAAAAKMTk3NTc4NjYyMgMAAAADMTYwAgAAAAYxMDAwNjAEAAAA | DN1: ATAHAAAACTkvMjAvMjAxOecQwSddQNcIt6P+J11A1wgpQ0lRLlRTRTo3OTc0LklRX0NMT1NFUFJJQ0UuMjAxNi0xMS0yMi5VU0QBAAAApF0NAAIAAAAKMjUwLjY3NDk0NADnEMEnXUDXCAMGAShdQNcILENJUS5UU0U6Nzk3NC5JUV9URVZfRUJJVERBLklRX0xUTS4yMDE5LTAzLTI2AQAAAKRdDQACAAAACTExLjAzNTY3MQEHAAAABQAAAAExAQAAAAoxOTQ0NTk3NjU4AwAAAAEwAgAAAAYxMDAwMzAEAAAAATAHAAAACTMvMjYvMjAxOQgAAAAJMy8yNi8yMDE55xDBJ11A1whiygUoXUDXCClDSVEuVFNFOjc5NzQuSVFfQ0xPU0VQUklDRS4yMDE3LTA1LTAyLlVTRAEAAACkXQ0AAgAAAAoyNTIuOTQzODExAOcQwSddQNcIt6P+J11A1wgsQ0lRLlRTRTo3OTc0LklRX1RFVl9FQklUREEuSVFfTFRNLjIwMTctMTAtMDMBAAAApF0NAAIAAAAJNDkuMjkxMzAxAQcAAAAFAAAAATEBAAAACjE4NTQwNDM4ODgDAAAAATACAAAABjEwMDAzMAQAAAABMAcAAAAJMTAvMy8yMDE3CAAAAAkxMC8zLzIwMTfnEMEnXUDXCGtB/CddQNcIK0NJUS5FTlhUUEE6VUJJLklRX0NMT1NFUFJJQ0UuMjAxOS0wOS0yMy5VU0QBAAAAGXYNAAIAAAAJNzYuMDA2MTU4AOcQwSddQNcIa0H8J11A1wgwQ0lRLlRTRTo3OTc0LklRX0RBX1NVUFBMLkNZMjAxNi4yMDE5LTA5LTIzLi4uVVNEAQAAAKRdDQACAAAACTUyLjU2NTMwNwEIAAAABQAAAAEx | DO1: AQAAAAoxODI3NzY3Nzk3AwAAAAMxNjACAAAAAjQxBAAAAAEwBwAAAAk5LzIzLzIwMTkIAAAACjEyLzMxLzIwMTYJAAAAATCnmconXUDXCGLKBShdQNcIL0NJUS5OQVNEQVFHUzpUVFdPLklRX0dQLkNZMjAxOC4yMDE5LTA5LTIzLi4uVVNEAQAAAFGqBQACAAAACDExMzMuMjQ2AQgAAAAFAAAAATEBAAAACjE5NDM5MjUyMzYDAAAAAzE2MAIAAAACMTAEAAAAATAHAAAACTkvMjMvMjAxOQgAAAAKMTIvMzEvMjAxOAkAAAABMOcQwSddQNcIYsoFKF1A1wg2Q0lRLktPU0U6QTI1MTI3MC5JUV9FQklUREFfRVNULkNZMjAyMS4yMDE5LTA5LTIzLi4uVVNEAQAAAFnuLwkCAAAADzQyOC43MzM1MDg5NTYyMQEOAAAABQAAAAIxMQEAAAABMAIAAAAKMTAwMzczODI5MAMAAAAGMTAwMTg3BAAAAAEzBgAAAAEwBwAAAAMxNjAIAAAAATAJAAAAATEKAAAAATALAAAACzExNjEwODE2NjYwDAAAAAE3DQAAAAk5LzI0LzIwMTkQAAAACTkvMjMvMjAxOecQwSddQNcIAwYBKF1A1wgwQ0lRLk5BU0RBUUdTOlRUV08uSVFfQ09NUEFOWV9OQU1FLjIwMTktMDktMjMuVVNEAQAAAFGqBQADAAAAI1Rha2UtVHdvIEludGVyYWN0aXZlIFNvZnR3YXJlLCBJbmMuAOcQwSddQNcIAwYBKF1A1wgxQ0lRLlRTRTozNjU5LklRX1RPVEFMX1JFVi5DWTIwMTYuMjAxOS0wOS0yMy4uLlVTRAEAAACeH4IIAgAAAAoxNTY4LjU0ODA5AQgAAAAFAAAA | DP1: ATEBAAAACjE4MzUwNDI5MDcDAAAAAzE2MAIAAAACMjgEAAAAATAHAAAACTkvMjMvMjAxOQgAAAAKMTIvMzEvMjAxNgkAAAABMOcQwSddQNcIYsoFKF1A1wgsQ0lRLlRTRTo3OTc0LklRX1RFVl9FQklUREEuSVFfTFRNLjIwMTgtMDUtMjIBAAAApF0NAAIAAAAIMjIuMDMzNzUBBwAAAAUAAAABMQEAAAAKMTg4NDg2NDk2NAMAAAABMAIAAAAGMTAwMDMwBAAAAAEwBwAAAAk1LzIyLzIwMTgIAAAACTUvMjIvMjAxOOcQwSddQNcIcWgDKF1A1wgpQ0lRLlRTRTo3OTc0LklRX0NMT1NFUFJJQ0UuMjAxNi0xMS0yOS5VU0QBAAAApF0NAAIAAAAKMjQ3Ljc4NjgyMQDnEMEnXUDXCGtB/CddQNcIJUNJUS5OQVNEQVFHUzpFQS5JUV9URVYuMjAxOS0wOS0yMy5VU0QBAAAAO20AAAIAAAAMMjQ5ODIuMzgxNDY2AQYAAAAFAAAAATEBAAAACjE5NzQyMzUzNDkDAAAAAzE2MAIAAAAGMTAwMDYwBAAAAAEwBwAAAAk5LzIzLzIwMTnnEMEnXUDXCHFoAyhdQNcILUNJUS5UU0U6Nzk3NC5JUV9DQVBFWC5DWTIwMTYuMjAxOS0wOS0yMy4uLlVTRAEAAACkXQ0AAwAAAAAAp5nKJ11A1whiygUoXUDXCCxDSVEuVFNFOjc5NzQuSVFfVEVWX0VCSVREQS5JUV9MVE0uMjAxOC0wMS0wOQEAAACkXQ0AAgAAAAk0Mi44MjAyMDQBBwAAAAUAAAABMQEAAAAKMTg2NTc5MjM2MwMAAAABMAIAAAAGMTAwMDMwBAAAAAEwBwAAAAgxLzkvMjAxOAgA | DQ1: AAAIMS85LzIwMTjnEMEnXUDXCLej/iddQNcIKUNJUS5UU0U6Nzk3NC5JUV9DTE9TRVBSSUNFLjIwMTgtMDctMTcuVVNEAQAAAKRdDQACAAAACjMzMS41NTk4MjYA5xDBJ11A1whxaAMoXUDXCClDSVEuVFNFOjc5NzQuSVFfQ0xPU0VQUklDRS4yMDE4LTAyLTI3LlVTRAEAAACkXQ0AAgAAAAk0NjAuMDQ5MzEA5xDBJ11A1whxaAMoXUDXCClDSVEuVFNFOjc5NzQuSVFfQ0xPU0VQUklDRS4yMDE3LTAxLTMxLlVTRAEAAACkXQ0AAgAAAAoyMDQuOTgyNzA2AOcQwSddQNcIcWgDKF1A1wgsQ0lRLlRTRTo3OTc0LklRX1RFVl9FQklUREEuSVFfTFRNLjIwMTgtMTEtMjcBAAAApF0NAAIAAAAJMTQuNDgzNTUyAQcAAAAFAAAAATEBAAAACjE5MjE1MTg0MjMDAAAAATACAAAABjEwMDAzMAQAAAABMAcAAAAKMTEvMjcvMjAxOAgAAAAKMTEvMjcvMjAxOOcQwSddQNcIa0H8J11A1wgwQ0lRLlRTRTo3OTc0LklRX0RBX1NVUFBMLkNZMjAxOC4yMDE5LTA5LTIzLi4uVVNEAQAAAKRdDQACAAAACTQ2LjkwMzM0MQEIAAAABQAAAAExAQAAAAoxOTQ0NTk3NjU4AwAAAAMxNjACAAAAAjQxBAAAAAEwBwAAAAk5LzIzLzIwMTkIAAAACjEyLzMxLzIwMTgJAAAAATCnmconXUDXCGLKBShdQNcIKkNJUS5UU0U6Nzk3NC5JUV9URVYuNDIzNjkuMjAxOS0wOS0yMy4uLlVTRAEAAACkXQ0AAgAAAAs5NDI3LjUyMjU1MgEGAAAABQAAAAEx | DR1: AQAAAAoxNzY1MTQ2OTQxAwAAAAMxNjACAAAABjEwMDA2MAQAAAABMAcAAAAKMTIvMzEvMjAxNecQwSddQNcIYsoFKF1A1wgpQ0lRLlRTRTo3OTc0LklRX0NMT1NFUFJJQ0UuMjAxNi0wNS0xNy5VU0QBAAAApF0NAAIAAAAKMTQ2LjgyMTM4NwDnEMEnXUDXCGtB/CddQNcILENJUS5UU0U6Nzk3NC5JUV9URVZfRUJJVERBLklRX0xUTS4yMDE2LTAyLTAyAQAAAKRdDQACAAAACTI2LjM1NjEwOQEHAAAABQAAAAExAQAAAAoxNzc0MjgxNjI4AwAAAAEwAgAAAAYxMDAwMzAEAAAAATAHAAAACDIvMi8yMDE2CAAAAAgyLzIvMjAxNucQwSddQNcIcWgDKF1A1wgsQ0lRLlRTRTo3OTc0LklRX1RFVl9FQklUREEuSVFfTFRNLjIwMTctMTEtMjgBAAAApF0NAAIAAAAJNDcuNjA2NzE4AQcAAAAFAAAAATEBAAAACjE4NjU3OTIzNjMDAAAAATACAAAABjEwMDAzMAQAAAABMAcAAAAKMTEvMjgvMjAxNwgAAAAKMTEvMjgvMjAxN+cQwSddQNcIa0H8J11A1wgpQ0lRLlRTRTo3OTc0LklRX0NMT1NFUFJJQ0UuMjAxNi0wOC0xNi5VU0QBAAAApF0NAAIAAAAKMjE2LjUyODc2NQDnEMEnXUDXCHFoAyhdQNcIKUNJUS5UU0U6Nzk3NC5JUV9DTE9TRVBSSUNFLjIwMTYtMDYtMDcuVVNEAQAAAKRdDQACAAAACTE1MS4zNjk3NADnEMEnXUDXCAMGAShdQNcIOENJUS5OQVNEQVFHUzpUVFdPLklRX1JFVkVOVUVfRVNULkNZMjAyMi4yMDE5 | DS1: LTA5LTIzLi4uVVNEAQAAAFGqBQACAAAACTM3NjguNjc4NgEOAAAABQAAAAIxMQEAAAABMAIAAAAHMTMxNDc1MAMAAAAGMTAwMTgwBAAAAAEyBgAAAAEwBwAAAAMxNjAIAAAAATAJAAAAATEKAAAAATALAAAACzExNjExMjk2NTYxDAAAAAE3DQAAAAk5LzI0LzIwMTkQAAAACTkvMjMvMjAxOecQwSddQNcIt6P+J11A1wguQ0lRLlRTRTozNjU5LklRX0VCSVREQS5DWTIwMTcuMjAxOS0wOS0yMy4uLlVTRAEAAACeH4IIAgAAAAo5NjMuNzY3OTIyAQgAAAAFAAAAATEBAAAACjE4ODE0Mzg3MTQDAAAAAzE2MAIAAAAENDA1MQQAAAABMAcAAAAJOS8yMy8yMDE5CAAAAAoxMi8zMS8yMDE3CQAAAAEw5xDBJ11A1whxaAMoXUDXCClDSVEuVFNFOjc5NzQuSVFfQ0xPU0VQUklDRS4yMDE5LTA5LTI0LlVTRAEAAACkXQ0AAgAAAAozOTYuODA1NTU5AKeZyiddQNcIAwYBKF1A1wgsQ0lRLlRTRTo3OTc0LklRX1RFVl9FQklUREEuSVFfTFRNLjIwMTYtMDUtMDMBAAAApF0NAAIAAAAJMjAuMTUzODU0AQcAAAAFAAAAATEBAAAACjE3ODc5MjU4NzYDAAAAATACAAAABjEwMDAzMAQAAAABMAcAAAAINS8yLzIwMTYIAAAACDUvMi8yMDE25xDBJ11A1wgDBgEoXUDXCClDSVEuVFNFOjc5NzQuSVFfQ0xPU0VQUklDRS4yMDE4LTA2LTI2LlVTRAEAAACkXQ0AAgAAAAkzMjguMTMyODMA5xDBJ11A1wi3o/4nXUDXCCxDSVEuVFNFOjc5 | DT1: NzQuSVFfVEVWX0VCSVREQS5JUV9MVE0uMjAxNS0wOS0yMgEAAACkXQ0AAgAAAAgzNy4yNzY0NQEHAAAABQAAAAExAQAAAAoxNzQ5ODU3MDk3AwAAAAEwAgAAAAYxMDAwMzAEAAAAATAHAAAACTkvMTgvMjAxNQgAAAAJOS8xOC8yMDE15xDBJ11A1wgDBgEoXUDXCCxDSVEuVFNFOjc5NzQuSVFfVEVWX0VCSVREQS5JUV9MVE0uMjAxNS0wOC0yNQEAAACkXQ0AAgAAAAk0MC43OTgxNzgBBwAAAAUAAAABMQEAAAAKMTc0OTg1NzA5NwMAAAABMAIAAAAGMTAwMDMwBAAAAAEwBwAAAAk4LzI1LzIwMTUIAAAACTgvMjUvMjAxNecQwSddQNcIAwYBKF1A1wgpQ0lRLlRTRTo3OTc0LklRX0NMT1NFUFJJQ0UuMjAxNi0xMC0yNS5VU0QBAAAApF0NAAIAAAAKMjM2LjQ4MDMyNQDnEMEnXUDXCAMGAShdQNcIKUNJUS5UU0U6Nzk3NC5JUV9DTE9TRVBSSUNFLjIwMTYtMDQtMjYuVVNEAQAAAKRdDQACAAAACjE0OS44MDQ0ODUA5xDBJ11A1whxaAMoXUDXCClDSVEuVFNFOjc5NzQuSVFfQ0xPU0VQUklDRS4yMDE2LTA3LTEyLlVTRAEAAACkXQ0AAgAAAAoyMTguMTQ3MDc4AOcQwSddQNcIa0H8J11A1wgpQ0lRLlRTRTo3OTc0LklRX0NMT1NFUFJJQ0UuMjAxNS0xMC0yNy5VU0QBAAAApF0NAAIAAAAKMTkzLjEzNDEwNgDnEMEnXUDXCAMGAShdQNcIMUNJUS5UU0U6OTY4NC5JUV9UT1RBTF9SRVYuQ1kyMDE4LjIwMTktMDktMjMu | DU1: Li5VU0QBAAAAqX0NAAIAAAALMjIwMC4wMDkxMTYBCAAAAAUAAAABMQEAAAAKMTk0NDM4ODIyNAMAAAADMTYwAgAAAAIyOAQAAAABMAcAAAAJOS8yMy8yMDE5CAAAAAoxMi8zMS8yMDE4CQAAAAEw5xDBJ11A1wgDBgEoXUDXCC5DSVEuS09TRTpBMjUxMjcwLklRX1RFVi40MzEwMC4yMDE5LTA5LTIzLi4uVVNEAQAAAFnuLwkCAAAADDEyODA5LjY2NDA1OQEGAAAABQAAAAExAQAAAAoxODY3MzM0MzgxAwAAAAMxNjACAAAABjEwMDA2MAQAAAABMAcAAAAKMTIvMzEvMjAxN+cQwSddQNcIa0H8J11A1wgpQ0lRLlRTRTo3OTc0LklRX0NMT1NFUFJJQ0UuMjAxOS0wNy0wMi5VU0QBAAAApF0NAAIAAAAKMzcxLjUxMTg3NgCnmconXUDXCAMGAShdQNcINENJUS5FTlhUUEE6VUJJLklRX0VCSVREQV9FU1QuQ1kyMDIwLjIwMTktMDktMjMuLi5VU0QBAAAAGXYNAAIAAAANNjc0LjA3MDgxNTg1MQEOAAAABQAAAAIxMQEAAAABMAIAAAAINDc1MTQ3MTcDAAAABjEwMDE4NwQAAAABMwYAAAABMAcAAAADMTYwCAAAAAEwCQAAAAExCgAAAAEwCwAAAAsxMTU5OTI1OTM1MQwAAAABNw0AAAAJOS8yNC8yMDE5EAAAAAk5LzIzLzIwMTnnEMEnXUDXCLej/iddQNcINENJUS5OQVNEQVFHUzpFQS5JUV9UT1RBTF9SRVYuQ1kyMDE2LjIwMTktMDktMjMuLi5VU0QBAAAAO20AAAIAAAAENDYyNgEIAAAABQAAAAExAQAAAAoxODczMjY3 | DV1: NDAwAwAAAAMxNjACAAAAAjI4BAAAAAEwBwAAAAk5LzIzLzIwMTkIAAAACjEyLzMxLzIwMTYJAAAAATDnEMEnXUDXCLej/iddQNcIQkNJUS5UU0U6Nzk3NC5JUV9DSEFOR0VfTkVUX1dPUktJTkdfQ0FQSVRBTC5DWTIwMTguMjAxOS0wOS0yMy4uLlVTRAEAAACkXQ0AAgAAAAsxMzI1LjE0MjQxNQEIAAAABQAAAAExAQAAAAoxOTQ0NTk3NjU4AwAAAAMxNjACAAAABDQ0MjEEAAAAATAHAAAACTkvMjMvMjAxOQgAAAAKMTIvMzEvMjAxOAkAAAABMKeZyiddQNcIYsoFKF1A1wguQ0lRLlRTRTo3OTc0LklRX0VCSVREQS5JUV9MVE0uMjAxOS0wOS0yMy4uLlVTRAEAAACkXQ0AAgAAAAsyMzc3LjczMzQ5OQEIAAAABQAAAAExAQAAAAoxOTc1NzkyNDcwAwAAAAMxNjACAAAABDQwNTEEAAAAATAHAAAACTkvMjMvMjAxOQgAAAAJNi8zMC8yMDE5CQAAAAEwp5nKJ11A1whiygUoXUDXCCxDSVEuVFNFOjc5NzQuSVFfVEVWX0VCSVREQS5JUV9MVE0uMjAxOC0wNy0xMAEAAACkXQ0AAgAAAAkxNi42NjYwNzEBBwAAAAUAAAABMQEAAAAKMTg5NTE5MDMxMgMAAAABMAIAAAAGMTAwMDMwBAAAAAEwBwAAAAk3LzEwLzIwMTgIAAAACTcvMTAvMjAxOOcQwSddQNcIa0H8J11A1wg7Q0lRLkVOWFRQQTpVQkkuSVFfVE9UQUxfREVCVF9FUVVJVFkuSVFfTFRNLjIwMTktMDktMjMuLi5VU0QBAAAAGXYNAAIAAAAIMTQ2LjA0NzYBCAAA | DW1: AAUAAAABMQEAAAAKMTk2ODQ2Mjg3MQMAAAACNTACAAAABDQwMzQEAAAAATAHAAAACTkvMjMvMjAxOQgAAAAJMy8zMS8yMDE5CQAAAAEwp5nKJ11A1whxaAMoXUDXCCxDSVEuVFNFOjc5NzQuSVFfVEVWX0VCSVREQS5JUV9MVE0uMjAxOS0wNC0xNgEAAACkXQ0AAgAAAAkxMi4yMTk5MDkBBwAAAAUAAAABMQEAAAAKMTk0NDU5NzY1OAMAAAABMAIAAAAGMTAwMDMwBAAAAAEwBwAAAAk0LzE2LzIwMTkIAAAACTQvMTYvMjAxOecQwSddQNcIa0H8J11A1wguQ0lRLktPU0U6QTI1MTI3MC5JUV9HUC5DWTIwMTYuMjAxOS0wOS0yMy4uLlVTRAEAAABZ7i8JAgAAAAsxMjQ1LjU5MDc1NwEIAAAABQAAAAExAQAAAAoxODgwMjYyMTMyAwAAAAMxNjACAAAAAjEwBAAAAAEwBwAAAAk5LzIzLzIwMTkIAAAACjEyLzMxLzIwMTYJAAAAATDnEMEnXUDXCGtB/CddQNcILENJUS5UU0U6Nzk3NC5JUV9URVZfRUJJVERBLklRX0xUTS4yMDE1LTEwLTEzAQAAAKRdDQACAAAACTM5Ljk2ODczNgEHAAAABQAAAAExAQAAAAoxNzQ5ODU3MDk3AwAAAAEwAgAAAAYxMDAwMzAEAAAAATAHAAAACjEwLzEzLzIwMTUIAAAACjEwLzEzLzIwMTXnEMEnXUDXCGLKBShdQNcIMUNJUS5UU0U6OTY4NC5JUV9UT1RBTF9SRVYuQ1kyMDE2LjIwMTktMDktMjMuLi5VU0QBAAAAqX0NAAIAAAALMjE1My41MzMwNjcBCAAAAAUAAAABMQEAAAAKMTgyNzUw | DX1: ODIwNwMAAAADMTYwAgAAAAIyOAQAAAABMAcAAAAJOS8yMy8yMDE5CAAAAAoxMi8zMS8yMDE2CQAAAAEw5xDBJ11A1whrQfwnXUDXCC9DSVEuTkFTREFRR1M6QVRWSS5JUV9URVYuNDMxMDAuMjAxOS0wOS0yMy4uLlVTRAEAAAAXbUAAAgAAAAs0ODYwOC4yMTc0OQEGAAAABQAAAAExAQAAAAoxODYzODk2MTE2AwAAAAMxNjACAAAABjEwMDA2MAQAAAABMAcAAAAKMTIvMzEvMjAxN+cQwSddQNcIcWgDKF1A1wgpQ0lRLlRTRTo3OTc0LklRX0NMT1NFUFJJQ0UuMjAxNi0xMi0yMC5VU0QBAAAApF0NAAIAAAAKMjEwLjA2NTE3OQDnEMEnXUDXCAMGAShdQNcIPENJUS5OQVNEQVFHUzpBVFZJLklRX0VGRkVDVF9UQVhfUkFURS5JUV9MVE0uMjAxOS0wOS0yMy4uLlVTRAEAAAAXbUAAAgAAAAY4LjM3NDEBCAAAAAUAAAABMQEAAAAKMTk3NTAzOTA1MgMAAAADMTYwAgAAAAQ0Mzc2BAAAAAEwBwAAAAk5LzIzLzIwMTkIAAAACTYvMzAvMjAxOQkAAAABMKeZyiddQNcIt6P+J11A1wgpQ0lRLlRTRTo3OTc0LklRX0NMT1NFUFJJQ0UuMjAxNy0wMS0xMC5VU0QBAAAApF0NAAIAAAAKMjEwLjk3NzQwMgDnEMEnXUDXCLej/iddQNcILENJUS5UU0U6Nzk3NC5JUV9URVZfRUJJVERBLklRX0xUTS4yMDE2LTAzLTAxAQAAAKRdDQACAAAACTIxLjQ4MDY0NQEHAAAABQAAAAExAQAAAAoxNzc2NTg0MDQzAwAAAAEwAgAAAAYxMDAw | DY1: MzAEAAAAATAHAAAACDMvMS8yMDE2CAAAAAgzLzEvMjAxNucQwSddQNcIYsoFKF1A1wgsQ0lRLlRTRTo3OTc0LklRX1RFVl9FQklUREEuSVFfTFRNLjIwMTYtMDQtMjYBAAAApF0NAAIAAAAJMjQuOTYzMTE5AQcAAAAFAAAAATEBAAAACjE3NzY1ODQwNDMDAAAAATACAAAABjEwMDAzMAQAAAABMAcAAAAJNC8yNi8yMDE2CAAAAAk0LzI2LzIwMTbnEMEnXUDXCGLKBShdQNcIKUNJUS5UU0U6Nzk3NC5JUV9DTE9TRVBSSUNFLjIwMTYtMTAtMTguVVNEAQAAAKRdDQACAAAACjI1Mi41Mjg2NDkA5xDBJ11A1wi3o/4nXUDXCClDSVEuVFNFOjc5NzQuSVFfQ0xPU0VQUklDRS4yMDE3LTAxLTAzLlVTRAEAAACkXQ0AAwAAAAAA5xDBJ11A1whxaAMoXUDXCDhDSVEuTkFTREFRR1M6RUEuSVFfQ0FTSF9JTlRFUkVTVC5JUV9MVE0uMjAxOS0wOS0yMy4uLlVTRAEAAAA7bQAAAgAAAAI0MgEIAAAABQAAAAExAQAAAAoxOTc0MjM1ODEyAwAAAAMxNjACAAAABDMwMjgEAAAAATAHAAAACTkvMjMvMjAxOQgAAAAJNi8zMC8yMDE5CQAAAAEwp5nKJ11A1whxaAMoXUDXCDVDSVEuTkFTREFRR1M6RUEuSVFfRUJJVERBX0VTVC5DWTIwMjEuMjAxOS0wOS0yMy4uLlVTRAEAAAA7bQAAAgAAAAkyMDgwLjE2NDEBDgAAAAUAAAACMTEBAAAAATACAAAACDUxMjA0ODkzAwAAAAYxMDAxODcEAAAAATIGAAAAATAHAAAAAzE2MAgAAAABMAkA | DZ1: AAABMQoAAAABMAsAAAALMTE1NDQwOTgxMzAMAAAAATcNAAAACTkvMjQvMjAxORAAAAAJOS8yMy8yMDE55xDBJ11A1whiygUoXUDXCC9DSVEuTkFTREFRR1M6VFRXTy5JUV9URVYuNDIzNjkuMjAxOS0wOS0yMy4uLlVTRAEAAABRqgUAAgAAAAsyMjYwLjE2NTkxNQEGAAAABQAAAAExAQAAAAoxNzYzMjUzMDA1AwAAAAMxNjACAAAABjEwMDA2MAQAAAABMAcAAAAKMTIvMzEvMjAxNecQwSddQNcIt6P+J11A1wg2Q0lRLk5BU0RBUUdTOkVBLklRX1JFVkVOVUVfRVNULkNZMjAyMS4yMDE5LTA5LTIzLi4uVVNEAQAAADttAAACAAAACTU4MjIuMzk0OQEOAAAABQAAAAIxMQEAAAABMAIAAAAINTEyMDQ4OTMDAAAABjEwMDE4MAQAAAABMgYAAAABMAcAAAADMTYwCAAAAAEwCQAAAAExCgAAAAEwCwAAAAsxMTU1NTAxMzEzNgwAAAABNw0AAAAJOS8yNC8yMDE5EAAAAAk5LzIzLzIwMTnnEMEnXUDXCGtB/CddQNcIKUNJUS5UU0U6Nzk3NC5JUV9DTE9TRVBSSUNFLjIwMTYtMDQtMTIuVVNEAQAAAKRdDQACAAAACjE1MC4zMjIyODEA5xDBJ11A1wgDBgEoXUDXCC1DSVEuTkFTREFRR1M6QVRWSS5JUV9NQVJLRVRDQVAuMjAxOS0wOS0yMy5VU0QBAAAAF21AAAIAAAAMNDE1NTcuNDY1NDI5AQYAAAAFAAAAATEBAAAACjE5NzUwMzg3OTkDAAAAAzE2MAIAAAAGMTAwMDU0BAAAAAEwBwAAAAk5LzIzLzIwMTnnEMEnXUDXCHFo | EA1: AyhdQNcIKkNJUS5UU0U6OTY4NC5JUV9URVYuNDM4MzAuMjAxOS0wOS0yMy4uLlVTRAEAAACpfQ0AAgAAAAs0MTMwLjYwNjczNgEGAAAABQAAAAExAQAAAAoxOTc1Nzg2NjA5AwAAAAMxNjACAAAABjEwMDA2MAQAAAABMAcAAAAJOS8yMC8yMDE55xDBJ11A1wgDBgEoXUDXCDJDSVEuVFNFOjM2NTkuSVFfRUJJVERBX0VTVC5DWTIwMjEuMjAxOS0wOS0yMy4uLlVTRAEAAACeH4IIAgAAABAxMTU3LjUxOTM2MDU2MjIyAQ4AAAAFAAAAAjExAQAAAAEwAgAAAAoxMDAxNjQ4ODIyAwAAAAYxMDAxODcEAAAAATMGAAAAATAHAAAAAzE2MAgAAAABMAkAAAABMQoAAAABMAsAAAALMTE2MDM0NDc4MDQMAAAAATcNAAAACTkvMjQvMjAxORAAAAAJOS8yMy8yMDE55xDBJ11A1wi3o/4nXUDXCCxDSVEuVFNFOjc5NzQuSVFfVEVWX0VCSVREQS5JUV9MVE0uMjAxOC0xMC0xNgEAAACkXQ0AAgAAAAkxOC44ODQ0MjYBBwAAAAUAAAABMQEAAAAKMTkwMDI3Mjc5NgMAAAABMAIAAAAGMTAwMDMwBAAAAAEwBwAAAAoxMC8xNi8yMDE4CAAAAAoxMC8xNi8yMDE45xDBJ11A1wi3o/4nXUDXCDdDSVEuTkFTREFRR1M6QVRWSS5JUV9FQklUREFfRVNULkNZMjAyMi4yMDE5LTA5LTIzLi4uVVNEAQAAABdtQAACAAAABzMzNDQuMjYBDgAAAAUAAAACMTEBAAAAATACAAAACjEwMDEzOTkyMTUDAAAABjEwMDE4NwQAAAABMgYAAAABMAcAAAAD | EB1: MTYwCAAAAAEwCQAAAAExCgAAAAEwCwAAAAsxMTU2MzM0OTkzNgwAAAABNw0AAAAJOS8yNC8yMDE5EAAAAAk5LzIzLzIwMTnnEMEnXUDXCLej/iddQNcINENJUS5FTlhUUEE6VUJJLklRX0VCSVREQV9FU1QuQ1kyMDIxLjIwMTktMDktMjMuLi5VU0QBAAAAGXYNAAIAAAAQMTIzMS40NDM5MTg5MzY3NAEOAAAABQAAAAIxMQEAAAABMAIAAAAINDc1MTQ3MTgDAAAABjEwMDE4NwQAAAABMwYAAAABMAcAAAADMTYwCAAAAAEwCQAAAAExCgAAAAEwCwAAAAsxMTYxMTcxMDIwNAwAAAABNw0AAAAJOS8yNC8yMDE5EAAAAAk5LzIzLzIwMTnnEMEnXUDXCAMGAShdQNcIKUNJUS5UU0U6Nzk3NC5JUV9DTE9TRVBSSUNFLjIwMTYtMDItMDkuVVNEAQAAAKRdDQACAAAACjEzNy41NzYwMTYA5xDBJ11A1wi3o/4nXUDXCClDSVEuVFNFOjc5NzQuSVFfQ0xPU0VQUklDRS4yMDE1LTEyLTAxLlVTRAEAAACkXQ0AAgAAAAoxNTYuNTUzOTM0AOcQwSddQNcIa0H8J11A1wg2Q0lRLktPU0U6QTI1MTI3MC5JUV9FQklUREFfRVNULkNZMjAyMC4yMDE5LTA5LTIzLi4uVVNEAQAAAFnuLwkCAAAADzQwNS44NDI2NzYxMjkyNwEOAAAABQAAAAIxMQEAAAABMAIAAAAKMTAwMzczODI4OQMAAAAGMTAwMTg3BAAAAAEzBgAAAAEwBwAAAAMxNjAIAAAAATAJAAAAATEKAAAAATALAAAACzExNjEwODE3OTYwDAAAAAE3DQAAAAk5LzI0LzIwMTkQ | EC1: AAAACTkvMjMvMjAxOecQwSddQNcIAwYBKF1A1wghQ0lRLklRVFI1NTE3OTk2NjkuSVFfVFJfQlVZRVJOQU1FAQAAAHXL4yADAAAAVlNoZW56aGVuIEhlbmd0YWkgU3RhYmxlIEdyb3d0aCBJbnZlc3RtZW50IFBhcnRuZXJzaGlwIEVudGVycHJpc2UgKExpbWl0ZWQgUGFydG5lcnNoaXApAOcQwSddQNcIAwYBKF1A1wgsQ0lRLlRTRTo3OTc0LklRX1RFVl9FQklUREEuSVFfTFRNLjIwMTYtMDMtMTUBAAAApF0NAAIAAAAJMjIuOTAwOTQ4AQcAAAAFAAAAATEBAAAACjE3NzY1ODQwNDMDAAAAATACAAAABjEwMDAzMAQAAAABMAcAAAAJMy8xNS8yMDE2CAAAAAkzLzE1LzIwMTbnEMEnXUDXCDbf+SddQNcILENJUS5UU0U6Nzk3NC5JUV9URVZfRUJJVERBLklRX0xUTS4yMDE2LTAzLTA4AQAAAKRdDQACAAAACTIyLjY2ODc4MwEHAAAABQAAAAExAQAAAAoxNzc2NTg0MDQzAwAAAAEwAgAAAAYxMDAwMzAEAAAAATAHAAAACDMvOC8yMDE2CAAAAAgzLzgvMjAxNucQwSddQNcIAwYBKF1A1wgqQ0lRLlRTRTo3OTc0LklRX0dQLkNZMjAxNi4yMDE5LTA5LTIzLi4uVVNEAQAAAKRdDQACAAAACzE1MjIuMzIxMTEyAQgAAAAFAAAAATEBAAAACjE4Mjc3Njc3OTcDAAAAAzE2MAIAAAACMTAEAAAAATAHAAAACTkvMjMvMjAxOQgAAAAKMTIvMzEvMjAxNgkAAAABMOcQwSddQNcIYsoFKF1A1wgsQ0lRLlRTRTo3OTc0LklRX1RF | ED1: Vl9FQklUREEuSVFfTFRNLjIwMTctMDYtMjABAAAApF0NAAIAAAAINjEuMjU1OTEBBwAAAAUAAAABMQEAAAAKMTgzODIwNDA3NAMAAAABMAIAAAAGMTAwMDMwBAAAAAEwBwAAAAk2LzIwLzIwMTcIAAAACTYvMjAvMjAxN+cQwSddQNcIYsoFKF1A1wgpQ0lRLlRTRTo3OTc0LklRX0NMT1NFUFJJQ0UuMjAxNS0wOS0yOS5VU0QBAAAApF0NAAIAAAAKMTYxLjE0NDk2MgDnEMEnXUDXCAMGAShdQNcIKUNJUS5UU0U6Nzk3NC5JUV9DTE9TRVBSSUNFLjIwMTYtMTItMjcuVVNEAQAAAKRdDQACAAAACjIwOC45MDc2MDUA5xDBJ11A1whrQfwnXUDXCDRDSVEuRU5YVFBBOlVCSS5JUV9UT1RBTF9ERUJULklRX0xUTS4yMDE5LTA5LTIzLi4uVVNEAQAAABl2DQACAAAACzE1MDguMDQxNTI3AQgAAAAFAAAAATEBAAAACjE5Njg0NjI4NzEDAAAAAzE2MAIAAAAENDE3MwQAAAABMAcAAAAJOS8yMy8yMDE5CAAAAAkzLzMxLzIwMTkJAAAAATCnmconXUDXCDbf+SddQNcILENJUS5UU0U6Nzk3NC5JUV9URVZfRUJJVERBLklRX0xUTS4yMDE4LTAzLTI3AQAAAKRdDQACAAAACTI2LjQ3NzM4OQEHAAAABQAAAAExAQAAAAoxODc0MTkzMzQwAwAAAAEwAgAAAAYxMDAwMzAEAAAAATAHAAAACTMvMjcvMjAxOAgAAAAJMy8yNy8yMDE45xDBJ11A1whiygUoXUDXCDZDSVEuTkFTREFRR1M6VFRXTy5JUV9UT1RBTF9SRVYuQ1kyMDE3LjIw | EE1: MTktMDktMjMuLi5VU0QBAAAAUaoFAAIAAAAIMTkxNC4xNzQBCAAAAAUAAAABMQEAAAAKMTk0MzkyNTIzNAMAAAADMTYwAgAAAAIyOAQAAAABMAcAAAAJOS8yMy8yMDE5CAAAAAoxMi8zMS8yMDE3CQAAAAEw5xDBJ11A1whxaAMoXUDXCCxDSVEuVFNFOjc5NzQuSVFfVEVWX0VCSVREQS5JUV9MVE0uMjAxNS0wNi0zMAEAAACkXQ0AAgAAAAk0NS43MDMyNjkBBwAAAAUAAAABMQEAAAAKMTc0NTkyMjc3MgMAAAABMAIAAAAGMTAwMDMwBAAAAAEwBwAAAAk2LzMwLzIwMTUIAAAACTYvMzAvMjAxNecQwSddQNcIAwYBKF1A1wgpQ0lRLlRTRTo3OTc0LklRX0NMT1NFUFJJQ0UuMjAxOC0xMS0yNy5VU0QBAAAApF0NAAIAAAAJMjg3LjI5NjcxAOcQwSddQNcINt/5J11A1wgsQ0lRLlRTRTo3OTc0LklRX1RFVl9FQklUREEuSVFfTFRNLjIwMTctMDUtMDkBAAAApF0NAAIAAAAJNDMuMjA1Njk0AQcAAAAFAAAAATEBAAAACjE4MzgyMDQwNzQDAAAAATACAAAABjEwMDAzMAQAAAABMAcAAAAINS85LzIwMTcIAAAACDUvOS8yMDE35xDBJ11A1wg23/knXUDXCClDSVEuVFNFOjc5NzQuSVFfQ0xPU0VQUklDRS4yMDE4LTA3LTEwLlVTRAEAAACkXQ0AAgAAAAozMTkuMjQ4Mzk0AOcQwSddQNcIa0H8J11A1wg2Q0lRLlRTRTo5Njg0LklRX0RJTFVUX0VQU19FWENMLklRX0xUTS4yMDE5LTA5LTIzLi4uVVNEAQAAAKl9DQACAAAA | EF1: CDEuMjk5MzM3AQgAAAAFAAAAATEBAAAACjE5NzU3OTI2NDMDAAAAAzE2MAIAAAADMTQyBAAAAAEwBwAAAAk5LzIzLzIwMTkIAAAACTYvMzAvMjAxOQkAAAABMOcQwSddQNcIcWgDKF1A1wgsQ0lRLlRTRTo3OTc0LklRX1RFVl9FQklUREEuSVFfTFRNLjIwMTUtMTItMDgBAAAApF0NAAIAAAAJMzAuMjU2NzMyAQcAAAAFAAAAATEBAAAACjE3NjUxNTM2NzEDAAAAATACAAAABjEwMDAzMAQAAAABMAcAAAAJMTIvOC8yMDE1CAAAAAkxMi84LzIwMTXnEMEnXUDXCGLKBShdQNcILUNJUS5OQVNEQVFHUzpFQS5JUV9URVYuNDQ5MjYuMjAxOS0wOS0yMy4uLlVTRAEAAAA7bQAAAgAAAAwyNDk4Mi4zODE0NjYBBgAAAAUAAAABMQEAAAAKMTk3NDIzNTM0OQMAAAADMTYwAgAAAAYxMDAwNjAEAAAAATAHAAAACTkvMjMvMjAxOecQwSddQNcIa0H8J11A1wgsQ0lRLlRTRTo3OTc0LklRX1RFVl9FQklUREEuSVFfTFRNLjIwMTktMDctMjMBAAAApF0NAAIAAAAJMTMuODI3NzI1AQcAAAAFAAAAATEBAAAACjE5NzAyMjA1MTUDAAAAATACAAAABjEwMDAzMAQAAAABMAcAAAAJNy8yMy8yMDE5CAAAAAk3LzIzLzIwMTmnmconXUDXCLej/iddQNcIKUNJUS5UU0U6Nzk3NC5JUV9DTE9TRVBSSUNFLjIwMTYtMTAtMTEuVVNEAQAAAKRdDQACAAAACjI1NC4yNTYxNDYA5xDBJ11A1whxaAMoXUDXCClDSVEuVFNFOjc5NzQuSVFfQ0xP | EG1: U0VQUklDRS4yMDE2LTA1LTEwLlVTRAEAAACkXQ0AAgAAAAoxMzkuMDQ2NzQ5AOcQwSddQNcIAwYBKF1A1wgpQ0lRLlRTRTo3OTc0LklRX0NMT1NFUFJJQ0UuMjAxNy0xMS0yOC5VU0QBAAAApF0NAAIAAAAJNDIyLjk4MTg4AOcQwSddQNcIa0H8J11A1wgiQ0lRLlRTRTo3OTc0LklRX1RFVi4yMDE5LTA5LTIzLlVTRAEAAACkXQ0AAgAAAAwzODg3MS4zMjkxNDEBBgAAAAUAAAABMQEAAAAKMTk3NTc4NzA4NgMAAAADMTYwAgAAAAYxMDAwNjAEAAAAATAHAAAACTkvMjAvMjAxOecQwSddQNcIcWgDKF1A1wgsQ0lRLlRTRTo3OTc0LklRX1RFVl9FQklUREEuSVFfTFRNLjIwMTUtMTItMTUBAAAApF0NAAIAAAAJMjYuMjkzOTkxAQcAAAAFAAAAATEBAAAACjE3NjUxNTM2NzEDAAAAATACAAAABjEwMDAzMAQAAAABMAcAAAAKMTIvMTUvMjAxNQgAAAAKMTIvMTUvMjAxNecQwSddQNcIAwYBKF1A1wgpQ0lRLlRTRTo3OTc0LklRX0NMT1NFUFJJQ0UuMjAxOS0wNC0wOS5VU0QBAAAApF0NAAIAAAAKMjk5LjEwOTE0MwDnEMEnXUDXCAMGAShdQNcILENJUS5UU0U6Nzk3NC5JUV9URVZfRUJJVERBLklRX0xUTS4yMDE2LTEyLTEzAQAAAKRdDQACAAAACDYyLjg4OTM1AQcAAAAFAAAAATEBAAAACjE4MTgwNjgyMjEDAAAAATACAAAABjEwMDAzMAQAAAABMAcAAAAKMTIvMTMvMjAxNggAAAAKMTIvMTMvMjAxNucQwSddQNcI | EH1: AwYBKF1A1wg2Q0lRLktPU0U6QTI1MTI3MC5JUV9FQklUREFfRVNULkNZMjAxOS4yMDE5LTA5LTIzLi4uVVNEAQAAAFnuLwkCAAAADzMwNC44ODkzMTI1MjE5OAEOAAAABQAAAAIxMQEAAAABMAIAAAAKMTAwMzY2MzEwOQMAAAAGMTAwMTg3BAAAAAEzBgAAAAEwBwAAAAMxNjAIAAAAATAJAAAAATEKAAAAATALAAAACzExNjEwODEyODcyDAAAAAE3DQAAAAk5LzI0LzIwMTkQAAAACTkvMjMvMjAxOecQwSddQNcIt6P+J11A1wgpQ0lRLlRTRTo3OTc0LklRX0NMT1NFUFJJQ0UuMjAxNS0wOC0wNC5VU0QBAAAApF0NAAIAAAAKMTgwLjA3MjYwNADnEMEnXUDXCAMGAShdQNcILENJUS5UU0U6Nzk3NC5JUV9URVZfRUJJVERBLklRX0xUTS4yMDE5LTAyLTE5AQAAAKRdDQACAAAACDkuOTgxNjk1AQcAAAAFAAAAATEBAAAACjE5NDQ1OTc2NTgDAAAAATACAAAABjEwMDAzMAQAAAABMAcAAAAJMi8xOS8yMDE5CAAAAAkyLzE5LzIwMTnnEMEnXUDXCGtB/CddQNcIN0NJUS5UU0U6Nzk3NC5JUV9FRkZFQ1RfVEFYX1JBVEUuQ1kyMDE4LjIwMTktMDktMjMuLi5VU0QBAAAApF0NAAIAAAAHMjkuMTc3OAEIAAAABQAAAAExAQAAAAoxOTQ0NTk3NjU4AwAAAAI3OQIAAAAENDM3NgQAAAABMAcAAAAJOS8yMy8yMDE5CAAAAAoxMi8zMS8yMDE4CQAAAAEwp5nKJ11A1whiygUoXUDXCClDSVEuVFNFOjc5NzQuSVFfQ0xPU0VQUklD | EI1: RS4yMDE2LTAzLTE1LlVTRAEAAACkXQ0AAgAAAAoxNDAuODg5OTcxAOcQwSddQNcIAwYBKF1A1wgpQ0lRLlRTRTo3OTc0LklRX0NMT1NFUFJJQ0UuMjAxOS0wMy0xOS5VU0QBAAAApF0NAAIAAAAKMjgyLjgyNzM3MgDnEMEnXUDXCDbf+SddQNcIMkNJUS5UU0U6OTY4NC5JUV9FQklUREFfRVNULkNZMjAxOS4yMDE5LTA5LTIzLi4uVVNEAQAAAKl9DQACAAAAEDMzMS4xODQwMzc1ODI2NTIBDgAAAAUAAAACMTEBAAAAATACAAAACDQ2ODI3MzM1AwAAAAYxMDAxODcEAAAAAjU2BgAAAAEwBwAAAAMxNjAIAAAAATAJAAAAATEKAAAAATALAAAACzExNjA5Mzc4ODgwDAAAAAE3DQAAAAk5LzI0LzIwMTkQAAAACTkvMjMvMjAxOecQwSddQNcIAwYBKF1A1wgpQ0lRLlRTRTo3OTc0LklRX0NMT1NFUFJJQ0UuMjAxOC0wNi0xOS5VU0QBAAAApF0NAAIAAAAKMzI3Ljc1ODU3MQDnEMEnXUDXCHFoAyhdQNcIKUNJUS5UU0U6Nzk3NC5JUV9DTE9TRVBSSUNFLjIwMTYtMDMtMDguVVNEAQAAAKRdDQACAAAACjE0MC42NDE2NjUA5xDBJ11A1wi3o/4nXUDXCDpDSVEuTkFTREFRR1M6QVRWSS5JUV9DQVNIX0lOVEVSRVNULklRX0xUTS4yMDE5LTA5LTIzLi4uVVNEAQAAABdtQAACAAAAAzE1MAEIAAAABQAAAAExAQAAAAoxOTc1MDM5MDUyAwAAAAMxNjACAAAABDMwMjgEAAAAATAHAAAACTkvMjMvMjAxOQgAAAAJNi8zMC8yMDE5 | EJ1: CQAAAAEwp5nKJ11A1wi3o/4nXUDXCDxDSVEuTkFTREFRR1M6RUEuSVFfU0hPUlRfQlVTSU5FU1NfREVTQ1JJUFRJT04uMjAxOS0wOS0yMy5VU0QBAAAAO20AAAMAAACdAUVsZWN0cm9uaWMgQXJ0cyBJbmMuIGRldmVsb3BzLCBtYXJrZXRzLCBwdWJsaXNoZXMsIGFuZCBkaXN0cmlidXRlcyBnYW1lcywgY29udGVudCwgYW5kIHNlcnZpY2VzIGZvciBnYW1lIGNvbnNvbGVzLCBQQ3MsIG1vYmlsZSBwaG9uZXMsIGFuZCB0YWJsZXRzIHdvcmxkd2lkZS4A5xDBJ11A1whrQfwnXUDXCClDSVEuVFNFOjc5NzQuSVFfQ0xPU0VQUklDRS4yMDE1LTEwLTIwLlVTRAEAAACkXQ0AAgAAAAgxOTQuMzEyNADnEMEnXUDXCLej/iddQNcILkNJUS5UU0U6OTY4NC5JUV9FQklUREEuQ1kyMDE3LjIwMTktMDktMjMuLi5VU0QBAAAAqX0NAAIAAAAKNDQyLjM3MzU5NgEIAAAABQAAAAExAQAAAAoxODc0MDA3OTE1AwAAAAMxNjACAAAABDQwNTEEAAAAATAHAAAACTkvMjMvMjAxOQgAAAAKMTIvMzEvMjAxNwkAAAABMOcQwSddQNcIa0H8J11A1wg2Q0lRLk5BU0RBUUdTOkVBLklRX1JFVkVOVUVfRVNULkNZMjAxOS4yMDE5LTA5LTIzLi4uVVNEAQAAADttAAACAAAACTUyOTAuNDg3MgEOAAAABQAAAAIxMQEAAAABMAIAAAAHNzg3NTM2MQMAAAAGMTAwMTgwBAAAAAEyBgAAAAEwBwAAAAMxNjAIAAAAATAJAAAAATEKAAAAATALAAAA | EK1: CzExNTk5MjYxMTEzDAAAAAE3DQAAAAk5LzI0LzIwMTkQAAAACTkvMjMvMjAxOecQwSddQNcIYsoFKF1A1wgsQ0lRLlRTRTo3OTc0LklRX1RFVl9FQklUREEuSVFfTFRNLjIwMTgtMDgtMDcBAAAApF0NAAIAAAAJMTcuMjg5OTI1AQcAAAAFAAAAATEBAAAACjE4OTc3ODIyNTkDAAAAATACAAAABjEwMDAzMAQAAAABMAcAAAAIOC83LzIwMTgIAAAACDgvNy8yMDE45xDBJ11A1whrQfwnXUDXCClDSVEuVFNFOjc5NzQuSVFfQ0xPU0VQUklDRS4yMDE4LTAxLTAyLlVTRAEAAACkXQ0AAwAAAAAA5xDBJ11A1whxaAMoXUDXCClDSVEuVFNFOjc5NzQuSVFfQ0xPU0VQUklDRS4yMDE2LTExLTAxLlVTRAEAAACkXQ0AAgAAAAoyNDQuMDQxNjIxAOcQwSddQNcIa0H8J11A1wg5Q0lRLlRTRTozNjU5LklRX1NIT1JUX0JVU0lORVNTX0RFU0NSSVBUSU9OLjIwMTktMDktMjMuVVNEAQAAAJ4fgggDAAAAQU5FWE9OIENvLiwgTHRkLiBkZXZlbG9wcyBhbmQgc2VydmljZXMgUEMgb25saW5lIGFuZCBtb2JpbGUgZ2FtZXMuAOcQwSddQNcIAwYBKF1A1wgsQ0lRLlRTRTo3OTc0LklRX1RFVl9FQklUREEuSVFfTFRNLjIwMTYtMDEtMjYBAAAApF0NAAIAAAAJMjMuMjQ5OTQ4AQcAAAAFAAAAATEBAAAACjE3NjUxNTM2NzEDAAAAATACAAAABjEwMDAzMAQAAAABMAcAAAAJMS8yNi8yMDE2CAAAAAkxLzI2LzIwMTbnEMEnXUDXCGtB | EL1: /CddQNcIKENJUS5UU0U6MzY1OS5JUV9NQVJLRVRDQVAuMjAxOS0wOS0yMy5VU0QBAAAAnh+CCAIAAAAMMTE3MTMuMDc0NjYyAQYAAAAFAAAAATEBAAAACjE5NzU3ODY2MjIDAAAAAzE2MAIAAAAGMTAwMDU0BAAAAAEwBwAAAAk5LzIwLzIwMTnnEMEnXUDXCDbf+SddQNcIKUNJUS5UU0U6Nzk3NC5JUV9DTE9TRVBSSUNFLjIwMTktMDYtMjUuVVNEAQAAAKRdDQACAAAACjM1Ni43MjU0MjgAp5nKJ11A1wi3o/4nXUDXCDVDSVEuTkFTREFRR1M6RUEuSVFfRUJJVERBX0VTVC5DWTIwMjAuMjAxOS0wOS0yMy4uLlVTRAEAAAA7bQAAAgAAAAkxODQ5LjkxNDcBDgAAAAUAAAACMTEBAAAAATACAAAACDI4NzExMjAzAwAAAAYxMDAxODcEAAAAATIGAAAAATAHAAAAAzE2MAgAAAABMAkAAAABMQoAAAABMAsAAAALMTE1NDQ1MTEzNTcMAAAAATcNAAAACTkvMjQvMjAxORAAAAAJOS8yMy8yMDE55xDBJ11A1whxaAMoXUDXCClDSVEuVFNFOjc5NzQuSVFfQ0xPU0VQUklDRS4yMDE1LTA4LTI1LlVTRAEAAACkXQ0AAgAAAAoxODYuMzI3NjM2AOcQwSddQNcIt6P+J11A1wgpQ0lRLlRTRTo3OTc0LklRX0NMT1NFUFJJQ0UuMjAxNy0wNC0yNS5VU0QBAAAApF0NAAIAAAAKMjUyLjAzOTQ5MgDnEMEnXUDXCHFoAyhdQNcILENJUS5UU0U6Nzk3NC5JUV9URVZfRUJJVERBLklRX0xUTS4yMDE3LTAyLTIxAQAAAKRdDQACAAAACTQw | EM1: Ljk1NDM1MgEHAAAABQAAAAExAQAAAAoxODI3NzY3Nzk3AwAAAAEwAgAAAAYxMDAwMzAEAAAAATAHAAAACTIvMjEvMjAxNwgAAAAJMi8yMS8yMDE35xDBJ11A1whrQfwnXUDXCCxDSVEuVFNFOjc5NzQuSVFfVEVWX0VCSVREQS5JUV9MVE0uMjAxNi0xMS0wOAEAAACkXQ0AAgAAAAk1Mi4xMzY4MzUBBwAAAAUAAAABMQEAAAAKMTgxNDU2NzEwOAMAAAABMAIAAAAGMTAwMDMwBAAAAAEwBwAAAAkxMS84LzIwMTYIAAAACTExLzgvMjAxNucQwSddQNcIYsoFKF1A1wgsQ0lRLlRTRTo3OTc0LklRX1RFVl9FQklUREEuSVFfTFRNLjIwMTktMDktMjQBAAAApF0NAAIAAAAJMTUuOTM4OTM4AQcAAAAFAAAAATEBAAAACjE5NzU3OTI0NzADAAAAATACAAAABjEwMDAzMAQAAAABMAcAAAAJOS8yMC8yMDE5CAAAAAk5LzIwLzIwMTmnmconXUDXCGtB/CddQNcILENJUS5UU0U6Nzk3NC5JUV9URVZfRUJJVERBLklRX0xUTS4yMDE2LTEwLTI1AQAAAKRdDQACAAAACTU3LjI3MTMyMQEHAAAABQAAAAExAQAAAAoxODAyNzc2Nzc1AwAAAAEwAgAAAAYxMDAwMzAEAAAAATAHAAAACjEwLzI1LzIwMTYIAAAACjEwLzI1LzIwMTbnEMEnXUDXCDbf+SddQNcIL0NJUS5OQVNEQVFHUzpBVFZJLklRX1RFVi40NDU2MS4yMDE5LTA5LTIzLi4uVVNEAQAAABdtQAACAAAADDM5ODQ5LjQ2NTQyOQEGAAAABQAAAAExAQAAAAoxOTc1MDM4Nzk5 | EN1: AwAAAAMxNjACAAAABjEwMDA2MAQAAAABMAcAAAAJOS8yMy8yMDE55xDBJ11A1wi3o/4nXUDXCDdDSVEuS09TRTpBMjUxMjcwLklRX1JFVkVOVUVfRVNULkNZMjAyMS4yMDE5LTA5LTIzLi4uVVNEAQAAAFnuLwkCAAAAEDIyOTUuNjM1MzA3NjQ2MzIBDgAAAAUAAAACMTEBAAAAATACAAAACjEwMDM3MzgyOTADAAAABjEwMDE4MAQAAAABMwYAAAABMAcAAAADMTYwCAAAAAEwCQAAAAExCgAAAAEwCwAAAAsxMTYxMDg0NjgyMAwAAAABNw0AAAAJOS8yNC8yMDE5EAAAAAk5LzIzLzIwMTnnEMEnXUDXCGLKBShdQNcIKkNJUS5UU0U6MzY1OS5JUV9URVYuNDMxMDAuMjAxOS0wOS0yMy4uLlVTRAEAAACeH4IIAgAAAAs5NTAxLjM3NzQ0MgEGAAAABQAAAAExAQAAAAoxODY1NzgyNDI1AwAAAAMxNjACAAAABjEwMDA2MAQAAAABMAcAAAAKMTIvMzEvMjAxN+cQwSddQNcIYsoFKF1A1wgsQ0lRLlRTRTo3OTc0LklRX1RFVl9FQklUREEuSVFfTFRNLjIwMTYtMTEtMTUBAAAApF0NAAIAAAAJNTIuNjc2NTI5AQcAAAAFAAAAATEBAAAACjE4MTgwNjgyMjEDAAAAATACAAAABjEwMDAzMAQAAAABMAcAAAAKMTEvMTUvMjAxNggAAAAKMTEvMTUvMjAxNucQwSddQNcIAwYBKF1A1wgsQ0lRLlRTRTo3OTc0LklRX1RFVl9FQklUREEuSVFfTFRNLjIwMTgtMDItMjABAAAApF0NAAIAAAAJMjUuODU0Nzc0AQcAAAAFAAAAATEBAAAA | EO1: CjE4NzQxOTMzNDADAAAAATACAAAABjEwMDAzMAQAAAABMAcAAAAJMi8yMC8yMDE4CAAAAAkyLzIwLzIwMTjnEMEnXUDXCGtB/CddQNcILENJUS5UU0U6Nzk3NC5JUV9URVZfRUJJVERBLklRX0xUTS4yMDE5LTA3LTAyAQAAAKRdDQACAAAACTEzLjkxMjc0NgEHAAAABQAAAAExAQAAAAoxOTcwMjIwNTE1AwAAAAEwAgAAAAYxMDAwMzAEAAAAATAHAAAACDcvMi8yMDE5CAAAAAg3LzIvMjAxOaeZyiddQNcINt/5J11A1wgsQ0lRLlRTRTo3OTc0LklRX1RFVl9FQklUREEuSVFfTFRNLjIwMTgtMDgtMjEBAAAApF0NAAIAAAAJMTcuNDI0MzY3AQcAAAAFAAAAATEBAAAACjE5MDAyNzI3OTYDAAAAATACAAAABjEwMDAzMAQAAAABMAcAAAAJOC8yMS8yMDE4CAAAAAk4LzIxLzIwMTjnEMEnXUDXCLej/iddQNcIKUNJUS5UU0U6Nzk3NC5JUV9DTE9TRVBSSUNFLjIwMTctMTAtMzEuVVNEAQAAAKRdDQACAAAACjM4NS4yMDczMzQA5xDBJ11A1whrQfwnXUDXCCxDSVEuVFNFOjc5NzQuSVFfVEVWX0VCSVREQS5JUV9MVE0uMjAxOS0wMS0xNQEAAACkXQ0AAgAAAAkxMy45NDU2MDIBBwAAAAUAAAABMQEAAAAKMTkyMTUxODQyMwMAAAABMAIAAAAGMTAwMDMwBAAAAAEwBwAAAAkxLzE1LzIwMTkIAAAACTEvMTUvMjAxOecQwSddQNcINt/5J11A1wglQ0lRLlRTRTo3OTc0LklRX1RFVi4uMjAxOS0wOS0yMy4uLlVTRAEAAACk | EP1: XQ0AAgAAAAwzODg3MS4zMjkxNDEBBgAAAAUAAAABMQEAAAAKMTk3NTc4NzA4NgMAAAADMTYwAgAAAAYxMDAwNjAEAAAAATAHAAAACTkvMjAvMjAxOecQwSddQNcINt/5J11A1wgpQ0lRLlRTRTo3OTc0LklRX0NMT1NFUFJJQ0UuMjAxOC0wNC0xMC5VU0QBAAAApF0NAAIAAAAKNDE5LjY1NTM0NgDnEMEnXUDXCAMGAShdQNcILkNJUS5OQVNEQVFHUzpFQS5JUV9DT01QQU5ZX05BTUUuMjAxOS0wOS0yMy5VU0QBAAAAO20AAAMAAAAURWxlY3Ryb25pYyBBcnRzIEluYy4A5xDBJ11A1wi3o/4nXUDXCCtDSVEuTkFTREFRR1M6RUEuSVFfTUFSS0VUQ0FQLjIwMTktMDktMjMuVVNEAQAAADttAAACAAAADDI4OTM0LjM4MTQ2NgEGAAAABQAAAAExAQAAAAoxOTc0MjM1MzQ5AwAAAAMxNjACAAAABjEwMDA1NAQAAAABMAcAAAAJOS8yMy8yMDE55xDBJ11A1wgDBgEoXUDXCClDSVEuVFNFOjc5NzQuSVFfQ0xPU0VQUklDRS4yMDE4LTA1LTI5LlVTRAEAAACkXQ0AAgAAAAkzODkuOTM4ODUA5xDBJ11A1wi3o/4nXUDXCClDSVEuVFNFOjc5NzQuSVFfQ0xPU0VQUklDRS4yMDE1LTExLTI0LlVTRAEAAACkXQ0AAgAAAAoxNTcuNzI5MzU1AOcQwSddQNcIAwYBKF1A1wgqQ0lRLlRTRTo5Njg0LklRX1RFVi40MjM2OS4yMDE5LTA5LTIzLi4uVVNEAQAAAKl9DQACAAAACzIyMzYuODc0MTAzAQYAAAAFAAAAATEBAAAACjE3NjUx | EQ1: NDczNTQDAAAAAzE2MAIAAAAGMTAwMDYwBAAAAAEwBwAAAAoxMi8zMS8yMDE15xDBJ11A1wg23/knXUDXCDZDSVEuTkFTREFRR1M6VFRXTy5JUV9UT1RBTF9SRVYuQ1kyMDE2LjIwMTktMDktMjMuLi5VU0QBAAAAUaoFAAIAAAAIMTU4NS4zOTgBCAAAAAUAAAABMQEAAAAKMTg3MzUzNDI4MgMAAAADMTYwAgAAAAIyOAQAAAABMAcAAAAJOS8yMy8yMDE5CAAAAAoxMi8zMS8yMDE2CQAAAAEw5xDBJ11A1wgDBgEoXUDXCCxDSVEuVFNFOjc5NzQuSVFfVEVWX0VCSVREQS5JUV9MVE0uMjAxOS0wNS0yOAEAAACkXQ0AAgAAAAkxMy40NTE5NjgBBwAAAAUAAAABMQEAAAAKMTk1Njc0ODA4NgMAAAABMAIAAAAGMTAwMDMwBAAAAAEwBwAAAAk1LzI4LzIwMTkIAAAACTUvMjgvMjAxOecQwSddQNcIt6P+J11A1wgyQ0lRLk5BU0RBUUdTOkFUVkkuSVFfQ1VTVE9NX0JFVEEuLjIwMTktMDktMjMuLi5VU0QBAAAAF21AAAIAAAARMC44Njc2NDQxNjU4MzA2MDIAp5nKJ11A1wg23/knXUDXCCxDSVEuVFNFOjc5NzQuSVFfVEVWX0VCSVREQS5JUV9MVE0uMjAxNy0wNy0wNAEAAACkXQ0AAgAAAAk1Ni4zNjc4NzgBBwAAAAUAAAABMQEAAAAKMTg0OTAzMzEzOAMAAAABMAIAAAAGMTAwMDMwBAAAAAEwBwAAAAg3LzQvMjAxNwgAAAAINy80LzIwMTfnEMEnXUDXCDbf+SddQNcILENJUS5UU0U6Nzk3NC5JUV9URVZfRUJJVERBLklR | ER1: X0xUTS4yMDE1LTExLTAzAQAAAKRdDQACAAAACTM0LjE2NTQ2MQEHAAAABQAAAAExAQAAAAoxNzYxNTE0MzM2AwAAAAEwAgAAAAYxMDAwMzAEAAAAATAHAAAACTExLzIvMjAxNQgAAAAJMTEvMi8yMDE15xDBJ11A1whrQfwnXUDXCC9DSVEuTkFTREFRR1M6VFRXTy5JUV9URVYuNDI3MzUuMjAxOS0wOS0yMy4uLlVTRAEAAABRqgUAAgAAAAkzNjAzLjU4NDQBBgAAAAUAAAABMQEAAAAKMTgxNjIyNjA0NAMAAAADMTYwAgAAAAYxMDAwNjAEAAAAATAHAAAACjEyLzMxLzIwMTbnEMEnXUDXCLej/iddQNcILENJUS5UU0U6Nzk3NC5JUV9URVZfRUJJVERBLklRX0xUTS4yMDE1LTA1LTE5AQAAAKRdDQACAAAACTUwLjE3Mzc1MQEHAAAABQAAAAExAQAAAAoxNzMyNjYwNjYyAwAAAAEwAgAAAAYxMDAwMzAEAAAAATAHAAAACTUvMTkvMjAxNQgAAAAJNS8xOS8yMDE15xDBJ11A1whrQfwnXUDXCDZDSVEuTkFTREFRR1M6QVRWSS5JUV9UT1RBTF9SRVYuQ1kyMDE3LjIwMTktMDktMjMuLi5VU0QBAAAAF21AAAIAAAAENzAxNwEIAAAABQAAAAExAQAAAAoxOTQ3ODI4NzYwAwAAAAMxNjACAAAAAjI4BAAAAAEwBwAAAAk5LzIzLzIwMTkIAAAACjEyLzMxLzIwMTcJAAAAATDnEMEnXUDXCHFoAyhdQNcIMUNJUS5UU0U6OTY4NC5JUV9UT1RBTF9SRVYuSVFfTFRNLjIwMTktMDktMjMuLi5VU0QBAAAAqX0NAAIAAAALMjU4Ny42 | ES1: MjM1NjIBCAAAAAUAAAABMQEAAAAKMTk3NTc5MjY0MwMAAAADMTYwAgAAAAIyOAQAAAABMAcAAAAJOS8yMy8yMDE5CAAAAAk2LzMwLzIwMTkJAAAAATDnEMEnXUDXCAMGAShdQNcIKUNJUS5UU0U6Nzk3NC5JUV9DTE9TRVBSSUNFLjIwMTctMTItMTIuVVNEAQAAAKRdDQACAAAACjM4Ni4yMDU2ODQA5xDBJ11A1wi3o/4nXUDXCClDSVEuVFNFOjc5NzQuSVFfQ0xPU0VQUklDRS4yMDE1LTEyLTA4LlVTRAEAAACkXQ0AAgAAAAoxNDkuMzMwODQ3AOcQwSddQNcIcWgDKF1A1wgpQ0lRLlRTRTo3OTc0LklRX0NMT1NFUFJJQ0UuMjAxNS0xMC0wNi5VU0QBAAAApF0NAAIAAAAKMTc4LjMyOTM5MwDnEMEnXUDXCGtB/CddQNcIKUNJUS5UU0U6Nzk3NC5JUV9DTE9TRVBSSUNFLjIwMTctMTAtMTAuVVNEAQAAAKRdDQACAAAACjM4Ni45NjE1NjYA5xDBJ11A1whxaAMoXUDXCCxDSVEuVFNFOjc5NzQuSVFfVEVWX0VCSVREQS5JUV9MVE0uMjAxNi0wOS0xMwEAAACkXQ0AAgAAAAk2MC4yNzAwODQBBwAAAAUAAAABMQEAAAAKMTgwMjc3Njc3NQMAAAABMAIAAAAGMTAwMDMwBAAAAAEwBwAAAAk5LzEzLzIwMTYIAAAACTkvMTMvMjAxNucQwSddQNcIcWgDKF1A1wgsQ0lRLlRTRTo3OTc0LklRX1RFVl9FQklUREEuSVFfTFRNLjIwMTgtMTAtMzABAAAApF0NAAIAAAAJMTUuNDU4MjAzAQcAAAAFAAAAATEBAAAACjE5MTY3NDY1 | ET1: NzgDAAAAATACAAAABjEwMDAzMAQAAAABMAcAAAAKMTAvMzAvMjAxOAgAAAAKMTAvMzAvMjAxOOcQwSddQNcIa0H8J11A1wgpQ0lRLlRTRTo3OTc0LklRX0NMT1NFUFJJQ0UuMjAxOS0wNC0zMC5VU0QBAAAApF0NAAMAAAAAAOcQwSddQNcIcWgDKF1A1wgxQ0lRLktPU0U6QTI1MTI3MC5JUV9DVVNUT01fQkVUQS4uMjAxOS0wOS0yMy4uLlVTRAEAAABZ7i8JAgAAABEwLjgzNDQ5MzcyOTA1NTcyNACnmconXUDXCGtB/CddQNcIL0NJUS5OQVNEQVFHUzpBVFZJLklRX1RFVi40NDkyNi4yMDE5LTA5LTIzLi4uVVNEAQAAABdtQAACAAAADDM5ODQ5LjQ2NTQyOQEGAAAABQAAAAExAQAAAAoxOTc1MDM4Nzk5AwAAAAMxNjACAAAABjEwMDA2MAQAAAABMAcAAAAJOS8yMy8yMDE55xDBJ11A1wi3o/4nXUDXCC1DSVEuTkFTREFRR1M6VFRXTy5JUV9NQVJLRVRDQVAuMjAxOS0wOS0yMy5VU0QBAAAAUaoFAAIAAAALMTM0NjYuODI3NTIBBgAAAAUAAAABMQEAAAAKMTk3NDMwMjQ4OAMAAAADMTYwAgAAAAYxMDAwNTQEAAAAATAHAAAACTkvMjMvMjAxOecQwSddQNcIcWgDKF1A1wgsQ0lRLlRTRTo3OTc0LklRX1RFVl9FQklUREEuSVFfTFRNLjIwMTgtMDEtMTYBAAAApF0NAAIAAAAJNDUuMjEzNDYxAQcAAAAFAAAAATEBAAAACjE4NjU3OTIzNjMDAAAAATACAAAABjEwMDAzMAQAAAABMAcAAAAJMS8xNi8yMDE4CAAAAAkx | EU1: LzE2LzIwMTjnEMEnXUDXCDbf+SddQNcIKUNJUS5UU0U6Nzk3NC5JUV9DTE9TRVBSSUNFLjIwMTgtMDktMDQuVVNEAQAAAKRdDQACAAAACjM1Ni42NzgxODEA5xDBJ11A1whrQfwnXUDXCC5DSVEuVFNFOjk2ODQuSVFfRUJJVERBLkNZMjAxNi4yMDE5LTA5LTIzLi4uVVNEAQAAAKl9DQACAAAACTI1NS4xMzcwMwEIAAAABQAAAAExAQAAAAoxODI3NTA4MjA3AwAAAAMxNjACAAAABDQwNTEEAAAAATAHAAAACTkvMjMvMjAxOQgAAAAKMTIvMzEvMjAxNgkAAAABMOcQwSddQNcINt/5J11A1wgpQ0lRLlRTRTo3OTc0LklRX0NMT1NFUFJJQ0UuMjAxNi0wNC0wNS5VU0QBAAAApF0NAAIAAAAKMTM1LjkxNTMwNADnEMEnXUDXCLej/iddQNcIQkNJUS5UU0U6Nzk3NC5JUV9DSEFOR0VfTkVUX1dPUktJTkdfQ0FQSVRBTC5DWTIwMTcuMjAxOS0wOS0yMy4uLlVTRAEAAACkXQ0AAgAAAAstMTEzLjA2NDMyMwEIAAAABQAAAAExAQAAAAoxODc0MTkzMzQwAwAAAAMxNjACAAAABDQ0MjEEAAAAATAHAAAACTkvMjMvMjAxOQgAAAAKMTIvMzEvMjAxNwkAAAABMKeZyiddQNcIYsoFKF1A1wgsQ0lRLlRTRTo3OTc0LklRX1RFVl9FQklUREEuSVFfTFRNLjIwMTUtMTItMjIBAAAApF0NAAIAAAAJMjQuNTExNDQzAQcAAAAFAAAAATEBAAAACjE3NjUxNTM2NzEDAAAAATACAAAABjEwMDAzMAQAAAABMAcAAAAKMTIvMjIvMjAxNQgA | EV1: AAAKMTIvMjIvMjAxNecQwSddQNcINt/5J11A1wg3Q0lRLlRTRTo3OTc0LklRX0NBU0hfQUNRVUlSRV9DRi5DWTIwMTYuMjAxOS0wOS0yMy4uLlVTRAEAAACkXQ0AAwAAAAAAp5nKJ11A1whiygUoXUDXCClDSVEuVFNFOjc5NzQuSVFfQ0xPU0VQUklDRS4yMDE3LTEyLTI2LlVTRAEAAACkXQ0AAgAAAAozNjguMTQ5MTAzAOcQwSddQNcIa0H8J11A1wgsQ0lRLlRTRTo3OTc0LklRX1RFVl9FQklUREEuSVFfTFRNLjIwMTctMDEtMTABAAAApF0NAAIAAAAJNTEuMjExMTQ2AQcAAAAFAAAAATEBAAAACjE4MTgwNjgyMjEDAAAAATACAAAABjEwMDAzMAQAAAABMAcAAAAJMS8xMC8yMDE3CAAAAAkxLzEwLzIwMTfnEMEnXUDXCAMGAShdQNcINkNJUS5OQVNEQVFHUzpUVFdPLklRX1RPVEFMX1JFVi5JUV9MVE0uMjAxOS0wOS0yMy4uLlVTRAEAAABRqgUAAgAAAAgyODIwLjg3MQEIAAAABQAAAAExAQAAAAoxOTc0MzA0MDY2AwAAAAMxNjACAAAAAjI4BAAAAAEwBwAAAAk5LzIzLzIwMTkIAAAACTYvMzAvMjAxOQkAAAABMOcQwSddQNcIYsoFKF1A1wgpQ0lRLlRTRTo3OTc0LklRX0NMT1NFUFJJQ0UuMjAxOS0wMS0wMS5VU0QBAAAApF0NAAMAAAAAAOcQwSddQNcIcWgDKF1A1wgsQ0lRLlRTRTo3OTc0LklRX1RFVl9FQklUREEuSVFfTFRNLjIwMTYtMDgtMDkBAAAApF0NAAIAAAAJNTEuNDE3MzU0AQcAAAAFAAAAATEB | EW1: AAAACjE4MDI3NzY3NzUDAAAAATACAAAABjEwMDAzMAQAAAABMAcAAAAIOC85LzIwMTYIAAAACDgvOS8yMDE25xDBJ11A1whrQfwnXUDXCClDSVEuVFNFOjc5NzQuSVFfQ0xPU0VQUklDRS4yMDE1LTA5LTIyLlVTRAEAAACkXQ0AAwAAAAAA5xDBJ11A1whxaAMoXUDXCCxDSVEuVFNFOjc5NzQuSVFfVEVWX0VCSVREQS5JUV9MVE0uMjAxOS0wNi0xMQEAAACkXQ0AAgAAAAkxMy41NjgzMTMBBwAAAAUAAAABMQEAAAAKMTk1Njc0ODA4NgMAAAABMAIAAAAGMTAwMDMwBAAAAAEwBwAAAAk2LzExLzIwMTkIAAAACTYvMTEvMjAxOaeZyiddQNcIa0H8J11A1wgqQ0lRLk5BU0RBUUdTOlRUV08uSVFfVEVWLi4yMDE5LTA5LTIzLi4uVVNEAQAAAFGqBQACAAAACzEyMDcxLjQ3MTUyAQYAAAAFAAAAATEBAAAACjE5NzQzMDI0ODgDAAAAAzE2MAIAAAAGMTAwMDYwBAAAAAEwBwAAAAk5LzIzLzIwMTnnEMEnXUDXCHFoAyhdQNcIM0NJUS5UU0U6OTY4NC5JUV9SRVZFTlVFX0VTVC5DWTIwMTkuMjAxOS0wOS0yMy4uLlVTRAEAAACpfQ0AAgAAABAyNTEwLjQzNzkwNjcxODczAQ4AAAAFAAAAAjExAQAAAAEwAgAAAAg0NjgyNzMzNQMAAAAGMTAwMTgwBAAAAAI1NgYAAAABMAcAAAADMTYwCAAAAAEwCQAAAAExCgAAAAEwCwAAAAsxMTYwODgwODI5NQwAAAABNw0AAAAJOS8yNC8yMDE5EAAAAAk5LzIzLzIwMTnnEMEnXUDXCHFo | EX1: AyhdQNcIMUNJUS5UU0U6MzY1OS5JUV9UT1RBTF9SRVYuQ1kyMDE4LjIwMTktMDktMjMuLi5VU0QBAAAAnh+CCAIAAAALMjMxMi41NDYxNDQBCAAAAAUAAAABMQEAAAAKMTk1MTg2NzkyOQMAAAADMTYwAgAAAAIyOAQAAAABMAcAAAAJOS8yMy8yMDE5CAAAAAoxMi8zMS8yMDE4CQAAAAEw5xDBJ11A1whrQfwnXUDXCC5DSVEuS09TRTpBMjUxMjcwLklRX0dQLkNZMjAxOC4yMDE5LTA5LTIzLi4uVVNEAQAAAFnuLwkCAAAACzE4MTUuNDM1NjE1AQgAAAAFAAAAATEBAAAACjE5NTA5MzY1MzgDAAAAAzE2MAIAAAACMTAEAAAAATAHAAAACTkvMjMvMjAxOQgAAAAKMTIvMzEvMjAxOAkAAAABMOcQwSddQNcIAwYBKF1A1wgwQ0lRLkVOWFRQQTpVQkkuSVFfRUJJVERBLkNZMjAxOC4yMDE5LTA5LTIzLi4uVVNEAQAAABl2DQACAAAACjU4My4wNDQ5OTcBCAAAAAUAAAABMQEAAAAKMTk2ODQ2MjkwMAMAAAADMTYwAgAAAAQ0MDUxBAAAAAEwBwAAAAk5LzIzLzIwMTkIAAAACjEyLzMxLzIwMTgJAAAAATDnEMEnXUDXCDbf+SddQNcIKUNJUS5UU0U6Nzk3NC5JUV9DTE9TRVBSSUNFLjIwMTYtMTEtMDguVVNEAQAAAKRdDQACAAAACjIzMi42MTU3MzgA5xDBJ11A1whxaAMoXUDXCClDSVEuVFNFOjc5NzQuSVFfQ0xPU0VQUklDRS4yMDE5LTA2LTA0LlVTRAEAAACkXQ0AAgAAAAkzNDcuNDg0OTkAp5nKJ11A1wgDBgEoXUDX | EY1: CCxDSVEuVFNFOjc5NzQuSVFfVEVWX0VCSVREQS5JUV9MVE0uMjAxNy0wNi0xMwEAAACkXQ0AAgAAAAk1NC40NDE3NzIBBwAAAAUAAAABMQEAAAAKMTgzODIwNDA3NAMAAAABMAIAAAAGMTAwMDMwBAAAAAEwBwAAAAk2LzEzLzIwMTcIAAAACTYvMTMvMjAxN+cQwSddQNcIa0H8J11A1wgpQ0lRLlRTRTo3OTc0LklRX0NMT1NFUFJJQ0UuMjAxOC0xMC0wOS5VU0QBAAAApF0NAAIAAAAKMzU0Ljk1NDI0NwDnEMEnXUDXCHFoAyhdQNcILENJUS5UU0U6Nzk3NC5JUV9URVZfRUJJVERBLklRX0xUTS4yMDE3LTA5LTI2AQAAAKRdDQACAAAACTQ3LjMzOTc5MwEHAAAABQAAAAExAQAAAAoxODU0MDQzODg4AwAAAAEwAgAAAAYxMDAwMzAEAAAAATAHAAAACTkvMjYvMjAxNwgAAAAJOS8yNi8yMDE35xDBJ11A1wg23/knXUDXCCxDSVEuVFNFOjc5NzQuSVFfVEVWX0VCSVREQS5JUV9MVE0uMjAxNi0wNi0xNAEAAACkXQ0AAgAAAAkyMC45NDcyNzQBBwAAAAUAAAABMQEAAAAKMTc4NzkyNTg3NgMAAAABMAIAAAAGMTAwMDMwBAAAAAEwBwAAAAk2LzE0LzIwMTYIAAAACTYvMTQvMjAxNucQwSddQNcIa0H8J11A1wguQ0lRLk5BU0RBUUdTOkFUVkkuSVFfQ0xPU0VQUklDRS4yMDE5LTA5LTIzLlVTRAEAAAAXbUAAAgAAAAU1NC4xOADnEMEnXUDXCGLKBShdQNcINkNJUS5OQVNEQVFHUzpFQS5JUV9SRVZFTlVFX0VTVC5DWTIw | EZ1: MjIuMjAxOS0wOS0yMy4uLlVTRAEAAAA7bQAAAgAAAAk2MDMwLjE5MDgBDgAAAAUAAAACMTEBAAAAATACAAAACTI2OTA3NjIzMgMAAAAGMTAwMTgwBAAAAAEyBgAAAAEwBwAAAAMxNjAIAAAAATAJAAAAATEKAAAAATALAAAACzExNTk5MjYxMTg1DAAAAAE3DQAAAAk5LzI0LzIwMTkQAAAACTkvMjMvMjAxOecQwSddQNcIt6P+J11A1wghQ0lRLklRVFIyMzMzNzg0MzkuSVFfQ09NUEFOWV9OQU1FAQAAABo9PAEDAAAAIUd1bmdIbyBPbmxpbmUgRW50ZXJ0YWlubWVudCwgSW5jLgDnEMEnXUDXCGtB/CddQNcIKUNJUS5UU0U6Nzk3NC5JUV9DTE9TRVBSSUNFLjIwMTUtMTEtMTcuVVNEAQAAAKRdDQACAAAACjE1NS45MjA5MzgA5xDBJ11A1wi3o/4nXUDXCDZDSVEuTkFTREFRR1M6QVRWSS5JUV9UT1RBTF9SRVYuSVFfTFRNLjIwMTktMDktMjMuLi5VU0QBAAAAF21AAAIAAAAENzExMwEIAAAABQAAAAExAQAAAAoxOTc1MDM5MDUyAwAAAAMxNjACAAAAAjI4BAAAAAEwBwAAAAk5LzIzLzIwMTkIAAAACTYvMzAvMjAxOQkAAAABMOcQwSddQNcINt/5J11A1wgsQ0lRLlRTRTo3OTc0LklRX1RFVl9FQklUREEuSVFfTFRNLjIwMTgtMDUtMDgBAAAApF0NAAIAAAAJMjMuODIwOTM2AQcAAAAFAAAAATEBAAAACjE4ODQ4NjQ5NjQDAAAAATACAAAABjEwMDAzMAQAAAABMAcAAAAINS84LzIwMTgIAAAACDUvOC8yMDE45xDB | FA1: J11A1wg23/knXUDXCA==

Sheet Title
B2: Investment Presentation
B9: SEMPRA INFRASTRUCTURE
B10: Investment Presentation Exhibits
B11: =TODAY() -> 46134
B43: Cells with black text are formulas

Sheet Instructions
B2: Instructions
B3: ="Investment Presentation | "&TEXT(TODAY(),"mmmm d, yyyy") -> Investment Presentation | April 22, 2026
B7: 1. Fill out the Excel file
B9: The title and instructions sheets can remained untouched.
B10: The other sheets must be changed completely - all values are placeholders and all formulas must be tailored to the specific investment being presented. The Excel file is meant for formatting use only.
B11: Once the data in the other sheets has been added, review the excel workbook for any errors or misrepresentations.
B13: 2. Fill out the PowerPoint file
B15: Replace logos, images, and excel workbook exhibits with updated and corrected information from the Excel file.
B16: Replace text and commentary with that specific to the investment being presented.
B17: Once completed, review all written and calculated text to ensure completeness and correctness.
B19: 3. Review
B21: All work done should be reviewed, whether it be manual entry, formulas, or written text.

Sheet Precedents
B2: Target Name | C2: Acquirer Name | D2: Date | E2: Size ($B) | F2: EV / EBITDA
B4: Dominion Gas Utilities | C4: Enbridge | D4: 45055 | E4: 14 | F4: =E4/0.85 -> 16.470588 | I4: Source: S&P Global. (n.d.). Capital IQ Pro. https://www.capitaliq.spglobal.com/web/client?auth=inherit#ratingsdirect/home
B5: SCANA | C5: Dominion Energy | D5: 43110 | E5: 14.6 | F5: =14.6/1.15 -> 12.695652
B6: Spectra Energy | C6: Enbridge | D6: 42619 | E6: 28 | F6: =E6/2.2 -> 12.727273
B7: Integrys Enegy Group | C7: Wisconsin Energy | D7: 41813 | E7: 9.1 | F7: =E7/0.88 -> 10.340909
B10: Precedents Average | F10: =AVERAGE(F4:F7) -> 13.058606
B12: Sempra Energy | E12: ='DCF '!R31 -> 70401898 | F12: ='Peer Comps'!AB8 -> 14.242202

Sheet Valuation
C3: Valuation Method | D3: Multiples | G3: Implied Equity Value | J3: Share Price
D4: Min | E4: Median | F4: Max | G4: Min | H4: Median | I4: Max | J4: Min | K4: Median | L4: Max | M4: First | N4: Second | O4: Third
C5: Public Comps (EV / EBITDA) | D5: ='Peer Comps'!G15 -> 7.106218 | E5: ='Peer Comps'!E12 -> 11.24 | F5: ='Peer Comps'!E14 -> 12.61 | G5: =D5*'DCF '!C11/1000 -> 35991.857 | H5: =E5*'DCF '!C11/1000 -> 56928.802 | I5: =F5*'DCF '!C11/1000 -> 63867.632 | J5: =G5/'DCF '!R38*1000 -> 55.144594 | K5: =H5/'DCF '!R38*1000 -> 87.222941 | L5: =I5/'DCF '!R38*1000 -> 97.854207 | M5: 55.1 | N5: 42.7 | O5: 97.9
C6: Public Comps (P / E) | D6: ='Peer Comps'!M15 -> 10.092263 | E6: ='Peer Comps'!M12 -> 14.5 | F6: ='Peer Comps'!M14 -> 18.422622 | G6: =D6*Exhibits!AN31/1000 -> 23211.397 | H6: =E6*Exhibits!AN31/1000 -> 33348.84 | I6: =F6*Exhibits!AN31/1000 -> 42370.558 | J6: =G6/'DCF '!R38*1000 -> 35.563128 | K6: =H6/'DCF '!R38*1000 -> 51.095119 | L6: =I6/'DCF '!R38*1000 -> 64.917661
C7: Precedents (EV/EBITDA) | D7: 10.3 | E7: 12.7 | F7: 16.5 | G7: 56627.6 | H7: 69830 | I7: 90733.8 | J7: 86.76 | K7: 107 | L7: 139.02 | M7: 86.8 | N7: 52.3 | O7: 64.9
C8: Public Comps EV/ REV | D8: 3.7x | E8: 4.3x | F8: 6.2x | G8: =3.7*Exhibits!AM6/1000 -> 43922.7 | H8: =4.3*Exhibits!AM6/1000 -> 51045.3 | I8: =6.2*Exhibits!AM6/1000 -> 73600.2 | J8: =(G8*1000)/'DCF '!R38 -> 67.295762 | K8: =(H8*1000)/'DCF '!R38 -> 78.208588 | L8: =(I8*1000)/'DCF '!R38 -> 112.76587 | M8: 67.3 | N8: 45.5 | O8: 68.4
C9: DCF | G9: 26629.4 | H9: 62331.1 | I9: 98359.1 | J9: 40.8 | K9: 95.5 | L9: 150.7 | M9: 40.8 | N9: 109.9 | O9: 68.4
C10: Average | D10: =AVERAGE(D5:D7) -> 9.1661602 | E10: =AVERAGE(E5:E7) -> 12.813333 | F10: =AVERAGE(F5:F7) -> 15.844207 | G10: =AVERAGE(G5:G9) -> 37276.591 | H10: =AVERAGE(H5:H9) -> 54696.808 | I10: =AVERAGE(I5:I9) -> 73786.258 | J10: =AVERAGE(J5:J9) -> 57.112697 | K10: =AVERAGE(K5:K9) -> 83.805329 | L10: =AVERAGE(L5:L9) -> 113.05155

Sheet Peer Comps
B2: Company Name | C2: Market Cap ($M) | D2: Enterprise Value ($M) | E2: EV / EBITDA | I2: EV / EBIT | K2: P / BV | M2: P/E | O2: EV/REV LTM | P2: Dividend Yield % | Q2: Net Debt / EBITDA | W2: Company Name | X2: Market Cap ($M) | Y2: Enterprise Value ($M) | Z2: EV / EBITDA | AD2: EV / EBIT | AF2: P / BV | AH2: P/E | AJ2: EV/REV LTM | AK2: Dividend Yield % | AL2: Net Debt / EBITDA
E3: 2026E | F3: 2027E | G3: LTM | H3: 2026E | I3: 2027E | J3: LTM | K3: LTM | L3: 2026E | M3: 2027E | N3: LTM | Z3: 2026E | AA3: 2027E | AB3: LTM | AC3: 2026E | AD3: 2027E | AE3: LTM | AF3: LTM | AG3: 2026E | AH3: 2027E | AI3: LTM
B4: Xcel Energy Inc. | C4: 51806.73 | D4: 87614.7 | E4: 12.61 | F4: 10.92 | G4: 14.06 | H4: 25.22 | I4: 20.95 | J4: 30.05 | K4: 2.19 | L4: 20.2 | M4: 18.3 | N4: 24.28 | O4: =D4/14612 -> 5.9960786 | P4: 0.0285 | Q4: 5.76 | W4: Dominion Energy Inc. | X4: 54985.62 | Y4: 109737.6 | Z4: 12.95 | AA4: 11.91 | AB4: 13.4 | AC4: 19.73 | AD4: 17.93 | AE4: 20.33 | AF4: 1.96 | AG4: 17.4 | AH4: 16.3 | AI4: 18.12 | AJ4: =Y4/16506 -> 6.6483461 | AK4: 0.0427 | AL4: 6.06
B5: Eversource Energy | C5: 28282.4 | D5: 58546.6 | E5: 11.24 | F5: 10.52 | G5: 12.33 | H5: 17.11 | I5: 15.94 | J5: 18.6 | K5: 1.75 | L5: 15.4 | M5: 14.5 | N5: 16.52 | O5: =D5/13547 -> 4.3217391 | P5: 0.0418 | Q5: 6.37 | W5: NextEra Energy Inc. | X5: 192934.13 | Y5: 299213.1 | Z5: 15.83 | AA5: 14.58 | AB5: 21.44 | AC5: 26.46 | AD5: 23.51 | AE5: 36.93 | AF5: 3.53 | AG5: 23 | AH5: 21.1 | AI5: 28.06 | AJ5: =Y5/27412 -> 10.915406 | AK5: 0.0269 | AL5: 6.678
B6: Edison International | C6: 28432.2 | D6: 72000.2 | E6: 9.1055724 | F6: 8.5000176 | G6: 7.106218 | H6: 15.398131 | I6: 14.514128 | J6: 13.155527 | K6: 1.6644516 | L6: 12.133941 | M6: 11.351904 | N6: 6.396295 | O6: =D6/19317 -> 3.7272972 | P6: 0.0475 | Q6: 4.085 | W6: Entergy Corporation | X6: 48238.89 | Y6: 77949.3 | Z6: 12.07 | AA6: 10.61 | AB6: 13.78 | AC6: 20.43 | AD6: 17.48 | AE6: 23.84 | AF6: 2.85 | AG6: 24.2 | AH6: 21.6 | AI6: 27.24 | AJ6: 5.96 | AK6: 0.024 | AL6: 5.2 | AP6: Mean
B7: Duke Energy Corporation | C7: 102559.23 | D7: 195598.2 | E7: 11.575094 | F7: 10.663428 | G7: 11.73897 | H7: 20.313712 | I7: 18.952641 | J7: 22.667041 | K7: 2.0170072 | L7: 19.676181 | M7: 18.422622 | N7: 20.886918 | O7: =D7/31790 -> 6.1528216 | P7: 0.0323 | Q7: 5.471 | AP7: Maximum
B8: PG&E Corporation | C8: 39959.057 | D8: 102412.1 | E8: 9.1383586 | F8: 8.2992689 | G8: 10.198373 | H8: 15.565217 | I8: 13.836148 | J8: 19.160348 | K8: 1.2906432 | L8: 11.048784 | M8: 10.092263 | N8: 15.40678 | O8: 4.11 | P8: 0.011 | Q8: 6.037 | W8: Sempra | X8: 62316.774 | Y8: 108987.77 | Z8: 17.285686 | AA8: 16.68465 | AB8: 14.242202 | AC8: 31.15 | AD8: 30.4 | AE8: 23.72 | AF8: 1.97 | AG8: 18.7 | AH8: 17.3 | AI8: 34.69 | AJ8: 7.73 | AK8: 0.0276 | AL8: 6.08 | AP8: Minimum
B10: Sempra | C10: 62316.774 | D10: 108987.77 | E10: 17.285686 | F10: 16.68465 | G10: 14.242202 | H10: 31.15 | I10: 30.4 | J10: 23.72 | K10: 1.97 | L10: 18.7 | M10: 17.3 | N10: 34.69 | O10: 7.73 | P10: 0.0276 | Q10: 6.08 | W10: Median | X10: =MEDIAN(X4:X6) -> 54985.62 | Y10: =MEDIAN(Y4:Y6) -> 109737.6 | Z10: =MEDIAN(Z4:Z6) -> 12.95 | AA10: =MEDIAN(AA4:AA6) -> 11.91 | AB10: =MEDIAN(AB4:AB6) -> 13.78 | AC10: =MEDIAN(AC4:AC6) -> 20.43 | AD10: =MEDIAN(AD4:AD6) -> 17.93 | AE10: =MEDIAN(AE4:AE6) -> 23.84 | ... AL10: =MEDIAN(AL4:AL6) -> 6.06
W11: Mean | X11: =AVERAGE(X4:X6) -> 98719.547 | Y11: =AVERAGE(Y4:Y6) -> 162300 | Z11: =AVERAGE(Z4:Z6) -> 13.616667 | AA11: =AVERAGE(AA4:AA6) -> 12.366667 | AB11: =AVERAGE(AB4:AB6) -> 16.206667 | AC11: =AVERAGE(AC4:AC6) -> 22.206667 | AD11: =AVERAGE(AD4:AD6) -> 19.64 | AE11: =AVERAGE(AE4:AE6) -> 27.033333 | ... AL11: =AVERAGE(AL4:AL6) -> 5.9793333
B12: Median | C12: =MEDIAN(C4:C8) -> 39959.057 | D12: =MEDIAN(D4:D8) -> 87614.7 | E12: =MEDIAN(E4:E8) -> 11.24 | F12: =MEDIAN(F4:F8) -> 10.52 | G12: =MEDIAN(G4:G8) -> 11.73897 | H12: =MEDIAN(H4:H8) -> 17.11 | I12: =MEDIAN(I4:I8) -> 15.94 | J12: =MEDIAN(J4:J8) -> 19.160348 | ... Q12: =MEDIAN(Q4:Q8) -> 5.76 | W12: Maximum | X12: =MAX(X4:X6) -> 192934.13 | Y12: =MAX(Y4:Y6) -> 299213.1 | Z12: =MAX(Z4:Z6) -> 15.83 | AA12: =MAX(AA4:AA6) -> 14.58 | AB12: =MAX(AB4:AB6) -> 21.44 | AC12: =MAX(AC4:AC6) -> 26.46 | AD12: =MAX(AD4:AD6) -> 23.51 | AE12: =MAX(AE4:AE6) -> 36.93 | ... AL12: =MAX(AL4:AL6) -> 6.678
B13: Mean | C13: =AVERAGE(C4:C8) -> 50207.923 | D13: =AVERAGE(D4:D8) -> 103234.36 | E13: =AVERAGE(E4:E8) -> 10.733805 | F13: =AVERAGE(F4:F8) -> 9.7805429 | G13: =AVERAGE(G4:G8) -> 11.086712 | H13: =AVERAGE(H4:H8) -> 18.721412 | I13: =AVERAGE(I4:I8) -> 16.838583 | J13: =AVERAGE(J4:J8) -> 20.726583 | ... Q13: =AVERAGE(Q4:Q8) -> 5.5446 | W13: Minimum | X13: =MIN(X4:X6) -> 48238.89 | Y13: =MIN(Y4:Y6) -> 77949.3 | Z13: =MIN(Z4:Z6) -> 12.07 | AA13: =MIN(AA4:AA6) -> 10.61 | AB13: =MIN(AB4:AB6) -> 13.4 | AC13: =MIN(AC4:AC6) -> 19.73 | AD13: =MIN(AD4:AD6) -> 17.48 | AE13: =MIN(AE4:AE6) -> 20.33 | ... AL13: =MIN(AL4:AL6) -> 5.2
B14: Maximum | C14: =MAX(C4:C8) -> 102559.23 | D14: =MAX(D4:D8) -> 195598.2 | E14: =MAX(E4:E8) -> 12.61 | F14: =MAX(F4:F8) -> 10.92 | G14: =MAX(G4:G8) -> 14.06 | H14: =MAX(H4:H8) -> 25.22 | I14: =MAX(I4:I8) -> 20.95 | J14: =MAX(J4:J8) -> 30.05 | ... O14: =MAX(O4:O8) -> 6.1528216 | P14: =MAX(P4:P9) -> 0.0475 | Q14: =MAX(Q4:Q8) -> 6.37
B15: Minimum | C15: =MIN(C4:C8) -> 28282.4 | D15: =MIN(D4:D8) -> 58546.6 | E15: =MIN(E4:E8) -> 9.1055724 | F15: =MIN(F4:F8) -> 8.2992689 | G15: =MIN(G4:G8) -> 7.106218 | H15: =MIN(H4:H8) -> 15.398131 | I15: =MIN(I4:I8) -> 13.836148 | J15: =MIN(J4:J8) -> 13.155527 | ... Q15: =MIN(Q4:Q8) -> 4.085
B27: Valuation Method | C27: 2026E Metric | D27: Multiple | E27: Implied Value $B
B28: P/E (Trailing - Net Income) | C28: =Exhibits!AM31/1000 -> 2072 | D28: =N13 -> 16.697999 | E28: =C28*D28/1000 -> 34.598253
B29: EV/EBITDA (Trailling - EBITDA) | C29: =Exhibits!AM12/1000 -> 4688.8568 | D29: =G13 -> 11.086712 | E29: =C29*11.3/1000 -> 52.984082
B30: EV/Revenue (Trailling - Revenue) | C30: =Exhibits!AM6/1000 -> 11871 | D30: =O13 -> 4.8615873 | E30: =C30*D30/1000 -> 57.711903
B31: Forward P/E (2026E - Net Income ) | C31: =Exhibits!AN31/1000 -> 2299.92 | D31: =L13 -> 15.691781 | E31: =C31*D31/1000 -> 36.089842
B32: Forward EV/EBITDA (2026E - EBITDA ) | C32: =Exhibits!C15/1000 -> 5064.84 | D32: =E13 -> 10.733805 | E32: =C32*11.1/1000 -> 56.219724
D33: Valuation Range | E33: $53-57.7B

Sheet DCF 
B2: Operating Forecast | C2: 2026 | D2: 2027E | E2: 2028E | F2: 2029E | G2: 2030E | H2: 2031E | I2: 2032E | J2: 2033E | K2: 2034E | L2: 2035E | O2: WACC Build-Up
O3: Cost of Debt | R3: 0.0555
B4: Revenue | C4: ='Forecasting '!B4*(1+$C$65) -> 13076910 | D4: =C4*(1+$C$65) -> 14515370 | E4: =D4*(1+$C$65) -> 16112061 | F4: =E4*(1+$C$65) -> 17884388 | G4: =F4*(1+$C$65) -> 19851670 | H4: =Exhibits!H7 -> 21638320 | I4: =Exhibits!I7 -> 23369386 | J4: =Exhibits!J7 -> 25005243 | K4: =Exhibits!K7 -> 26505558 | L4: =Exhibits!L7 -> 27830836 | O4: Tax Rate | R4: 0.2661
B5: Growth | C5: =(C4-Exhibits!AM6)/Exhibits!AM6 -> 0.10158453 | D5: =(D4-C4)/C4 -> 0.11 | E5: =(E4-D4)/D4 -> 0.11 | F5: =(F4-E4)/E4 -> 0.11 | G5: =(G4-F4)/F4 -> 0.11 | H5: =(H4-G4)/G4 -> 0.09 | I5: =(I4-H4)/H4 -> 0.08 | J5: =(J4-I4)/I4 -> 0.07 | K5: =(K4-J4)/J4 -> 0.06 | L5: =(L4-K4)/K4 -> 0.05 | O5: Tax-Shielded Cost of Debt | R5: =R3*(1-R4) -> 0.04073145
U6: Source: S&P Global. (n.d.). Capital IQ Pro. https://www.capitaliq.spglobal.com/web/client?auth=inherit#ratingsdirect/home
B7: COGS | C7: =Exhibits!C10 -> 7909370 | D7: =Exhibits!D10 -> 8146651.1 | E7: =Exhibits!E10 -> 8350317.4 | F7: =Exhibits!F10 -> 8559075.3 | G7: =Exhibits!G10 -> 8773052.2 | H7: =Exhibits!H10 -> 8992378.5 | I7: =Exhibits!I10 -> 9217188 | J7: =Exhibits!J10 -> 9447617.7 | ... L7: =Exhibits!L10 -> 9925903.3 | O7: Risk Free Rate | R7: 0.04111
B8: Gross Profit | C8: =C4-C7 -> 5167540 | D8: =D4-D7 -> 6368719 | E8: =E4-E7 -> 7761743.4 | F8: =F4-F7 -> 9325312.2 | G8: =G4-G7 -> 11078618 | H8: =H4-H7 -> 12645942 | I8: =I4-I7 -> 14152198 | J8: =J4-J7 -> 15557625 | ... L8: =L4-L7 -> 17904932 | O8: Historical Market Return | R8: 0.0838
O9: Market Risk Premium | R9: =R8-R7 -> 0.04269
B10: Operating Expenses | C10: =Exhibits!C14 -> 102700 | D10: =Exhibits!D14 -> 105472.9 | E10: =Exhibits!E14 -> 108320.67 | F10: =Exhibits!F14 -> 111245.33 | G10: =Exhibits!G14 -> 114248.95 | H10: =Exhibits!H14 -> 117333.67 | I10: =Exhibits!I14 -> 120501.68 | J10: =Exhibits!J14 -> 123755.23 | ... L10: =Exhibits!L14 -> 130528.23
B11: EBITDA | C11: =C8-C10 -> 5064840 | D11: =D8-D10 -> 6263246.1 | E11: =E8-E10 -> 7653422.8 | F11: =F8-F10 -> 9214066.9 | G11: =G8-G10 -> 10964369 | H11: =H8-H10 -> 12528608 | I11: =I8-I10 -> 14031696 | J11: =J8-J10 -> 15433870 | ... L11: =L8-L10 -> 17774404 | O11: beta | R11: 0.42
B12: Margin | C12: =C11/C4 -> 0.38731168 | D12: =D11/D4 -> 0.43149062 | E12: =E11/E4 -> 0.47501203 | F12: =F11/F4 -> 0.5152017 | G12: =G11/G4 -> 0.55231469 | H12: =H11/H4 -> 0.57900096 | I12: =I11/I4 -> 0.60043068 | J12: =J11/J4 -> 0.61722536 | ... L12: =L11/L4 -> 0.63865866 | O12: Cost of Equity | R12: =R7+R11*(R8-R7) -> 0.0590398
B14: D&A | C14: =Exhibits!C19 -> 2617440 | D14: =Exhibits!D19 -> 2931532.8 | E14: =Exhibits!E19 -> 3283316.7 | F14: =Exhibits!F19 -> 3677314.7 | G14: =Exhibits!G19 -> 4118592.5 | H14: =Exhibits!H19 -> 4612823.6 | I14: =Exhibits!I19 -> 5166362.4 | J14: =Exhibits!J19 -> 5786325.9 | ... L14: =Exhibits!L19 -> 7258367.3 | O14: Debt / EV | R14: 0.358
B15: EBIT | C15: =C11-C14 -> 2447400 | D15: =D11-D14 -> 3331713.3 | E15: =E11-E14 -> 4370106 | F15: =F11-F14 -> 5536752.1 | G15: =G11-G14 -> 6845776.5 | H15: =H11-H14 -> 7915784.7 | I15: =I11-I14 -> 8865334 | J15: =J11-J14 -> 9647544.3 | ... L15: =L11-L14 -> 10516037 | O15: Equity / EV | R15: =1-R14 -> 0.642
O16: WACC | R16: =(R14*R5)+(R15*R12) -> 0.052485411
B17: Tax | C17: =C15*Exhibits!C21 -> 482364.58 | D17: =D15*Exhibits!D21 -> 682209.46 | E17: =E15*Exhibits!E21 -> 928350.57 | F17: =F15*Exhibits!F21 -> 1218648.8 | G17: =G15*Exhibits!G21 -> 1559272.3 | H17: =H15*Exhibits!H21 -> 1863701.2 | I17: =I15*Exhibits!I21 -> 2155258.6 | J17: =J15*Exhibits!J21 -> 2419416.1 | ... L17: =L15*Exhibits!L21 -> 2798526.6
B18: NOPAT | C18: =C15-C17 -> 1965035.4 | D18: =D15-D17 -> 2649503.8 | E18: =E15-E17 -> 3441755.5 | F18: =F15-F17 -> 4318103.3 | G18: =G15-G17 -> 5286504.2 | H18: =H15-H17 -> 6052083.4 | I18: =I15-I17 -> 6710075.4 | J18: =J15-J17 -> 7228128.2 | ... L18: =L15-L17 -> 7717510.2 | O18: Valuation
O19: WACC | R19: =R16 -> 0.052485411 | AP19: Year | AQ19: PV of FCFF ($m)
B20: Capex | C20: =12700000 -> 12700000 | D20: 12075000 | E20: 12075000 | F20: 12075000 | G20: 12075000 | H20: =G20-'Forecasting '!$G$9 -> 11860000 | I20: =H20-'Forecasting '!$G$9 -> 11645000 | J20: =I20-'Forecasting '!$G$9 -> 11430000 | K20: =J20-'Forecasting '!$G$9 -> 11215000 | L20: =K20-'Forecasting '!$G$9 -> 11000000 | O20: Present Value of Future Cash Flows | R20: =SUM(C24:L24) -> -19687569 | AP20: 2026E | AQ20: =-7754855.55538018/1000 -> -7754.8556
B21: Acquisition Spend | AP21: 2027E | AQ21: =-5894894.20518348/1000 -> -5894.8942
B22: Change in NWC | C22: =Exhibits!C22 -> 44347.75 | D22: =Exhibits!D22 -> 35961.503 | E22: =Exhibits!E22 -> 39917.268 | F22: =Exhibits!F22 -> 44308.167 | G22: =Exhibits!G22 -> 49182.066 | H22: =Exhibits!H22 -> 44666.258 | I22: =Exhibits!I22 -> 43276.641 | J22: =Exhibits!J22 -> 40896.426 | ... L22: =Exhibits!L22 -> 33131.947 | O22: Terminal Year Unlevered FCF (Excl. M&A) | R22: =L24*(1+R23) -> 4033428.7 | AP22: 2028E | AQ22: =-4623044.01808386/1000 -> -4623.044
B23: D&A | C23: =C14 -> 2617440 | D23: =D14 -> 2931532.8 | E23: =E14 -> 3283316.7 | F23: =F14 -> 3677314.7 | G23: =G14 -> 4118592.5 | H23: =H14 -> 4612823.6 | I23: =I14 -> 5166362.4 | J23: =J14 -> 5786325.9 | ... L23: =L14 -> 7258367.3 | O23: Long-Term Growth Rate | R23: 0.023 | AP23: 2029E | AQ23: =-3360800.5744626/1000 -> -3360.8006
B24: Unlevered FCF | C24: =C18-C20-C22+C23 -> -8161872.3 | D24: =D18-D20-D22+D23 -> -6529924.9 | E24: =E18-E20-E22+E23 -> -5389845.1 | F24: =F18-F20-F22+F23 -> -4123890.1 | G24: =G18-G20-G22+G23 -> -2719085.4 | H24: =H18-H20-H22+H23 -> -1239759.2 | I24: =I18-I20-I22+I23 -> 188161.21 | J24: =J18-J20-J22+J23 -> 1543557.7 | ... L24: =L18-L20-L22+L23 -> 3942745.5 | O24: Terminal Value | R24: =(R22*1+R23)/(R16-R23) -> 1.3679405e+08 | AP24: 2030E | AQ24: =-2105437.84095161/1000 -> -2105.4378
C25: 1 | D25: 2 | E25: 3 | F25: 4 | G25: 5 | H25: 6 | I25: 7 | J25: 8 | K25: 9 | L25: 10 | AP25: 2031E | AQ25: =-912096.608941968/1000 -> -912.09661
B26: PV OF FCF | C26: =C24/(1+$R$16)^C25 -> -7754855.6 | D26: =D24/(1+$R$16)^D25 -> -5894894.2 | E26: =E24/(1+$R$16)^E25 -> -4623044 | F26: =F24/(1+$R$16)^F25 -> -3360800.6 | G26: =G24/(1+$R$16)^G25 -> -2105437.8 | H26: =H24/(1+$R$16)^H25 -> -912096.61 | I26: =I24/(1+$R$16)^I25 -> 131527.79 | J26: =J24/(1+$R$16)^J25 -> 1025166 | ... L26: =L24/(1+$R$16)^L25 -> 2363947.9 | AP26: 2032E | AQ26: =131527.78801577/1000 -> 131.52779
B27: Sensitivity | O27: Present Value of Terminal Value | R27: =R24/(1+R19)^10 -> 82017468 | AP27: 2033E | AQ27: =1025166.02059663/1000 -> 1025.166
O28: Excess cash | R28: 0 | AP28: 2034E | AQ28: =1768383.84553331/1000 -> 1768.3838
O29: Marketable securities | R29: 147000 | AP29: 2035E | AQ29: =2363947.90935516/1000 -> 2363.9479
O30: Non-consolidated subsidiaries | R30: =31700000*0.25 -> 7925000
O31: Total Enterprise Value | R31: =R20+R27+R29+R30 -> 70401898
G32: WACC | O32: Net Debt | R32: -32688
C33: Terminal CAGR | D33: =R39 -> 95.452695 | E33: 0.048 | F33: 0.05 | G33: 0.0525 | H33: 0.054 | I33: 0.056
D34: 0.01 | E34: 70.257142 | F34: 63.431338 | G34: 55.851869 | H34: 51.742472 | I34: 46.707288 | O34: Unfunded pension liabilities | R34: 124000
D35: 0.015 | E35: 86.052095 | F35: 77.33841 | G35: 67.809587 | H35: 62.706867 | I35: 56.514612 | O35: Preffered stock | R35: 20000
D36: 0.0225 | E36: 121.35846 | F36: 107.68111 | G36: 93.219737 | H36: 85.679884 | I36: 76.71477
D37: 0.025 | E37: 138.24412 | F37: 121.84104 | G37: 104.76981 | H37: 95.978134 | I37: 85.620216 | O37: Implied Equity Value | R37: =+R31+R32-R34-R35-R30 -> 62300210
D38: 0.03 | E38: 186.0868 | F38: 160.78084 | G38: 135.56999 | H38: 123.01104 | I38: 108.56887 | O38: Shares Outstanding | R38: =652681521/1000 -> 652681.52
O39: Implied Share Price | R39: =R37/R38 -> 95.452695
BL46: 9970000
BL47: 10860000
BL48: 12520000
BL49: 13649000
AY50: Year | AZ50: Forecasted Revenue ($M) | BL50: 11303000
AY51: 2026E | AZ51: =13076910/1000 -> 13076.91 | BL51: 11871000
G52: Targetted rate base cagr | H52: 0.11 | AY52: 2027E | AZ52: =14515370.1/1000 -> 14515.37
B53: SENSITIVITY TO WACC | AY53: 2028E | AZ53: =16112060.811/1000 -> 16112.061
B54: WACC | D54: 0.048 | E54: 0.05 | F54: 0.052 | G54: 0.054 | H54: 0.056 | J54: BETAS | AY54: 2029E | AZ54: =17884387.50021/1000 -> 17884.388
B55: DCF VALUE PER SHARE | C55: =R39 -> 95.452695 | D55: 124.46542 | E55: 110.30332 | F55: 98.146827 | G55: 87.606654 | H55: 78.387914 | AY55: 2030E | AZ55: =19851670.1252331/1000 -> 19851.67
J56: Comparables | K56: BETA | L56: unlevered | M56: sempra = 0.42 | AY56: 2031E | AZ56: =21638320.4389837/1000 -> 21638.32
B57: SENSITIVITY TO TERMINAL GROWTH RATE | J57: #VALUE! | K57: 0.78 | L57: 0.41 | AM57: 13076910 | AN57: 14515370 | AO57: 16112061 | AP57: 17884388 | AQ57: 19851670 | AR57: 21638320 | AS57: 23369386 | AT57: 25005243 | AU57: 26505558 | AV57: 27830836 | AY57: 2032E | AZ57: =23369386.0741023/1000 -> 23369.386
B58: TGR | D58: 0.01 | E58: 0.015 | F58: 0.02 | G58: 0.025 | H58: 0.03 | J58: #VALUE! | K58: 0.75 | L58: 0.32 | AY58: 2033E | AZ58: =25005243.0992895/1000 -> 25005.243
B59: DCF VALUE PER SHARE | C59: =R39 -> 95.452695 | D59: 55.893357 | E59: 67.861329 | F59: 83.513409 | G59: 104.86017 | H59: 135.70055 | J59: #VALUE! | K59: 0.43 | L59: 0.21 | AY59: 2034E | AZ59: =26505557.6852469/1000 -> 26505.558
J60: DUKE ENERGY | K60: 0.47 | L60: 0.24 | AY60: 2035E | AZ60: =27830835.5695092/1000 -> 27830.836
B61: SENSITIVITY TO CAGR 2026 -2030
B62: SENSITIVITY TO CAGR | D62: 0.09 | E62: 0.1 | F62: 0.11 | G62: 0.12 | H62: 0.13 | K62: =AVERAGE(K57:K60) -> 0.6075 | L62: =AVERAGE(L57:L60) -> 0.295
B63: DCF CALUE PER SHARE | C63: =R39 -> 95.452695 | D63: 89.958975 | E63: 92.670935 | F63: 95.452695 | G63: 98.305736 | H63: 101.23156 | J63: sempra | K63: 6
BJ64: 9970000 | BK64: 10860000 | BL64: 12520000 | BM64: 13649000 | BN64: 11303000 | BO64: 11871000
B65: CARG 2025 - 2030 | C65: 0.11
AY67: Year | AZ67: YOY Growth %
AY68: 2026E | AZ68: 0.11
AY69: 2027E | AZ69: 0.11
AY70: 2028E | AZ70: 0.11
AY71: 2029E | AZ71: 0.11
AY72: 2030E | AZ72: 0.11
AY73: 2031E | AZ73: 0.09
AY74: 2032E | AZ74: 0.08
AY75: 2033E | AZ75: 0.07
AY76: 2034E | AZ76: 0.06
AY77: 2035E | AZ77: 0.05

Sheet Exhibits
B3: Financial Forecast | V3: Historical Financials(Sempra)
N4: CAGR's
C5: 2026E | D5: 2027 | E5: 2028 | F5: 2029 | G5: 2030E | H5: 2031E | I5: 2032E | J5: 2033E | K5: 2034 | L5: 2035E | N5: '25-'27 | O5: 27-'30 | P5: 30'-'35 | AH5: 2020 | AI5: 2021 | AJ5: 2022 | AK5: 2023 | AL5: 2024 | AM5: 2025A | AN5: CAGR's
V6: Revenue | AH6: ='historicals + revenue split '!C7 -> 9970000 | AI6: ='historicals + revenue split '!D7 -> 10860000 | AJ6: ='historicals + revenue split '!E7 -> 12520000 | AK6: ='historicals + revenue split '!F7 -> 13649000 | AL6: ='historicals + revenue split '!G7 -> 11303000 | AM6: =11871*1000 -> 11871000 | AN6: =(AM6/AH6)^(1/5) - 1 -> 0.035519852
B7: Revenue | C7: ='Forecasting '!C4 -> 13076910 | D7: ='Forecasting '!D4 -> 14515370 | E7: ='Forecasting '!E4 -> 16112061 | F7: ='Forecasting '!F4 -> 17884388 | G7: ='Forecasting '!G4 -> 19851670 | H7: ='Forecasting '!H4 -> 21638320 | I7: ='Forecasting '!I4 -> 23369386 | J7: ='Forecasting '!J4 -> 25005243 | ... L7: ='Forecasting '!L4 -> 27830836 | N7: 0.11 | O7: =(G7/D7)^(1/3)-1 -> 0.11 | P7: =(L7/G7)^(1/5)-1 -> 0.069906532 | V7: YoY Growth | AI7: =AI6/AH6-1 -> 0.089267803 | AJ7: =AJ6/AI6-1 -> 0.15285451 | AK7: =AK6/AJ6-1 -> 0.090175719 | AL7: =AL6/AK6-1 -> -0.17188072 | AM7: =AM6/AL6-1 -> 0.050252145
B8: YoY Growth | D8: =(D7/C7)-1 -> 0.11 | E8: =(E7/D7)-1 -> 0.11 | F8: =(F7/E7)-1 -> 0.11 | G8: =(G7/F7)-1 -> 0.11 | H8: =(H7/G7)-1 -> 0.09 | I8: =(I7/H7)-1 -> 0.08 | J8: =(J7/I7)-1 -> 0.07 | K8: =(K7/J7)-1 -> 0.06 | L8: =(L7/K7)-1 -> 0.05 | V8: COGS | AH8: 6596000 | AI8: 7544000 | AJ8: 8921000 | AK8: 10229000 | AL8: 7679000 | AM8: 7679000 | AN8: =(AM8/AH8)^(1/5)-1 -> 0.030872143 | AW8: Source: S&P Global. (n.d.). Capital IQ Pro. https://www.capitaliq.spglobal.com/web/client?auth=inherit#ratingsdirect/home
V9: Gross Profit | AH9: =AH6-AH8 -> 3374000 | AI9: =AI6-AI8 -> 3316000 | AJ9: =AJ6-AJ8 -> 3599000 | AK9: =AK6-AK8 -> 3420000 | AL9: =AL6-AL8 -> 3624000 | AM9: =AM6-AM8 -> 4192000 | AN9: =(AM9/AH9)^(1/5)-1 -> 0.044372047
B10: COGS | C10: =AM8*(1+N10) -> 7909370 | D10: =C10*(1+N10) -> 8146651.1 | E10: =D10*(1+$O$10) -> 8350317.4 | F10: =E10*(1+$O$10) -> 8559075.3 | G10: =F10*(1+$O$10) -> 8773052.2 | H10: =G10*(1+$O$10) -> 8992378.5 | I10: =H10*(1+$O$10) -> 9217188 | J10: =I10*(1+$O$10) -> 9447617.7 | K10: =J10*(1+$O$10) -> 9683808.1 | L10: =K10*(1+$O$10) -> 9925903.3 | N10: 0.03 | O10: 0.025 | P10: =(L10/G10)^(1/5)-1 -> 0.025 | V10: Margin | AH10: =(AH9/AH6) -> 0.33841525 | AI10: =(AI9/AI6) -> 0.3053407 | AJ10: =(AJ9/AJ6) -> 0.28746006 | AK10: =(AK9/AK6) -> 0.25056781 | AL10: =(AL9/AL6) -> 0.32062284 | AM10: =(AM9/AM6) -> 0.35312948
B11: Gross Profit | C11: =C7-C10 -> 5167540 | D11: =D7-D10 -> 6368719 | E11: =E7-E10 -> 7761743.4 | F11: =F7-F10 -> 9325312.2 | G11: =G7-G10 -> 11078618 | H11: =H7-H10 -> 12645942 | I11: =I7-I10 -> 14152198 | J11: =J7-J10 -> 15557625 | ... L11: =L7-L10 -> 17904932 | N11: =(D11/AM9)^(1/2)-1 -> 0.23258082 | O11: =(G11/D11)^(1/3)-1 -> 0.20266452 | P11: =(L11/G11)^(1/5)-1 -> 0.10077212 | V11: Operating expenditures | AH11: =1768000*AH41 -> 1550304.3 | AI11: =1922000*AI41 -> 1623467.4 | AJ11: =2078000*AJ41 -> 1801825.6 | AK11: =2333000*AK41 -> 1904492.6 | AL11: =2538000*AL41 -> 2175731.1 | AM11: =AL11*(1+AO11)*AM41 -> 1840143.2
B12: Margin | C12: =(C11/C7) -> 0.39516522 | D12: =(D11/D7) -> 0.43875691 | E12: =(E11/E7) -> 0.48173499 | F12: =(F11/F7) -> 0.52142195 | G12: =(G11/G7) -> 0.55806982 | H12: =(H11/H7) -> 0.58442345 | I12: =(I11/I7) -> 0.60558707 | J12: =(J11/J7) -> 0.62217453 | ... L12: =(L11/L7) -> 0.64334871 | V12: EBITDA | AH12: =AH9-AH11+AH19 -> 3291695.7 | AI12: =AI9-AI11+AI19 -> 3308532.6 | AJ12: =AJ9-AJ11+AJ19 -> 3540174.4 | AK12: =AK9-AK11+AK19 -> 3452507.4 | AL12: =AL9-AL11+AL19 -> 3581268.9 | AM12: =AM9-AM11+AM19 -> 4688856.8 | AN12: =(AM12/AH12)^(1/5)-1 -> 0.073320584
V13: YoY Growth | AI13: =AI12/AH12-1 -> 0.005114974 | AJ13: =AJ12/AI12-1 -> 0.070013443 | AK13: =AK12/AJ12-1 -> -0.024763478 | AL13: =AL12/AK12-1 -> 0.037295094 | AM13: =AM12/AL12-1 -> 0.30927246
B14: OpEx Excl. D&A | C14: =100000*1.027 -> 102700 | D14: =C14*1.027 -> 105472.9 | E14: =D14*1.027 -> 108320.67 | F14: =E14*1.027 -> 111245.33 | G14: =F14*1.027 -> 114248.95 | H14: =G14*1.027 -> 117333.67 | I14: =H14*1.027 -> 120501.68 | J14: =I14*1.027 -> 123755.23 | K14: =J14*1.027 -> 127096.62 | L14: =K14*1.027 -> 130528.23 | V14: Margin | AI14: =(AI$12-AH$12)/AH$12 -> 0.005114974 | AJ14: =(AJ$12-AI$12)/AI$12 -> 0.070013443 | AK14: =(AK$12-AJ$12)/AJ$12 -> -0.024763478 | AL14: =(AL$12-AK$12)/AK$12 -> 0.037295094 | AM14: =(AM$12-AL$12)/AL$12 -> 0.30927246
B15: EBITDA | C15: =C11-C14 -> 5064840 | D15: =D11-D14 -> 6263246.1 | E15: =E11-E14 -> 7653422.8 | F15: =F11-F14 -> 9214066.9 | G15: =G11-G14 -> 10964369 | H15: =H11-H14 -> 12528608 | I15: =I11-I14 -> 14031696 | J15: =J11-J14 -> 15433870 | ... L15: =L11-L14 -> 17774404 | N15: =(D15/AM12)^(1/2)-1 -> 0.15575626 | O15: =(G15/D15)^(1/3)-1 -> 0.20520629 | P15: =(L15/G15)^(1/5)-1 -> 0.10144364
B16: YoY Growth | C16: =(C15/AM12)-1 -> 0.080186538 | D16: =(D15/C15)-1 -> 0.23661282 | E16: =(E15/D15)-1 -> 0.22195785 | F16: =(F15/E15)-1 -> 0.20391453 | G16: =(G15/F15)-1 -> 0.18995978 | H16: =(H15/G15)-1 -> 0.14266569 | I16: =(I15/H15)-1 -> 0.11997248 | J16: =(J15/I15)-1 -> 0.099929028 | K16: =(K15/J15)-1 -> 0.081689345 | L16: =(L15/K15)-1 -> 0.064676461 | V16: Note: R&D
B17: EBITDA Margin | C17: =(C15/C7) -> 0.38731168 | D17: =(D15/D7) -> 0.43149062 | E17: =(E15/E7) -> 0.47501203 | F17: =(F15/F7) -> 0.5152017 | G17: =(G15/G7) -> 0.55231469 | H17: =(H15/H7) -> 0.57900096 | I17: =(I15/I7) -> 0.60043068 | J17: =(J15/J7) -> 0.61722536 | ... L17: =(L15/L7) -> 0.63865866 | O17: 0 | V17: EBIT | AH17: =AH12-AH19 -> 1823695.7 | AI17: =AI12-AI19 -> 1692532.6 | AJ17: =AJ12-AJ19 -> 1797174.4 | AK17: =AK12-AK19 -> 1515507.4 | AL17: =AL12-AL19 -> 1448268.9 | AM17: =AM12-AM19 -> 2351856.8 | AN17: =(AM17/AH17)^(1/5)-1 -> 0.052184018
B19: D&A | C19: =AM19*(1+N19) -> 2617440 | D19: =C19*(1+N19) -> 2931532.8 | E19: =D19*(1+$O$19) -> 3283316.7 | F19: =E19*(1+$O$19) -> 3677314.7 | G19: =F19*(1+$O$19) -> 4118592.5 | H19: =G19*(1+$O$19) -> 4612823.6 | I19: =H19*(1+$O$19) -> 5166362.4 | J19: =I19*(1+$O$19) -> 5786325.9 | K19: =J19*(1+$O$19) -> 6480685.1 | L19: =K19*(1+$O$19) -> 7258367.3 | N19: 0.12 | O19: 0.12 | P19: =(L19/G19)^(1/5)-1 -> 0.12 | V19: D&A | AH19: ='Segment Analysis from cap iq '!B103 -> 1468000 | AI19: ='Segment Analysis from cap iq '!C103 -> 1616000 | AJ19: ='Segment Analysis from cap iq '!D103 -> 1743000 | AK19: ='Segment Analysis from cap iq '!E103 -> 1937000 | AL19: ='Segment Analysis from cap iq '!F103 -> 2133000 | AM19: 2337000 | AN19: =(AM19/AH19)^(1/5)-1 -> 0.09745452
B20: EBIT | C20: =C15-C19 -> 2447400 | D20: =D15-D19 -> 3331713.3 | E20: =E15-E19 -> 4370106 | F20: =F15-F19 -> 5536752.1 | G20: =G15-G19 -> 6845776.5 | H20: =H15-H19 -> 7915784.7 | I20: =I15-I19 -> 8865334 | J20: =J15-J19 -> 9647544.3 | ... L20: =L15-L19 -> 10516037 | V20: YoY Growth | AQ20: 2020 | AR20: 2021 | AS20: 2022 | AT20: 2023 | AU20: 2024 | AV20: 2025A | AX20: 2020 | AY20: 2021 | AZ20: 2022 | BA20: 2023 | BB20: 2024 | BC20: 2025A | BE20: 2020 | BF20: 2021 | BG20: 2022 | BH20: 2023 | BI20: 2024 | BJ20: 2025A
B21: TAX RATES | C21: ='Forecasting '!B16 -> 0.19709266 | D21: ='Forecasting '!C16 -> 0.20476236 | E21: ='Forecasting '!D16 -> 0.21243205 | F21: ='Forecasting '!E16 -> 0.22010174 | G21: ='Forecasting '!F16 -> 0.22777143 | H21: ='Forecasting '!G16 -> 0.23544112 | I21: ='Forecasting '!H16 -> 0.24311082 | J21: ='Forecasting '!I16 -> 0.25078051 | ... L21: ='Forecasting '!K16 -> 0.26611989 | AR21: 0.005 | AS21: 0.07 | AT21: -0.025 | AU21: 0.037 | AV21: 0.309 | AX21: 3291695.7 | AY21: 3308532.6 | AZ21: 3540174.4 | BA21: 3452507.4 | BB21: 3581268.9 | BC21: 4688856.8 | BE21: 3785000 | BF21: 4204000 | BG21: 4466000 | BH21: 4560000 | BI21: 4753000 | BJ21: 6556000
B22: Change in Nwc | C22: =(C7-AL6)*0.025 -> 44347.75 | D22: =(D7-C7)*0.025 -> 35961.503 | E22: =(E7-D7)*0.025 -> 39917.268 | F22: =(F7-E7)*0.025 -> 44308.167 | G22: =(G7-F7)*0.025 -> 49182.066 | H22: =(H7-G7)*0.025 -> 44666.258 | I22: =(I7-H7)*0.025 -> 43276.641 | J22: =(J7-I7)*0.025 -> 40896.426 | K22: =(K7-J7)*0.025 -> 37507.865 | L22: =(L7-K7)*0.025 -> 33131.947 | N22: 0.5% of change in Revenue
B23: NOPAT | C23: =C20*(1-C21) -> 1965035.4 | D23: =D20*(1-D21) -> 2649503.8 | E23: =E20*(1-E21) -> 3441755.5 | F23: =F20*(1-F21) -> 4318103.3 | G23: =G20*(1-G21) -> 5286504.2 | H23: =H20*(1-H21) -> 6052083.4 | I23: =I20*(1-I21) -> 6710075.4 | J23: =J20*(1-J21) -> 7228128.2 | ... L23: =L20*(1-L21) -> 7717510.2
V24: COGS | AH24: =AH6-AH9 -> 6596000 | AI24: =AI6-AI9 -> 7544000 | AJ24: =AJ6-AJ9 -> 8921000 | AK24: =AK6-AK9 -> 10229000 | AL24: =AL6-AL9 -> 7679000 | AM24: 7
V25: YoY Growth | AI25: =(AI24-AH24)/AH24 -> 0.14372347 | AJ25: =(AJ24-AI24)/AI24 -> 0.18252916 | AK25: =(AK24-AJ24)/AJ24 -> 0.14662033 | AL25: =(AL24-AK24)/AK24 -> -0.24929123 | AN25: =AVERAGE(AD25:AK25) -> 0.15762432
V27: CAPEX | AH27: 3785000 | AI27: 4204000 | AJ27: 4466000 | AK27: 4560000 | AL27: 4753000 | AM27: 6556000
B28: Interest Coverage Ratio | V28: YoY growth | AI28: =(AI27-AH27)/AI27 -> 0.099666984 | AJ28: =(AJ27-AI27)/AJ27 -> 0.058665472 | AK28: =(AK27-AJ27)/AK27 -> 0.020614035 | AL28: =(AL27-AK27)/AL27 -> 0.040605933 | AM28: =(AM27-AL27)/AM27 -> 0.27501525 | AN28: =(AM27/AH27)^(1/5)-1 -> 0.11612956
B29: Net Debt to EBITDA | U29: =#REF!*(1+0.06) -> #REF! | V29: Tax | AH29: 0.09948 | AI29: 0.06342 | AJ29: 0.19577 | AK29: 0.11931 | AL29: 0.0589 | AM29: =701/1169 -> 0.59965783
B30: CAPEX - D&A | C30: ='DCF '!C20-'DCF '!C14 -> 10082560 | D30: ='DCF '!D20-'DCF '!D14 -> 9143467.2 | E30: ='DCF '!E20-'DCF '!E14 -> 8791683.3 | F30: ='DCF '!F20-'DCF '!F14 -> 8397685.3 | G30: ='DCF '!G20-'DCF '!G14 -> 7956407.5 | H30: ='DCF '!H20-'DCF '!H14 -> 7247176.4 | I30: ='DCF '!I20-'DCF '!I14 -> 6478637.6 | J30: ='DCF '!J20-'DCF '!J14 -> 5643674.1 | ... L30: ='DCF '!L20-'DCF '!L14 -> 3741632.7
B31: RATE BASE | V31: Net Income | AH31: ='Segment Analysis from cap iq '!B74-'Segment Analysis from cap iq '!B63 -> 3184000 | AI31: ='Segment Analysis from cap iq '!C74-'Segment Analysis from cap iq '!C63 -> 572000 | AJ31: ='Segment Analysis from cap iq '!D74-'Segment Analysis from cap iq '!D63 -> 1784000 | AK31: ='Segment Analysis from cap iq '!E74-'Segment Analysis from cap iq '!E63 -> 2153000 | AL31: ='Segment Analysis from cap iq '!F74-'Segment Analysis from cap iq '!F63 -> 1906000 | AM31: 2072000 | AN31: =AM31*1.11 -> 2299920
B32: REALISATION RATE | V32: NOPAT ($M) | AH32: =AH$17*(1-AH$29) -> 1642274.4 | AI32: =AI$17*(1-AI$29) -> 1585192.2 | AJ32: =AJ$17*(1-AJ$29) -> 1445341.6 | AK32: =AK$17*(1-AK$29) -> 1334692.2 | AL32: =AL$17*(1-AL$29) -> 1362965.9 | AM32: =AM$17*(1-AM$29) -> 941547.46
B33: RATE BASE * REALISATION RATE
AJ36: =AL31/'Segment Analysis from cap iq '!F74 -> 0.67660632
V41: WEIGHTINGS | AH41: ='historicals + revenue split '!C8 -> 0.87686895 | AI41: ='historicals + revenue split '!D8 -> 0.84467605 | AJ41: ='historicals + revenue split '!E8 -> 0.86709606 | AK41: ='historicals + revenue split '!F8 -> 0.81632775 | AL41: ='historicals + revenue split '!G8 -> 0.85726204 | AM41: ='historicals + revenue split '!I8 -> 0.84575857
B44: Stock Charts | P44: Sales by Segment
AE50: Item | AH50: 2022A | AI50: 2023A | AJ50: 2024A | AK50: 2025A
AE51: Revenue ($M) | AH51: 12520000 | AI51: 13649000 | AJ51: 11303000 | AK51: 11871000
AE52: EBITDA ($M) | AH52: 3540174.4 | AI52: 3452507.4 | AJ52: 3581268.9 | AK52: 4688856.8
AE53: EBITDA Margin (%) | AH53: 0.07 | AI53: -0.025 | AJ53: 0.037 | AK53: 0.309
AE54: Operating Income ($M) | AH54: 1797174.4 | AI54: 1515507.4 | AJ54: 1448268.9 | AK54: 2351856.8
AE55: Net Income ($M) | AH55: 1784000 | AI55: 2153000 | AJ55: 1906000 | AK55: 2072000
AE56: NOPAT ($M) | AH56: 1445341.6 | AI56: 1334692.2 | AJ56: 1362965.9 | AK56: 941547.46
AE57: ROIC (%) | AH57: =AH$56/R$81 -> 14.606639 | AI57: =AI$56/S$81 -> 11.882732 | AJ57: =AJ$56/T$81 -> 10.794658 | AK57: =AK$56/U$81 -> 9.2640993
AC61: ITEM | AD61: 2026E | AE61: 2027E | AH61: 2028E | AI61: 2029E | AJ61: 2030E | AK61: 2031E | AL61: 2032E | AM61: 2033E | AN61: 2034E | AO61: 2035E
AC62: REVENUE GROWTH | AD62: ='DCF '!C5 -> 0.10158453 | AE62: ='DCF '!D5 -> 0.11 | AH62: ='DCF '!E5 -> 0.11 | AI62: ='DCF '!F5 -> 0.11 | AJ62: ='DCF '!G5 -> 0.11 | AK62: ='DCF '!H5 -> 0.09 | AL62: ='DCF '!I5 -> 0.08 | AM62: ='DCF '!J5 -> 0.07 | AN62: ='DCF '!K5 -> 0.06 | AO62: ='DCF '!L5 -> 0.05
AC63: EBITDA MARGIN | AD63: ='DCF '!C12 -> 0.38731168 | AE63: ='DCF '!D12 -> 0.43149062 | AH63: ='DCF '!E12 -> 0.47501203 | AI63: ='DCF '!F12 -> 0.5152017 | AJ63: ='DCF '!G12 -> 0.55231469 | AK63: ='DCF '!H12 -> 0.57900096 | AL63: ='DCF '!I12 -> 0.60043068 | AM63: ='DCF '!J12 -> 0.61722536 | AN63: ='DCF '!K12 -> 0.62985481 | AO63: ='DCF '!L12 -> 0.63865866
AC64: D&A (% OF REVENUE) | AD64: ='DCF '!C23/'DCF '!C4 -> 0.20015738 | AE64: ='DCF '!D23/'DCF '!D4 -> 0.2019606 | AH64: ='DCF '!E23/'DCF '!E4 -> 0.20378006 | AI64: ='DCF '!F23/'DCF '!F4 -> 0.20561592 | AJ64: ='DCF '!G23/'DCF '!G4 -> 0.20746831 | AK64: ='DCF '!H23/'DCF '!H4 -> 0.21317845 | AL64: ='DCF '!I23/'DCF '!I4 -> 0.22107395 | AM64: ='DCF '!J23/'DCF '!J4 -> 0.23140451 | AN64: ='DCF '!K23/'DCF '!K4 -> 0.24450287 | AO64: ='DCF '!L23/'DCF '!L4 -> 0.26080307
AC65: OPERATING MARGIN | AD65: ='DCF '!C15/'DCF '!C4 -> 0.1871543 | AE65: ='DCF '!D15/'DCF '!D4 -> 0.22953003 | AH65: ='DCF '!E15/'DCF '!E4 -> 0.27123197 | AI65: ='DCF '!F15/'DCF '!F4 -> 0.30958578 | AJ65: ='DCF '!G15/'DCF '!G4 -> 0.34484637 | AK65: ='DCF '!H15/'DCF '!H4 -> 0.36582251 | AL65: ='DCF '!I15/'DCF '!I4 -> 0.37935673 | AM65: ='DCF '!J15/'DCF '!J4 -> 0.38582085 | AN65: ='DCF '!K15/'DCF '!K4 -> 0.38535193 | AO65: ='DCF '!L15/'DCF '!L4 -> 0.37785559
B66: Share Price Data | AC66: TAX RATE | AD66: =C21 -> 0.19709266 | AE66: =D21 -> 0.20476236 | AH66: =E21 -> 0.21243205 | AI66: =F21 -> 0.22010174 | AJ66: =G21 -> 0.22777143 | AK66: =H21 -> 0.23544112 | AL66: =I21 -> 0.24311082 | AM66: =J21 -> 0.25078051 | AN66: =K21 -> 0.2584502 | AO66: =L21 -> 0.26611989
B67: Date | C67: Price | D67: EV/EBITDA
B68: 31/03/2016 | C68: 42.4629 | D68: 13.68
B69: 30/04/2016 | C69: 42.181 | D69: 13.46 | AC69: ITEM | AD69: =AD61 -> 2026E | AE69: =AE61 -> 2027E | AH69: =AH61 -> 2028E | AI69: =AI61 -> 2029E | AJ69: =AJ61 -> 2030E
B70: 31/05/2016 | C70: 43.7152 | D70: 13.57 | AC70: OPERATING CASH FLOW | AD70: ='DCF '!C24+'DCF '!C20 -> 4538127.7 | AE70: ='DCF '!D24+'DCF '!D20 -> 5545075.1 | AH70: ='DCF '!E24+'DCF '!E20 -> 6685154.9 | AI70: ='DCF '!F24+'DCF '!F20 -> 7951109.9 | AJ70: ='DCF '!G24+'DCF '!G20 -> 9355914.6
B71: 30/06/2016 | C71: 46.8428 | D71: 13.53 | AC71: CAPEX | AD71: ='DCF '!C20 -> 12700000 | AE71: ='DCF '!D20 -> 12075000 | AH71: ='DCF '!E20 -> 12075000 | AI71: ='DCF '!F20 -> 12075000 | AJ71: ='DCF '!G20 -> 12075000
B72: 31/07/2016 | C72: 45.9782 | D72: 12.46 | AC72: FCF CONVERSION | AD72: ='DCF '!C24 -> -8161872.3 | AE72: ='DCF '!D24 -> -6529924.9 | AH72: ='DCF '!E24 -> -5389845.1 | AI72: ='DCF '!F24 -> -4123890.1 | AJ72: ='DCF '!G24 -> -2719085.4
B73: 31/08/2016 | C73: 42.995 | D73: 12.11 | P73: Currency | Q73: USD | R73: USD | S73: USD | T73: USD | U73: USD
B74: 30/09/2016 | C74: 44.3518 | D74: 11.96 | P74: Units | Q74: Millions | R74: Millions | S74: Millions | T74: Millions | U74: Millions | AC74: ITEM | AD74: =AK61 -> 2031E | AE74: =AL61 -> 2032E | AH74: =AM61 -> 2033E | AI74: =AN61 -> 2034E | AJ74: =AO61 -> 2035E
B75: 31/10/2016 | C75: 44.3114 | D75: 12.06 | Q75: 2021 | R75: 2022 | S75: 2023 | T75: 2024 | U75: 2025 | AC75: OPERATING CASH FLOW | AD75: ='DCF '!H24+'DCF '!H20 -> 10620241 | AE75: ='DCF '!I24+'DCF '!I20 -> 11833161 | AH75: ='DCF '!J24+'DCF '!J20 -> 12973558 | AI75: ='DCF '!K24+'DCF '!K20 -> 14017343 | AJ75: ='DCF '!L24+'DCF '!L20 -> 14942746
B76: 30/11/2016 | C76: 41.2893 | D76: 11.39 | P76: Operating current assets | Q76: 3148 | R76: 4040 | S76: 3523 | T76: 3319 | U76: 2747 | AC76: CAPEX | AD76: ='DCF '!H20 -> 11860000 | AE76: ='DCF '!I20 -> 11645000 | AH76: ='DCF '!J20 -> 11430000 | AI76: ='DCF '!K20 -> 11215000 | AJ76: ='DCF '!L20 -> 11000000
B77: 31/12/2016 | C77: 41.9475 | D77: 11.96 | P77: operating current liabiliteis | Q77: 3459 | R77: 4133 | S77: 4335 | T77: 4255 | U77: 3164 | AC77: FCF CONVERSION | AD77: ='DCF '!H24 -> -1239759.2 | AE77: ='DCF '!I24 -> 188161.21 | AH77: ='DCF '!J24 -> 1543557.7 | AI77: ='DCF '!K24 -> 2802343.1 | AJ77: ='DCF '!L24 -> 3942745.5
B78: 31/01/2017 | C78: 42.6812 | D78: 12.42 | P78: Net PP&E | Q78: 43894 | R78: 47782 | S78: 54960 | T78: 61437 | U78: 49011
B79: 28/02/2017 | C79: 45.9782 | D79: 11.98 | P79: Operating non-current liabilities | Q79: 46855 | R79: 51262 | S79: 58174 | T79: 65762 | U79: 53040
B80: 31/03/2017 | C80: 46.4064 | D80: 11.7
B81: 30/04/2017 | C81: 47.4562 | D81: 12.02 | P81: Invested capital | Q81: 90438 | R81: 98951 | S81: 112322 | T81: 126263 | U81: 101634
B82: 31/05/2017 | C82: 48.925 | D82: 11.97
B83: 30/06/2017 | C83: 47.343 | D83: 12.18 | V83: Historical Revenue
B84: 31/07/2017 | C84: 47.8105 | D84: 12.79
B85: 31/08/2017 | C85: 49.8945 | D85: 13.25 | V85: Year 2022 | AC85: Year 2023 | AD85: Year 2024 | AE85: Year 2025
B86: 30/09/2017 | C86: 48.6323 | D86: 13.49 | V86: 12520000 | AC86: 13649000 | AD86: 11303000 | AE86: 11871000
B87: 31/10/2017 | C87: 50.0575 | D87: 14.67
B88: 30/11/2017 | C88: 51.55 | D88: 14.9
B89: 31/12/2017 | C89: 45.9014 | D89: 14.7
B90: 31/01/2018 | C90: 45.9467 | D90: 14.45
B91: 28/02/2018 | C91: 46.7818 | D91: 14.55
B92: 31/03/2018 | C92: 48.1362 | D92: 14.64
B93: 30/04/2018 | C93: 48.3944 | D93: 14.92
B94: 31/05/2018 | C94: 46.1078 | D94: 15.46
B95: 30/06/2018 | C95: 50.653 | D95: 15.56
B96: 31/07/2018 | C96: 50.427 | D96: 14.94
B97: 31/08/2018 | C97: 50.6385 | D97: 14.89
B98: 30/09/2018 | C98: 50.0225 | D98: 14.68
... B128: 31/03/2021 | C128: 63.2315 | D128: 14.82
B129: 30/04/2021 | C129: 65.6165 | D129: 15.01 | J129: Valuation Method | K129: Value/share | L129: Weight
B130: 31/05/2021 | C130: 64.621 | D130: 13.67 | J130: DCF(Base Case) | K130: 95.5 | L130: 0.5
B131: 30/06/2021 | C131: 63.1875 | D131: 13.89 | J131: EV/EBITDA Comps (Median) | K131: 87.22 | L131: 0.25
B132: 31/07/2021 | C132: 62.828 | D132: 12.91 | J132: EV/Revenue Comps (Median | K132: 78.21 | L132: 0.15
B133: 31/08/2021 | C133: 63.6555 | D133: 12.92 | J133: Precedent M&A Analysis | K133: 107 | L133: 0.1
B134: 30/09/2021 | C134: 61.3495 | D134: 12.82 | J134: Weighted Average | K134: =(95.5*0.5)+(87.22*0.25)+(78.21*0.15)+(107*0.1) -> 91.9865 | L134: 1 | V134: Terminal Value Calculation | AK134: Revenue Build-up
B135: 31/10/2021 | C135: 61.8965 | D135: 11.6 | J135: Margin of Safety | K135: =K134*0.9 -> 82.78785
B136: 30/11/2021 | C136: 58.1325 | D136: 10.99 | V136: ITEM | AC136: =AD61 -> 2026E | AD136: =AE61 -> 2027E | AE136: =AH61 -> 2028E | AH136: =AI61 -> 2029E | AI136: =AJ61 -> 2030E | AK136: Revenue Segment | AL136: 2026E Growth | AM136: 2027E Growth | AN136: Notes
B137: 31/12/2021 | C137: 64.705 | D137: 11.39 | V137: OPERATING INCOME | AC137: ='DCF '!C15 -> 2447400 | AD137: ='DCF '!D15 -> 3331713.3 | AE137: ='DCF '!E15 -> 4370106 | AH137: ='DCF '!F15 -> 5536752.1 | AI137: ='DCF '!G15 -> 6845776.5 | AK137: Sempra California | AL137: 6% | AM137: 6% | AN137: Stable market, strong capex investment
B138: 31/01/2022 | C138: 67.582 | D138: 12.23 | V138: TAX RATE | AC138: =AD66 -> 0.19709266 | AD138: =AE66 -> 0.20476236 | AE138: =AH66 -> 0.21243205 | AH138: =AI66 -> 0.22010174 | AI138: =AJ66 -> 0.22777143 | AK138: Sempra Texas | AL138: 15.2% | AM138: 17% | AN138: Growing customer base, major investment plan, growing rate base
B139: 28/02/2022 | C139: 70.5435 | D139: 12.19 | I139: Item | J139: Value | V139: NOPAT | AC139: ='DCF '!C18 -> 1965035.4 | AD139: ='DCF '!D18 -> 2649503.8 | AE139: ='DCF '!E18 -> 3441755.5 | AH139: ='DCF '!F18 -> 4318103.3 | AI139: ='DCF '!G18 -> 5286504.2 | AK139: Total Revenue | AL139: 10.2% | AM139: 11%
B140: 31/03/2022 | C140: 82.8305 | D140: 11.85 | I140: Rating | J140: HOLD | V140: ADD: D&A | AC140: ='DCF '!C14 -> 2617440 | AD140: ='DCF '!D14 -> 2931532.8 | AE140: ='DCF '!E14 -> 3283316.7 | AH140: ='DCF '!F14 -> 3677314.7 | AI140: ='DCF '!G14 -> 4118592.5
B141: 30/04/2022 | C141: 79.5 | D141: 11.98 | I141: Price Target (12 months) | J141: $82.79 | V141: LESS CAPEX | AC141: ='DCF '!C20 -> 12700000 | AD141: ='DCF '!D20 -> 12075000 | AE141: ='DCF '!E20 -> 12075000 | AH141: ='DCF '!F20 -> 12075000 | AI141: ='DCF '!G20 -> 12075000
B142: 31/05/2022 | C142: 80.732 | D142: 12.43 | I142: Current Price (as of 09/03/2026) | J142: $91.56 | V142: LESS NWC | AC142: ='DCF '!C22 -> 44347.75 | AD142: ='DCF '!D22 -> 35961.503 | AE142: ='DCF '!E22 -> 39917.268 | AH142: ='DCF '!F22 -> 44308.167 | AI142: ='DCF '!G22 -> 49182.066
B143: 30/06/2022 | C143: 74.036 | D143: 12.94 | I143: Downside Potential | J143: =82.79/91.56-1 -> -0.095784185 | V143: FREE CASH FLOW | AC143: =AC139+AC140-AC141-AC142 -> -8161872.3 | AD143: =AD139+AD140-AD141-AD142 -> -6529924.9 | AE143: =AE139+AE140-AE141-AE142 -> -5389845.1 | AH143: =AH139+AH140-AH141-AH142 -> -4123890.1 | AI143: =AI139+AI140-AI141-AI142 -> -2719085.4
B144: 31/07/2022 | C144: 82.329 | D144: 12.61 | I144: Risk Rating | J144: Medium
B145: 31/08/2022 | C145: 81.917 | D145: 12.61 | V145: ITEM | AC145: =AK61 -> 2031E | AD145: =AL61 -> 2032E | AE145: =AM61 -> 2033E | AH145: =AN61 -> 2034E | AI145: =AO61 -> 2035E
B146: 30/09/2022 | C146: 74.97 | D146: 12.3 | V146: OPERATING INCOME | AC146: ='DCF '!H15 -> 7915784.7 | AD146: ='DCF '!I15 -> 8865334 | AE146: ='DCF '!J15 -> 9647544.3 | AH146: ='DCF '!K15 -> 10213968 | AI146: ='DCF '!L15 -> 10516037
B147: 31/10/2022 | C147: 75.47 | D147: 12.7 | V147: TAX RATE | AC147: =AK66 -> 0.23544112 | AD147: =AL66 -> 0.24311082 | AE147: =AM66 -> 0.25078051 | AH147: =AN66 -> 0.2584502 | AI147: =AO66 -> 0.26611989
B148: 30/11/2022 | C148: 83.095 | D148: 12.73 | V148: NOPAT | AC148: ='DCF '!H18 -> 6052083.4 | AD148: ='DCF '!I18 -> 6710075.4 | AE148: ='DCF '!J18 -> 7228128.2 | AH148: ='DCF '!K18 -> 7574165.9 | AI148: ='DCF '!L18 -> 7717510.2
B149: 31/12/2022 | C149: 77.27 | D149: 12.51 | V149: ADD: D&A | AC149: ='DCF '!H14 -> 4612823.6 | AD149: ='DCF '!I14 -> 5166362.4 | AE149: ='DCF '!J14 -> 5786325.9 | AH149: ='DCF '!K14 -> 6480685.1 | AI149: ='DCF '!L14 -> 7258367.3
...

Sheet Forecasting 
A1: Metric | B1: 2025A | C1: 2026E | D1: 2027E | E1: 2028E | F1: 2029E | G1: 2030E | H1: 2031E | I1: 2032E | J1: 2033E | K1: 2034E | L1: 2035E
A2: Typical allowed return | B2: 0.075 | C2: 0.075 | D2: 0.075 | E2: 0.075 | F2: 0.075 | G2: 0.075 | H2: 0.075 | I2: 0.075 | J2: 0.075 | K2: 0.075 | L2: 0.075
A3: Base Rate Growth | B3: 57000000 | C3: =B3*1.11 -> 63270000 | D3: =C3*1.11 -> 70229700 | E3: =D3*1.11 -> 77954967 | F3: =E3*1.11 -> 86530013 | G3: =F3*1.11 -> 96048315 | H3: =G3*1.09 -> 1.0469266e+08 | I3: =H3*1.08 -> 1.1306808e+08 | J3: =I3*1.07 -> 1.2098284e+08 | K3: =J3*1.06 -> 1.2824181e+08 | L3: =K3*1.05 -> 1.346539e+08 | M3: CARG 2025 - 2030 | N3: 0.11
A4: Projected Revenue | B4: =11781*1000 -> 11781000 | C4: =C5*2.755789474 -> 13076910 | D4: =D5*2.755789474 -> 14515370 | E4: =E5*2.755789474 -> 16112061 | F4: =F5*2.755789474 -> 17884388 | G4: =G5*2.755789474 -> 19851670 | H4: =H5*2.755789474 -> 21638320 | I4: =I5*2.755789474 -> 23369386 | J4: =J5*2.755789474 -> 25005243 | ... L4: =L5*2.755789474 -> 27830836 | P4: Source: S&P Global. (n.d.). Capital IQ Pro. https://www.capitaliq.spglobal.com/web/client?auth=inherit#ratingsdirect/home
A5: Allowed Return | B5: =B2*B3 -> 4275000 | C5: =C3*0.075 -> 4745250 | D5: =D3*0.075 -> 5267227.5 | E5: =E3*0.075 -> 5846622.5 | F5: =F3*0.075 -> 6489751 | G5: =G3*0.075 -> 7203623.6 | H5: =H3*0.075 -> 7851949.7 | I5: =I3*0.075 -> 8480105.7 | J5: =J3*0.075 -> 9073713.1 | ... L5: =L3*0.075 -> 10099043
A6: Realisation factor | B6: =B4/B5 -> 2.7557895
B8: 2031E | C8: 2032E | D8: 2033E | E8: 2034E | F8: 2035E | G8: YOY CHANGE
A9: Final 5 Year Capex Decline | B9: ='DCF '!H20 -> 11860000 | C9: ='DCF '!I20 -> 11645000 | D9: ='DCF '!J20 -> 11430000 | E9: ='DCF '!K20 -> 11215000 | F9: ='DCF '!L20 -> 11000000 | G9: =('DCF '!G20-11000000)/5 -> 215000
A11: Year | B11: 2020 | C11: 2021 | D11: 2022 | E11: 2023 | F11: 2024 | G11: 2025 | H11: Average
A12: Effective Tax Rate | B12: 0.09948 | C12: 0.06342 | D12: 0.19577 | E12: 0.11931 | F12: 0.0589 | G12: =701/1169 -> 0.59965783 | H12: =AVERAGE(B12:G12) -> 0.18942297
A15: Year | B15: 2026E | C15: 2027E | D15: 2028E | E15: 2029E | F15: 2030E | G15: 2031E | H15: 2032E | I15: 2033E | J15: 2034E | K15: 2035E
A16: Tax Per Year | B16: =H12+C43 -> 0.19709266 | C16: =B16+C43 -> 0.20476236 | D16: =C16+C43 -> 0.21243205 | E16: =D16+C43 -> 0.22010174 | F16: =E16+C43 -> 0.22777143 | G16: =F16+C43 -> 0.23544112 | H16: =G16+C43 -> 0.24311082 | I16: =H16+C43 -> 0.25078051 | J16: =I16+C43 -> 0.2584502 | K16: =J16+C43 -> 0.26611989
A22: Statutory tax rate | C22: 0.21
A24: Net income california | C24: 1846000
A26: Net income texas | C26: 781000
A28: Total net income | C28: =C26+C24 -> 2627000
A30: Weight california | C30: =C24/C28 -> 0.7027027
A32: Weight texas | C32: =C26/C28 -> 0.2972973
A34: California corporate tax rate | C34: 0.0884
A36: Texas Effective Franchise Equivalent | C36: 0.03
A38: Weighted state tax | C38: =(C30*C34)+(C32*C36) -> 0.071037838
A40: Marginal corporate tax | C40: =C22+C38*(1-C22) -> 0.26611989
A42: Difference between Marginal and avg effective | C42: =C40-H12 -> 0.076696921
A43: diffence 10 year period | C43: =C42/10 -> 0.0076696921

Sheet Analysis
A1: DETECTING MOMENTUM | B1: USING THE WINDSHIELD INSTEAD OF THE REARVIEW MIRROR
A2: RETURN ON NEW EQUITY (CHANGE IN INCOME / CHANGE IN BOOK EQUITY ) | C2: RETURN ON EQUITY | J2: NET INC | K2: BOOK E | L2: CHANGE IN NET INCOME | M2: CHANGE IN BOOK E | N2: RETURN ON EQUITY
A3: 2019 | B3: =L4/M4 -> 0.44896363 | C3: =J4/K4 -> 0.10075671 | I3: 2018 | J3: 1049 | K3: 19248
A4: 2020 | B4: =L5/M5 -> 0.55449025 | C4: =J5/K5 -> 0.15769632 | I4: 2019 | J4: 2197 | K4: 21805 | L4: =J4-J3 -> 1148 | M4: =K4-K3 -> 2557
A5: 2021 | B5: =L6/M6 -> -1.0523139 | C5: =J6/K6 -> 0.048032386 | I5: 2020 | J5: 3932 | K5: 24934 | L5: =J5-J4 -> 1735 | M5: =K5-K4 -> 3129
A6: 2023 | B6: =L7/M7 -> 0.44692433 | C6: =J7/K7 -> 0.073079027 | I6: 2021 | J6: 1317 | K6: 27419 | L6: =J6-J5 -> -2615 | M6: =K6-K5 -> 2485
A7: 2024 | B7: =L8/M8 -> 0.21282401 | C7: =J8/K8 -> 0.091341297 | I7: 2022 | J7: 2138 | K7: 29256 | L7: =J7-J6 -> 821 | M7: =K7-K6 -> 1837
A8: RETURN ON NEW EQUITY HAS BEEN SIGNIFICANTLY THAN AVERAGE RETURN ON EQUITY | I8: 2023 | J8: 3074 | K8: 33654 | L8: =J8-J7 -> 936 | M8: =K8-K7 -> 4398
A9: SIGNALLING UPWARD TREND. | I9: 2024 | J9: 2861 | K9: 37788 | L9: =J9-J8 -> -213 | M9: =K9-K8 -> 4134
A12: change in revenues | L12: 2026
L13: 2027
L14: 2028
L15: 2029
L16: 2030
L17: 2031
L18: 2032
L19: 2033
L20: 2034
L21: 2035

Sheet Segments
A2: In Millions of the reported currency.
A3: Business Segments
A4: For the Fiscal Period Ending | B4: Reclassified 12 months Dec-31-2015 | C4: Reclassified 12 months Dec-31-2016 | D4: Reclassified 12 months Dec-31-2017 | E4: Reclassified 12 months Dec-31-2018 | F4: 12 months Dec-31-2019 | G4: Reclassified 12 months Dec-31-2020 | H4: Reclassified 12 months Dec-31-2021 | I4: 12 months Dec-31-2022 | J4: Reclassified 12 months Dec-31-2023 | K4: 12 months Dec-31-2024
A5: Currency | B5: USD | C5: USD | D5: USD | E5: USD | F5: USD | G5: USD | H5: USD | I5: USD | J5: USD | K5: USD
A6: Revenues
A7: Sempra Infrastructure | B7: - | C7: - | D7: - | E7: - | F7: 1454 | G7: 1400 | H7: 1997 | I7: 1919 | J7: 3071 | K7: 1882
A8: Sempra California | B8: - | C8: - | D8: - | E8: - | F8: - | G8: - | H8: 10926 | I8: 12577 | J8: 13761 | K8: 11382
A9: Unallocated Adjustments | B9: -2 | C9: - | D9: -1 | E9: -3 | F9: -3 | G9: -3 | H9: - | I9: - | J9: - | K9: -
A10: Intersegment Eliminations | B10: -377 | C10: -364 | D10: -450 | E10: -397 | F10: -85 | G10: -90 | H10: -71 | I10: -57 | J10: -112 | K10: -79
A11: All Other | B11: - | C11: - | D11: - | E11: - | F11: 3 | G11: 2 | H11: 5 | I11: - | J11: - | K11: - | N11: Year 2015 | O11: Year 2016 | P11: Year 2017 | Q11: Year 2018 | R11: Year 2019 | S11: Year 2020 | T11: Year 2021 | U11: Year 2022 | V11: Year 2023 | W11: Year 2024
A12: SAN Diego Gas & Electric Company (SDG&E) | B12: 4219 | C12: 4253 | D12: 4476 | E12: 4568 | F12: 4925 | G12: 5313 | H12: - | I12: - | J12: - | K12: - | M12: Utilities | N12: =B$12+B$13+B$17 -> 9252 | O12: =C$12+C$13+C$17 -> 9280 | P12: =D$12+D13 -> 8261 | Q12: =E$12+E13 -> 8530 | R12: =F$12+F13 -> 9450 | S12: =G$12+G13 -> 10061 | T12: =H8 -> 10926 | U12: =I8 -> 12577 | V12: =J8 -> 13761 | W12: =K8 -> 11382
A13: Southern California Gas Company (Socalgas) | B13: 3489 | C13: 3471 | D13: 3785 | E13: 3962 | F13: 4525 | G13: 4748 | H13: - | I13: - | J13: - | K13: - | M13: Infrastructure | N13: =B$15+B$16 -> 1322 | O13: =C$15+C$16 -> 1233 | P13: =D$15+D$16 -> 1736 | Q13: =E$15+E$16 -> 1848 | R13: =F7 -> 1454 | S13: =G7 -> 1400 | T13: =H7 -> 1997 | U13: =I7 -> 1919 | V13: =J7 -> 3071 | W13: =K7 -> 1882
A14: Sempra Renewables | B14: 36 | C14: 34 | D14: 94 | E14: 124 | F14: 10 | G14: - | H14: - | I14: - | J14: - | K14: - | M14: Non-core | N14: =B9+B10 -> -379 | O14: =C10 -> -364 | P14: =D$9+D$10 -> -451 | Q14: =E$9+E$10 -> -400 | R14: =F$9+F$10 -> -88 | S14: =G$9+G$10 -> -93 | T14: =H$10 -> -71 | U14: =I$10 -> -57 | V14: =J$10 -> -112 | W14: =K$10 -> -79
A15: Sempra Mexico | B15: 669 | C15: 725 | D15: 1196 | E15: 1376 | F15: - | G15: - | H15: - | I15: - | J15: - | K15: - | M15: All other | N15: =B$14 -> 36 | O15: =C$14 -> 34 | P15: =D$14 -> 94 | Q15: =E$14 -> 124 | R15: =F14+F11 -> 13 | S15: =G11 -> 2 | T15: =H11 -> 5
A16: Sempra LNG | B16: 653 | C16: 508 | D16: 540 | E16: 472 | F16: - | G16: - | H16: - | I16: - | J16: - | K16: -
A17: Sempra South American Utilities | B17: 1544 | C17: 1556 | D17: - | E17: - | F17: - | G17: - | H17: - | I17: - | J17: - | K17: -
A18: Total Revenues | B18: 10231 | C18: 10183 | D18: 9640 | E18: 10102 | F18: 10829 | G18: 11370 | H18: 12857 | I18: 14439 | J18: 16720 | K18: 13185
A20: Interest Expense
A21: Sempra Infrastructure | B21: - | C21: - | D21: - | E21: - | F21: -155 | G21: -174 | H21: -205 | I21: -104 | J21: -129 | K21: 243
A22: Sempra California | B22: - | C22: - | D22: - | E22: - | F22: - | G22: - | H22: -569 | I22: -647 | J22: -782 | K22: -848
A23: Intersegment Eliminations | B23: 120 | C23: 119 | D23: 118 | E23: 106 | F23: 83 | G23: 54 | H23: 20 | I23: - | J23: - | K23: -
A24: All Other | B24: -263 | C24: -282 | D24: -284 | E24: -496 | F24: -450 | G24: -390 | H24: -444 | I24: - | J24: - | K24: -
A25: SAN Diego Gas & Electric Company (SDG&E) | B25: -204 | C25: -195 | D25: -203 | E25: -221 | F25: -411 | G25: -413 | H25: - | I25: - | J25: - | K25: -
A26: Southern California Gas Company (Socalgas) | B26: -84 | C26: -97 | D26: -102 | E26: -115 | F26: -141 | G26: -158 | H26: - | I26: - | J26: - | K26: -
A27: Sempra Renewables | B27: -3 | C27: -4 | D27: -15 | E27: -19 | F27: -3 | G27: - | H27: - | I27: - | J27: - | K27: -
A28: Sempra Mexico | B28: -23 | C28: -13 | D28: -97 | E28: -120 | F28: - | G28: - | H28: - | I28: - | J28: - | K28: -
A29: Sempra LNG | B29: -72 | C29: -43 | D29: -39 | E29: -21 | F29: - | G29: - | H29: - | I29: - | J29: - | K29: -
A30: Sempra South American Utilities | B30: -32 | C30: -38 | D30: - | E30: - | F30: - | G30: - | H30: - | I30: - | J30: - | K30: -
A31: Total Interest Expense | B31: -561 | C31: -553 | D31: -622 | E31: -886 | F31: -1077 | G31: -1081 | H31: -1198 | I31: -751 | J31: -911 | K31: -605
A33: Tax Expense
A34: Sempra Infrastructure | B34: - | C34: - | D34: - | E34: - | F34: 222 | G34: 149 | H34: 238 | I34: 249 | J34: 673 | K34: -164
A35: Sempra California | B35: - | C35: - | D35: - | E35: - | F35: - | G35: - | H35: -109 | I35: 320 | J35: -31 | K35: 184
A36: Sempra Texas Utilities | B36: - | C36: - | D36: - | E36: - | F36: - | G36: 1 | H36: - | I36: - | J36: - | K36: -
A37: All Other | B37: -138 | C37: -184 | D37: 741 | E37: -135 | F37: -202 | G37: -187 | H37: -30 | I37: - | J37: - | K37: -
A38: SAN Diego Gas & Electric Company (SDG&E) | B38: 284 | C38: 280 | D38: 155 | E38: 173 | F38: 171 | G38: 190 | H38: - | I38: - | J38: - | K38: -
A39: Southern California Gas Company (Socalgas) | B39: 138 | C39: 143 | D39: 160 | E39: 92 | F39: 120 | G39: 96 | H39: - | I39: - | J39: - | K39: -
A40: Sempra Renewables | B40: -49 | C40: -38 | D40: -226 | E40: 71 | F40: 4 | G40: - | H40: - | I40: - | J40: - | K40: -
A41: Sempra Mexico | B41: 11 | C41: 188 | D41: 227 | E41: 185 | F41: - | G41: - | H41: - | I41: - | J41: - | K41: -
A42: Sempra LNG | B42: 28 | C42: -80 | D42: -119 | E42: -435 | F42: - | G42: - | H42: - | I42: - | J42: - | K42: -
A43: Sempra South American Utilities | B43: 67 | C43: 80 | D43: - | E43: - | F43: - | G43: - | H43: - | I43: - | J43: - | K43: -
A44: Total Tax Expense | B44: 341 | C44: 389 | D44: 938 | E44: -49 | F44: 315 | G44: 249 | H44: 99 | I44: 569 | J44: 642 | K44: 20
A46: Net Profit After Tax
A47: Sempra Infrastructure | B47: - | C47: - | D47: - | E47: - | F47: 247 | G47: 580 | H47: 682 | I47: 310 | J47: 877 | K47: 911
A48: Sempra California | B48: - | C48: - | D48: - | E48: - | F48: - | G48: - | H48: 392 | I48: 1514 | J48: 1747 | K48: 1846
A49: Sempra Texas Utilities | B49: - | C49: - | D49: - | E49: 371 | F49: 528 | G49: 579 | H49: 616 | I49: 736 | J49: 694 | K49: 781
A50: Parent & Other | B50: - | C50: - | D50: - | E50: - | F50: - | G50: - | H50: - | I50: -466 | J50: -288 | K50: -721
A51: All Other | B51: -152 | C51: -116 | D51: -1060 | E51: -620 | F51: -515 | G51: -563 | H51: -436 | I51: - | J51: - | K51: -
A52: SAN Diego Gas & Electric Company (SDG&E) | B52: 587 | C52: 570 | D52: 407 | E52: 669 | F52: 767 | G52: 824 | H52: - | I52: - | J52: - | K52: -
A53: Southern California Gas Company (Socalgas) | B53: 419 | C53: 349 | D53: 396 | E53: 400 | F53: 641 | G53: 504 | H53: - | I53: - | J53: - | K53: -
A54: Discontinued Operations | B54: - | C54: - | D54: - | E54: - | F54: - | G54: 1840 | H54: - | I54: - | J54: - | K54: -
A55: Sempra Renewables | B55: 63 | C55: 55 | D55: 252 | E55: 328 | F55: 59 | G55: - | H55: - | I55: - | J55: - | K55: -
A56: Sempra South American Utilities - Discontinued Operations | B56: - | C56: - | D56: -58 | E56: 156 | F56: 328 | G56: - | H56: - | I56: - | J56: - | K56: -
A57: Sempra Mexico | B57: 213 | C57: 463 | D57: 169 | E57: 237 | F57: - | G57: - | H57: - | I57: - | J57: - | K57: -
A58: Sempra LNG | B58: 44 | C58: -107 | D58: 150 | E58: -617 | F58: - | G58: - | H58: - | I58: - | J58: - | K58: -
A59: Sempra South American Utilities | B59: 175 | C59: 156 | D59: - | E59: - | F59: - | G59: - | H59: - | I59: - | J59: - | K59: -
A60: Total Net Profit After Tax | B60: 1349 | C60: 1370 | D60: 256 | E60: 924 | F60: 2055 | G60: 3764 | H60: 1254 | I60: 2094 | J60: 3030 | K60: 2817
A62: Assets
A63: Sempra Infrastructure | B63: - | C63: - | D63: - | E63: - | F63: 13660 | G63: - | H63: 14408 | I63: 15760 | J63: 19430 | K63: 22954
A64: Sempra California | B64: - | C64: - | D64: - | E64: - | F64: - | G64: - | H64: - | I64: 48696 | J64: 53430 | K64: 56116
A65: Intersegment Eliminations | B65: -2228 | C65: -4173 | D65: -2785 | E65: -4190 | F65: -1972 | G65: - | H65: -1191 | I65: -1039 | J65: -1038 | K65: -1071
A66: Sempra Texas Utilities | B66: - | C66: - | D66: - | E66: 9652 | F66: 11619 | G66: - | H66: 13047 | I66: 13781 | J66: 14392 | K66: 15534
A67: Parent & Other | B67: - | C67: - | D67: - | E67: - | F67: - | G67: - | H67: - | I67: - | J67: 967 | K67: 2622
A68: All Other | B68: 734 | C68: 475 | D68: 1351 | E68: 1070 | F68: 763 | G68: - | H68: 1399 | I68: 1376 | J68: - | K68: -
A69: SAN Diego Gas & Electric Company (SDG&E) | B69: 16515 | C69: 17719 | D69: 17844 | E69: 19225 | F69: 20560 | G69: - | H69: 24058 | I69: - | J69: - | K69: -
A70: Southern California Gas Company (Socalgas) | B70: 12104 | C70: 13424 | D70: 14159 | E70: 15389 | F70: 17077 | G70: - | H70: 20324 | I70: - | J70: - | K70: -
A71: Sempra Renewables | B71: 1441 | C71: 3644 | D71: 2898 | E71: 2549 | F71: - | G71: - | H71: - | I71: - | J71: - | K71: -
A72: Sempra South American Utilities - Discontinued Operations | B72: - | C72: - | D72: 3561 | E72: 3718 | F72: 3958 | G72: - | H72: - | I72: - | J72: - | K72: -
A73: Sempra Mexico | B73: 3783 | C73: 7542 | D73: 8554 | E73: 9165 | F73: - | G73: - | H73: - | I73: - | J73: - | K73: -
A74: Sempra LNG | B74: 5566 | C74: 5564 | D74: 4872 | E74: 4060 | F74: - | G74: - | H74: - | I74: - | J74: - | K74: -
A75: Sempra South American Utilities | B75: 3235 | C75: 3591 | D75: - | E75: - | F75: - | G75: - | H75: - | I75: - | J75: - | K75: -
A76: Total Assets | B76: 41150 | C76: 47786 | D76: 50454 | E76: 60638 | F76: 65665 | G76: - | H76: 72045 | I76: 78574 | J76: 87181 | K76: 96155
A78: Depreciation & Amortization
A79: Sempra Infrastructure | B79: - | C79: - | D79: - | E79: - | F79: 193 | G79: 198 | H79: 239 | I79: 268 | J79: 281 | K79: 297
A80: Sempra California | B80: - | C80: - | D80: - | E80: - | F80: - | G80: - | H80: 1605 | I80: 1743 | J80: 1937 | K80: 2133
A81: All Other | B81: 10 | C81: 11 | D81: 15 | E81: 19 | F81: 14 | G81: 13 | H81: 11 | I81: - | J81: - | K81: -
A82: SAN Diego Gas & Electric Company (SDG&E) | B82: 604 | C82: 646 | D82: 670 | E82: 688 | F82: 760 | G82: 801 | H82: - | I82: - | J82: - | K82: -
